/*     */ package com.groom.dao.impl;
/*     */ 
/*     */ import com.groom.bean.QuizQuestionDetails;
/*     */ import com.groom.dao.AdminDAO;
/*     */ import com.groom.dao.BaseDAO;
/*     */ import java.io.PrintStream;
/*     */ import java.sql.Connection;
/*     */ import java.sql.Date;
/*     */ import java.sql.PreparedStatement;
/*     */ import java.sql.SQLException;
/*     */ import javax.sql.DataSource;
/*     */ 
/*     */ 
/*     */ 
/*     */ 
/*     */ public class AdminDAOImpl
/*     */   extends BaseDAO
/*     */   implements AdminDAO
/*     */ {
/*     */   public boolean addSubjectTopic(String subject, String topicName, int standard, Date testDate, int test_category_id, String test_by, int test_time)
/*     */     throws SQLException
/*     */   {
/*  23 */     Connection connection = ds.getConnection();
/*  24 */     PreparedStatement preparedStatement = null;
/*     */     try
/*     */     {
/*  27 */       String query = "INSERT INTO " + subject + 
/*  28 */         "_TOPICS(TOPIC_NAME,TOPIC_CLASS,TEST_DATE,TEST_CATEGORY_ID,TEST_BY,TEST_TIME) VALUES(?,?,?,?,?,?)";
/*  29 */       System.out.println(query);
/*  30 */       preparedStatement = connection.prepareStatement(query);
/*     */       
/*  32 */       preparedStatement.setString(1, topicName);
/*  33 */       preparedStatement.setInt(2, standard);
/*  34 */       preparedStatement.setDate(3, testDate);
/*  35 */       preparedStatement.setInt(4, test_category_id);
/*  36 */       preparedStatement.setString(5, test_by);
/*  37 */       preparedStatement.setInt(6, test_time);
/*  38 */       int status = preparedStatement.executeUpdate();
/*  39 */       if (status == 1)
/*  40 */         return true;
/*     */     } catch (SQLException exception) {
/*  42 */       exception.printStackTrace();
/*     */     }
/*     */     finally {
/*  45 */       if (preparedStatement != null)
/*  46 */         preparedStatement.close();
/*  47 */       if (connection != null) {
/*  48 */         connection.close();
/*     */       }
/*     */     }
/*  45 */     if (preparedStatement != null)
/*  46 */       preparedStatement.close();
/*  47 */     if (connection != null) {
/*  48 */       connection.close();
/*     */     }
/*  50 */     return false;
/*     */   }
/*     */   
/*     */   /* Error */
/*     */   public java.util.HashMap<Integer, String> getTopics(String subject)
/*     */     throws SQLException
/*     */   {
/*     */     // Byte code:
/*     */     //   0: getstatic 21	com/groom/dao/impl/AdminDAOImpl:ds	Ljavax/sql/DataSource;
/*     */     //   3: invokeinterface 25 1 0
/*     */     //   8: astore_2
/*     */     //   9: aconst_null
/*     */     //   10: astore_3
/*     */     //   11: aconst_null
/*     */     //   12: astore 4
/*     */     //   14: new 119	java/util/HashMap
/*     */     //   17: dup
/*     */     //   18: invokespecial 121	java/util/HashMap:<init>	()V
/*     */     //   21: astore 5
/*     */     //   23: new 31	java/lang/StringBuilder
/*     */     //   26: dup
/*     */     //   27: ldc 122
/*     */     //   29: invokespecial 35	java/lang/StringBuilder:<init>	(Ljava/lang/String;)V
/*     */     //   32: aload_1
/*     */     //   33: invokevirtual 38	java/lang/StringBuilder:append	(Ljava/lang/String;)Ljava/lang/StringBuilder;
/*     */     //   36: ldc 124
/*     */     //   38: invokevirtual 38	java/lang/StringBuilder:append	(Ljava/lang/String;)Ljava/lang/StringBuilder;
/*     */     //   41: invokevirtual 44	java/lang/StringBuilder:toString	()Ljava/lang/String;
/*     */     //   44: astore 6
/*     */     //   46: getstatic 48	java/lang/System:out	Ljava/io/PrintStream;
/*     */     //   49: aload 6
/*     */     //   51: invokevirtual 54	java/io/PrintStream:println	(Ljava/lang/String;)V
/*     */     //   54: aload_2
/*     */     //   55: aload 6
/*     */     //   57: invokeinterface 59 2 0
/*     */     //   62: astore_3
/*     */     //   63: aload_3
/*     */     //   64: invokeinterface 126 1 0
/*     */     //   69: astore 4
/*     */     //   71: goto +30 -> 101
/*     */     //   74: aload 5
/*     */     //   76: aload 4
/*     */     //   78: ldc -126
/*     */     //   80: invokeinterface 132 2 0
/*     */     //   85: invokestatic 138	java/lang/Integer:valueOf	(I)Ljava/lang/Integer;
/*     */     //   88: aload 4
/*     */     //   90: ldc -112
/*     */     //   92: invokeinterface 146 2 0
/*     */     //   97: invokevirtual 150	java/util/HashMap:put	(Ljava/lang/Object;Ljava/lang/Object;)Ljava/lang/Object;
/*     */     //   100: pop
/*     */     //   101: aload 4
/*     */     //   103: invokeinterface 154 1 0
/*     */     //   108: ifne -34 -> 74
/*     */     //   111: goto +58 -> 169
/*     */     //   114: astore 6
/*     */     //   116: aload 6
/*     */     //   118: invokevirtual 87	java/sql/SQLException:printStackTrace	()V
/*     */     //   121: aload_3
/*     */     //   122: ifnull +9 -> 131
/*     */     //   125: aload_3
/*     */     //   126: invokeinterface 83 1 0
/*     */     //   131: aload_2
/*     */     //   132: ifnull +57 -> 189
/*     */     //   135: aload_2
/*     */     //   136: invokeinterface 86 1 0
/*     */     //   141: goto +48 -> 189
/*     */     //   144: astore 7
/*     */     //   146: aload_3
/*     */     //   147: ifnull +9 -> 156
/*     */     //   150: aload_3
/*     */     //   151: invokeinterface 83 1 0
/*     */     //   156: aload_2
/*     */     //   157: ifnull +9 -> 166
/*     */     //   160: aload_2
/*     */     //   161: invokeinterface 86 1 0
/*     */     //   166: aload 7
/*     */     //   168: athrow
/*     */     //   169: aload_3
/*     */     //   170: ifnull +9 -> 179
/*     */     //   173: aload_3
/*     */     //   174: invokeinterface 83 1 0
/*     */     //   179: aload_2
/*     */     //   180: ifnull +9 -> 189
/*     */     //   183: aload_2
/*     */     //   184: invokeinterface 86 1 0
/*     */     //   189: aload 5
/*     */     //   191: areturn
/*     */     // Line number table:
/*     */     //   Java source line #56	-> byte code offset #0
/*     */     //   Java source line #57	-> byte code offset #9
/*     */     //   Java source line #58	-> byte code offset #11
/*     */     //   Java source line #59	-> byte code offset #14
/*     */     //   Java source line #61	-> byte code offset #23
/*     */     //   Java source line #62	-> byte code offset #46
/*     */     //   Java source line #63	-> byte code offset #54
/*     */     //   Java source line #64	-> byte code offset #63
/*     */     //   Java source line #65	-> byte code offset #71
/*     */     //   Java source line #66	-> byte code offset #74
/*     */     //   Java source line #67	-> byte code offset #88
/*     */     //   Java source line #66	-> byte code offset #97
/*     */     //   Java source line #65	-> byte code offset #101
/*     */     //   Java source line #70	-> byte code offset #111
/*     */     //   Java source line #71	-> byte code offset #116
/*     */     //   Java source line #74	-> byte code offset #121
/*     */     //   Java source line #75	-> byte code offset #125
/*     */     //   Java source line #76	-> byte code offset #131
/*     */     //   Java source line #77	-> byte code offset #135
/*     */     //   Java source line #72	-> byte code offset #144
/*     */     //   Java source line #74	-> byte code offset #146
/*     */     //   Java source line #75	-> byte code offset #150
/*     */     //   Java source line #76	-> byte code offset #156
/*     */     //   Java source line #77	-> byte code offset #160
/*     */     //   Java source line #78	-> byte code offset #166
/*     */     //   Java source line #74	-> byte code offset #169
/*     */     //   Java source line #75	-> byte code offset #173
/*     */     //   Java source line #76	-> byte code offset #179
/*     */     //   Java source line #77	-> byte code offset #183
/*     */     //   Java source line #79	-> byte code offset #189
/*     */     // Local variable table:
/*     */     //   start	length	slot	name	signature
/*     */     //   0	192	0	this	AdminDAOImpl
/*     */     //   0	192	1	subject	String
/*     */     //   8	176	2	connection	Connection
/*     */     //   10	164	3	preparedStatement	PreparedStatement
/*     */     //   12	90	4	resultSet	java.sql.ResultSet
/*     */     //   21	169	5	map	java.util.HashMap<Integer, String>
/*     */     //   44	12	6	query	String
/*     */     //   114	3	6	exception	SQLException
/*     */     //   144	23	7	localObject	Object
/*     */     // Exception table:
/*     */     //   from	to	target	type
/*     */     //   23	111	114	java/sql/SQLException
/*     */     //   23	121	144	finally
/*     */   }
/*     */   
/*     */   /* Error */
/*     */   public java.util.HashMap<Integer, String> getTopicsByStandard(String subject, int standard, int division)
/*     */     throws SQLException
/*     */   {
/*     */     // Byte code:
/*     */     //   0: getstatic 21	com/groom/dao/impl/AdminDAOImpl:ds	Ljavax/sql/DataSource;
/*     */     //   3: invokeinterface 25 1 0
/*     */     //   8: astore 4
/*     */     //   10: aconst_null
/*     */     //   11: astore 5
/*     */     //   13: aconst_null
/*     */     //   14: astore 6
/*     */     //   16: new 119	java/util/HashMap
/*     */     //   19: dup
/*     */     //   20: invokespecial 121	java/util/HashMap:<init>	()V
/*     */     //   23: astore 7
/*     */     //   25: new 31	java/lang/StringBuilder
/*     */     //   28: dup
/*     */     //   29: ldc 122
/*     */     //   31: invokespecial 35	java/lang/StringBuilder:<init>	(Ljava/lang/String;)V
/*     */     //   34: aload_1
/*     */     //   35: invokevirtual 38	java/lang/StringBuilder:append	(Ljava/lang/String;)Ljava/lang/StringBuilder;
/*     */     //   38: ldc -89
/*     */     //   40: invokevirtual 38	java/lang/StringBuilder:append	(Ljava/lang/String;)Ljava/lang/StringBuilder;
/*     */     //   43: invokevirtual 44	java/lang/StringBuilder:toString	()Ljava/lang/String;
/*     */     //   46: astore 8
/*     */     //   48: aload 4
/*     */     //   50: aload 8
/*     */     //   52: invokeinterface 59 2 0
/*     */     //   57: astore 5
/*     */     //   59: aload 5
/*     */     //   61: iconst_1
/*     */     //   62: iload_2
/*     */     //   63: invokeinterface 71 3 0
/*     */     //   68: getstatic 48	java/lang/System:out	Ljava/io/PrintStream;
/*     */     //   71: aload 8
/*     */     //   73: invokevirtual 54	java/io/PrintStream:println	(Ljava/lang/String;)V
/*     */     //   76: aload 5
/*     */     //   78: invokeinterface 126 1 0
/*     */     //   83: astore 6
/*     */     //   85: goto +30 -> 115
/*     */     //   88: aload 7
/*     */     //   90: aload 6
/*     */     //   92: ldc -126
/*     */     //   94: invokeinterface 132 2 0
/*     */     //   99: invokestatic 138	java/lang/Integer:valueOf	(I)Ljava/lang/Integer;
/*     */     //   102: aload 6
/*     */     //   104: ldc -112
/*     */     //   106: invokeinterface 146 2 0
/*     */     //   111: invokevirtual 150	java/util/HashMap:put	(Ljava/lang/Object;Ljava/lang/Object;)Ljava/lang/Object;
/*     */     //   114: pop
/*     */     //   115: aload 6
/*     */     //   117: invokeinterface 154 1 0
/*     */     //   122: ifne -34 -> 88
/*     */     //   125: goto +66 -> 191
/*     */     //   128: astore 8
/*     */     //   130: aload 8
/*     */     //   132: invokevirtual 87	java/sql/SQLException:printStackTrace	()V
/*     */     //   135: aload 5
/*     */     //   137: ifnull +10 -> 147
/*     */     //   140: aload 5
/*     */     //   142: invokeinterface 83 1 0
/*     */     //   147: aload 4
/*     */     //   149: ifnull +66 -> 215
/*     */     //   152: aload 4
/*     */     //   154: invokeinterface 86 1 0
/*     */     //   159: goto +56 -> 215
/*     */     //   162: astore 9
/*     */     //   164: aload 5
/*     */     //   166: ifnull +10 -> 176
/*     */     //   169: aload 5
/*     */     //   171: invokeinterface 83 1 0
/*     */     //   176: aload 4
/*     */     //   178: ifnull +10 -> 188
/*     */     //   181: aload 4
/*     */     //   183: invokeinterface 86 1 0
/*     */     //   188: aload 9
/*     */     //   190: athrow
/*     */     //   191: aload 5
/*     */     //   193: ifnull +10 -> 203
/*     */     //   196: aload 5
/*     */     //   198: invokeinterface 83 1 0
/*     */     //   203: aload 4
/*     */     //   205: ifnull +10 -> 215
/*     */     //   208: aload 4
/*     */     //   210: invokeinterface 86 1 0
/*     */     //   215: aload 7
/*     */     //   217: areturn
/*     */     // Line number table:
/*     */     //   Java source line #85	-> byte code offset #0
/*     */     //   Java source line #86	-> byte code offset #10
/*     */     //   Java source line #87	-> byte code offset #13
/*     */     //   Java source line #88	-> byte code offset #16
/*     */     //   Java source line #92	-> byte code offset #25
/*     */     //   Java source line #93	-> byte code offset #48
/*     */     //   Java source line #94	-> byte code offset #59
/*     */     //   Java source line #96	-> byte code offset #68
/*     */     //   Java source line #97	-> byte code offset #76
/*     */     //   Java source line #98	-> byte code offset #85
/*     */     //   Java source line #99	-> byte code offset #88
/*     */     //   Java source line #100	-> byte code offset #102
/*     */     //   Java source line #99	-> byte code offset #111
/*     */     //   Java source line #98	-> byte code offset #115
/*     */     //   Java source line #102	-> byte code offset #125
/*     */     //   Java source line #103	-> byte code offset #130
/*     */     //   Java source line #106	-> byte code offset #135
/*     */     //   Java source line #107	-> byte code offset #140
/*     */     //   Java source line #108	-> byte code offset #147
/*     */     //   Java source line #109	-> byte code offset #152
/*     */     //   Java source line #104	-> byte code offset #162
/*     */     //   Java source line #106	-> byte code offset #164
/*     */     //   Java source line #107	-> byte code offset #169
/*     */     //   Java source line #108	-> byte code offset #176
/*     */     //   Java source line #109	-> byte code offset #181
/*     */     //   Java source line #110	-> byte code offset #188
/*     */     //   Java source line #106	-> byte code offset #191
/*     */     //   Java source line #107	-> byte code offset #196
/*     */     //   Java source line #108	-> byte code offset #203
/*     */     //   Java source line #109	-> byte code offset #208
/*     */     //   Java source line #111	-> byte code offset #215
/*     */     // Local variable table:
/*     */     //   start	length	slot	name	signature
/*     */     //   0	218	0	this	AdminDAOImpl
/*     */     //   0	218	1	subject	String
/*     */     //   0	218	2	standard	int
/*     */     //   0	218	3	division	int
/*     */     //   8	201	4	connection	Connection
/*     */     //   11	186	5	preparedStatement	PreparedStatement
/*     */     //   14	102	6	resultSet	java.sql.ResultSet
/*     */     //   23	193	7	map	java.util.HashMap<Integer, String>
/*     */     //   46	26	8	query	String
/*     */     //   128	3	8	exception	SQLException
/*     */     //   162	27	9	localObject	Object
/*     */     // Exception table:
/*     */     //   from	to	target	type
/*     */     //   25	125	128	java/sql/SQLException
/*     */     //   25	135	162	finally
/*     */   }
/*     */   
/*     */   /* Error */
/*     */   public java.util.HashMap<String, String> getCategoryByStandard(int standard)
/*     */     throws SQLException
/*     */   {
/*     */     // Byte code:
/*     */     //   0: getstatic 21	com/groom/dao/impl/AdminDAOImpl:ds	Ljavax/sql/DataSource;
/*     */     //   3: invokeinterface 25 1 0
/*     */     //   8: astore_2
/*     */     //   9: aconst_null
/*     */     //   10: astore_3
/*     */     //   11: aconst_null
/*     */     //   12: astore 4
/*     */     //   14: new 119	java/util/HashMap
/*     */     //   17: dup
/*     */     //   18: invokespecial 121	java/util/HashMap:<init>	()V
/*     */     //   21: astore 5
/*     */     //   23: ldc -83
/*     */     //   25: astore 6
/*     */     //   27: aload_2
/*     */     //   28: aload 6
/*     */     //   30: invokeinterface 59 2 0
/*     */     //   35: astore_3
/*     */     //   36: aload_3
/*     */     //   37: iconst_1
/*     */     //   38: iload_1
/*     */     //   39: invokeinterface 71 3 0
/*     */     //   44: getstatic 48	java/lang/System:out	Ljava/io/PrintStream;
/*     */     //   47: aload 6
/*     */     //   49: invokevirtual 54	java/io/PrintStream:println	(Ljava/lang/String;)V
/*     */     //   52: aload_3
/*     */     //   53: invokeinterface 126 1 0
/*     */     //   58: astore 4
/*     */     //   60: goto +27 -> 87
/*     */     //   63: aload 5
/*     */     //   65: aload 4
/*     */     //   67: ldc -81
/*     */     //   69: invokeinterface 146 2 0
/*     */     //   74: aload 4
/*     */     //   76: ldc -79
/*     */     //   78: invokeinterface 146 2 0
/*     */     //   83: invokevirtual 150	java/util/HashMap:put	(Ljava/lang/Object;Ljava/lang/Object;)Ljava/lang/Object;
/*     */     //   86: pop
/*     */     //   87: aload 4
/*     */     //   89: invokeinterface 154 1 0
/*     */     //   94: ifne -31 -> 63
/*     */     //   97: goto +58 -> 155
/*     */     //   100: astore 6
/*     */     //   102: aload 6
/*     */     //   104: invokevirtual 87	java/sql/SQLException:printStackTrace	()V
/*     */     //   107: aload_3
/*     */     //   108: ifnull +9 -> 117
/*     */     //   111: aload_3
/*     */     //   112: invokeinterface 83 1 0
/*     */     //   117: aload_2
/*     */     //   118: ifnull +57 -> 175
/*     */     //   121: aload_2
/*     */     //   122: invokeinterface 86 1 0
/*     */     //   127: goto +48 -> 175
/*     */     //   130: astore 7
/*     */     //   132: aload_3
/*     */     //   133: ifnull +9 -> 142
/*     */     //   136: aload_3
/*     */     //   137: invokeinterface 83 1 0
/*     */     //   142: aload_2
/*     */     //   143: ifnull +9 -> 152
/*     */     //   146: aload_2
/*     */     //   147: invokeinterface 86 1 0
/*     */     //   152: aload 7
/*     */     //   154: athrow
/*     */     //   155: aload_3
/*     */     //   156: ifnull +9 -> 165
/*     */     //   159: aload_3
/*     */     //   160: invokeinterface 83 1 0
/*     */     //   165: aload_2
/*     */     //   166: ifnull +9 -> 175
/*     */     //   169: aload_2
/*     */     //   170: invokeinterface 86 1 0
/*     */     //   175: aload 5
/*     */     //   177: areturn
/*     */     // Line number table:
/*     */     //   Java source line #117	-> byte code offset #0
/*     */     //   Java source line #118	-> byte code offset #9
/*     */     //   Java source line #119	-> byte code offset #11
/*     */     //   Java source line #120	-> byte code offset #14
/*     */     //   Java source line #122	-> byte code offset #23
/*     */     //   Java source line #123	-> byte code offset #27
/*     */     //   Java source line #124	-> byte code offset #36
/*     */     //   Java source line #125	-> byte code offset #44
/*     */     //   Java source line #126	-> byte code offset #52
/*     */     //   Java source line #127	-> byte code offset #60
/*     */     //   Java source line #128	-> byte code offset #63
/*     */     //   Java source line #129	-> byte code offset #74
/*     */     //   Java source line #128	-> byte code offset #83
/*     */     //   Java source line #127	-> byte code offset #87
/*     */     //   Java source line #131	-> byte code offset #97
/*     */     //   Java source line #132	-> byte code offset #102
/*     */     //   Java source line #135	-> byte code offset #107
/*     */     //   Java source line #136	-> byte code offset #111
/*     */     //   Java source line #137	-> byte code offset #117
/*     */     //   Java source line #138	-> byte code offset #121
/*     */     //   Java source line #133	-> byte code offset #130
/*     */     //   Java source line #135	-> byte code offset #132
/*     */     //   Java source line #136	-> byte code offset #136
/*     */     //   Java source line #137	-> byte code offset #142
/*     */     //   Java source line #138	-> byte code offset #146
/*     */     //   Java source line #139	-> byte code offset #152
/*     */     //   Java source line #135	-> byte code offset #155
/*     */     //   Java source line #136	-> byte code offset #159
/*     */     //   Java source line #137	-> byte code offset #165
/*     */     //   Java source line #138	-> byte code offset #169
/*     */     //   Java source line #140	-> byte code offset #175
/*     */     // Local variable table:
/*     */     //   start	length	slot	name	signature
/*     */     //   0	178	0	this	AdminDAOImpl
/*     */     //   0	178	1	standard	int
/*     */     //   8	162	2	connection	Connection
/*     */     //   10	150	3	preparedStatement	PreparedStatement
/*     */     //   12	76	4	resultSet	java.sql.ResultSet
/*     */     //   21	155	5	map	java.util.HashMap<String, String>
/*     */     //   25	23	6	query	String
/*     */     //   100	3	6	exception	SQLException
/*     */     //   130	23	7	localObject	Object
/*     */     // Exception table:
/*     */     //   from	to	target	type
/*     */     //   23	97	100	java/sql/SQLException
/*     */     //   23	107	130	finally
/*     */   }
/*     */   
/*     */   /* Error */
/*     */   public int getMaxID(String subject)
/*     */     throws SQLException
/*     */   {
/*     */     // Byte code:
/*     */     //   0: getstatic 21	com/groom/dao/impl/AdminDAOImpl:ds	Ljavax/sql/DataSource;
/*     */     //   3: invokeinterface 25 1 0
/*     */     //   8: astore_2
/*     */     //   9: aconst_null
/*     */     //   10: astore_3
/*     */     //   11: aconst_null
/*     */     //   12: astore 4
/*     */     //   14: iconst_0
/*     */     //   15: istore 5
/*     */     //   17: new 31	java/lang/StringBuilder
/*     */     //   20: dup
/*     */     //   21: ldc -75
/*     */     //   23: invokespecial 35	java/lang/StringBuilder:<init>	(Ljava/lang/String;)V
/*     */     //   26: aload_1
/*     */     //   27: invokevirtual 38	java/lang/StringBuilder:append	(Ljava/lang/String;)Ljava/lang/StringBuilder;
/*     */     //   30: invokevirtual 44	java/lang/StringBuilder:toString	()Ljava/lang/String;
/*     */     //   33: astore 6
/*     */     //   35: getstatic 48	java/lang/System:out	Ljava/io/PrintStream;
/*     */     //   38: aload 6
/*     */     //   40: invokevirtual 54	java/io/PrintStream:println	(Ljava/lang/String;)V
/*     */     //   43: aload_2
/*     */     //   44: aload 6
/*     */     //   46: invokeinterface 59 2 0
/*     */     //   51: astore_3
/*     */     //   52: aload_3
/*     */     //   53: invokeinterface 126 1 0
/*     */     //   58: astore 4
/*     */     //   60: goto +13 -> 73
/*     */     //   63: aload 4
/*     */     //   65: iconst_1
/*     */     //   66: invokeinterface 183 2 0
/*     */     //   71: istore 5
/*     */     //   73: aload 4
/*     */     //   75: invokeinterface 154 1 0
/*     */     //   80: ifne -17 -> 63
/*     */     //   83: goto +58 -> 141
/*     */     //   86: astore 6
/*     */     //   88: aload 6
/*     */     //   90: invokevirtual 87	java/sql/SQLException:printStackTrace	()V
/*     */     //   93: aload_3
/*     */     //   94: ifnull +9 -> 103
/*     */     //   97: aload_3
/*     */     //   98: invokeinterface 83 1 0
/*     */     //   103: aload_2
/*     */     //   104: ifnull +57 -> 161
/*     */     //   107: aload_2
/*     */     //   108: invokeinterface 86 1 0
/*     */     //   113: goto +48 -> 161
/*     */     //   116: astore 7
/*     */     //   118: aload_3
/*     */     //   119: ifnull +9 -> 128
/*     */     //   122: aload_3
/*     */     //   123: invokeinterface 83 1 0
/*     */     //   128: aload_2
/*     */     //   129: ifnull +9 -> 138
/*     */     //   132: aload_2
/*     */     //   133: invokeinterface 86 1 0
/*     */     //   138: aload 7
/*     */     //   140: athrow
/*     */     //   141: aload_3
/*     */     //   142: ifnull +9 -> 151
/*     */     //   145: aload_3
/*     */     //   146: invokeinterface 83 1 0
/*     */     //   151: aload_2
/*     */     //   152: ifnull +9 -> 161
/*     */     //   155: aload_2
/*     */     //   156: invokeinterface 86 1 0
/*     */     //   161: iload 5
/*     */     //   163: ireturn
/*     */     // Line number table:
/*     */     //   Java source line #145	-> byte code offset #0
/*     */     //   Java source line #146	-> byte code offset #9
/*     */     //   Java source line #147	-> byte code offset #11
/*     */     //   Java source line #148	-> byte code offset #14
/*     */     //   Java source line #150	-> byte code offset #17
/*     */     //   Java source line #151	-> byte code offset #35
/*     */     //   Java source line #152	-> byte code offset #43
/*     */     //   Java source line #153	-> byte code offset #52
/*     */     //   Java source line #154	-> byte code offset #60
/*     */     //   Java source line #155	-> byte code offset #63
/*     */     //   Java source line #154	-> byte code offset #73
/*     */     //   Java source line #158	-> byte code offset #83
/*     */     //   Java source line #159	-> byte code offset #88
/*     */     //   Java source line #162	-> byte code offset #93
/*     */     //   Java source line #163	-> byte code offset #97
/*     */     //   Java source line #164	-> byte code offset #103
/*     */     //   Java source line #165	-> byte code offset #107
/*     */     //   Java source line #160	-> byte code offset #116
/*     */     //   Java source line #162	-> byte code offset #118
/*     */     //   Java source line #163	-> byte code offset #122
/*     */     //   Java source line #164	-> byte code offset #128
/*     */     //   Java source line #165	-> byte code offset #132
/*     */     //   Java source line #166	-> byte code offset #138
/*     */     //   Java source line #162	-> byte code offset #141
/*     */     //   Java source line #163	-> byte code offset #145
/*     */     //   Java source line #164	-> byte code offset #151
/*     */     //   Java source line #165	-> byte code offset #155
/*     */     //   Java source line #167	-> byte code offset #161
/*     */     // Local variable table:
/*     */     //   start	length	slot	name	signature
/*     */     //   0	164	0	this	AdminDAOImpl
/*     */     //   0	164	1	subject	String
/*     */     //   8	148	2	connection	Connection
/*     */     //   10	136	3	preparedStatement	PreparedStatement
/*     */     //   12	62	4	resultSet	java.sql.ResultSet
/*     */     //   15	147	5	maxid	int
/*     */     //   33	12	6	query	String
/*     */     //   86	3	6	exception	SQLException
/*     */     //   116	23	7	localObject	Object
/*     */     // Exception table:
/*     */     //   from	to	target	type
/*     */     //   17	83	86	java/sql/SQLException
/*     */     //   17	93	116	finally
/*     */   }
/*     */   
/*     */   public boolean saveQuestion(QuizQuestionDetails questionDetails, String subject, String user)
/*     */     throws SQLException
/*     */   {
/* 173 */     Connection connection = ds.getConnection();
/* 174 */     PreparedStatement preparedStatement = null;
/*     */     try
/*     */     {
/* 177 */       String query = "INSERT INTO " + 
/* 178 */         subject + 
/* 179 */         "(QUESTION,OPTION_A,OPTION_B,OPTION_C,OPTION_D,ANSWER,TOPIC_ID,Q_IMAGE_NAME,Q_EXPLANATION,CREATED_ON,CREATED_BY) VALUES(?,?,?,?,?,?,?,?,?,CURRENT_TIMESTAMP,?)";
/* 180 */       System.out.println(query);
/* 181 */       preparedStatement = connection.prepareStatement(query);
/*     */       
/* 183 */       preparedStatement.setString(1, questionDetails.getQuestion());
/* 184 */       preparedStatement.setString(2, questionDetails.getOption_a());
/* 185 */       preparedStatement.setString(3, questionDetails.getOption_b());
/* 186 */       preparedStatement.setString(4, questionDetails.getOption_c());
/* 187 */       preparedStatement.setString(5, questionDetails.getOption_d());
/* 188 */       preparedStatement.setString(6, questionDetails.getAnswer());
/* 189 */       preparedStatement.setInt(7, questionDetails.getTopicid());
/* 190 */       preparedStatement.setString(8, questionDetails.getImage_name());
/* 191 */       preparedStatement.setString(9, questionDetails.getExplanation());
/* 192 */       preparedStatement.setString(10, user);
/*     */       
/*     */ 
/* 195 */       int status = preparedStatement.executeUpdate();
/* 196 */       if (status == 1)
/* 197 */         return true;
/*     */     } catch (SQLException exception) {
/* 199 */       exception.printStackTrace();
/*     */     }
/*     */     finally {
/* 202 */       if (preparedStatement != null)
/* 203 */         preparedStatement.close();
/* 204 */       if (connection != null) {
/* 205 */         connection.close();
/*     */       }
/*     */     }
/* 202 */     if (preparedStatement != null)
/* 203 */       preparedStatement.close();
/* 204 */     if (connection != null) {
/* 205 */       connection.close();
/*     */     }
/* 207 */     return false;
/*     */   }
/*     */   
/*     */   /* Error */
/*     */   public java.util.List<String> getShineResultNames()
/*     */     throws SQLException
/*     */   {
/*     */     // Byte code:
/*     */     //   0: getstatic 21	com/groom/dao/impl/AdminDAOImpl:ds	Ljavax/sql/DataSource;
/*     */     //   3: invokeinterface 25 1 0
/*     */     //   8: astore_1
/*     */     //   9: aconst_null
/*     */     //   10: astore_2
/*     */     //   11: aconst_null
/*     */     //   12: astore_3
/*     */     //   13: new 226	java/util/ArrayList
/*     */     //   16: dup
/*     */     //   17: invokespecial 228	java/util/ArrayList:<init>	()V
/*     */     //   20: astore 4
/*     */     //   22: ldc -27
/*     */     //   24: astore 5
/*     */     //   26: aload_1
/*     */     //   27: aload 5
/*     */     //   29: invokeinterface 59 2 0
/*     */     //   34: astore_2
/*     */     //   35: aload_2
/*     */     //   36: invokeinterface 126 1 0
/*     */     //   41: astore_3
/*     */     //   42: goto +19 -> 61
/*     */     //   45: aload 4
/*     */     //   47: aload_3
/*     */     //   48: ldc -25
/*     */     //   50: invokeinterface 146 2 0
/*     */     //   55: invokeinterface 233 2 0
/*     */     //   60: pop
/*     */     //   61: aload_3
/*     */     //   62: invokeinterface 154 1 0
/*     */     //   67: ifne -22 -> 45
/*     */     //   70: goto +58 -> 128
/*     */     //   73: astore 5
/*     */     //   75: aload 5
/*     */     //   77: invokevirtual 87	java/sql/SQLException:printStackTrace	()V
/*     */     //   80: aload_2
/*     */     //   81: ifnull +9 -> 90
/*     */     //   84: aload_2
/*     */     //   85: invokeinterface 83 1 0
/*     */     //   90: aload_1
/*     */     //   91: ifnull +57 -> 148
/*     */     //   94: aload_1
/*     */     //   95: invokeinterface 86 1 0
/*     */     //   100: goto +48 -> 148
/*     */     //   103: astore 6
/*     */     //   105: aload_2
/*     */     //   106: ifnull +9 -> 115
/*     */     //   109: aload_2
/*     */     //   110: invokeinterface 83 1 0
/*     */     //   115: aload_1
/*     */     //   116: ifnull +9 -> 125
/*     */     //   119: aload_1
/*     */     //   120: invokeinterface 86 1 0
/*     */     //   125: aload 6
/*     */     //   127: athrow
/*     */     //   128: aload_2
/*     */     //   129: ifnull +9 -> 138
/*     */     //   132: aload_2
/*     */     //   133: invokeinterface 83 1 0
/*     */     //   138: aload_1
/*     */     //   139: ifnull +9 -> 148
/*     */     //   142: aload_1
/*     */     //   143: invokeinterface 86 1 0
/*     */     //   148: aload 4
/*     */     //   150: areturn
/*     */     // Line number table:
/*     */     //   Java source line #212	-> byte code offset #0
/*     */     //   Java source line #213	-> byte code offset #9
/*     */     //   Java source line #214	-> byte code offset #11
/*     */     //   Java source line #215	-> byte code offset #13
/*     */     //   Java source line #217	-> byte code offset #22
/*     */     //   Java source line #219	-> byte code offset #26
/*     */     //   Java source line #220	-> byte code offset #35
/*     */     //   Java source line #221	-> byte code offset #42
/*     */     //   Java source line #222	-> byte code offset #45
/*     */     //   Java source line #221	-> byte code offset #61
/*     */     //   Java source line #225	-> byte code offset #70
/*     */     //   Java source line #226	-> byte code offset #75
/*     */     //   Java source line #229	-> byte code offset #80
/*     */     //   Java source line #230	-> byte code offset #84
/*     */     //   Java source line #231	-> byte code offset #90
/*     */     //   Java source line #232	-> byte code offset #94
/*     */     //   Java source line #227	-> byte code offset #103
/*     */     //   Java source line #229	-> byte code offset #105
/*     */     //   Java source line #230	-> byte code offset #109
/*     */     //   Java source line #231	-> byte code offset #115
/*     */     //   Java source line #232	-> byte code offset #119
/*     */     //   Java source line #233	-> byte code offset #125
/*     */     //   Java source line #229	-> byte code offset #128
/*     */     //   Java source line #230	-> byte code offset #132
/*     */     //   Java source line #231	-> byte code offset #138
/*     */     //   Java source line #232	-> byte code offset #142
/*     */     //   Java source line #234	-> byte code offset #148
/*     */     // Local variable table:
/*     */     //   start	length	slot	name	signature
/*     */     //   0	151	0	this	AdminDAOImpl
/*     */     //   8	135	1	connection	Connection
/*     */     //   10	123	2	preparedStatement	PreparedStatement
/*     */     //   12	50	3	resultSet	java.sql.ResultSet
/*     */     //   20	129	4	names	java.util.List<String>
/*     */     //   24	4	5	query	String
/*     */     //   73	3	5	exception	SQLException
/*     */     //   103	23	6	localObject	Object
/*     */     // Exception table:
/*     */     //   from	to	target	type
/*     */     //   22	70	73	java/sql/SQLException
/*     */     //   22	80	103	finally
/*     */   }
/*     */   
/*     */   /* Error */
/*     */   public com.groom.bean.Shine getUserResults(int standard, String school_code, String roll_number)
/*     */     throws SQLException
/*     */   {
/*     */     // Byte code:
/*     */     //   0: getstatic 21	com/groom/dao/impl/AdminDAOImpl:ds	Ljavax/sql/DataSource;
/*     */     //   3: invokeinterface 25 1 0
/*     */     //   8: astore 4
/*     */     //   10: aconst_null
/*     */     //   11: astore 5
/*     */     //   13: aconst_null
/*     */     //   14: astore 6
/*     */     //   16: new 244	com/groom/bean/Shine
/*     */     //   19: dup
/*     */     //   20: invokespecial 246	com/groom/bean/Shine:<init>	()V
/*     */     //   23: astore 7
/*     */     //   25: ldc -9
/*     */     //   27: astore 8
/*     */     //   29: aload 4
/*     */     //   31: aload 8
/*     */     //   33: invokeinterface 59 2 0
/*     */     //   38: astore 5
/*     */     //   40: aload 5
/*     */     //   42: iconst_1
/*     */     //   43: iload_1
/*     */     //   44: invokeinterface 71 3 0
/*     */     //   49: aload 5
/*     */     //   51: iconst_2
/*     */     //   52: aload_3
/*     */     //   53: invokeinterface 65 3 0
/*     */     //   58: aload 5
/*     */     //   60: iconst_3
/*     */     //   61: aload_2
/*     */     //   62: invokeinterface 65 3 0
/*     */     //   67: aload 5
/*     */     //   69: invokeinterface 126 1 0
/*     */     //   74: astore 6
/*     */     //   76: goto +286 -> 362
/*     */     //   79: aload 7
/*     */     //   81: aload 6
/*     */     //   83: ldc -25
/*     */     //   85: invokeinterface 146 2 0
/*     */     //   90: invokevirtual 249	com/groom/bean/Shine:setName	(Ljava/lang/String;)V
/*     */     //   93: aload 7
/*     */     //   95: aload 6
/*     */     //   97: ldc -4
/*     */     //   99: invokeinterface 132 2 0
/*     */     //   104: invokevirtual 254	com/groom/bean/Shine:setStandard	(I)V
/*     */     //   107: aload 7
/*     */     //   109: aload 6
/*     */     //   111: ldc_w 258
/*     */     //   114: invokeinterface 146 2 0
/*     */     //   119: invokevirtual 260	com/groom/bean/Shine:setRool_number	(Ljava/lang/String;)V
/*     */     //   122: aload 7
/*     */     //   124: aload 6
/*     */     //   126: ldc_w 263
/*     */     //   129: invokeinterface 132 2 0
/*     */     //   134: invokevirtual 265	com/groom/bean/Shine:setMa_right	(I)V
/*     */     //   137: aload 7
/*     */     //   139: aload 6
/*     */     //   141: ldc_w 268
/*     */     //   144: invokeinterface 132 2 0
/*     */     //   149: invokevirtual 270	com/groom/bean/Shine:setMa_ua	(I)V
/*     */     //   152: aload 7
/*     */     //   154: aload 6
/*     */     //   156: ldc_w 273
/*     */     //   159: invokeinterface 132 2 0
/*     */     //   164: invokevirtual 275	com/groom/bean/Shine:setMa_wrong	(I)V
/*     */     //   167: aload 7
/*     */     //   169: aload 6
/*     */     //   171: ldc_w 278
/*     */     //   174: invokeinterface 132 2 0
/*     */     //   179: invokevirtual 280	com/groom/bean/Shine:setB_right	(I)V
/*     */     //   182: aload 7
/*     */     //   184: aload 6
/*     */     //   186: ldc_w 283
/*     */     //   189: invokeinterface 132 2 0
/*     */     //   194: invokevirtual 285	com/groom/bean/Shine:setB_ua	(I)V
/*     */     //   197: aload 7
/*     */     //   199: aload 6
/*     */     //   201: ldc_w 288
/*     */     //   204: invokeinterface 132 2 0
/*     */     //   209: invokevirtual 290	com/groom/bean/Shine:setB_wrong	(I)V
/*     */     //   212: aload 7
/*     */     //   214: aload 6
/*     */     //   216: ldc_w 293
/*     */     //   219: invokeinterface 132 2 0
/*     */     //   224: invokevirtual 295	com/groom/bean/Shine:setM_right	(I)V
/*     */     //   227: aload 7
/*     */     //   229: aload 6
/*     */     //   231: ldc_w 298
/*     */     //   234: invokeinterface 132 2 0
/*     */     //   239: invokevirtual 300	com/groom/bean/Shine:setM_ua	(I)V
/*     */     //   242: aload 7
/*     */     //   244: aload 6
/*     */     //   246: ldc_w 303
/*     */     //   249: invokeinterface 132 2 0
/*     */     //   254: invokevirtual 305	com/groom/bean/Shine:setM_wrong	(I)V
/*     */     //   257: aload 7
/*     */     //   259: aload 6
/*     */     //   261: ldc_w 308
/*     */     //   264: invokeinterface 132 2 0
/*     */     //   269: invokevirtual 310	com/groom/bean/Shine:setPc_right	(I)V
/*     */     //   272: aload 7
/*     */     //   274: aload 6
/*     */     //   276: ldc_w 313
/*     */     //   279: invokeinterface 132 2 0
/*     */     //   284: invokevirtual 315	com/groom/bean/Shine:setPc_ua	(I)V
/*     */     //   287: aload 7
/*     */     //   289: aload 6
/*     */     //   291: ldc_w 318
/*     */     //   294: invokeinterface 132 2 0
/*     */     //   299: invokevirtual 320	com/groom/bean/Shine:setPc_wrong	(I)V
/*     */     //   302: aload 7
/*     */     //   304: aload 6
/*     */     //   306: ldc_w 323
/*     */     //   309: invokeinterface 132 2 0
/*     */     //   314: invokevirtual 325	com/groom/bean/Shine:setTotal_right	(I)V
/*     */     //   317: aload 7
/*     */     //   319: aload 6
/*     */     //   321: ldc_w 328
/*     */     //   324: invokeinterface 132 2 0
/*     */     //   329: invokevirtual 330	com/groom/bean/Shine:setTotal_ua	(I)V
/*     */     //   332: aload 7
/*     */     //   334: aload 6
/*     */     //   336: ldc_w 333
/*     */     //   339: invokeinterface 132 2 0
/*     */     //   344: invokevirtual 335	com/groom/bean/Shine:setTotal_wrong	(I)V
/*     */     //   347: aload 7
/*     */     //   349: aload 6
/*     */     //   351: ldc_w 338
/*     */     //   354: invokeinterface 132 2 0
/*     */     //   359: invokevirtual 340	com/groom/bean/Shine:setTotal_score	(I)V
/*     */     //   362: aload 6
/*     */     //   364: invokeinterface 154 1 0
/*     */     //   369: ifne -290 -> 79
/*     */     //   372: goto +66 -> 438
/*     */     //   375: astore 8
/*     */     //   377: aload 8
/*     */     //   379: invokevirtual 87	java/sql/SQLException:printStackTrace	()V
/*     */     //   382: aload 5
/*     */     //   384: ifnull +10 -> 394
/*     */     //   387: aload 5
/*     */     //   389: invokeinterface 83 1 0
/*     */     //   394: aload 4
/*     */     //   396: ifnull +66 -> 462
/*     */     //   399: aload 4
/*     */     //   401: invokeinterface 86 1 0
/*     */     //   406: goto +56 -> 462
/*     */     //   409: astore 9
/*     */     //   411: aload 5
/*     */     //   413: ifnull +10 -> 423
/*     */     //   416: aload 5
/*     */     //   418: invokeinterface 83 1 0
/*     */     //   423: aload 4
/*     */     //   425: ifnull +10 -> 435
/*     */     //   428: aload 4
/*     */     //   430: invokeinterface 86 1 0
/*     */     //   435: aload 9
/*     */     //   437: athrow
/*     */     //   438: aload 5
/*     */     //   440: ifnull +10 -> 450
/*     */     //   443: aload 5
/*     */     //   445: invokeinterface 83 1 0
/*     */     //   450: aload 4
/*     */     //   452: ifnull +10 -> 462
/*     */     //   455: aload 4
/*     */     //   457: invokeinterface 86 1 0
/*     */     //   462: aload 7
/*     */     //   464: areturn
/*     */     // Line number table:
/*     */     //   Java source line #240	-> byte code offset #0
/*     */     //   Java source line #241	-> byte code offset #10
/*     */     //   Java source line #242	-> byte code offset #13
/*     */     //   Java source line #243	-> byte code offset #16
/*     */     //   Java source line #245	-> byte code offset #25
/*     */     //   Java source line #247	-> byte code offset #29
/*     */     //   Java source line #248	-> byte code offset #40
/*     */     //   Java source line #249	-> byte code offset #49
/*     */     //   Java source line #250	-> byte code offset #58
/*     */     //   Java source line #251	-> byte code offset #67
/*     */     //   Java source line #252	-> byte code offset #76
/*     */     //   Java source line #253	-> byte code offset #79
/*     */     //   Java source line #254	-> byte code offset #93
/*     */     //   Java source line #255	-> byte code offset #107
/*     */     //   Java source line #256	-> byte code offset #122
/*     */     //   Java source line #257	-> byte code offset #137
/*     */     //   Java source line #258	-> byte code offset #152
/*     */     //   Java source line #259	-> byte code offset #167
/*     */     //   Java source line #260	-> byte code offset #182
/*     */     //   Java source line #261	-> byte code offset #197
/*     */     //   Java source line #262	-> byte code offset #212
/*     */     //   Java source line #263	-> byte code offset #227
/*     */     //   Java source line #264	-> byte code offset #242
/*     */     //   Java source line #265	-> byte code offset #257
/*     */     //   Java source line #266	-> byte code offset #272
/*     */     //   Java source line #267	-> byte code offset #287
/*     */     //   Java source line #268	-> byte code offset #302
/*     */     //   Java source line #269	-> byte code offset #317
/*     */     //   Java source line #270	-> byte code offset #332
/*     */     //   Java source line #271	-> byte code offset #347
/*     */     //   Java source line #252	-> byte code offset #362
/*     */     //   Java source line #274	-> byte code offset #372
/*     */     //   Java source line #275	-> byte code offset #377
/*     */     //   Java source line #278	-> byte code offset #382
/*     */     //   Java source line #279	-> byte code offset #387
/*     */     //   Java source line #280	-> byte code offset #394
/*     */     //   Java source line #281	-> byte code offset #399
/*     */     //   Java source line #276	-> byte code offset #409
/*     */     //   Java source line #278	-> byte code offset #411
/*     */     //   Java source line #279	-> byte code offset #416
/*     */     //   Java source line #280	-> byte code offset #423
/*     */     //   Java source line #281	-> byte code offset #428
/*     */     //   Java source line #282	-> byte code offset #435
/*     */     //   Java source line #278	-> byte code offset #438
/*     */     //   Java source line #279	-> byte code offset #443
/*     */     //   Java source line #280	-> byte code offset #450
/*     */     //   Java source line #281	-> byte code offset #455
/*     */     //   Java source line #283	-> byte code offset #462
/*     */     // Local variable table:
/*     */     //   start	length	slot	name	signature
/*     */     //   0	465	0	this	AdminDAOImpl
/*     */     //   0	465	1	standard	int
/*     */     //   0	465	2	school_code	String
/*     */     //   0	465	3	roll_number	String
/*     */     //   8	448	4	connection	Connection
/*     */     //   11	433	5	preparedStatement	PreparedStatement
/*     */     //   14	349	6	resultSet	java.sql.ResultSet
/*     */     //   23	440	7	result	com.groom.bean.Shine
/*     */     //   27	5	8	query	String
/*     */     //   375	3	8	exception	SQLException
/*     */     //   409	27	9	localObject	Object
/*     */     // Exception table:
/*     */     //   from	to	target	type
/*     */     //   25	372	375	java/sql/SQLException
/*     */     //   25	382	409	finally
/*     */   }
/*     */   
/*     */   /* Error */
/*     */   public java.util.HashMap<Integer, String> getTestCategories()
/*     */     throws SQLException
/*     */   {
/*     */     // Byte code:
/*     */     //   0: getstatic 21	com/groom/dao/impl/AdminDAOImpl:ds	Ljavax/sql/DataSource;
/*     */     //   3: invokeinterface 25 1 0
/*     */     //   8: astore_1
/*     */     //   9: aconst_null
/*     */     //   10: astore_2
/*     */     //   11: aconst_null
/*     */     //   12: astore_3
/*     */     //   13: new 119	java/util/HashMap
/*     */     //   16: dup
/*     */     //   17: invokespecial 121	java/util/HashMap:<init>	()V
/*     */     //   20: astore 4
/*     */     //   22: ldc_w 350
/*     */     //   25: astore 5
/*     */     //   27: aload_1
/*     */     //   28: aload 5
/*     */     //   30: invokeinterface 59 2 0
/*     */     //   35: astore_2
/*     */     //   36: aload_2
/*     */     //   37: invokeinterface 126 1 0
/*     */     //   42: astore_3
/*     */     //   43: goto +29 -> 72
/*     */     //   46: aload 4
/*     */     //   48: aload_3
/*     */     //   49: ldc_w 352
/*     */     //   52: invokeinterface 132 2 0
/*     */     //   57: invokestatic 138	java/lang/Integer:valueOf	(I)Ljava/lang/Integer;
/*     */     //   60: aload_3
/*     */     //   61: ldc -81
/*     */     //   63: invokeinterface 146 2 0
/*     */     //   68: invokevirtual 150	java/util/HashMap:put	(Ljava/lang/Object;Ljava/lang/Object;)Ljava/lang/Object;
/*     */     //   71: pop
/*     */     //   72: aload_3
/*     */     //   73: invokeinterface 154 1 0
/*     */     //   78: ifne -32 -> 46
/*     */     //   81: goto +58 -> 139
/*     */     //   84: astore 5
/*     */     //   86: aload 5
/*     */     //   88: invokevirtual 87	java/sql/SQLException:printStackTrace	()V
/*     */     //   91: aload_2
/*     */     //   92: ifnull +9 -> 101
/*     */     //   95: aload_2
/*     */     //   96: invokeinterface 83 1 0
/*     */     //   101: aload_1
/*     */     //   102: ifnull +57 -> 159
/*     */     //   105: aload_1
/*     */     //   106: invokeinterface 86 1 0
/*     */     //   111: goto +48 -> 159
/*     */     //   114: astore 6
/*     */     //   116: aload_2
/*     */     //   117: ifnull +9 -> 126
/*     */     //   120: aload_2
/*     */     //   121: invokeinterface 83 1 0
/*     */     //   126: aload_1
/*     */     //   127: ifnull +9 -> 136
/*     */     //   130: aload_1
/*     */     //   131: invokeinterface 86 1 0
/*     */     //   136: aload 6
/*     */     //   138: athrow
/*     */     //   139: aload_2
/*     */     //   140: ifnull +9 -> 149
/*     */     //   143: aload_2
/*     */     //   144: invokeinterface 83 1 0
/*     */     //   149: aload_1
/*     */     //   150: ifnull +9 -> 159
/*     */     //   153: aload_1
/*     */     //   154: invokeinterface 86 1 0
/*     */     //   159: aload 4
/*     */     //   161: areturn
/*     */     // Line number table:
/*     */     //   Java source line #288	-> byte code offset #0
/*     */     //   Java source line #289	-> byte code offset #9
/*     */     //   Java source line #290	-> byte code offset #11
/*     */     //   Java source line #291	-> byte code offset #13
/*     */     //   Java source line #293	-> byte code offset #22
/*     */     //   Java source line #295	-> byte code offset #27
/*     */     //   Java source line #296	-> byte code offset #36
/*     */     //   Java source line #297	-> byte code offset #43
/*     */     //   Java source line #298	-> byte code offset #46
/*     */     //   Java source line #297	-> byte code offset #72
/*     */     //   Java source line #301	-> byte code offset #81
/*     */     //   Java source line #302	-> byte code offset #86
/*     */     //   Java source line #305	-> byte code offset #91
/*     */     //   Java source line #306	-> byte code offset #95
/*     */     //   Java source line #307	-> byte code offset #101
/*     */     //   Java source line #308	-> byte code offset #105
/*     */     //   Java source line #303	-> byte code offset #114
/*     */     //   Java source line #305	-> byte code offset #116
/*     */     //   Java source line #306	-> byte code offset #120
/*     */     //   Java source line #307	-> byte code offset #126
/*     */     //   Java source line #308	-> byte code offset #130
/*     */     //   Java source line #309	-> byte code offset #136
/*     */     //   Java source line #305	-> byte code offset #139
/*     */     //   Java source line #306	-> byte code offset #143
/*     */     //   Java source line #307	-> byte code offset #149
/*     */     //   Java source line #308	-> byte code offset #153
/*     */     //   Java source line #310	-> byte code offset #159
/*     */     // Local variable table:
/*     */     //   start	length	slot	name	signature
/*     */     //   0	162	0	this	AdminDAOImpl
/*     */     //   8	146	1	connection	Connection
/*     */     //   10	134	2	preparedStatement	PreparedStatement
/*     */     //   12	61	3	resultSet	java.sql.ResultSet
/*     */     //   20	140	4	categories	java.util.HashMap<Integer, String>
/*     */     //   25	4	5	query	String
/*     */     //   84	3	5	exception	SQLException
/*     */     //   114	23	6	localObject	Object
/*     */     // Exception table:
/*     */     //   from	to	target	type
/*     */     //   22	81	84	java/sql/SQLException
/*     */     //   22	91	114	finally
/*     */   }
/*     */   
/*     */   public boolean saveVideoURL(int standard, String subject, String title, String description, String url)
/*     */     throws SQLException
/*     */   {
/* 315 */     Connection connection = ds.getConnection();
/* 316 */     PreparedStatement preparedStatement = null;
/*     */     try
/*     */     {
/* 319 */       String query = "INSERT INTO VIDEOS_INFO (STANDARD,SUBJECT,TITLE,DESCRIPTION,URL) VALUES(?,?,?,?,?)";
/* 320 */       System.out.println(query);
/* 321 */       preparedStatement = connection.prepareStatement(query);
/*     */       
/* 323 */       preparedStatement.setInt(1, standard);
/* 324 */       preparedStatement.setString(2, subject);
/* 325 */       preparedStatement.setString(3, title);
/* 326 */       preparedStatement.setString(4, description);
/* 327 */       preparedStatement.setString(5, url);
/* 328 */       int status = preparedStatement.executeUpdate();
/* 329 */       if (status == 1)
/* 330 */         return true;
/*     */     } catch (SQLException exception) {
/* 332 */       exception.printStackTrace();
/*     */     }
/*     */     finally {
/* 335 */       if (preparedStatement != null)
/* 336 */         preparedStatement.close();
/* 337 */       if (connection != null) {
/* 338 */         connection.close();
/*     */       }
/*     */     }
/* 335 */     if (preparedStatement != null)
/* 336 */       preparedStatement.close();
/* 337 */     if (connection != null) {
/* 338 */       connection.close();
/*     */     }
/* 340 */     return false;
/*     */   }
/*     */   
/*     */   /* Error */
/*     */   public java.util.List<com.groom.bean.Video> getAllVideos()
/*     */     throws SQLException
/*     */   {
/*     */     // Byte code:
/*     */     //   0: getstatic 21	com/groom/dao/impl/AdminDAOImpl:ds	Ljavax/sql/DataSource;
/*     */     //   3: invokeinterface 25 1 0
/*     */     //   8: astore_1
/*     */     //   9: aconst_null
/*     */     //   10: astore_2
/*     */     //   11: aconst_null
/*     */     //   12: astore_3
/*     */     //   13: new 226	java/util/ArrayList
/*     */     //   16: dup
/*     */     //   17: invokespecial 228	java/util/ArrayList:<init>	()V
/*     */     //   20: astore 4
/*     */     //   22: ldc_w 364
/*     */     //   25: astore 5
/*     */     //   27: aload_1
/*     */     //   28: aload 5
/*     */     //   30: invokeinterface 59 2 0
/*     */     //   35: astore_2
/*     */     //   36: aload_2
/*     */     //   37: invokeinterface 126 1 0
/*     */     //   42: astore_3
/*     */     //   43: goto +106 -> 149
/*     */     //   46: new 366	com/groom/bean/Video
/*     */     //   49: dup
/*     */     //   50: invokespecial 368	com/groom/bean/Video:<init>	()V
/*     */     //   53: astore 6
/*     */     //   55: aload 6
/*     */     //   57: aload_3
/*     */     //   58: ldc_w 369
/*     */     //   61: invokeinterface 132 2 0
/*     */     //   66: invokevirtual 371	com/groom/bean/Video:setId	(I)V
/*     */     //   69: aload 6
/*     */     //   71: aload_3
/*     */     //   72: ldc_w 374
/*     */     //   75: invokeinterface 132 2 0
/*     */     //   80: invokevirtual 376	com/groom/bean/Video:setStandard	(I)V
/*     */     //   83: aload 6
/*     */     //   85: aload_3
/*     */     //   86: ldc_w 377
/*     */     //   89: invokeinterface 146 2 0
/*     */     //   94: invokevirtual 379	com/groom/bean/Video:setSubject	(Ljava/lang/String;)V
/*     */     //   97: aload 6
/*     */     //   99: aload_3
/*     */     //   100: ldc_w 382
/*     */     //   103: invokeinterface 146 2 0
/*     */     //   108: invokevirtual 384	com/groom/bean/Video:setTitle	(Ljava/lang/String;)V
/*     */     //   111: aload 6
/*     */     //   113: aload_3
/*     */     //   114: ldc_w 387
/*     */     //   117: invokeinterface 146 2 0
/*     */     //   122: invokevirtual 389	com/groom/bean/Video:setDescription	(Ljava/lang/String;)V
/*     */     //   125: aload 6
/*     */     //   127: aload_3
/*     */     //   128: ldc_w 392
/*     */     //   131: invokeinterface 146 2 0
/*     */     //   136: invokevirtual 394	com/groom/bean/Video:setUrl	(Ljava/lang/String;)V
/*     */     //   139: aload 4
/*     */     //   141: aload 6
/*     */     //   143: invokeinterface 233 2 0
/*     */     //   148: pop
/*     */     //   149: aload_3
/*     */     //   150: invokeinterface 154 1 0
/*     */     //   155: ifne -109 -> 46
/*     */     //   158: goto +78 -> 236
/*     */     //   161: astore 5
/*     */     //   163: aload 5
/*     */     //   165: invokevirtual 87	java/sql/SQLException:printStackTrace	()V
/*     */     //   168: aload_3
/*     */     //   169: ifnull +9 -> 178
/*     */     //   172: aload_3
/*     */     //   173: invokeinterface 397 1 0
/*     */     //   178: aload_2
/*     */     //   179: ifnull +9 -> 188
/*     */     //   182: aload_2
/*     */     //   183: invokeinterface 83 1 0
/*     */     //   188: aload_1
/*     */     //   189: ifnull +77 -> 266
/*     */     //   192: aload_1
/*     */     //   193: invokeinterface 86 1 0
/*     */     //   198: goto +68 -> 266
/*     */     //   201: astore 7
/*     */     //   203: aload_3
/*     */     //   204: ifnull +9 -> 213
/*     */     //   207: aload_3
/*     */     //   208: invokeinterface 397 1 0
/*     */     //   213: aload_2
/*     */     //   214: ifnull +9 -> 223
/*     */     //   217: aload_2
/*     */     //   218: invokeinterface 83 1 0
/*     */     //   223: aload_1
/*     */     //   224: ifnull +9 -> 233
/*     */     //   227: aload_1
/*     */     //   228: invokeinterface 86 1 0
/*     */     //   233: aload 7
/*     */     //   235: athrow
/*     */     //   236: aload_3
/*     */     //   237: ifnull +9 -> 246
/*     */     //   240: aload_3
/*     */     //   241: invokeinterface 397 1 0
/*     */     //   246: aload_2
/*     */     //   247: ifnull +9 -> 256
/*     */     //   250: aload_2
/*     */     //   251: invokeinterface 83 1 0
/*     */     //   256: aload_1
/*     */     //   257: ifnull +9 -> 266
/*     */     //   260: aload_1
/*     */     //   261: invokeinterface 86 1 0
/*     */     //   266: aload 4
/*     */     //   268: areturn
/*     */     // Line number table:
/*     */     //   Java source line #345	-> byte code offset #0
/*     */     //   Java source line #346	-> byte code offset #9
/*     */     //   Java source line #347	-> byte code offset #11
/*     */     //   Java source line #348	-> byte code offset #13
/*     */     //   Java source line #350	-> byte code offset #22
/*     */     //   Java source line #351	-> byte code offset #27
/*     */     //   Java source line #353	-> byte code offset #36
/*     */     //   Java source line #354	-> byte code offset #43
/*     */     //   Java source line #355	-> byte code offset #46
/*     */     //   Java source line #357	-> byte code offset #55
/*     */     //   Java source line #358	-> byte code offset #69
/*     */     //   Java source line #359	-> byte code offset #83
/*     */     //   Java source line #360	-> byte code offset #97
/*     */     //   Java source line #361	-> byte code offset #111
/*     */     //   Java source line #362	-> byte code offset #125
/*     */     //   Java source line #363	-> byte code offset #139
/*     */     //   Java source line #354	-> byte code offset #149
/*     */     //   Java source line #367	-> byte code offset #158
/*     */     //   Java source line #368	-> byte code offset #163
/*     */     //   Java source line #370	-> byte code offset #168
/*     */     //   Java source line #371	-> byte code offset #172
/*     */     //   Java source line #372	-> byte code offset #178
/*     */     //   Java source line #373	-> byte code offset #182
/*     */     //   Java source line #374	-> byte code offset #188
/*     */     //   Java source line #375	-> byte code offset #192
/*     */     //   Java source line #369	-> byte code offset #201
/*     */     //   Java source line #370	-> byte code offset #203
/*     */     //   Java source line #371	-> byte code offset #207
/*     */     //   Java source line #372	-> byte code offset #213
/*     */     //   Java source line #373	-> byte code offset #217
/*     */     //   Java source line #374	-> byte code offset #223
/*     */     //   Java source line #375	-> byte code offset #227
/*     */     //   Java source line #376	-> byte code offset #233
/*     */     //   Java source line #370	-> byte code offset #236
/*     */     //   Java source line #371	-> byte code offset #240
/*     */     //   Java source line #372	-> byte code offset #246
/*     */     //   Java source line #373	-> byte code offset #250
/*     */     //   Java source line #374	-> byte code offset #256
/*     */     //   Java source line #375	-> byte code offset #260
/*     */     //   Java source line #377	-> byte code offset #266
/*     */     // Local variable table:
/*     */     //   start	length	slot	name	signature
/*     */     //   0	269	0	this	AdminDAOImpl
/*     */     //   8	253	1	connection	Connection
/*     */     //   10	241	2	preparedStatement	PreparedStatement
/*     */     //   12	229	3	resultSet	java.sql.ResultSet
/*     */     //   20	247	4	videos	java.util.List<com.groom.bean.Video>
/*     */     //   25	4	5	query	String
/*     */     //   161	3	5	exception	SQLException
/*     */     //   53	89	6	video	com.groom.bean.Video
/*     */     //   201	33	7	localObject	Object
/*     */     // Exception table:
/*     */     //   from	to	target	type
/*     */     //   22	158	161	java/sql/SQLException
/*     */     //   22	168	201	finally
/*     */   }
/*     */   
/*     */   /* Error */
/*     */   public com.groom.bean.Video getVideoById(int id)
/*     */     throws SQLException
/*     */   {
/*     */     // Byte code:
/*     */     //   0: getstatic 21	com/groom/dao/impl/AdminDAOImpl:ds	Ljavax/sql/DataSource;
/*     */     //   3: invokeinterface 25 1 0
/*     */     //   8: astore_2
/*     */     //   9: aconst_null
/*     */     //   10: astore_3
/*     */     //   11: aconst_null
/*     */     //   12: astore 4
/*     */     //   14: new 366	com/groom/bean/Video
/*     */     //   17: dup
/*     */     //   18: invokespecial 368	com/groom/bean/Video:<init>	()V
/*     */     //   21: astore 5
/*     */     //   23: ldc_w 404
/*     */     //   26: astore 6
/*     */     //   28: aload_2
/*     */     //   29: aload 6
/*     */     //   31: invokeinterface 59 2 0
/*     */     //   36: astore_3
/*     */     //   37: aload_3
/*     */     //   38: iconst_1
/*     */     //   39: iload_1
/*     */     //   40: invokeinterface 71 3 0
/*     */     //   45: aload_3
/*     */     //   46: invokeinterface 126 1 0
/*     */     //   51: astore 4
/*     */     //   53: goto +93 -> 146
/*     */     //   56: aload 5
/*     */     //   58: aload 4
/*     */     //   60: ldc_w 369
/*     */     //   63: invokeinterface 132 2 0
/*     */     //   68: invokevirtual 371	com/groom/bean/Video:setId	(I)V
/*     */     //   71: aload 5
/*     */     //   73: aload 4
/*     */     //   75: ldc_w 374
/*     */     //   78: invokeinterface 132 2 0
/*     */     //   83: invokevirtual 376	com/groom/bean/Video:setStandard	(I)V
/*     */     //   86: aload 5
/*     */     //   88: aload 4
/*     */     //   90: ldc_w 377
/*     */     //   93: invokeinterface 146 2 0
/*     */     //   98: invokevirtual 379	com/groom/bean/Video:setSubject	(Ljava/lang/String;)V
/*     */     //   101: aload 5
/*     */     //   103: aload 4
/*     */     //   105: ldc_w 382
/*     */     //   108: invokeinterface 146 2 0
/*     */     //   113: invokevirtual 384	com/groom/bean/Video:setTitle	(Ljava/lang/String;)V
/*     */     //   116: aload 5
/*     */     //   118: aload 4
/*     */     //   120: ldc_w 387
/*     */     //   123: invokeinterface 146 2 0
/*     */     //   128: invokevirtual 389	com/groom/bean/Video:setDescription	(Ljava/lang/String;)V
/*     */     //   131: aload 5
/*     */     //   133: aload 4
/*     */     //   135: ldc_w 392
/*     */     //   138: invokeinterface 146 2 0
/*     */     //   143: invokevirtual 394	com/groom/bean/Video:setUrl	(Ljava/lang/String;)V
/*     */     //   146: aload 4
/*     */     //   148: invokeinterface 154 1 0
/*     */     //   153: ifne -97 -> 56
/*     */     //   156: goto +82 -> 238
/*     */     //   159: astore 6
/*     */     //   161: aload 6
/*     */     //   163: invokevirtual 87	java/sql/SQLException:printStackTrace	()V
/*     */     //   166: aload 4
/*     */     //   168: ifnull +10 -> 178
/*     */     //   171: aload 4
/*     */     //   173: invokeinterface 397 1 0
/*     */     //   178: aload_3
/*     */     //   179: ifnull +9 -> 188
/*     */     //   182: aload_3
/*     */     //   183: invokeinterface 83 1 0
/*     */     //   188: aload_2
/*     */     //   189: ifnull +81 -> 270
/*     */     //   192: aload_2
/*     */     //   193: invokeinterface 86 1 0
/*     */     //   198: goto +72 -> 270
/*     */     //   201: astore 7
/*     */     //   203: aload 4
/*     */     //   205: ifnull +10 -> 215
/*     */     //   208: aload 4
/*     */     //   210: invokeinterface 397 1 0
/*     */     //   215: aload_3
/*     */     //   216: ifnull +9 -> 225
/*     */     //   219: aload_3
/*     */     //   220: invokeinterface 83 1 0
/*     */     //   225: aload_2
/*     */     //   226: ifnull +9 -> 235
/*     */     //   229: aload_2
/*     */     //   230: invokeinterface 86 1 0
/*     */     //   235: aload 7
/*     */     //   237: athrow
/*     */     //   238: aload 4
/*     */     //   240: ifnull +10 -> 250
/*     */     //   243: aload 4
/*     */     //   245: invokeinterface 397 1 0
/*     */     //   250: aload_3
/*     */     //   251: ifnull +9 -> 260
/*     */     //   254: aload_3
/*     */     //   255: invokeinterface 83 1 0
/*     */     //   260: aload_2
/*     */     //   261: ifnull +9 -> 270
/*     */     //   264: aload_2
/*     */     //   265: invokeinterface 86 1 0
/*     */     //   270: aload 5
/*     */     //   272: areturn
/*     */     // Line number table:
/*     */     //   Java source line #382	-> byte code offset #0
/*     */     //   Java source line #383	-> byte code offset #9
/*     */     //   Java source line #384	-> byte code offset #11
/*     */     //   Java source line #385	-> byte code offset #14
/*     */     //   Java source line #387	-> byte code offset #23
/*     */     //   Java source line #388	-> byte code offset #28
/*     */     //   Java source line #389	-> byte code offset #37
/*     */     //   Java source line #390	-> byte code offset #45
/*     */     //   Java source line #391	-> byte code offset #53
/*     */     //   Java source line #394	-> byte code offset #56
/*     */     //   Java source line #395	-> byte code offset #71
/*     */     //   Java source line #396	-> byte code offset #86
/*     */     //   Java source line #397	-> byte code offset #101
/*     */     //   Java source line #398	-> byte code offset #116
/*     */     //   Java source line #399	-> byte code offset #131
/*     */     //   Java source line #391	-> byte code offset #146
/*     */     //   Java source line #403	-> byte code offset #156
/*     */     //   Java source line #404	-> byte code offset #161
/*     */     //   Java source line #406	-> byte code offset #166
/*     */     //   Java source line #407	-> byte code offset #171
/*     */     //   Java source line #408	-> byte code offset #178
/*     */     //   Java source line #409	-> byte code offset #182
/*     */     //   Java source line #410	-> byte code offset #188
/*     */     //   Java source line #411	-> byte code offset #192
/*     */     //   Java source line #405	-> byte code offset #201
/*     */     //   Java source line #406	-> byte code offset #203
/*     */     //   Java source line #407	-> byte code offset #208
/*     */     //   Java source line #408	-> byte code offset #215
/*     */     //   Java source line #409	-> byte code offset #219
/*     */     //   Java source line #410	-> byte code offset #225
/*     */     //   Java source line #411	-> byte code offset #229
/*     */     //   Java source line #412	-> byte code offset #235
/*     */     //   Java source line #406	-> byte code offset #238
/*     */     //   Java source line #407	-> byte code offset #243
/*     */     //   Java source line #408	-> byte code offset #250
/*     */     //   Java source line #409	-> byte code offset #254
/*     */     //   Java source line #410	-> byte code offset #260
/*     */     //   Java source line #411	-> byte code offset #264
/*     */     //   Java source line #413	-> byte code offset #270
/*     */     // Local variable table:
/*     */     //   start	length	slot	name	signature
/*     */     //   0	273	0	this	AdminDAOImpl
/*     */     //   0	273	1	id	int
/*     */     //   8	257	2	connection	Connection
/*     */     //   10	245	3	preparedStatement	PreparedStatement
/*     */     //   12	232	4	resultSet	java.sql.ResultSet
/*     */     //   21	250	5	video	com.groom.bean.Video
/*     */     //   26	4	6	query	String
/*     */     //   159	3	6	exception	SQLException
/*     */     //   201	35	7	localObject	Object
/*     */     // Exception table:
/*     */     //   from	to	target	type
/*     */     //   23	156	159	java/sql/SQLException
/*     */     //   23	166	201	finally
/*     */   }
/*     */   
/*     */   /* Error */
/*     */   public java.util.List<com.groom.bean.Video> getAllVideosBySubject(String subject)
/*     */     throws SQLException
/*     */   {
/*     */     // Byte code:
/*     */     //   0: getstatic 21	com/groom/dao/impl/AdminDAOImpl:ds	Ljavax/sql/DataSource;
/*     */     //   3: invokeinterface 25 1 0
/*     */     //   8: astore_2
/*     */     //   9: aconst_null
/*     */     //   10: astore_3
/*     */     //   11: aconst_null
/*     */     //   12: astore 4
/*     */     //   14: new 226	java/util/ArrayList
/*     */     //   17: dup
/*     */     //   18: invokespecial 228	java/util/ArrayList:<init>	()V
/*     */     //   21: astore 5
/*     */     //   23: ldc_w 410
/*     */     //   26: astore 6
/*     */     //   28: aload_2
/*     */     //   29: aload 6
/*     */     //   31: invokeinterface 59 2 0
/*     */     //   36: astore_3
/*     */     //   37: aload_3
/*     */     //   38: iconst_1
/*     */     //   39: aload_1
/*     */     //   40: invokeinterface 65 3 0
/*     */     //   45: aload_3
/*     */     //   46: invokeinterface 126 1 0
/*     */     //   51: astore 4
/*     */     //   53: goto +112 -> 165
/*     */     //   56: new 366	com/groom/bean/Video
/*     */     //   59: dup
/*     */     //   60: invokespecial 368	com/groom/bean/Video:<init>	()V
/*     */     //   63: astore 7
/*     */     //   65: aload 7
/*     */     //   67: aload 4
/*     */     //   69: ldc_w 369
/*     */     //   72: invokeinterface 132 2 0
/*     */     //   77: invokevirtual 371	com/groom/bean/Video:setId	(I)V
/*     */     //   80: aload 7
/*     */     //   82: aload 4
/*     */     //   84: ldc_w 374
/*     */     //   87: invokeinterface 132 2 0
/*     */     //   92: invokevirtual 376	com/groom/bean/Video:setStandard	(I)V
/*     */     //   95: aload 7
/*     */     //   97: aload 4
/*     */     //   99: ldc_w 377
/*     */     //   102: invokeinterface 146 2 0
/*     */     //   107: invokevirtual 379	com/groom/bean/Video:setSubject	(Ljava/lang/String;)V
/*     */     //   110: aload 7
/*     */     //   112: aload 4
/*     */     //   114: ldc_w 382
/*     */     //   117: invokeinterface 146 2 0
/*     */     //   122: invokevirtual 384	com/groom/bean/Video:setTitle	(Ljava/lang/String;)V
/*     */     //   125: aload 7
/*     */     //   127: aload 4
/*     */     //   129: ldc_w 387
/*     */     //   132: invokeinterface 146 2 0
/*     */     //   137: invokevirtual 389	com/groom/bean/Video:setDescription	(Ljava/lang/String;)V
/*     */     //   140: aload 7
/*     */     //   142: aload 4
/*     */     //   144: ldc_w 392
/*     */     //   147: invokeinterface 146 2 0
/*     */     //   152: invokevirtual 394	com/groom/bean/Video:setUrl	(Ljava/lang/String;)V
/*     */     //   155: aload 5
/*     */     //   157: aload 7
/*     */     //   159: invokeinterface 233 2 0
/*     */     //   164: pop
/*     */     //   165: aload 4
/*     */     //   167: invokeinterface 154 1 0
/*     */     //   172: ifne -116 -> 56
/*     */     //   175: goto +82 -> 257
/*     */     //   178: astore 6
/*     */     //   180: aload 6
/*     */     //   182: invokevirtual 87	java/sql/SQLException:printStackTrace	()V
/*     */     //   185: aload 4
/*     */     //   187: ifnull +10 -> 197
/*     */     //   190: aload 4
/*     */     //   192: invokeinterface 397 1 0
/*     */     //   197: aload_3
/*     */     //   198: ifnull +9 -> 207
/*     */     //   201: aload_3
/*     */     //   202: invokeinterface 83 1 0
/*     */     //   207: aload_2
/*     */     //   208: ifnull +81 -> 289
/*     */     //   211: aload_2
/*     */     //   212: invokeinterface 86 1 0
/*     */     //   217: goto +72 -> 289
/*     */     //   220: astore 8
/*     */     //   222: aload 4
/*     */     //   224: ifnull +10 -> 234
/*     */     //   227: aload 4
/*     */     //   229: invokeinterface 397 1 0
/*     */     //   234: aload_3
/*     */     //   235: ifnull +9 -> 244
/*     */     //   238: aload_3
/*     */     //   239: invokeinterface 83 1 0
/*     */     //   244: aload_2
/*     */     //   245: ifnull +9 -> 254
/*     */     //   248: aload_2
/*     */     //   249: invokeinterface 86 1 0
/*     */     //   254: aload 8
/*     */     //   256: athrow
/*     */     //   257: aload 4
/*     */     //   259: ifnull +10 -> 269
/*     */     //   262: aload 4
/*     */     //   264: invokeinterface 397 1 0
/*     */     //   269: aload_3
/*     */     //   270: ifnull +9 -> 279
/*     */     //   273: aload_3
/*     */     //   274: invokeinterface 83 1 0
/*     */     //   279: aload_2
/*     */     //   280: ifnull +9 -> 289
/*     */     //   283: aload_2
/*     */     //   284: invokeinterface 86 1 0
/*     */     //   289: aload 5
/*     */     //   291: areturn
/*     */     // Line number table:
/*     */     //   Java source line #418	-> byte code offset #0
/*     */     //   Java source line #419	-> byte code offset #9
/*     */     //   Java source line #420	-> byte code offset #11
/*     */     //   Java source line #421	-> byte code offset #14
/*     */     //   Java source line #423	-> byte code offset #23
/*     */     //   Java source line #424	-> byte code offset #28
/*     */     //   Java source line #425	-> byte code offset #37
/*     */     //   Java source line #427	-> byte code offset #45
/*     */     //   Java source line #428	-> byte code offset #53
/*     */     //   Java source line #429	-> byte code offset #56
/*     */     //   Java source line #431	-> byte code offset #65
/*     */     //   Java source line #432	-> byte code offset #80
/*     */     //   Java source line #433	-> byte code offset #95
/*     */     //   Java source line #434	-> byte code offset #110
/*     */     //   Java source line #435	-> byte code offset #125
/*     */     //   Java source line #436	-> byte code offset #140
/*     */     //   Java source line #437	-> byte code offset #155
/*     */     //   Java source line #428	-> byte code offset #165
/*     */     //   Java source line #441	-> byte code offset #175
/*     */     //   Java source line #442	-> byte code offset #180
/*     */     //   Java source line #444	-> byte code offset #185
/*     */     //   Java source line #445	-> byte code offset #190
/*     */     //   Java source line #446	-> byte code offset #197
/*     */     //   Java source line #447	-> byte code offset #201
/*     */     //   Java source line #448	-> byte code offset #207
/*     */     //   Java source line #449	-> byte code offset #211
/*     */     //   Java source line #443	-> byte code offset #220
/*     */     //   Java source line #444	-> byte code offset #222
/*     */     //   Java source line #445	-> byte code offset #227
/*     */     //   Java source line #446	-> byte code offset #234
/*     */     //   Java source line #447	-> byte code offset #238
/*     */     //   Java source line #448	-> byte code offset #244
/*     */     //   Java source line #449	-> byte code offset #248
/*     */     //   Java source line #450	-> byte code offset #254
/*     */     //   Java source line #444	-> byte code offset #257
/*     */     //   Java source line #445	-> byte code offset #262
/*     */     //   Java source line #446	-> byte code offset #269
/*     */     //   Java source line #447	-> byte code offset #273
/*     */     //   Java source line #448	-> byte code offset #279
/*     */     //   Java source line #449	-> byte code offset #283
/*     */     //   Java source line #451	-> byte code offset #289
/*     */     // Local variable table:
/*     */     //   start	length	slot	name	signature
/*     */     //   0	292	0	this	AdminDAOImpl
/*     */     //   0	292	1	subject	String
/*     */     //   8	276	2	connection	Connection
/*     */     //   10	264	3	preparedStatement	PreparedStatement
/*     */     //   12	251	4	resultSet	java.sql.ResultSet
/*     */     //   21	269	5	videos	java.util.List<com.groom.bean.Video>
/*     */     //   26	4	6	query	String
/*     */     //   178	3	6	exception	SQLException
/*     */     //   63	95	7	video	com.groom.bean.Video
/*     */     //   220	35	8	localObject	Object
/*     */     // Exception table:
/*     */     //   from	to	target	type
/*     */     //   23	175	178	java/sql/SQLException
/*     */     //   23	185	220	finally
/*     */   }
/*     */   
/*     */   /* Error */
/*     */   public java.util.List<com.groom.bean.Video> getAllVideosByStandard(int standard)
/*     */     throws SQLException
/*     */   {
/*     */     // Byte code:
/*     */     //   0: getstatic 21	com/groom/dao/impl/AdminDAOImpl:ds	Ljavax/sql/DataSource;
/*     */     //   3: invokeinterface 25 1 0
/*     */     //   8: astore_2
/*     */     //   9: aconst_null
/*     */     //   10: astore_3
/*     */     //   11: aconst_null
/*     */     //   12: astore 4
/*     */     //   14: new 226	java/util/ArrayList
/*     */     //   17: dup
/*     */     //   18: invokespecial 228	java/util/ArrayList:<init>	()V
/*     */     //   21: astore 5
/*     */     //   23: ldc_w 415
/*     */     //   26: astore 6
/*     */     //   28: aload_2
/*     */     //   29: aload 6
/*     */     //   31: invokeinterface 59 2 0
/*     */     //   36: astore_3
/*     */     //   37: aload_3
/*     */     //   38: iconst_1
/*     */     //   39: iload_1
/*     */     //   40: invokeinterface 71 3 0
/*     */     //   45: aload_3
/*     */     //   46: invokeinterface 126 1 0
/*     */     //   51: astore 4
/*     */     //   53: goto +112 -> 165
/*     */     //   56: new 366	com/groom/bean/Video
/*     */     //   59: dup
/*     */     //   60: invokespecial 368	com/groom/bean/Video:<init>	()V
/*     */     //   63: astore 7
/*     */     //   65: aload 7
/*     */     //   67: aload 4
/*     */     //   69: ldc_w 369
/*     */     //   72: invokeinterface 132 2 0
/*     */     //   77: invokevirtual 371	com/groom/bean/Video:setId	(I)V
/*     */     //   80: aload 7
/*     */     //   82: aload 4
/*     */     //   84: ldc_w 374
/*     */     //   87: invokeinterface 132 2 0
/*     */     //   92: invokevirtual 376	com/groom/bean/Video:setStandard	(I)V
/*     */     //   95: aload 7
/*     */     //   97: aload 4
/*     */     //   99: ldc_w 377
/*     */     //   102: invokeinterface 146 2 0
/*     */     //   107: invokevirtual 379	com/groom/bean/Video:setSubject	(Ljava/lang/String;)V
/*     */     //   110: aload 7
/*     */     //   112: aload 4
/*     */     //   114: ldc_w 382
/*     */     //   117: invokeinterface 146 2 0
/*     */     //   122: invokevirtual 384	com/groom/bean/Video:setTitle	(Ljava/lang/String;)V
/*     */     //   125: aload 7
/*     */     //   127: aload 4
/*     */     //   129: ldc_w 387
/*     */     //   132: invokeinterface 146 2 0
/*     */     //   137: invokevirtual 389	com/groom/bean/Video:setDescription	(Ljava/lang/String;)V
/*     */     //   140: aload 7
/*     */     //   142: aload 4
/*     */     //   144: ldc_w 392
/*     */     //   147: invokeinterface 146 2 0
/*     */     //   152: invokevirtual 394	com/groom/bean/Video:setUrl	(Ljava/lang/String;)V
/*     */     //   155: aload 5
/*     */     //   157: aload 7
/*     */     //   159: invokeinterface 233 2 0
/*     */     //   164: pop
/*     */     //   165: aload 4
/*     */     //   167: invokeinterface 154 1 0
/*     */     //   172: ifne -116 -> 56
/*     */     //   175: goto +82 -> 257
/*     */     //   178: astore 6
/*     */     //   180: aload 6
/*     */     //   182: invokevirtual 87	java/sql/SQLException:printStackTrace	()V
/*     */     //   185: aload 4
/*     */     //   187: ifnull +10 -> 197
/*     */     //   190: aload 4
/*     */     //   192: invokeinterface 397 1 0
/*     */     //   197: aload_3
/*     */     //   198: ifnull +9 -> 207
/*     */     //   201: aload_3
/*     */     //   202: invokeinterface 83 1 0
/*     */     //   207: aload_2
/*     */     //   208: ifnull +81 -> 289
/*     */     //   211: aload_2
/*     */     //   212: invokeinterface 86 1 0
/*     */     //   217: goto +72 -> 289
/*     */     //   220: astore 8
/*     */     //   222: aload 4
/*     */     //   224: ifnull +10 -> 234
/*     */     //   227: aload 4
/*     */     //   229: invokeinterface 397 1 0
/*     */     //   234: aload_3
/*     */     //   235: ifnull +9 -> 244
/*     */     //   238: aload_3
/*     */     //   239: invokeinterface 83 1 0
/*     */     //   244: aload_2
/*     */     //   245: ifnull +9 -> 254
/*     */     //   248: aload_2
/*     */     //   249: invokeinterface 86 1 0
/*     */     //   254: aload 8
/*     */     //   256: athrow
/*     */     //   257: aload 4
/*     */     //   259: ifnull +10 -> 269
/*     */     //   262: aload 4
/*     */     //   264: invokeinterface 397 1 0
/*     */     //   269: aload_3
/*     */     //   270: ifnull +9 -> 279
/*     */     //   273: aload_3
/*     */     //   274: invokeinterface 83 1 0
/*     */     //   279: aload_2
/*     */     //   280: ifnull +9 -> 289
/*     */     //   283: aload_2
/*     */     //   284: invokeinterface 86 1 0
/*     */     //   289: aload 5
/*     */     //   291: areturn
/*     */     // Line number table:
/*     */     //   Java source line #456	-> byte code offset #0
/*     */     //   Java source line #457	-> byte code offset #9
/*     */     //   Java source line #458	-> byte code offset #11
/*     */     //   Java source line #459	-> byte code offset #14
/*     */     //   Java source line #461	-> byte code offset #23
/*     */     //   Java source line #462	-> byte code offset #28
/*     */     //   Java source line #463	-> byte code offset #37
/*     */     //   Java source line #465	-> byte code offset #45
/*     */     //   Java source line #466	-> byte code offset #53
/*     */     //   Java source line #467	-> byte code offset #56
/*     */     //   Java source line #469	-> byte code offset #65
/*     */     //   Java source line #470	-> byte code offset #80
/*     */     //   Java source line #471	-> byte code offset #95
/*     */     //   Java source line #472	-> byte code offset #110
/*     */     //   Java source line #473	-> byte code offset #125
/*     */     //   Java source line #474	-> byte code offset #140
/*     */     //   Java source line #475	-> byte code offset #155
/*     */     //   Java source line #466	-> byte code offset #165
/*     */     //   Java source line #479	-> byte code offset #175
/*     */     //   Java source line #480	-> byte code offset #180
/*     */     //   Java source line #482	-> byte code offset #185
/*     */     //   Java source line #483	-> byte code offset #190
/*     */     //   Java source line #484	-> byte code offset #197
/*     */     //   Java source line #485	-> byte code offset #201
/*     */     //   Java source line #486	-> byte code offset #207
/*     */     //   Java source line #487	-> byte code offset #211
/*     */     //   Java source line #481	-> byte code offset #220
/*     */     //   Java source line #482	-> byte code offset #222
/*     */     //   Java source line #483	-> byte code offset #227
/*     */     //   Java source line #484	-> byte code offset #234
/*     */     //   Java source line #485	-> byte code offset #238
/*     */     //   Java source line #486	-> byte code offset #244
/*     */     //   Java source line #487	-> byte code offset #248
/*     */     //   Java source line #488	-> byte code offset #254
/*     */     //   Java source line #482	-> byte code offset #257
/*     */     //   Java source line #483	-> byte code offset #262
/*     */     //   Java source line #484	-> byte code offset #269
/*     */     //   Java source line #485	-> byte code offset #273
/*     */     //   Java source line #486	-> byte code offset #279
/*     */     //   Java source line #487	-> byte code offset #283
/*     */     //   Java source line #489	-> byte code offset #289
/*     */     // Local variable table:
/*     */     //   start	length	slot	name	signature
/*     */     //   0	292	0	this	AdminDAOImpl
/*     */     //   0	292	1	standard	int
/*     */     //   8	276	2	connection	Connection
/*     */     //   10	264	3	preparedStatement	PreparedStatement
/*     */     //   12	251	4	resultSet	java.sql.ResultSet
/*     */     //   21	269	5	videos	java.util.List<com.groom.bean.Video>
/*     */     //   26	4	6	query	String
/*     */     //   178	3	6	exception	SQLException
/*     */     //   63	95	7	video	com.groom.bean.Video
/*     */     //   220	35	8	localObject	Object
/*     */     // Exception table:
/*     */     //   from	to	target	type
/*     */     //   23	175	178	java/sql/SQLException
/*     */     //   23	185	220	finally
/*     */   }
/*     */   
/*     */   /* Error */
/*     */   public java.util.List<com.groom.bean.Video> getAllVideosByStandardAndSubject(int standard, String subject)
/*     */     throws SQLException
/*     */   {
/*     */     // Byte code:
/*     */     //   0: getstatic 21	com/groom/dao/impl/AdminDAOImpl:ds	Ljavax/sql/DataSource;
/*     */     //   3: invokeinterface 25 1 0
/*     */     //   8: astore_3
/*     */     //   9: aconst_null
/*     */     //   10: astore 4
/*     */     //   12: aconst_null
/*     */     //   13: astore 5
/*     */     //   15: getstatic 48	java/lang/System:out	Ljava/io/PrintStream;
/*     */     //   18: new 31	java/lang/StringBuilder
/*     */     //   21: dup
/*     */     //   22: ldc_w 420
/*     */     //   25: invokespecial 35	java/lang/StringBuilder:<init>	(Ljava/lang/String;)V
/*     */     //   28: aload_2
/*     */     //   29: invokevirtual 38	java/lang/StringBuilder:append	(Ljava/lang/String;)Ljava/lang/StringBuilder;
/*     */     //   32: invokevirtual 44	java/lang/StringBuilder:toString	()Ljava/lang/String;
/*     */     //   35: invokevirtual 54	java/io/PrintStream:println	(Ljava/lang/String;)V
/*     */     //   38: getstatic 48	java/lang/System:out	Ljava/io/PrintStream;
/*     */     //   41: new 31	java/lang/StringBuilder
/*     */     //   44: dup
/*     */     //   45: ldc_w 420
/*     */     //   48: invokespecial 35	java/lang/StringBuilder:<init>	(Ljava/lang/String;)V
/*     */     //   51: iload_1
/*     */     //   52: invokevirtual 422	java/lang/StringBuilder:append	(I)Ljava/lang/StringBuilder;
/*     */     //   55: invokevirtual 44	java/lang/StringBuilder:toString	()Ljava/lang/String;
/*     */     //   58: invokevirtual 54	java/io/PrintStream:println	(Ljava/lang/String;)V
/*     */     //   61: new 226	java/util/ArrayList
/*     */     //   64: dup
/*     */     //   65: invokespecial 228	java/util/ArrayList:<init>	()V
/*     */     //   68: astore 6
/*     */     //   70: iload_1
/*     */     //   71: ifeq +86 -> 157
/*     */     //   74: aload_2
/*     */     //   75: ifnull +82 -> 157
/*     */     //   78: ldc_w 425
/*     */     //   81: astore 7
/*     */     //   83: aload_3
/*     */     //   84: aload 7
/*     */     //   86: invokeinterface 59 2 0
/*     */     //   91: astore 4
/*     */     //   93: aload 4
/*     */     //   95: iconst_1
/*     */     //   96: iload_1
/*     */     //   97: invokeinterface 71 3 0
/*     */     //   102: aload 4
/*     */     //   104: iconst_2
/*     */     //   105: aload_2
/*     */     //   106: invokeinterface 65 3 0
/*     */     //   111: getstatic 48	java/lang/System:out	Ljava/io/PrintStream;
/*     */     //   114: new 31	java/lang/StringBuilder
/*     */     //   117: dup
/*     */     //   118: ldc_w 427
/*     */     //   121: invokespecial 35	java/lang/StringBuilder:<init>	(Ljava/lang/String;)V
/*     */     //   124: aload_2
/*     */     //   125: invokevirtual 38	java/lang/StringBuilder:append	(Ljava/lang/String;)Ljava/lang/StringBuilder;
/*     */     //   128: invokevirtual 44	java/lang/StringBuilder:toString	()Ljava/lang/String;
/*     */     //   131: invokevirtual 54	java/io/PrintStream:println	(Ljava/lang/String;)V
/*     */     //   134: getstatic 48	java/lang/System:out	Ljava/io/PrintStream;
/*     */     //   137: new 31	java/lang/StringBuilder
/*     */     //   140: dup
/*     */     //   141: ldc_w 427
/*     */     //   144: invokespecial 35	java/lang/StringBuilder:<init>	(Ljava/lang/String;)V
/*     */     //   147: iload_1
/*     */     //   148: invokevirtual 422	java/lang/StringBuilder:append	(I)Ljava/lang/StringBuilder;
/*     */     //   151: invokevirtual 44	java/lang/StringBuilder:toString	()Ljava/lang/String;
/*     */     //   154: invokevirtual 54	java/io/PrintStream:println	(Ljava/lang/String;)V
/*     */     //   157: iload_1
/*     */     //   158: ifne +31 -> 189
/*     */     //   161: aload_2
/*     */     //   162: ifnull +27 -> 189
/*     */     //   165: ldc_w 410
/*     */     //   168: astore 7
/*     */     //   170: aload_3
/*     */     //   171: aload 7
/*     */     //   173: invokeinterface 59 2 0
/*     */     //   178: astore 4
/*     */     //   180: aload 4
/*     */     //   182: iconst_1
/*     */     //   183: aload_2
/*     */     //   184: invokeinterface 65 3 0
/*     */     //   189: iload_1
/*     */     //   190: ifeq +31 -> 221
/*     */     //   193: aload_2
/*     */     //   194: ifnonnull +27 -> 221
/*     */     //   197: ldc_w 415
/*     */     //   200: astore 7
/*     */     //   202: aload_3
/*     */     //   203: aload 7
/*     */     //   205: invokeinterface 59 2 0
/*     */     //   210: astore 4
/*     */     //   212: aload 4
/*     */     //   214: iconst_1
/*     */     //   215: iload_1
/*     */     //   216: invokeinterface 71 3 0
/*     */     //   221: aload 4
/*     */     //   223: invokeinterface 126 1 0
/*     */     //   228: astore 5
/*     */     //   230: goto +112 -> 342
/*     */     //   233: new 366	com/groom/bean/Video
/*     */     //   236: dup
/*     */     //   237: invokespecial 368	com/groom/bean/Video:<init>	()V
/*     */     //   240: astore 7
/*     */     //   242: aload 7
/*     */     //   244: aload 5
/*     */     //   246: ldc_w 369
/*     */     //   249: invokeinterface 132 2 0
/*     */     //   254: invokevirtual 371	com/groom/bean/Video:setId	(I)V
/*     */     //   257: aload 7
/*     */     //   259: aload 5
/*     */     //   261: ldc_w 374
/*     */     //   264: invokeinterface 132 2 0
/*     */     //   269: invokevirtual 376	com/groom/bean/Video:setStandard	(I)V
/*     */     //   272: aload 7
/*     */     //   274: aload 5
/*     */     //   276: ldc_w 377
/*     */     //   279: invokeinterface 146 2 0
/*     */     //   284: invokevirtual 379	com/groom/bean/Video:setSubject	(Ljava/lang/String;)V
/*     */     //   287: aload 7
/*     */     //   289: aload 5
/*     */     //   291: ldc_w 382
/*     */     //   294: invokeinterface 146 2 0
/*     */     //   299: invokevirtual 384	com/groom/bean/Video:setTitle	(Ljava/lang/String;)V
/*     */     //   302: aload 7
/*     */     //   304: aload 5
/*     */     //   306: ldc_w 387
/*     */     //   309: invokeinterface 146 2 0
/*     */     //   314: invokevirtual 389	com/groom/bean/Video:setDescription	(Ljava/lang/String;)V
/*     */     //   317: aload 7
/*     */     //   319: aload 5
/*     */     //   321: ldc_w 392
/*     */     //   324: invokeinterface 146 2 0
/*     */     //   329: invokevirtual 394	com/groom/bean/Video:setUrl	(Ljava/lang/String;)V
/*     */     //   332: aload 6
/*     */     //   334: aload 7
/*     */     //   336: invokeinterface 233 2 0
/*     */     //   341: pop
/*     */     //   342: aload 5
/*     */     //   344: invokeinterface 154 1 0
/*     */     //   349: ifne -116 -> 233
/*     */     //   352: goto +86 -> 438
/*     */     //   355: astore 7
/*     */     //   357: aload 7
/*     */     //   359: invokevirtual 87	java/sql/SQLException:printStackTrace	()V
/*     */     //   362: aload 5
/*     */     //   364: ifnull +10 -> 374
/*     */     //   367: aload 5
/*     */     //   369: invokeinterface 397 1 0
/*     */     //   374: aload 4
/*     */     //   376: ifnull +10 -> 386
/*     */     //   379: aload 4
/*     */     //   381: invokeinterface 83 1 0
/*     */     //   386: aload_3
/*     */     //   387: ifnull +85 -> 472
/*     */     //   390: aload_3
/*     */     //   391: invokeinterface 86 1 0
/*     */     //   396: goto +76 -> 472
/*     */     //   399: astore 8
/*     */     //   401: aload 5
/*     */     //   403: ifnull +10 -> 413
/*     */     //   406: aload 5
/*     */     //   408: invokeinterface 397 1 0
/*     */     //   413: aload 4
/*     */     //   415: ifnull +10 -> 425
/*     */     //   418: aload 4
/*     */     //   420: invokeinterface 83 1 0
/*     */     //   425: aload_3
/*     */     //   426: ifnull +9 -> 435
/*     */     //   429: aload_3
/*     */     //   430: invokeinterface 86 1 0
/*     */     //   435: aload 8
/*     */     //   437: athrow
/*     */     //   438: aload 5
/*     */     //   440: ifnull +10 -> 450
/*     */     //   443: aload 5
/*     */     //   445: invokeinterface 397 1 0
/*     */     //   450: aload 4
/*     */     //   452: ifnull +10 -> 462
/*     */     //   455: aload 4
/*     */     //   457: invokeinterface 83 1 0
/*     */     //   462: aload_3
/*     */     //   463: ifnull +9 -> 472
/*     */     //   466: aload_3
/*     */     //   467: invokeinterface 86 1 0
/*     */     //   472: aload 6
/*     */     //   474: areturn
/*     */     // Line number table:
/*     */     //   Java source line #494	-> byte code offset #0
/*     */     //   Java source line #495	-> byte code offset #9
/*     */     //   Java source line #496	-> byte code offset #12
/*     */     //   Java source line #497	-> byte code offset #15
/*     */     //   Java source line #498	-> byte code offset #38
/*     */     //   Java source line #499	-> byte code offset #61
/*     */     //   Java source line #501	-> byte code offset #70
/*     */     //   Java source line #502	-> byte code offset #78
/*     */     //   Java source line #503	-> byte code offset #83
/*     */     //   Java source line #504	-> byte code offset #93
/*     */     //   Java source line #505	-> byte code offset #102
/*     */     //   Java source line #506	-> byte code offset #111
/*     */     //   Java source line #507	-> byte code offset #134
/*     */     //   Java source line #509	-> byte code offset #157
/*     */     //   Java source line #510	-> byte code offset #165
/*     */     //   Java source line #511	-> byte code offset #170
/*     */     //   Java source line #512	-> byte code offset #180
/*     */     //   Java source line #514	-> byte code offset #189
/*     */     //   Java source line #515	-> byte code offset #197
/*     */     //   Java source line #516	-> byte code offset #202
/*     */     //   Java source line #517	-> byte code offset #212
/*     */     //   Java source line #520	-> byte code offset #221
/*     */     //   Java source line #521	-> byte code offset #230
/*     */     //   Java source line #522	-> byte code offset #233
/*     */     //   Java source line #524	-> byte code offset #242
/*     */     //   Java source line #525	-> byte code offset #257
/*     */     //   Java source line #526	-> byte code offset #272
/*     */     //   Java source line #527	-> byte code offset #287
/*     */     //   Java source line #528	-> byte code offset #302
/*     */     //   Java source line #529	-> byte code offset #317
/*     */     //   Java source line #530	-> byte code offset #332
/*     */     //   Java source line #521	-> byte code offset #342
/*     */     //   Java source line #534	-> byte code offset #352
/*     */     //   Java source line #535	-> byte code offset #357
/*     */     //   Java source line #537	-> byte code offset #362
/*     */     //   Java source line #538	-> byte code offset #367
/*     */     //   Java source line #539	-> byte code offset #374
/*     */     //   Java source line #540	-> byte code offset #379
/*     */     //   Java source line #541	-> byte code offset #386
/*     */     //   Java source line #542	-> byte code offset #390
/*     */     //   Java source line #536	-> byte code offset #399
/*     */     //   Java source line #537	-> byte code offset #401
/*     */     //   Java source line #538	-> byte code offset #406
/*     */     //   Java source line #539	-> byte code offset #413
/*     */     //   Java source line #540	-> byte code offset #418
/*     */     //   Java source line #541	-> byte code offset #425
/*     */     //   Java source line #542	-> byte code offset #429
/*     */     //   Java source line #543	-> byte code offset #435
/*     */     //   Java source line #537	-> byte code offset #438
/*     */     //   Java source line #538	-> byte code offset #443
/*     */     //   Java source line #539	-> byte code offset #450
/*     */     //   Java source line #540	-> byte code offset #455
/*     */     //   Java source line #541	-> byte code offset #462
/*     */     //   Java source line #542	-> byte code offset #466
/*     */     //   Java source line #544	-> byte code offset #472
/*     */     // Local variable table:
/*     */     //   start	length	slot	name	signature
/*     */     //   0	475	0	this	AdminDAOImpl
/*     */     //   0	475	1	standard	int
/*     */     //   0	475	2	subject	String
/*     */     //   8	459	3	connection	Connection
/*     */     //   10	446	4	preparedStatement	PreparedStatement
/*     */     //   13	431	5	resultSet	java.sql.ResultSet
/*     */     //   68	405	6	videos	java.util.List<com.groom.bean.Video>
/*     */     //   81	4	7	query	String
/*     */     //   168	4	7	query	String
/*     */     //   200	4	7	query	String
/*     */     //   240	95	7	video	com.groom.bean.Video
/*     */     //   355	3	7	exception	SQLException
/*     */     //   399	37	8	localObject	Object
/*     */     // Exception table:
/*     */     //   from	to	target	type
/*     */     //   70	352	355	java/sql/SQLException
/*     */     //   70	362	399	finally
/*     */   }
/*     */   
/*     */   /* Error */
/*     */   public Integer getNoofQuestions(String category, int topicId)
/*     */     throws SQLException
/*     */   {
/*     */     // Byte code:
/*     */     //   0: iconst_0
/*     */     //   1: istore_3
/*     */     //   2: aconst_null
/*     */     //   3: astore 4
/*     */     //   5: aconst_null
/*     */     //   6: astore 5
/*     */     //   8: aconst_null
/*     */     //   9: astore 6
/*     */     //   11: getstatic 21	com/groom/dao/impl/AdminDAOImpl:ds	Ljavax/sql/DataSource;
/*     */     //   14: invokeinterface 25 1 0
/*     */     //   19: astore 4
/*     */     //   21: aload 4
/*     */     //   23: new 31	java/lang/StringBuilder
/*     */     //   26: dup
/*     */     //   27: ldc_w 431
/*     */     //   30: invokespecial 35	java/lang/StringBuilder:<init>	(Ljava/lang/String;)V
/*     */     //   33: aload_1
/*     */     //   34: invokevirtual 38	java/lang/StringBuilder:append	(Ljava/lang/String;)Ljava/lang/StringBuilder;
/*     */     //   37: ldc_w 433
/*     */     //   40: invokevirtual 38	java/lang/StringBuilder:append	(Ljava/lang/String;)Ljava/lang/StringBuilder;
/*     */     //   43: invokevirtual 44	java/lang/StringBuilder:toString	()Ljava/lang/String;
/*     */     //   46: invokeinterface 59 2 0
/*     */     //   51: astore 5
/*     */     //   53: aload 5
/*     */     //   55: iconst_1
/*     */     //   56: iload_2
/*     */     //   57: invokeinterface 71 3 0
/*     */     //   62: getstatic 48	java/lang/System:out	Ljava/io/PrintStream;
/*     */     //   65: new 31	java/lang/StringBuilder
/*     */     //   68: dup
/*     */     //   69: ldc_w 435
/*     */     //   72: invokespecial 35	java/lang/StringBuilder:<init>	(Ljava/lang/String;)V
/*     */     //   75: aload 5
/*     */     //   77: invokevirtual 437	java/lang/StringBuilder:append	(Ljava/lang/Object;)Ljava/lang/StringBuilder;
/*     */     //   80: invokevirtual 44	java/lang/StringBuilder:toString	()Ljava/lang/String;
/*     */     //   83: invokevirtual 54	java/io/PrintStream:println	(Ljava/lang/String;)V
/*     */     //   86: aload 5
/*     */     //   88: invokeinterface 126 1 0
/*     */     //   93: astore 6
/*     */     //   95: goto +12 -> 107
/*     */     //   98: aload 6
/*     */     //   100: iconst_1
/*     */     //   101: invokeinterface 183 2 0
/*     */     //   106: istore_3
/*     */     //   107: aload 6
/*     */     //   109: invokeinterface 154 1 0
/*     */     //   114: ifne -16 -> 98
/*     */     //   117: getstatic 48	java/lang/System:out	Ljava/io/PrintStream;
/*     */     //   120: new 31	java/lang/StringBuilder
/*     */     //   123: dup
/*     */     //   124: ldc_w 440
/*     */     //   127: invokespecial 35	java/lang/StringBuilder:<init>	(Ljava/lang/String;)V
/*     */     //   130: iload_3
/*     */     //   131: invokevirtual 422	java/lang/StringBuilder:append	(I)Ljava/lang/StringBuilder;
/*     */     //   134: invokevirtual 44	java/lang/StringBuilder:toString	()Ljava/lang/String;
/*     */     //   137: invokevirtual 54	java/io/PrintStream:println	(Ljava/lang/String;)V
/*     */     //   140: goto +44 -> 184
/*     */     //   143: astore 7
/*     */     //   145: aload 5
/*     */     //   147: ifnull +10 -> 157
/*     */     //   150: aload 5
/*     */     //   152: invokeinterface 83 1 0
/*     */     //   157: aload 6
/*     */     //   159: ifnull +10 -> 169
/*     */     //   162: aload 6
/*     */     //   164: invokeinterface 397 1 0
/*     */     //   169: aload 4
/*     */     //   171: ifnull +10 -> 181
/*     */     //   174: aload 4
/*     */     //   176: invokeinterface 86 1 0
/*     */     //   181: aload 7
/*     */     //   183: athrow
/*     */     //   184: aload 5
/*     */     //   186: ifnull +10 -> 196
/*     */     //   189: aload 5
/*     */     //   191: invokeinterface 83 1 0
/*     */     //   196: aload 6
/*     */     //   198: ifnull +10 -> 208
/*     */     //   201: aload 6
/*     */     //   203: invokeinterface 397 1 0
/*     */     //   208: aload 4
/*     */     //   210: ifnull +10 -> 220
/*     */     //   213: aload 4
/*     */     //   215: invokeinterface 86 1 0
/*     */     //   220: iload_3
/*     */     //   221: invokestatic 138	java/lang/Integer:valueOf	(I)Ljava/lang/Integer;
/*     */     //   224: areturn
/*     */     // Line number table:
/*     */     //   Java source line #548	-> byte code offset #0
/*     */     //   Java source line #550	-> byte code offset #2
/*     */     //   Java source line #551	-> byte code offset #5
/*     */     //   Java source line #552	-> byte code offset #8
/*     */     //   Java source line #554	-> byte code offset #11
/*     */     //   Java source line #555	-> byte code offset #21
/*     */     //   Java source line #556	-> byte code offset #23
/*     */     //   Java source line #555	-> byte code offset #51
/*     */     //   Java source line #557	-> byte code offset #53
/*     */     //   Java source line #558	-> byte code offset #62
/*     */     //   Java source line #559	-> byte code offset #86
/*     */     //   Java source line #560	-> byte code offset #95
/*     */     //   Java source line #561	-> byte code offset #98
/*     */     //   Java source line #560	-> byte code offset #107
/*     */     //   Java source line #562	-> byte code offset #117
/*     */     //   Java source line #563	-> byte code offset #140
/*     */     //   Java source line #564	-> byte code offset #145
/*     */     //   Java source line #565	-> byte code offset #150
/*     */     //   Java source line #567	-> byte code offset #157
/*     */     //   Java source line #568	-> byte code offset #162
/*     */     //   Java source line #569	-> byte code offset #169
/*     */     //   Java source line #570	-> byte code offset #174
/*     */     //   Java source line #571	-> byte code offset #181
/*     */     //   Java source line #564	-> byte code offset #184
/*     */     //   Java source line #565	-> byte code offset #189
/*     */     //   Java source line #567	-> byte code offset #196
/*     */     //   Java source line #568	-> byte code offset #201
/*     */     //   Java source line #569	-> byte code offset #208
/*     */     //   Java source line #570	-> byte code offset #213
/*     */     //   Java source line #572	-> byte code offset #220
/*     */     // Local variable table:
/*     */     //   start	length	slot	name	signature
/*     */     //   0	225	0	this	AdminDAOImpl
/*     */     //   0	225	1	category	String
/*     */     //   0	225	2	topicId	int
/*     */     //   1	220	3	noOfQues	int
/*     */     //   3	211	4	conn	Connection
/*     */     //   6	184	5	ps	PreparedStatement
/*     */     //   9	193	6	rs	java.sql.ResultSet
/*     */     //   143	39	7	localObject	Object
/*     */     // Exception table:
/*     */     //   from	to	target	type
/*     */     //   11	143	143	finally
/*     */   }
/*     */   
/*     */   /* Error */
/*     */   public boolean validateAdmin(String username, String password)
/*     */     throws SQLException
/*     */   {
/*     */     // Byte code:
/*     */     //   0: getstatic 21	com/groom/dao/impl/AdminDAOImpl:ds	Ljavax/sql/DataSource;
/*     */     //   3: invokeinterface 25 1 0
/*     */     //   8: astore_3
/*     */     //   9: aconst_null
/*     */     //   10: astore 4
/*     */     //   12: aconst_null
/*     */     //   13: astore 5
/*     */     //   15: iconst_0
/*     */     //   16: istore 6
/*     */     //   18: getstatic 48	java/lang/System:out	Ljava/io/PrintStream;
/*     */     //   21: new 31	java/lang/StringBuilder
/*     */     //   24: dup
/*     */     //   25: aload_1
/*     */     //   26: invokestatic 450	java/lang/String:valueOf	(Ljava/lang/Object;)Ljava/lang/String;
/*     */     //   29: invokespecial 35	java/lang/StringBuilder:<init>	(Ljava/lang/String;)V
/*     */     //   32: aload_2
/*     */     //   33: invokevirtual 38	java/lang/StringBuilder:append	(Ljava/lang/String;)Ljava/lang/StringBuilder;
/*     */     //   36: invokevirtual 44	java/lang/StringBuilder:toString	()Ljava/lang/String;
/*     */     //   39: invokevirtual 54	java/io/PrintStream:println	(Ljava/lang/String;)V
/*     */     //   42: ldc_w 453
/*     */     //   45: astore 7
/*     */     //   47: getstatic 48	java/lang/System:out	Ljava/io/PrintStream;
/*     */     //   50: aload 7
/*     */     //   52: invokevirtual 54	java/io/PrintStream:println	(Ljava/lang/String;)V
/*     */     //   55: aload_3
/*     */     //   56: aload 7
/*     */     //   58: invokeinterface 59 2 0
/*     */     //   63: astore 4
/*     */     //   65: aload 4
/*     */     //   67: iconst_1
/*     */     //   68: aload_1
/*     */     //   69: invokeinterface 65 3 0
/*     */     //   74: aload 4
/*     */     //   76: iconst_2
/*     */     //   77: aload_2
/*     */     //   78: invokeinterface 65 3 0
/*     */     //   83: aload 4
/*     */     //   85: invokeinterface 126 1 0
/*     */     //   90: astore 5
/*     */     //   92: goto +6 -> 98
/*     */     //   95: iconst_1
/*     */     //   96: istore 6
/*     */     //   98: aload 5
/*     */     //   100: invokeinterface 154 1 0
/*     */     //   105: ifne -10 -> 95
/*     */     //   108: goto +60 -> 168
/*     */     //   111: astore 7
/*     */     //   113: iconst_0
/*     */     //   114: istore 6
/*     */     //   116: aload 4
/*     */     //   118: ifnull +10 -> 128
/*     */     //   121: aload 4
/*     */     //   123: invokeinterface 83 1 0
/*     */     //   128: aload_3
/*     */     //   129: ifnull +61 -> 190
/*     */     //   132: aload_3
/*     */     //   133: invokeinterface 86 1 0
/*     */     //   138: goto +52 -> 190
/*     */     //   141: astore 8
/*     */     //   143: aload 4
/*     */     //   145: ifnull +10 -> 155
/*     */     //   148: aload 4
/*     */     //   150: invokeinterface 83 1 0
/*     */     //   155: aload_3
/*     */     //   156: ifnull +9 -> 165
/*     */     //   159: aload_3
/*     */     //   160: invokeinterface 86 1 0
/*     */     //   165: aload 8
/*     */     //   167: athrow
/*     */     //   168: aload 4
/*     */     //   170: ifnull +10 -> 180
/*     */     //   173: aload 4
/*     */     //   175: invokeinterface 83 1 0
/*     */     //   180: aload_3
/*     */     //   181: ifnull +9 -> 190
/*     */     //   184: aload_3
/*     */     //   185: invokeinterface 86 1 0
/*     */     //   190: iload 6
/*     */     //   192: ireturn
/*     */     // Line number table:
/*     */     //   Java source line #577	-> byte code offset #0
/*     */     //   Java source line #578	-> byte code offset #9
/*     */     //   Java source line #579	-> byte code offset #12
/*     */     //   Java source line #580	-> byte code offset #15
/*     */     //   Java source line #581	-> byte code offset #18
/*     */     //   Java source line #583	-> byte code offset #42
/*     */     //   Java source line #584	-> byte code offset #47
/*     */     //   Java source line #585	-> byte code offset #55
/*     */     //   Java source line #586	-> byte code offset #65
/*     */     //   Java source line #587	-> byte code offset #74
/*     */     //   Java source line #588	-> byte code offset #83
/*     */     //   Java source line #589	-> byte code offset #92
/*     */     //   Java source line #590	-> byte code offset #95
/*     */     //   Java source line #589	-> byte code offset #98
/*     */     //   Java source line #593	-> byte code offset #108
/*     */     //   Java source line #595	-> byte code offset #113
/*     */     //   Java source line #598	-> byte code offset #116
/*     */     //   Java source line #599	-> byte code offset #121
/*     */     //   Java source line #600	-> byte code offset #128
/*     */     //   Java source line #601	-> byte code offset #132
/*     */     //   Java source line #596	-> byte code offset #141
/*     */     //   Java source line #598	-> byte code offset #143
/*     */     //   Java source line #599	-> byte code offset #148
/*     */     //   Java source line #600	-> byte code offset #155
/*     */     //   Java source line #601	-> byte code offset #159
/*     */     //   Java source line #602	-> byte code offset #165
/*     */     //   Java source line #598	-> byte code offset #168
/*     */     //   Java source line #599	-> byte code offset #173
/*     */     //   Java source line #600	-> byte code offset #180
/*     */     //   Java source line #601	-> byte code offset #184
/*     */     //   Java source line #603	-> byte code offset #190
/*     */     // Local variable table:
/*     */     //   start	length	slot	name	signature
/*     */     //   0	193	0	this	AdminDAOImpl
/*     */     //   0	193	1	username	String
/*     */     //   0	193	2	password	String
/*     */     //   8	177	3	connection	Connection
/*     */     //   10	164	4	preparedStatement	PreparedStatement
/*     */     //   13	86	5	resultSet	java.sql.ResultSet
/*     */     //   16	175	6	is_admin_exist	boolean
/*     */     //   45	12	7	query	String
/*     */     //   111	3	7	exception	SQLException
/*     */     //   141	25	8	localObject	Object
/*     */     // Exception table:
/*     */     //   from	to	target	type
/*     */     //   42	108	111	java/sql/SQLException
/*     */     //   42	116	141	finally
/*     */   }
/*     */   
/*     */   public boolean updateQuestion(QuizQuestionDetails questionDetails, String subject, String user)
/*     */     throws SQLException
/*     */   {
/* 609 */     Connection connection = ds.getConnection();
/* 610 */     PreparedStatement preparedStatement = null;
/*     */     try
/*     */     {
/* 613 */       String query = "update " + 
/* 614 */         subject + 
/* 615 */         " set QUESTION=?,OPTION_A=?,OPTION_B=?,OPTION_C=?,OPTION_D=?,ANSWER=?,Q_EXPLANATION=?,CREATED_BY=? where q_id=?";
/* 616 */       System.out.println(query);
/*     */       
/* 618 */       preparedStatement = connection.prepareStatement(query);
/*     */       
/* 620 */       preparedStatement.setString(1, questionDetails.getQuestion());
/* 621 */       preparedStatement.setString(2, questionDetails.getOption_a());
/* 622 */       preparedStatement.setString(3, questionDetails.getOption_b());
/* 623 */       preparedStatement.setString(4, questionDetails.getOption_c());
/* 624 */       preparedStatement.setString(5, questionDetails.getOption_d());
/* 625 */       preparedStatement.setString(6, questionDetails.getAnswer());
/*     */       
/* 627 */       preparedStatement.setString(7, questionDetails.getExplanation());
/* 628 */       preparedStatement.setString(8, user);
/* 629 */       preparedStatement.setInt(9, questionDetails.getQ_id());
/*     */       
/*     */ 
/*     */ 
/* 633 */       int status = preparedStatement.executeUpdate();
/* 634 */       if (status == 1)
/* 635 */         return true;
/*     */     } catch (SQLException exception) {
/* 637 */       exception.printStackTrace();
/*     */     }
/*     */     finally {
/* 640 */       if (preparedStatement != null)
/* 641 */         preparedStatement.close();
/* 642 */       if (connection != null) {
/* 643 */         connection.close();
/*     */       }
/*     */     }
/* 640 */     if (preparedStatement != null)
/* 641 */       preparedStatement.close();
/* 642 */     if (connection != null) {
/* 643 */       connection.close();
/*     */     }
/* 645 */     return false;
/*     */   }
/*     */ }


/* Location:              D:\New folder\WEB-INF\classes\com\groom.zip!\groom\groom\dao\impl\AdminDAOImpl.class
 * Java compiler version: 7 (51.0)
 * JD-Core Version:       0.7.1
 */