/*     */ package com.groom.dao.impl;
/*     */ 
/*     */ import com.groom.dao.ArticleDAO;
/*     */ import com.groom.dao.BaseDAO;
/*     */ import java.sql.Connection;
/*     */ import java.sql.PreparedStatement;
/*     */ import java.sql.SQLException;
/*     */ import javax.sql.DataSource;
/*     */ 
/*     */ public class ArticleDAOImpl
/*     */   extends BaseDAO
/*     */   implements ArticleDAO
/*     */ {
/*     */   /* Error */
/*     */   public java.util.List<com.groom.bean.Article> getAllArticles()
/*     */     throws SQLException
/*     */   {
/*     */     // Byte code:
/*     */     //   0: getstatic 23	com/groom/dao/impl/ArticleDAOImpl:ds	Ljavax/sql/DataSource;
/*     */     //   3: invokeinterface 27 1 0
/*     */     //   8: astore_1
/*     */     //   9: aconst_null
/*     */     //   10: astore_2
/*     */     //   11: aconst_null
/*     */     //   12: astore_3
/*     */     //   13: new 33	java/util/ArrayList
/*     */     //   16: dup
/*     */     //   17: invokespecial 35	java/util/ArrayList:<init>	()V
/*     */     //   20: astore 4
/*     */     //   22: ldc 36
/*     */     //   24: astore 5
/*     */     //   26: aload_1
/*     */     //   27: aload 5
/*     */     //   29: invokeinterface 38 2 0
/*     */     //   34: astore_2
/*     */     //   35: aload_2
/*     */     //   36: invokeinterface 44 1 0
/*     */     //   41: astore_3
/*     */     //   42: goto +158 -> 200
/*     */     //   45: new 50	com/groom/bean/Article
/*     */     //   48: dup
/*     */     //   49: invokespecial 52	com/groom/bean/Article:<init>	()V
/*     */     //   52: astore 6
/*     */     //   54: aload 6
/*     */     //   56: aload_3
/*     */     //   57: ldc 53
/*     */     //   59: invokeinterface 55 2 0
/*     */     //   64: invokevirtual 61	com/groom/bean/Article:setArticleid	(I)V
/*     */     //   67: aload 6
/*     */     //   69: aload_3
/*     */     //   70: ldc 65
/*     */     //   72: invokeinterface 67 2 0
/*     */     //   77: invokevirtual 71	com/groom/bean/Article:setUser	(Ljava/lang/String;)V
/*     */     //   80: aload 6
/*     */     //   82: aload_3
/*     */     //   83: ldc 75
/*     */     //   85: invokeinterface 67 2 0
/*     */     //   90: invokevirtual 77	com/groom/bean/Article:setArticle_title	(Ljava/lang/String;)V
/*     */     //   93: aload 6
/*     */     //   95: new 80	java/lang/StringBuilder
/*     */     //   98: dup
/*     */     //   99: aload_3
/*     */     //   100: ldc 82
/*     */     //   102: invokeinterface 67 2 0
/*     */     //   107: iconst_0
/*     */     //   108: sipush 220
/*     */     //   111: invokevirtual 84	java/lang/String:substring	(II)Ljava/lang/String;
/*     */     //   114: invokestatic 90	java/lang/String:valueOf	(Ljava/lang/Object;)Ljava/lang/String;
/*     */     //   117: invokespecial 94	java/lang/StringBuilder:<init>	(Ljava/lang/String;)V
/*     */     //   120: ldc 96
/*     */     //   122: invokevirtual 98	java/lang/StringBuilder:append	(Ljava/lang/String;)Ljava/lang/StringBuilder;
/*     */     //   125: invokevirtual 102	java/lang/StringBuilder:toString	()Ljava/lang/String;
/*     */     //   128: invokevirtual 106	com/groom/bean/Article:setArticle_text	(Ljava/lang/String;)V
/*     */     //   131: aload_3
/*     */     //   132: ldc 109
/*     */     //   134: invokeinterface 111 2 0
/*     */     //   139: astore 7
/*     */     //   141: new 115	java/text/SimpleDateFormat
/*     */     //   144: dup
/*     */     //   145: ldc 117
/*     */     //   147: invokespecial 119	java/text/SimpleDateFormat:<init>	(Ljava/lang/String;)V
/*     */     //   150: aload 7
/*     */     //   152: invokevirtual 120	java/text/SimpleDateFormat:format	(Ljava/util/Date;)Ljava/lang/String;
/*     */     //   155: astore 8
/*     */     //   157: aload 6
/*     */     //   159: aload 8
/*     */     //   161: invokevirtual 124	com/groom/bean/Article:setArticle_date	(Ljava/lang/String;)V
/*     */     //   164: aload 6
/*     */     //   166: aload_3
/*     */     //   167: ldc 127
/*     */     //   169: invokeinterface 55 2 0
/*     */     //   174: invokevirtual 129	com/groom/bean/Article:setNo_of_views	(I)V
/*     */     //   177: aload 6
/*     */     //   179: aload_3
/*     */     //   180: ldc -124
/*     */     //   182: invokeinterface 67 2 0
/*     */     //   187: invokevirtual 134	com/groom/bean/Article:setTags	(Ljava/lang/String;)V
/*     */     //   190: aload 4
/*     */     //   192: aload 6
/*     */     //   194: invokeinterface 137 2 0
/*     */     //   199: pop
/*     */     //   200: aload_3
/*     */     //   201: invokeinterface 143 1 0
/*     */     //   206: ifne -161 -> 45
/*     */     //   209: goto +78 -> 287
/*     */     //   212: astore 5
/*     */     //   214: aload 5
/*     */     //   216: invokevirtual 147	java/sql/SQLException:printStackTrace	()V
/*     */     //   219: aload_3
/*     */     //   220: ifnull +9 -> 229
/*     */     //   223: aload_3
/*     */     //   224: invokeinterface 150 1 0
/*     */     //   229: aload_2
/*     */     //   230: ifnull +9 -> 239
/*     */     //   233: aload_2
/*     */     //   234: invokeinterface 153 1 0
/*     */     //   239: aload_1
/*     */     //   240: ifnull +77 -> 317
/*     */     //   243: aload_1
/*     */     //   244: invokeinterface 154 1 0
/*     */     //   249: goto +68 -> 317
/*     */     //   252: astore 9
/*     */     //   254: aload_3
/*     */     //   255: ifnull +9 -> 264
/*     */     //   258: aload_3
/*     */     //   259: invokeinterface 150 1 0
/*     */     //   264: aload_2
/*     */     //   265: ifnull +9 -> 274
/*     */     //   268: aload_2
/*     */     //   269: invokeinterface 153 1 0
/*     */     //   274: aload_1
/*     */     //   275: ifnull +9 -> 284
/*     */     //   278: aload_1
/*     */     //   279: invokeinterface 154 1 0
/*     */     //   284: aload 9
/*     */     //   286: athrow
/*     */     //   287: aload_3
/*     */     //   288: ifnull +9 -> 297
/*     */     //   291: aload_3
/*     */     //   292: invokeinterface 150 1 0
/*     */     //   297: aload_2
/*     */     //   298: ifnull +9 -> 307
/*     */     //   301: aload_2
/*     */     //   302: invokeinterface 153 1 0
/*     */     //   307: aload_1
/*     */     //   308: ifnull +9 -> 317
/*     */     //   311: aload_1
/*     */     //   312: invokeinterface 154 1 0
/*     */     //   317: aload 4
/*     */     //   319: areturn
/*     */     // Line number table:
/*     */     //   Java source line #20	-> byte code offset #0
/*     */     //   Java source line #21	-> byte code offset #9
/*     */     //   Java source line #22	-> byte code offset #11
/*     */     //   Java source line #23	-> byte code offset #13
/*     */     //   Java source line #25	-> byte code offset #22
/*     */     //   Java source line #26	-> byte code offset #26
/*     */     //   Java source line #28	-> byte code offset #35
/*     */     //   Java source line #29	-> byte code offset #42
/*     */     //   Java source line #30	-> byte code offset #45
/*     */     //   Java source line #32	-> byte code offset #54
/*     */     //   Java source line #33	-> byte code offset #67
/*     */     //   Java source line #34	-> byte code offset #80
/*     */     //   Java source line #35	-> byte code offset #93
/*     */     //   Java source line #36	-> byte code offset #131
/*     */     //   Java source line #37	-> byte code offset #141
/*     */     //   Java source line #38	-> byte code offset #150
/*     */     //   Java source line #37	-> byte code offset #155
/*     */     //   Java source line #39	-> byte code offset #157
/*     */     //   Java source line #40	-> byte code offset #164
/*     */     //   Java source line #41	-> byte code offset #177
/*     */     //   Java source line #43	-> byte code offset #190
/*     */     //   Java source line #29	-> byte code offset #200
/*     */     //   Java source line #47	-> byte code offset #209
/*     */     //   Java source line #48	-> byte code offset #214
/*     */     //   Java source line #50	-> byte code offset #219
/*     */     //   Java source line #51	-> byte code offset #223
/*     */     //   Java source line #52	-> byte code offset #229
/*     */     //   Java source line #53	-> byte code offset #233
/*     */     //   Java source line #54	-> byte code offset #239
/*     */     //   Java source line #55	-> byte code offset #243
/*     */     //   Java source line #49	-> byte code offset #252
/*     */     //   Java source line #50	-> byte code offset #254
/*     */     //   Java source line #51	-> byte code offset #258
/*     */     //   Java source line #52	-> byte code offset #264
/*     */     //   Java source line #53	-> byte code offset #268
/*     */     //   Java source line #54	-> byte code offset #274
/*     */     //   Java source line #55	-> byte code offset #278
/*     */     //   Java source line #56	-> byte code offset #284
/*     */     //   Java source line #50	-> byte code offset #287
/*     */     //   Java source line #51	-> byte code offset #291
/*     */     //   Java source line #52	-> byte code offset #297
/*     */     //   Java source line #53	-> byte code offset #301
/*     */     //   Java source line #54	-> byte code offset #307
/*     */     //   Java source line #55	-> byte code offset #311
/*     */     //   Java source line #57	-> byte code offset #317
/*     */     // Local variable table:
/*     */     //   start	length	slot	name	signature
/*     */     //   0	320	0	this	ArticleDAOImpl
/*     */     //   8	304	1	connection	Connection
/*     */     //   10	292	2	preparedStatement	PreparedStatement
/*     */     //   12	280	3	resultSet	java.sql.ResultSet
/*     */     //   20	298	4	articles	java.util.List<com.groom.bean.Article>
/*     */     //   24	4	5	query	String
/*     */     //   212	3	5	exception	SQLException
/*     */     //   52	141	6	article	com.groom.bean.Article
/*     */     //   139	12	7	timestamp	java.sql.Timestamp
/*     */     //   155	5	8	dateTime	String
/*     */     //   252	33	9	localObject	Object
/*     */     // Exception table:
/*     */     //   from	to	target	type
/*     */     //   22	209	212	java/sql/SQLException
/*     */     //   22	219	252	finally
/*     */   }
/*     */   
/*     */   /* Error */
/*     */   public com.groom.bean.Article getArticle(int articleid)
/*     */     throws SQLException
/*     */   {
/*     */     // Byte code:
/*     */     //   0: getstatic 23	com/groom/dao/impl/ArticleDAOImpl:ds	Ljavax/sql/DataSource;
/*     */     //   3: invokeinterface 27 1 0
/*     */     //   8: astore_2
/*     */     //   9: aconst_null
/*     */     //   10: astore_3
/*     */     //   11: aconst_null
/*     */     //   12: astore 4
/*     */     //   14: new 50	com/groom/bean/Article
/*     */     //   17: dup
/*     */     //   18: invokespecial 52	com/groom/bean/Article:<init>	()V
/*     */     //   21: astore 5
/*     */     //   23: ldc -77
/*     */     //   25: astore 6
/*     */     //   27: aload_2
/*     */     //   28: aload 6
/*     */     //   30: invokeinterface 38 2 0
/*     */     //   35: astore_3
/*     */     //   36: aload_3
/*     */     //   37: iconst_1
/*     */     //   38: iload_1
/*     */     //   39: invokeinterface 181 3 0
/*     */     //   44: aload_3
/*     */     //   45: invokeinterface 44 1 0
/*     */     //   50: astore 4
/*     */     //   52: goto +121 -> 173
/*     */     //   55: aload 5
/*     */     //   57: aload 4
/*     */     //   59: ldc 53
/*     */     //   61: invokeinterface 55 2 0
/*     */     //   66: invokevirtual 61	com/groom/bean/Article:setArticleid	(I)V
/*     */     //   69: aload 5
/*     */     //   71: aload 4
/*     */     //   73: ldc 65
/*     */     //   75: invokeinterface 67 2 0
/*     */     //   80: invokevirtual 71	com/groom/bean/Article:setUser	(Ljava/lang/String;)V
/*     */     //   83: aload 5
/*     */     //   85: aload 4
/*     */     //   87: ldc 75
/*     */     //   89: invokeinterface 67 2 0
/*     */     //   94: invokevirtual 77	com/groom/bean/Article:setArticle_title	(Ljava/lang/String;)V
/*     */     //   97: aload 5
/*     */     //   99: aload 4
/*     */     //   101: ldc 82
/*     */     //   103: invokeinterface 67 2 0
/*     */     //   108: invokevirtual 106	com/groom/bean/Article:setArticle_text	(Ljava/lang/String;)V
/*     */     //   111: aload 4
/*     */     //   113: ldc 109
/*     */     //   115: invokeinterface 111 2 0
/*     */     //   120: astore 7
/*     */     //   122: new 115	java/text/SimpleDateFormat
/*     */     //   125: dup
/*     */     //   126: ldc 117
/*     */     //   128: invokespecial 119	java/text/SimpleDateFormat:<init>	(Ljava/lang/String;)V
/*     */     //   131: aload 7
/*     */     //   133: invokevirtual 120	java/text/SimpleDateFormat:format	(Ljava/util/Date;)Ljava/lang/String;
/*     */     //   136: astore 8
/*     */     //   138: aload 5
/*     */     //   140: aload 8
/*     */     //   142: invokevirtual 124	com/groom/bean/Article:setArticle_date	(Ljava/lang/String;)V
/*     */     //   145: aload 5
/*     */     //   147: aload 4
/*     */     //   149: ldc 127
/*     */     //   151: invokeinterface 55 2 0
/*     */     //   156: invokevirtual 129	com/groom/bean/Article:setNo_of_views	(I)V
/*     */     //   159: aload 5
/*     */     //   161: aload 4
/*     */     //   163: ldc -124
/*     */     //   165: invokeinterface 67 2 0
/*     */     //   170: invokevirtual 134	com/groom/bean/Article:setTags	(Ljava/lang/String;)V
/*     */     //   173: aload 4
/*     */     //   175: invokeinterface 143 1 0
/*     */     //   180: ifne -125 -> 55
/*     */     //   183: goto +82 -> 265
/*     */     //   186: astore 6
/*     */     //   188: aload 6
/*     */     //   190: invokevirtual 147	java/sql/SQLException:printStackTrace	()V
/*     */     //   193: aload 4
/*     */     //   195: ifnull +10 -> 205
/*     */     //   198: aload 4
/*     */     //   200: invokeinterface 150 1 0
/*     */     //   205: aload_3
/*     */     //   206: ifnull +9 -> 215
/*     */     //   209: aload_3
/*     */     //   210: invokeinterface 153 1 0
/*     */     //   215: aload_2
/*     */     //   216: ifnull +81 -> 297
/*     */     //   219: aload_2
/*     */     //   220: invokeinterface 154 1 0
/*     */     //   225: goto +72 -> 297
/*     */     //   228: astore 9
/*     */     //   230: aload 4
/*     */     //   232: ifnull +10 -> 242
/*     */     //   235: aload 4
/*     */     //   237: invokeinterface 150 1 0
/*     */     //   242: aload_3
/*     */     //   243: ifnull +9 -> 252
/*     */     //   246: aload_3
/*     */     //   247: invokeinterface 153 1 0
/*     */     //   252: aload_2
/*     */     //   253: ifnull +9 -> 262
/*     */     //   256: aload_2
/*     */     //   257: invokeinterface 154 1 0
/*     */     //   262: aload 9
/*     */     //   264: athrow
/*     */     //   265: aload 4
/*     */     //   267: ifnull +10 -> 277
/*     */     //   270: aload 4
/*     */     //   272: invokeinterface 150 1 0
/*     */     //   277: aload_3
/*     */     //   278: ifnull +9 -> 287
/*     */     //   281: aload_3
/*     */     //   282: invokeinterface 153 1 0
/*     */     //   287: aload_2
/*     */     //   288: ifnull +9 -> 297
/*     */     //   291: aload_2
/*     */     //   292: invokeinterface 154 1 0
/*     */     //   297: aload 5
/*     */     //   299: areturn
/*     */     // Line number table:
/*     */     //   Java source line #62	-> byte code offset #0
/*     */     //   Java source line #63	-> byte code offset #9
/*     */     //   Java source line #64	-> byte code offset #11
/*     */     //   Java source line #65	-> byte code offset #14
/*     */     //   Java source line #67	-> byte code offset #23
/*     */     //   Java source line #68	-> byte code offset #27
/*     */     //   Java source line #69	-> byte code offset #36
/*     */     //   Java source line #70	-> byte code offset #44
/*     */     //   Java source line #71	-> byte code offset #52
/*     */     //   Java source line #74	-> byte code offset #55
/*     */     //   Java source line #75	-> byte code offset #69
/*     */     //   Java source line #76	-> byte code offset #83
/*     */     //   Java source line #77	-> byte code offset #97
/*     */     //   Java source line #78	-> byte code offset #111
/*     */     //   Java source line #79	-> byte code offset #122
/*     */     //   Java source line #80	-> byte code offset #131
/*     */     //   Java source line #79	-> byte code offset #136
/*     */     //   Java source line #81	-> byte code offset #138
/*     */     //   Java source line #82	-> byte code offset #145
/*     */     //   Java source line #83	-> byte code offset #159
/*     */     //   Java source line #71	-> byte code offset #173
/*     */     //   Java source line #89	-> byte code offset #183
/*     */     //   Java source line #90	-> byte code offset #188
/*     */     //   Java source line #92	-> byte code offset #193
/*     */     //   Java source line #93	-> byte code offset #198
/*     */     //   Java source line #94	-> byte code offset #205
/*     */     //   Java source line #95	-> byte code offset #209
/*     */     //   Java source line #96	-> byte code offset #215
/*     */     //   Java source line #97	-> byte code offset #219
/*     */     //   Java source line #91	-> byte code offset #228
/*     */     //   Java source line #92	-> byte code offset #230
/*     */     //   Java source line #93	-> byte code offset #235
/*     */     //   Java source line #94	-> byte code offset #242
/*     */     //   Java source line #95	-> byte code offset #246
/*     */     //   Java source line #96	-> byte code offset #252
/*     */     //   Java source line #97	-> byte code offset #256
/*     */     //   Java source line #98	-> byte code offset #262
/*     */     //   Java source line #92	-> byte code offset #265
/*     */     //   Java source line #93	-> byte code offset #270
/*     */     //   Java source line #94	-> byte code offset #277
/*     */     //   Java source line #95	-> byte code offset #281
/*     */     //   Java source line #96	-> byte code offset #287
/*     */     //   Java source line #97	-> byte code offset #291
/*     */     //   Java source line #99	-> byte code offset #297
/*     */     // Local variable table:
/*     */     //   start	length	slot	name	signature
/*     */     //   0	300	0	this	ArticleDAOImpl
/*     */     //   0	300	1	articleid	int
/*     */     //   8	284	2	connection	Connection
/*     */     //   10	272	3	preparedStatement	PreparedStatement
/*     */     //   12	259	4	resultSet	java.sql.ResultSet
/*     */     //   21	277	5	article	com.groom.bean.Article
/*     */     //   25	4	6	query	String
/*     */     //   186	3	6	exception	SQLException
/*     */     //   120	12	7	timestamp	java.sql.Timestamp
/*     */     //   136	5	8	dateTime	String
/*     */     //   228	35	9	localObject	Object
/*     */     // Exception table:
/*     */     //   from	to	target	type
/*     */     //   23	183	186	java/sql/SQLException
/*     */     //   23	193	228	finally
/*     */   }
/*     */   
/*     */   public boolean updateArticleViewsCount(int articleid)
/*     */     throws SQLException
/*     */   {
/* 104 */     Connection connection = ds.getConnection();
/* 105 */     PreparedStatement preparedStatement = null;
/*     */     try
/*     */     {
/* 108 */       String query = "UPDATE ARTICLE SET NO_OF_VIEWS=NO_OF_VIEWS+1 WHERE ARTICLE_ID=?";
/* 109 */       preparedStatement = connection.prepareStatement(query);
/* 110 */       preparedStatement.setInt(1, articleid);
/* 111 */       int updateStatus = preparedStatement.executeUpdate();
/* 112 */       if (updateStatus == 1) {
/* 113 */         return true;
/*     */       }
/*     */     } catch (SQLException exception) {
/* 116 */       exception.printStackTrace();
/*     */     }
/*     */     finally {
/* 119 */       if (preparedStatement != null)
/* 120 */         preparedStatement.close();
/* 121 */       if (connection != null) {
/* 122 */         connection.close();
/*     */       }
/*     */     }
/* 119 */     if (preparedStatement != null)
/* 120 */       preparedStatement.close();
/* 121 */     if (connection != null) {
/* 122 */       connection.close();
/*     */     }
/* 124 */     return false;
/*     */   }
/*     */ }


/* Location:              D:\New folder\WEB-INF\classes\com\groom.zip!\groom\groom\dao\impl\ArticleDAOImpl.class
 * Java compiler version: 6 (50.0)
 * JD-Core Version:       0.7.1
 */