/*     */ package com.groom.dao.impl;
/*     */ 
/*     */ import com.groom.dao.BaseDAO;
/*     */ import com.groom.dao.MiscDAO;
/*     */ import com.groom.util.GroomUtil;
/*     */ import java.io.PrintStream;
/*     */ import java.sql.Connection;
/*     */ import java.sql.Date;
/*     */ import java.sql.PreparedStatement;
/*     */ import java.sql.ResultSet;
/*     */ import java.sql.SQLException;
/*     */ import javax.sql.DataSource;
/*     */ 
/*     */ public class MiscDAOImpl
/*     */   extends BaseDAO
/*     */   implements MiscDAO
/*     */ {
/*     */   /* Error */
/*     */   public int addprodigy(String username, String teamname, String school, String teamdetails, String city, String email, String phone, String theme, String title, String idea)
/*     */     throws SQLException
/*     */   {
/*     */     // Byte code:
/*     */     //   0: getstatic 21	com/groom/dao/impl/MiscDAOImpl:ds	Ljavax/sql/DataSource;
/*     */     //   3: invokeinterface 25 1 0
/*     */     //   8: astore 11
/*     */     //   10: aconst_null
/*     */     //   11: astore 12
/*     */     //   13: aconst_null
/*     */     //   14: astore 13
/*     */     //   16: iconst_0
/*     */     //   17: istore 14
/*     */     //   19: ldc 31
/*     */     //   21: astore 15
/*     */     //   23: aload 11
/*     */     //   25: aload 15
/*     */     //   27: invokeinterface 33 2 0
/*     */     //   32: astore 12
/*     */     //   34: aload 12
/*     */     //   36: iconst_1
/*     */     //   37: aload_1
/*     */     //   38: invokeinterface 39 3 0
/*     */     //   43: aload 12
/*     */     //   45: iconst_2
/*     */     //   46: aload_2
/*     */     //   47: invokeinterface 39 3 0
/*     */     //   52: aload 12
/*     */     //   54: iconst_3
/*     */     //   55: aload_3
/*     */     //   56: invokeinterface 39 3 0
/*     */     //   61: aload 12
/*     */     //   63: iconst_4
/*     */     //   64: aload 4
/*     */     //   66: invokeinterface 39 3 0
/*     */     //   71: aload 12
/*     */     //   73: iconst_5
/*     */     //   74: aload 5
/*     */     //   76: invokeinterface 39 3 0
/*     */     //   81: aload 12
/*     */     //   83: bipush 6
/*     */     //   85: aload 6
/*     */     //   87: invokeinterface 39 3 0
/*     */     //   92: aload 12
/*     */     //   94: bipush 7
/*     */     //   96: aload 7
/*     */     //   98: invokeinterface 39 3 0
/*     */     //   103: aload 12
/*     */     //   105: bipush 8
/*     */     //   107: aload 8
/*     */     //   109: invokeinterface 39 3 0
/*     */     //   114: aload 12
/*     */     //   116: bipush 9
/*     */     //   118: aload 9
/*     */     //   120: invokeinterface 39 3 0
/*     */     //   125: aload 12
/*     */     //   127: bipush 10
/*     */     //   129: aload 10
/*     */     //   131: invokeinterface 39 3 0
/*     */     //   136: aload 12
/*     */     //   138: bipush 11
/*     */     //   140: invokestatic 45	com/groom/util/GroomUtil:getCurrentDate	()Ljava/sql/Date;
/*     */     //   143: invokeinterface 51 3 0
/*     */     //   148: aload 12
/*     */     //   150: invokeinterface 55 1 0
/*     */     //   155: iconst_1
/*     */     //   156: if_icmpne +131 -> 287
/*     */     //   159: aload 11
/*     */     //   161: ldc 59
/*     */     //   163: invokeinterface 33 2 0
/*     */     //   168: astore 12
/*     */     //   170: aload 12
/*     */     //   172: invokeinterface 61 1 0
/*     */     //   177: astore 13
/*     */     //   179: aload 13
/*     */     //   181: invokeinterface 65 1 0
/*     */     //   186: pop
/*     */     //   187: aload 13
/*     */     //   189: iconst_1
/*     */     //   190: invokeinterface 71 2 0
/*     */     //   195: istore 14
/*     */     //   197: goto +90 -> 287
/*     */     //   200: astore 15
/*     */     //   202: aload 15
/*     */     //   204: invokevirtual 75	java/sql/SQLException:printStackTrace	()V
/*     */     //   207: aload 13
/*     */     //   209: ifnull +10 -> 219
/*     */     //   212: aload 13
/*     */     //   214: invokeinterface 78 1 0
/*     */     //   219: aload 12
/*     */     //   221: ifnull +10 -> 231
/*     */     //   224: aload 12
/*     */     //   226: invokeinterface 81 1 0
/*     */     //   231: aload 11
/*     */     //   233: ifnull +90 -> 323
/*     */     //   236: aload 11
/*     */     //   238: invokeinterface 82 1 0
/*     */     //   243: goto +80 -> 323
/*     */     //   246: astore 16
/*     */     //   248: aload 13
/*     */     //   250: ifnull +10 -> 260
/*     */     //   253: aload 13
/*     */     //   255: invokeinterface 78 1 0
/*     */     //   260: aload 12
/*     */     //   262: ifnull +10 -> 272
/*     */     //   265: aload 12
/*     */     //   267: invokeinterface 81 1 0
/*     */     //   272: aload 11
/*     */     //   274: ifnull +10 -> 284
/*     */     //   277: aload 11
/*     */     //   279: invokeinterface 82 1 0
/*     */     //   284: aload 16
/*     */     //   286: athrow
/*     */     //   287: aload 13
/*     */     //   289: ifnull +10 -> 299
/*     */     //   292: aload 13
/*     */     //   294: invokeinterface 78 1 0
/*     */     //   299: aload 12
/*     */     //   301: ifnull +10 -> 311
/*     */     //   304: aload 12
/*     */     //   306: invokeinterface 81 1 0
/*     */     //   311: aload 11
/*     */     //   313: ifnull +10 -> 323
/*     */     //   316: aload 11
/*     */     //   318: invokeinterface 82 1 0
/*     */     //   323: iload 14
/*     */     //   325: ireturn
/*     */     // Line number table:
/*     */     //   Java source line #24	-> byte code offset #0
/*     */     //   Java source line #25	-> byte code offset #10
/*     */     //   Java source line #26	-> byte code offset #13
/*     */     //   Java source line #27	-> byte code offset #16
/*     */     //   Java source line #29	-> byte code offset #19
/*     */     //   Java source line #30	-> byte code offset #23
/*     */     //   Java source line #31	-> byte code offset #34
/*     */     //   Java source line #32	-> byte code offset #43
/*     */     //   Java source line #33	-> byte code offset #52
/*     */     //   Java source line #34	-> byte code offset #61
/*     */     //   Java source line #35	-> byte code offset #71
/*     */     //   Java source line #36	-> byte code offset #81
/*     */     //   Java source line #37	-> byte code offset #92
/*     */     //   Java source line #38	-> byte code offset #103
/*     */     //   Java source line #39	-> byte code offset #114
/*     */     //   Java source line #40	-> byte code offset #125
/*     */     //   Java source line #41	-> byte code offset #136
/*     */     //   Java source line #44	-> byte code offset #148
/*     */     //   Java source line #45	-> byte code offset #159
/*     */     //   Java source line #46	-> byte code offset #161
/*     */     //   Java source line #45	-> byte code offset #168
/*     */     //   Java source line #47	-> byte code offset #170
/*     */     //   Java source line #48	-> byte code offset #179
/*     */     //   Java source line #49	-> byte code offset #187
/*     */     //   Java source line #51	-> byte code offset #197
/*     */     //   Java source line #52	-> byte code offset #202
/*     */     //   Java source line #54	-> byte code offset #207
/*     */     //   Java source line #55	-> byte code offset #212
/*     */     //   Java source line #56	-> byte code offset #219
/*     */     //   Java source line #57	-> byte code offset #224
/*     */     //   Java source line #58	-> byte code offset #231
/*     */     //   Java source line #59	-> byte code offset #236
/*     */     //   Java source line #53	-> byte code offset #246
/*     */     //   Java source line #54	-> byte code offset #248
/*     */     //   Java source line #55	-> byte code offset #253
/*     */     //   Java source line #56	-> byte code offset #260
/*     */     //   Java source line #57	-> byte code offset #265
/*     */     //   Java source line #58	-> byte code offset #272
/*     */     //   Java source line #59	-> byte code offset #277
/*     */     //   Java source line #60	-> byte code offset #284
/*     */     //   Java source line #54	-> byte code offset #287
/*     */     //   Java source line #55	-> byte code offset #292
/*     */     //   Java source line #56	-> byte code offset #299
/*     */     //   Java source line #57	-> byte code offset #304
/*     */     //   Java source line #58	-> byte code offset #311
/*     */     //   Java source line #59	-> byte code offset #316
/*     */     //   Java source line #61	-> byte code offset #323
/*     */     // Local variable table:
/*     */     //   start	length	slot	name	signature
/*     */     //   0	326	0	this	MiscDAOImpl
/*     */     //   0	326	1	username	String
/*     */     //   0	326	2	teamname	String
/*     */     //   0	326	3	school	String
/*     */     //   0	326	4	teamdetails	String
/*     */     //   0	326	5	city	String
/*     */     //   0	326	6	email	String
/*     */     //   0	326	7	phone	String
/*     */     //   0	326	8	theme	String
/*     */     //   0	326	9	title	String
/*     */     //   0	326	10	idea	String
/*     */     //   8	309	11	connection	Connection
/*     */     //   11	294	12	preparedStatement	PreparedStatement
/*     */     //   14	279	13	resultSet	ResultSet
/*     */     //   17	307	14	id	int
/*     */     //   21	5	15	query	String
/*     */     //   200	3	15	exception	SQLException
/*     */     //   246	39	16	localObject	Object
/*     */     // Exception table:
/*     */     //   from	to	target	type
/*     */     //   19	197	200	java/sql/SQLException
/*     */     //   19	207	246	finally
/*     */   }
/*     */   
/*     */   /* Error */
/*     */   public com.groom.bean.ProdigyBean getProdigyContent(int id)
/*     */     throws SQLException
/*     */   {
/*     */     // Byte code:
/*     */     //   0: aconst_null
/*     */     //   1: astore_2
/*     */     //   2: aconst_null
/*     */     //   3: astore_3
/*     */     //   4: aconst_null
/*     */     //   5: astore 4
/*     */     //   7: new 112	com/groom/bean/ProdigyBean
/*     */     //   10: dup
/*     */     //   11: invokespecial 114	com/groom/bean/ProdigyBean:<init>	()V
/*     */     //   14: astore 5
/*     */     //   16: getstatic 21	com/groom/dao/impl/MiscDAOImpl:ds	Ljavax/sql/DataSource;
/*     */     //   19: invokeinterface 25 1 0
/*     */     //   24: astore_2
/*     */     //   25: ldc 115
/*     */     //   27: astore 6
/*     */     //   29: aload_2
/*     */     //   30: aload 6
/*     */     //   32: invokeinterface 33 2 0
/*     */     //   37: astore_3
/*     */     //   38: aload_3
/*     */     //   39: iconst_1
/*     */     //   40: iload_1
/*     */     //   41: invokeinterface 117 3 0
/*     */     //   46: aload_3
/*     */     //   47: invokeinterface 61 1 0
/*     */     //   52: astore 4
/*     */     //   54: goto +199 -> 253
/*     */     //   57: aload 5
/*     */     //   59: aload 4
/*     */     //   61: ldc 121
/*     */     //   63: invokeinterface 123 2 0
/*     */     //   68: invokevirtual 126	com/groom/bean/ProdigyBean:setId	(I)V
/*     */     //   71: aload 5
/*     */     //   73: aload 4
/*     */     //   75: ldc -126
/*     */     //   77: invokeinterface 132 2 0
/*     */     //   82: invokevirtual 136	com/groom/bean/ProdigyBean:setUsername	(Ljava/lang/String;)V
/*     */     //   85: aload 5
/*     */     //   87: aload 4
/*     */     //   89: ldc -116
/*     */     //   91: invokeinterface 132 2 0
/*     */     //   96: invokevirtual 142	com/groom/bean/ProdigyBean:setTeamname	(Ljava/lang/String;)V
/*     */     //   99: aload 5
/*     */     //   101: aload 4
/*     */     //   103: ldc -111
/*     */     //   105: invokeinterface 132 2 0
/*     */     //   110: invokevirtual 147	com/groom/bean/ProdigyBean:setSchoolname	(Ljava/lang/String;)V
/*     */     //   113: aload 5
/*     */     //   115: aload 4
/*     */     //   117: ldc -106
/*     */     //   119: invokeinterface 132 2 0
/*     */     //   124: invokevirtual 152	com/groom/bean/ProdigyBean:setTeamdetails	(Ljava/lang/String;)V
/*     */     //   127: aload 5
/*     */     //   129: aload 4
/*     */     //   131: ldc -101
/*     */     //   133: invokeinterface 132 2 0
/*     */     //   138: invokevirtual 157	com/groom/bean/ProdigyBean:setCity	(Ljava/lang/String;)V
/*     */     //   141: aload 5
/*     */     //   143: aload 4
/*     */     //   145: ldc -96
/*     */     //   147: invokeinterface 132 2 0
/*     */     //   152: invokevirtual 162	com/groom/bean/ProdigyBean:setEmail	(Ljava/lang/String;)V
/*     */     //   155: aload 5
/*     */     //   157: aload 4
/*     */     //   159: ldc -91
/*     */     //   161: invokeinterface 132 2 0
/*     */     //   166: invokevirtual 167	com/groom/bean/ProdigyBean:setPhone	(Ljava/lang/String;)V
/*     */     //   169: aload 5
/*     */     //   171: aload 4
/*     */     //   173: ldc -86
/*     */     //   175: invokeinterface 132 2 0
/*     */     //   180: invokevirtual 172	com/groom/bean/ProdigyBean:setTheme	(Ljava/lang/String;)V
/*     */     //   183: aload 5
/*     */     //   185: aload 4
/*     */     //   187: ldc -81
/*     */     //   189: invokeinterface 132 2 0
/*     */     //   194: invokevirtual 177	com/groom/bean/ProdigyBean:setTitle	(Ljava/lang/String;)V
/*     */     //   197: aload 5
/*     */     //   199: aload 4
/*     */     //   201: ldc -76
/*     */     //   203: invokeinterface 132 2 0
/*     */     //   208: invokevirtual 182	com/groom/bean/ProdigyBean:setYouridea	(Ljava/lang/String;)V
/*     */     //   211: aload 5
/*     */     //   213: aload 4
/*     */     //   215: ldc -71
/*     */     //   217: invokeinterface 123 2 0
/*     */     //   222: invokevirtual 187	com/groom/bean/ProdigyBean:setNo_of_views	(I)V
/*     */     //   225: aload 5
/*     */     //   227: aload 4
/*     */     //   229: ldc -66
/*     */     //   231: invokeinterface 123 2 0
/*     */     //   236: invokevirtual 192	com/groom/bean/ProdigyBean:setNo_of_votes	(I)V
/*     */     //   239: aload 5
/*     */     //   241: aload 4
/*     */     //   243: ldc -61
/*     */     //   245: invokeinterface 197 2 0
/*     */     //   250: invokevirtual 201	com/groom/bean/ProdigyBean:setPostedDate	(Ljava/sql/Date;)V
/*     */     //   253: aload 4
/*     */     //   255: invokeinterface 65 1 0
/*     */     //   260: ifne -203 -> 57
/*     */     //   263: aload 4
/*     */     //   265: invokeinterface 78 1 0
/*     */     //   270: goto +38 -> 308
/*     */     //   273: astore 6
/*     */     //   275: aload 6
/*     */     //   277: invokevirtual 75	java/sql/SQLException:printStackTrace	()V
/*     */     //   280: aload_2
/*     */     //   281: ifnull +37 -> 318
/*     */     //   284: aload_2
/*     */     //   285: invokeinterface 82 1 0
/*     */     //   290: goto +28 -> 318
/*     */     //   293: astore 7
/*     */     //   295: aload_2
/*     */     //   296: ifnull +9 -> 305
/*     */     //   299: aload_2
/*     */     //   300: invokeinterface 82 1 0
/*     */     //   305: aload 7
/*     */     //   307: athrow
/*     */     //   308: aload_2
/*     */     //   309: ifnull +9 -> 318
/*     */     //   312: aload_2
/*     */     //   313: invokeinterface 82 1 0
/*     */     //   318: aload 5
/*     */     //   320: areturn
/*     */     // Line number table:
/*     */     //   Java source line #65	-> byte code offset #0
/*     */     //   Java source line #66	-> byte code offset #2
/*     */     //   Java source line #67	-> byte code offset #4
/*     */     //   Java source line #68	-> byte code offset #7
/*     */     //   Java source line #70	-> byte code offset #16
/*     */     //   Java source line #71	-> byte code offset #25
/*     */     //   Java source line #72	-> byte code offset #29
/*     */     //   Java source line #73	-> byte code offset #38
/*     */     //   Java source line #74	-> byte code offset #46
/*     */     //   Java source line #76	-> byte code offset #54
/*     */     //   Java source line #77	-> byte code offset #57
/*     */     //   Java source line #78	-> byte code offset #71
/*     */     //   Java source line #79	-> byte code offset #85
/*     */     //   Java source line #80	-> byte code offset #99
/*     */     //   Java source line #81	-> byte code offset #113
/*     */     //   Java source line #82	-> byte code offset #127
/*     */     //   Java source line #83	-> byte code offset #141
/*     */     //   Java source line #84	-> byte code offset #155
/*     */     //   Java source line #85	-> byte code offset #169
/*     */     //   Java source line #86	-> byte code offset #183
/*     */     //   Java source line #87	-> byte code offset #197
/*     */     //   Java source line #88	-> byte code offset #211
/*     */     //   Java source line #89	-> byte code offset #225
/*     */     //   Java source line #90	-> byte code offset #239
/*     */     //   Java source line #76	-> byte code offset #253
/*     */     //   Java source line #93	-> byte code offset #263
/*     */     //   Java source line #94	-> byte code offset #270
/*     */     //   Java source line #95	-> byte code offset #275
/*     */     //   Java source line #97	-> byte code offset #280
/*     */     //   Java source line #98	-> byte code offset #284
/*     */     //   Java source line #96	-> byte code offset #293
/*     */     //   Java source line #97	-> byte code offset #295
/*     */     //   Java source line #98	-> byte code offset #299
/*     */     //   Java source line #100	-> byte code offset #305
/*     */     //   Java source line #97	-> byte code offset #308
/*     */     //   Java source line #98	-> byte code offset #312
/*     */     //   Java source line #101	-> byte code offset #318
/*     */     // Local variable table:
/*     */     //   start	length	slot	name	signature
/*     */     //   0	321	0	this	MiscDAOImpl
/*     */     //   0	321	1	id	int
/*     */     //   1	312	2	connection	Connection
/*     */     //   3	44	3	statement	PreparedStatement
/*     */     //   5	259	4	resultSet	ResultSet
/*     */     //   14	305	5	bean	com.groom.bean.ProdigyBean
/*     */     //   27	4	6	query	String
/*     */     //   273	3	6	exception	SQLException
/*     */     //   293	13	7	localObject	Object
/*     */     // Exception table:
/*     */     //   from	to	target	type
/*     */     //   16	270	273	java/sql/SQLException
/*     */     //   16	280	293	finally
/*     */   }
/*     */   
/*     */   public boolean voteProdigyEntry(String votinguser, int id)
/*     */     throws SQLException
/*     */   {
/* 107 */     Connection conn = null;
/* 108 */     PreparedStatement preparedStatement = null;
/* 109 */     PreparedStatement updateps = null;
/*     */     
/* 111 */     String date = null;
/*     */     try {
/* 113 */       conn = ds.getConnection();
/* 114 */       String selectQuery = "SELECT DATE_OF_LIKE FROM VALIDATE_LIKES WHERE USER_NAME=? AND ID=?";
/* 115 */       preparedStatement = conn.prepareStatement(selectQuery);
/* 116 */       preparedStatement.setString(1, votinguser);
/* 117 */       preparedStatement.setInt(2, id);
/* 118 */       ResultSet resultSet = preparedStatement.executeQuery();
/* 119 */       while (resultSet.next()) {
/* 120 */         System.out.println("already user is there");
/* 121 */         date = resultSet.getDate(1).toString();
/*     */       }
/* 123 */       if ((date == null) || (date != GroomUtil.getCurrentDate().toString())) {
/* 124 */         String query = "UPDATE PRODIGIES SET NO_OF_VOTES=NO_OF_VOTES+1 WHERE ID=?";
/* 125 */         preparedStatement = conn.prepareStatement(query);
/* 126 */         preparedStatement.setInt(1, id);
/* 127 */         String query1 = "INSERT INTO VALIDATE_LIKES(USER_NAME, ID, DATE_OF_LIKE) VALUES(?,?,?)";
/* 128 */         preparedStatement = conn.prepareStatement(query1);
/* 129 */         preparedStatement.setString(1, votinguser);
/* 130 */         preparedStatement.setInt(2, id);
/* 131 */         preparedStatement.setDate(3, GroomUtil.getCurrentDate());
/*     */         
/* 133 */         int status = updateps.executeUpdate();
/* 134 */         System.out.println("user updated");
/* 135 */         if (status > 0)
/* 136 */           return true;
/*     */       } else {
/* 138 */         System.out.println("Already voted today, Try again tomorrow");
/*     */       }
/*     */     } finally {
/* 141 */       if (preparedStatement != null)
/* 142 */         preparedStatement.close();
/* 143 */       if (updateps != null)
/* 144 */         updateps.close();
/* 145 */       if (conn != null) {
/* 146 */         conn.close();
/*     */       }
/*     */     }
/* 141 */     if (preparedStatement != null)
/* 142 */       preparedStatement.close();
/* 143 */     if (updateps != null)
/* 144 */       updateps.close();
/* 145 */     if (conn != null) {
/* 146 */       conn.close();
/*     */     }
/* 148 */     return false;
/*     */   }
/*     */   
/*     */   public boolean isProdigyExist(int id) throws SQLException {
/* 152 */     Connection connection = null;
/* 153 */     PreparedStatement statement = null;
/* 154 */     ResultSet resultSet = null;
/*     */     try {
/* 156 */       connection = ds.getConnection();
/* 157 */       String query = "SELECT * FROM PRODIGIES WHERE ID=?";
/* 158 */       statement = connection.prepareStatement(query);
/* 159 */       statement.setInt(1, id);
/* 160 */       resultSet = statement.executeQuery();
/* 161 */       return resultSet.next();
/*     */     } catch (SQLException exception) {
/* 163 */       exception.printStackTrace();
/*     */     } finally {
/* 165 */       if (connection != null)
/* 166 */         connection.close();
/*     */     }
/* 168 */     return false;
/*     */   }
/*     */ }


/* Location:              D:\New folder\WEB-INF\classes\com\groom.zip!\groom\dao\impl\MiscDAOImpl1.class
 * Java compiler version: 7 (51.0)
 * JD-Core Version:       0.7.1
 */