/*     */ package com.groom.dao.impl;
/*     */ 
/*     */ import com.groom.bean.QuizPoints;
/*     */ import com.groom.dao.BaseDAO;
/*     */ import com.groom.dao.QuizDAO;
/*     */ import com.groom.util.GroomUtil;
/*     */ import java.io.PrintStream;
/*     */ import java.sql.Connection;
/*     */ import java.sql.PreparedStatement;
/*     */ import java.sql.ResultSet;
/*     */ import java.sql.SQLException;
/*     */ import java.util.List;
/*     */ import javax.sql.DataSource;
/*     */ import org.apache.commons.lang3.StringUtils;
/*     */ 
/*     */ public class QuizDAOImpl
/*     */   extends BaseDAO
/*     */   implements QuizDAO
/*     */ {
/*     */   /* Error */
/*     */   public List<com.groom.bean.QuizQuestionDetails> getQuizDetails(String category, int topicid)
/*     */     throws SQLException
/*     */   {
/*     */     // Byte code:
/*     */     //   0: getstatic 23	com/groom/dao/impl/QuizDAOImpl:ds	Ljavax/sql/DataSource;
/*     */     //   3: invokeinterface 27 1 0
/*     */     //   8: astore_3
/*     */     //   9: aconst_null
/*     */     //   10: astore 4
/*     */     //   12: aconst_null
/*     */     //   13: astore 5
/*     */     //   15: new 33	java/util/ArrayList
/*     */     //   18: dup
/*     */     //   19: invokespecial 35	java/util/ArrayList:<init>	()V
/*     */     //   22: astore 6
/*     */     //   24: new 36	java/lang/StringBuilder
/*     */     //   27: dup
/*     */     //   28: ldc 38
/*     */     //   30: invokespecial 40	java/lang/StringBuilder:<init>	(Ljava/lang/String;)V
/*     */     //   33: aload_1
/*     */     //   34: invokevirtual 43	java/lang/StringBuilder:append	(Ljava/lang/String;)Ljava/lang/StringBuilder;
/*     */     //   37: ldc 47
/*     */     //   39: invokevirtual 43	java/lang/StringBuilder:append	(Ljava/lang/String;)Ljava/lang/StringBuilder;
/*     */     //   42: aload_1
/*     */     //   43: invokevirtual 43	java/lang/StringBuilder:append	(Ljava/lang/String;)Ljava/lang/StringBuilder;
/*     */     //   46: ldc 49
/*     */     //   48: invokevirtual 43	java/lang/StringBuilder:append	(Ljava/lang/String;)Ljava/lang/StringBuilder;
/*     */     //   51: ldc 51
/*     */     //   53: invokevirtual 43	java/lang/StringBuilder:append	(Ljava/lang/String;)Ljava/lang/StringBuilder;
/*     */     //   56: invokevirtual 53	java/lang/StringBuilder:toString	()Ljava/lang/String;
/*     */     //   59: astore 7
/*     */     //   61: getstatic 57	java/lang/System:out	Ljava/io/PrintStream;
/*     */     //   64: aload 7
/*     */     //   66: invokevirtual 63	java/io/PrintStream:println	(Ljava/lang/String;)V
/*     */     //   69: aload_3
/*     */     //   70: aload 7
/*     */     //   72: invokeinterface 68 2 0
/*     */     //   77: astore 4
/*     */     //   79: aload 4
/*     */     //   81: iconst_1
/*     */     //   82: iload_2
/*     */     //   83: invokeinterface 74 3 0
/*     */     //   88: aload 4
/*     */     //   90: invokeinterface 80 1 0
/*     */     //   95: astore 5
/*     */     //   97: goto +222 -> 319
/*     */     //   100: new 84	com/groom/bean/QuizQuestionDetails
/*     */     //   103: dup
/*     */     //   104: invokespecial 86	com/groom/bean/QuizQuestionDetails:<init>	()V
/*     */     //   107: astore 8
/*     */     //   109: aload 8
/*     */     //   111: aload 5
/*     */     //   113: ldc 87
/*     */     //   115: invokeinterface 89 2 0
/*     */     //   120: invokevirtual 95	com/groom/bean/QuizQuestionDetails:setQ_id	(I)V
/*     */     //   123: aload 8
/*     */     //   125: aload 5
/*     */     //   127: ldc 99
/*     */     //   129: invokeinterface 101 2 0
/*     */     //   134: invokevirtual 105	com/groom/bean/QuizQuestionDetails:setQuestion	(Ljava/lang/String;)V
/*     */     //   137: aload 8
/*     */     //   139: aload 5
/*     */     //   141: ldc 108
/*     */     //   143: invokeinterface 101 2 0
/*     */     //   148: invokevirtual 110	com/groom/bean/QuizQuestionDetails:setOption_a	(Ljava/lang/String;)V
/*     */     //   151: aload 8
/*     */     //   153: aload 5
/*     */     //   155: ldc 113
/*     */     //   157: invokeinterface 101 2 0
/*     */     //   162: invokevirtual 115	com/groom/bean/QuizQuestionDetails:setOption_b	(Ljava/lang/String;)V
/*     */     //   165: aload 8
/*     */     //   167: aload 5
/*     */     //   169: ldc 118
/*     */     //   171: invokeinterface 101 2 0
/*     */     //   176: invokevirtual 120	com/groom/bean/QuizQuestionDetails:setOption_c	(Ljava/lang/String;)V
/*     */     //   179: aload 8
/*     */     //   181: aload 5
/*     */     //   183: ldc 123
/*     */     //   185: invokeinterface 101 2 0
/*     */     //   190: invokevirtual 125	com/groom/bean/QuizQuestionDetails:setOption_d	(Ljava/lang/String;)V
/*     */     //   193: aload 8
/*     */     //   195: aload 5
/*     */     //   197: ldc -128
/*     */     //   199: invokeinterface 101 2 0
/*     */     //   204: invokevirtual 130	com/groom/bean/QuizQuestionDetails:setAnswer	(Ljava/lang/String;)V
/*     */     //   207: aload 8
/*     */     //   209: aload 5
/*     */     //   211: ldc -123
/*     */     //   213: invokeinterface 89 2 0
/*     */     //   218: invokevirtual 135	com/groom/bean/QuizQuestionDetails:setTopicid	(I)V
/*     */     //   221: aload 5
/*     */     //   223: ldc -118
/*     */     //   225: invokeinterface 101 2 0
/*     */     //   230: ifnull +23 -> 253
/*     */     //   233: aload 8
/*     */     //   235: aload 5
/*     */     //   237: ldc -118
/*     */     //   239: invokeinterface 101 2 0
/*     */     //   244: invokevirtual 140	java/lang/String:trim	()Ljava/lang/String;
/*     */     //   247: invokevirtual 145	com/groom/bean/QuizQuestionDetails:setImage_name	(Ljava/lang/String;)V
/*     */     //   250: goto +17 -> 267
/*     */     //   253: aload 8
/*     */     //   255: aload 5
/*     */     //   257: ldc -118
/*     */     //   259: invokeinterface 101 2 0
/*     */     //   264: invokevirtual 145	com/groom/bean/QuizQuestionDetails:setImage_name	(Ljava/lang/String;)V
/*     */     //   267: aload 8
/*     */     //   269: aload 5
/*     */     //   271: ldc -108
/*     */     //   273: invokeinterface 101 2 0
/*     */     //   278: invokevirtual 150	com/groom/bean/QuizQuestionDetails:setExplanation	(Ljava/lang/String;)V
/*     */     //   281: aload 8
/*     */     //   283: aload 5
/*     */     //   285: ldc -103
/*     */     //   287: invokeinterface 101 2 0
/*     */     //   292: invokevirtual 155	com/groom/bean/QuizQuestionDetails:setTest_by	(Ljava/lang/String;)V
/*     */     //   295: aload 8
/*     */     //   297: aload 5
/*     */     //   299: ldc -98
/*     */     //   301: invokeinterface 89 2 0
/*     */     //   306: invokevirtual 160	com/groom/bean/QuizQuestionDetails:setTest_time	(I)V
/*     */     //   309: aload 6
/*     */     //   311: aload 8
/*     */     //   313: invokeinterface 163 2 0
/*     */     //   318: pop
/*     */     //   319: aload 5
/*     */     //   321: invokeinterface 169 1 0
/*     */     //   326: ifne -226 -> 100
/*     */     //   329: goto +86 -> 415
/*     */     //   332: astore 7
/*     */     //   334: aload 7
/*     */     //   336: invokevirtual 173	java/sql/SQLException:printStackTrace	()V
/*     */     //   339: aload 5
/*     */     //   341: ifnull +10 -> 351
/*     */     //   344: aload 5
/*     */     //   346: invokeinterface 176 1 0
/*     */     //   351: aload 4
/*     */     //   353: ifnull +10 -> 363
/*     */     //   356: aload 4
/*     */     //   358: invokeinterface 179 1 0
/*     */     //   363: aload_3
/*     */     //   364: ifnull +85 -> 449
/*     */     //   367: aload_3
/*     */     //   368: invokeinterface 180 1 0
/*     */     //   373: goto +76 -> 449
/*     */     //   376: astore 9
/*     */     //   378: aload 5
/*     */     //   380: ifnull +10 -> 390
/*     */     //   383: aload 5
/*     */     //   385: invokeinterface 176 1 0
/*     */     //   390: aload 4
/*     */     //   392: ifnull +10 -> 402
/*     */     //   395: aload 4
/*     */     //   397: invokeinterface 179 1 0
/*     */     //   402: aload_3
/*     */     //   403: ifnull +9 -> 412
/*     */     //   406: aload_3
/*     */     //   407: invokeinterface 180 1 0
/*     */     //   412: aload 9
/*     */     //   414: athrow
/*     */     //   415: aload 5
/*     */     //   417: ifnull +10 -> 427
/*     */     //   420: aload 5
/*     */     //   422: invokeinterface 176 1 0
/*     */     //   427: aload 4
/*     */     //   429: ifnull +10 -> 439
/*     */     //   432: aload 4
/*     */     //   434: invokeinterface 179 1 0
/*     */     //   439: aload_3
/*     */     //   440: ifnull +9 -> 449
/*     */     //   443: aload_3
/*     */     //   444: invokeinterface 180 1 0
/*     */     //   449: aload 6
/*     */     //   451: areturn
/*     */     // Line number table:
/*     */     //   Java source line #32	-> byte code offset #0
/*     */     //   Java source line #33	-> byte code offset #9
/*     */     //   Java source line #34	-> byte code offset #12
/*     */     //   Java source line #35	-> byte code offset #15
/*     */     //   Java source line #39	-> byte code offset #24
/*     */     //   Java source line #40	-> byte code offset #51
/*     */     //   Java source line #39	-> byte code offset #56
/*     */     //   Java source line #41	-> byte code offset #61
/*     */     //   Java source line #42	-> byte code offset #69
/*     */     //   Java source line #43	-> byte code offset #79
/*     */     //   Java source line #44	-> byte code offset #88
/*     */     //   Java source line #45	-> byte code offset #97
/*     */     //   Java source line #46	-> byte code offset #100
/*     */     //   Java source line #47	-> byte code offset #109
/*     */     //   Java source line #48	-> byte code offset #123
/*     */     //   Java source line #49	-> byte code offset #137
/*     */     //   Java source line #50	-> byte code offset #151
/*     */     //   Java source line #51	-> byte code offset #165
/*     */     //   Java source line #52	-> byte code offset #179
/*     */     //   Java source line #53	-> byte code offset #193
/*     */     //   Java source line #54	-> byte code offset #207
/*     */     //   Java source line #55	-> byte code offset #221
/*     */     //   Java source line #56	-> byte code offset #233
/*     */     //   Java source line #57	-> byte code offset #244
/*     */     //   Java source line #56	-> byte code offset #247
/*     */     //   Java source line #57	-> byte code offset #250
/*     */     //   Java source line #59	-> byte code offset #253
/*     */     //   Java source line #60	-> byte code offset #267
/*     */     //   Java source line #61	-> byte code offset #281
/*     */     //   Java source line #62	-> byte code offset #295
/*     */     //   Java source line #63	-> byte code offset #309
/*     */     //   Java source line #45	-> byte code offset #319
/*     */     //   Java source line #67	-> byte code offset #329
/*     */     //   Java source line #68	-> byte code offset #334
/*     */     //   Java source line #70	-> byte code offset #339
/*     */     //   Java source line #71	-> byte code offset #344
/*     */     //   Java source line #72	-> byte code offset #351
/*     */     //   Java source line #73	-> byte code offset #356
/*     */     //   Java source line #74	-> byte code offset #363
/*     */     //   Java source line #75	-> byte code offset #367
/*     */     //   Java source line #69	-> byte code offset #376
/*     */     //   Java source line #70	-> byte code offset #378
/*     */     //   Java source line #71	-> byte code offset #383
/*     */     //   Java source line #72	-> byte code offset #390
/*     */     //   Java source line #73	-> byte code offset #395
/*     */     //   Java source line #74	-> byte code offset #402
/*     */     //   Java source line #75	-> byte code offset #406
/*     */     //   Java source line #76	-> byte code offset #412
/*     */     //   Java source line #70	-> byte code offset #415
/*     */     //   Java source line #71	-> byte code offset #420
/*     */     //   Java source line #72	-> byte code offset #427
/*     */     //   Java source line #73	-> byte code offset #432
/*     */     //   Java source line #74	-> byte code offset #439
/*     */     //   Java source line #75	-> byte code offset #443
/*     */     //   Java source line #77	-> byte code offset #449
/*     */     // Local variable table:
/*     */     //   start	length	slot	name	signature
/*     */     //   0	452	0	this	QuizDAOImpl
/*     */     //   0	452	1	category	String
/*     */     //   0	452	2	topicid	int
/*     */     //   8	436	3	connection	Connection
/*     */     //   10	423	4	preparedStatement	PreparedStatement
/*     */     //   13	408	5	resultSet	ResultSet
/*     */     //   22	428	6	questionDetails	List<com.groom.bean.QuizQuestionDetails>
/*     */     //   59	12	7	query	String
/*     */     //   332	3	7	exception	SQLException
/*     */     //   107	205	8	details	com.groom.bean.QuizQuestionDetails
/*     */     //   376	37	9	localObject	Object
/*     */     // Exception table:
/*     */     //   from	to	target	type
/*     */     //   24	329	332	java/sql/SQLException
/*     */     //   24	339	376	finally
/*     */   }
/*     */   
/*     */   /* Error */
/*     */   public java.util.Map<Integer, String> getQuizAnswers(String questionIds, String category)
/*     */     throws SQLException
/*     */   {
/*     */     // Byte code:
/*     */     //   0: getstatic 23	com/groom/dao/impl/QuizDAOImpl:ds	Ljavax/sql/DataSource;
/*     */     //   3: invokeinterface 27 1 0
/*     */     //   8: astore_3
/*     */     //   9: aconst_null
/*     */     //   10: astore 4
/*     */     //   12: aconst_null
/*     */     //   13: astore 5
/*     */     //   15: new 206	java/util/HashMap
/*     */     //   18: dup
/*     */     //   19: invokespecial 208	java/util/HashMap:<init>	()V
/*     */     //   22: astore 6
/*     */     //   24: new 36	java/lang/StringBuilder
/*     */     //   27: dup
/*     */     //   28: ldc -47
/*     */     //   30: invokespecial 40	java/lang/StringBuilder:<init>	(Ljava/lang/String;)V
/*     */     //   33: aload_2
/*     */     //   34: invokevirtual 43	java/lang/StringBuilder:append	(Ljava/lang/String;)Ljava/lang/StringBuilder;
/*     */     //   37: ldc -45
/*     */     //   39: invokevirtual 43	java/lang/StringBuilder:append	(Ljava/lang/String;)Ljava/lang/StringBuilder;
/*     */     //   42: aload_1
/*     */     //   43: invokevirtual 43	java/lang/StringBuilder:append	(Ljava/lang/String;)Ljava/lang/StringBuilder;
/*     */     //   46: ldc -43
/*     */     //   48: invokevirtual 43	java/lang/StringBuilder:append	(Ljava/lang/String;)Ljava/lang/StringBuilder;
/*     */     //   51: invokevirtual 53	java/lang/StringBuilder:toString	()Ljava/lang/String;
/*     */     //   54: astore 7
/*     */     //   56: aload_3
/*     */     //   57: aload 7
/*     */     //   59: invokeinterface 68 2 0
/*     */     //   64: astore 4
/*     */     //   66: aload 4
/*     */     //   68: invokeinterface 80 1 0
/*     */     //   73: astore 5
/*     */     //   75: goto +32 -> 107
/*     */     //   78: aload 6
/*     */     //   80: aload 5
/*     */     //   82: ldc 87
/*     */     //   84: invokeinterface 89 2 0
/*     */     //   89: invokestatic 215	java/lang/Integer:valueOf	(I)Ljava/lang/Integer;
/*     */     //   92: aload 5
/*     */     //   94: ldc -128
/*     */     //   96: invokeinterface 101 2 0
/*     */     //   101: invokeinterface 221 3 0
/*     */     //   106: pop
/*     */     //   107: aload 5
/*     */     //   109: invokeinterface 169 1 0
/*     */     //   114: ifne -36 -> 78
/*     */     //   117: goto +86 -> 203
/*     */     //   120: astore 7
/*     */     //   122: aload 7
/*     */     //   124: invokevirtual 173	java/sql/SQLException:printStackTrace	()V
/*     */     //   127: aload 5
/*     */     //   129: ifnull +10 -> 139
/*     */     //   132: aload 5
/*     */     //   134: invokeinterface 176 1 0
/*     */     //   139: aload 4
/*     */     //   141: ifnull +10 -> 151
/*     */     //   144: aload 4
/*     */     //   146: invokeinterface 179 1 0
/*     */     //   151: aload_3
/*     */     //   152: ifnull +85 -> 237
/*     */     //   155: aload_3
/*     */     //   156: invokeinterface 180 1 0
/*     */     //   161: goto +76 -> 237
/*     */     //   164: astore 8
/*     */     //   166: aload 5
/*     */     //   168: ifnull +10 -> 178
/*     */     //   171: aload 5
/*     */     //   173: invokeinterface 176 1 0
/*     */     //   178: aload 4
/*     */     //   180: ifnull +10 -> 190
/*     */     //   183: aload 4
/*     */     //   185: invokeinterface 179 1 0
/*     */     //   190: aload_3
/*     */     //   191: ifnull +9 -> 200
/*     */     //   194: aload_3
/*     */     //   195: invokeinterface 180 1 0
/*     */     //   200: aload 8
/*     */     //   202: athrow
/*     */     //   203: aload 5
/*     */     //   205: ifnull +10 -> 215
/*     */     //   208: aload 5
/*     */     //   210: invokeinterface 176 1 0
/*     */     //   215: aload 4
/*     */     //   217: ifnull +10 -> 227
/*     */     //   220: aload 4
/*     */     //   222: invokeinterface 179 1 0
/*     */     //   227: aload_3
/*     */     //   228: ifnull +9 -> 237
/*     */     //   231: aload_3
/*     */     //   232: invokeinterface 180 1 0
/*     */     //   237: aload 6
/*     */     //   239: areturn
/*     */     // Line number table:
/*     */     //   Java source line #83	-> byte code offset #0
/*     */     //   Java source line #84	-> byte code offset #9
/*     */     //   Java source line #85	-> byte code offset #12
/*     */     //   Java source line #86	-> byte code offset #15
/*     */     //   Java source line #88	-> byte code offset #24
/*     */     //   Java source line #89	-> byte code offset #37
/*     */     //   Java source line #88	-> byte code offset #51
/*     */     //   Java source line #90	-> byte code offset #56
/*     */     //   Java source line #92	-> byte code offset #66
/*     */     //   Java source line #93	-> byte code offset #75
/*     */     //   Java source line #95	-> byte code offset #78
/*     */     //   Java source line #96	-> byte code offset #92
/*     */     //   Java source line #95	-> byte code offset #101
/*     */     //   Java source line #93	-> byte code offset #107
/*     */     //   Java source line #99	-> byte code offset #117
/*     */     //   Java source line #100	-> byte code offset #122
/*     */     //   Java source line #102	-> byte code offset #127
/*     */     //   Java source line #103	-> byte code offset #132
/*     */     //   Java source line #104	-> byte code offset #139
/*     */     //   Java source line #105	-> byte code offset #144
/*     */     //   Java source line #106	-> byte code offset #151
/*     */     //   Java source line #107	-> byte code offset #155
/*     */     //   Java source line #101	-> byte code offset #164
/*     */     //   Java source line #102	-> byte code offset #166
/*     */     //   Java source line #103	-> byte code offset #171
/*     */     //   Java source line #104	-> byte code offset #178
/*     */     //   Java source line #105	-> byte code offset #183
/*     */     //   Java source line #106	-> byte code offset #190
/*     */     //   Java source line #107	-> byte code offset #194
/*     */     //   Java source line #108	-> byte code offset #200
/*     */     //   Java source line #102	-> byte code offset #203
/*     */     //   Java source line #103	-> byte code offset #208
/*     */     //   Java source line #104	-> byte code offset #215
/*     */     //   Java source line #105	-> byte code offset #220
/*     */     //   Java source line #106	-> byte code offset #227
/*     */     //   Java source line #107	-> byte code offset #231
/*     */     //   Java source line #109	-> byte code offset #237
/*     */     // Local variable table:
/*     */     //   start	length	slot	name	signature
/*     */     //   0	240	0	this	QuizDAOImpl
/*     */     //   0	240	1	questionIds	String
/*     */     //   0	240	2	category	String
/*     */     //   8	224	3	connection	Connection
/*     */     //   10	211	4	preparedStatement	PreparedStatement
/*     */     //   13	196	5	resultSet	ResultSet
/*     */     //   22	216	6	answers	java.util.Map<Integer, String>
/*     */     //   54	4	7	query	String
/*     */     //   120	3	7	exception	SQLException
/*     */     //   164	37	8	localObject	Object
/*     */     // Exception table:
/*     */     //   from	to	target	type
/*     */     //   24	117	120	java/sql/SQLException
/*     */     //   24	127	164	finally
/*     */   }
/*     */   
/*     */   public boolean saveQuizPoints(QuizPoints quizPoints)
/*     */     throws SQLException
/*     */   {
/* 114 */     Connection connection = ds.getConnection();
/* 115 */     PreparedStatement preparedStatement = null;
/* 116 */     ResultSet resultSet = null;
/*     */     try
/*     */     {
/* 119 */       String query = "INSERT INTO " + 
/* 120 */         quizPoints.getCateogry() + 
/* 121 */         "_TEST_POINTS(USER_ID,POINTS,TOPIC_ID,QUESTION_IDS,TIME,TEST_DATE,ANSWERS_GIVEN) VALUES(?,?,?,?,?,?,?)";
/*     */       
/* 123 */       preparedStatement = connection.prepareStatement(query);
/* 124 */       preparedStatement.setInt(1, quizPoints.getU_id());
/* 125 */       preparedStatement.setInt(2, quizPoints.getPoints());
/* 126 */       preparedStatement.setInt(3, quizPoints.getTopicid());
/* 127 */       preparedStatement.setString(4, quizPoints.getQuestionIds());
/* 128 */       preparedStatement.setTime(5, quizPoints.getTime());
/* 129 */       preparedStatement.setDate(6, quizPoints.getTestDate());
/* 130 */       preparedStatement.setString(7, quizPoints.getAnswers());
/*     */       
/* 132 */       int status = preparedStatement.executeUpdate();
/* 133 */       if (status == 1)
/* 134 */         return true;
/*     */     } catch (SQLException exception) {
/* 136 */       exception.printStackTrace();
/*     */     } finally {
/* 138 */       if (resultSet != null)
/* 139 */         resultSet.close();
/* 140 */       if (preparedStatement != null)
/* 141 */         preparedStatement.close();
/* 142 */       if (connection != null) {
/* 143 */         connection.close();
/*     */       }
/*     */     }
/* 138 */     if (resultSet != null)
/* 139 */       resultSet.close();
/* 140 */     if (preparedStatement != null)
/* 141 */       preparedStatement.close();
/* 142 */     if (connection != null) {
/* 143 */       connection.close();
/*     */     }
/* 145 */     return false;
/*     */   }
/*     */   
/*     */   public boolean getTestsAttemptedByUserStaus(int userid, String category)
/*     */     throws SQLException
/*     */   {
/* 151 */     Connection connection = ds.getConnection();
/* 152 */     PreparedStatement preparedStatement = null;
/* 153 */     ResultSet resultSet = null;
/*     */     try
/*     */     {
/* 156 */       String query = "SELECT * FROM " + category + 
/* 157 */         "_TEST_POINTS WHERE USER_ID=? AND TEST_DATE=?";
/* 158 */       preparedStatement = connection.prepareStatement(query);
/* 159 */       preparedStatement.setInt(1, userid);
/* 160 */       preparedStatement.setDate(2, GroomUtil.getCurrentDate());
/* 161 */       resultSet = preparedStatement.executeQuery();
/* 162 */       if (resultSet.next()) {
/* 163 */         return true;
/*     */       }
/*     */     } catch (SQLException exception) {
/* 166 */       exception.printStackTrace();
/*     */     } finally {
/* 168 */       if (resultSet != null)
/* 169 */         resultSet.close();
/* 170 */       if (preparedStatement != null)
/* 171 */         preparedStatement.close();
/* 172 */       if (connection != null) {
/* 173 */         connection.close();
/*     */       }
/*     */     }
/* 168 */     if (resultSet != null)
/* 169 */       resultSet.close();
/* 170 */     if (preparedStatement != null)
/* 171 */       preparedStatement.close();
/* 172 */     if (connection != null) {
/* 173 */       connection.close();
/*     */     }
/*     */     
/* 176 */     return false;
/*     */   }
/*     */   
/*     */   /* Error */
/*     */   public List<com.groom.bean.TestsTopicList> getTestTopics(int userid, String category, int standard, int test_category_id)
/*     */     throws SQLException
/*     */   {
/*     */     // Byte code:
/*     */     //   0: getstatic 23	com/groom/dao/impl/QuizDAOImpl:ds	Ljavax/sql/DataSource;
/*     */     //   3: invokeinterface 27 1 0
/*     */     //   8: astore 5
/*     */     //   10: aconst_null
/*     */     //   11: astore 6
/*     */     //   13: aconst_null
/*     */     //   14: astore 7
/*     */     //   16: new 33	java/util/ArrayList
/*     */     //   19: dup
/*     */     //   20: invokespecial 35	java/util/ArrayList:<init>	()V
/*     */     //   23: astore 8
/*     */     //   25: new 36	java/lang/StringBuilder
/*     */     //   28: dup
/*     */     //   29: ldc_w 286
/*     */     //   32: invokespecial 40	java/lang/StringBuilder:<init>	(Ljava/lang/String;)V
/*     */     //   35: aload_2
/*     */     //   36: invokevirtual 43	java/lang/StringBuilder:append	(Ljava/lang/String;)Ljava/lang/StringBuilder;
/*     */     //   39: ldc_w 299
/*     */     //   42: invokevirtual 43	java/lang/StringBuilder:append	(Ljava/lang/String;)Ljava/lang/StringBuilder;
/*     */     //   45: invokestatic 290	com/groom/util/GroomUtil:getCurrentDate	()Ljava/sql/Date;
/*     */     //   48: invokevirtual 301	java/lang/StringBuilder:append	(Ljava/lang/Object;)Ljava/lang/StringBuilder;
/*     */     //   51: ldc_w 304
/*     */     //   54: invokevirtual 43	java/lang/StringBuilder:append	(Ljava/lang/String;)Ljava/lang/StringBuilder;
/*     */     //   57: invokevirtual 53	java/lang/StringBuilder:toString	()Ljava/lang/String;
/*     */     //   60: astore 9
/*     */     //   62: aload 5
/*     */     //   64: aload 9
/*     */     //   66: invokeinterface 68 2 0
/*     */     //   71: astore 6
/*     */     //   73: aload 6
/*     */     //   75: iconst_1
/*     */     //   76: iload_3
/*     */     //   77: invokeinterface 74 3 0
/*     */     //   82: aload 6
/*     */     //   84: iconst_2
/*     */     //   85: iload 4
/*     */     //   87: invokeinterface 74 3 0
/*     */     //   92: aload 6
/*     */     //   94: invokeinterface 80 1 0
/*     */     //   99: astore 7
/*     */     //   101: new 306	java/util/Date
/*     */     //   104: dup
/*     */     //   105: invokestatic 290	com/groom/util/GroomUtil:getCurrentDate	()Ljava/sql/Date;
/*     */     //   108: invokevirtual 308	java/sql/Date:getTime	()J
/*     */     //   111: invokespecial 313	java/util/Date:<init>	(J)V
/*     */     //   114: astore 10
/*     */     //   116: new 316	java/text/SimpleDateFormat
/*     */     //   119: dup
/*     */     //   120: ldc_w 318
/*     */     //   123: invokespecial 320	java/text/SimpleDateFormat:<init>	(Ljava/lang/String;)V
/*     */     //   126: astore 11
/*     */     //   128: aload 11
/*     */     //   130: aload 11
/*     */     //   132: aload 10
/*     */     //   134: invokevirtual 321	java/text/SimpleDateFormat:format	(Ljava/util/Date;)Ljava/lang/String;
/*     */     //   137: invokevirtual 325	java/text/SimpleDateFormat:parse	(Ljava/lang/String;)Ljava/util/Date;
/*     */     //   140: astore 10
/*     */     //   142: goto +274 -> 416
/*     */     //   145: new 329	com/groom/bean/TestsTopicList
/*     */     //   148: dup
/*     */     //   149: invokespecial 331	com/groom/bean/TestsTopicList:<init>	()V
/*     */     //   152: astore 12
/*     */     //   154: aload 12
/*     */     //   156: aload 7
/*     */     //   158: ldc -123
/*     */     //   160: invokeinterface 89 2 0
/*     */     //   165: invokevirtual 332	com/groom/bean/TestsTopicList:setTopicId	(I)V
/*     */     //   168: aload 12
/*     */     //   170: aload 7
/*     */     //   172: ldc_w 335
/*     */     //   175: invokeinterface 101 2 0
/*     */     //   180: invokevirtual 337	com/groom/bean/TestsTopicList:setTopicName	(Ljava/lang/String;)V
/*     */     //   183: aload 12
/*     */     //   185: aload 7
/*     */     //   187: ldc_w 340
/*     */     //   190: invokeinterface 89 2 0
/*     */     //   195: invokevirtual 342	com/groom/bean/TestsTopicList:setTopicClass	(I)V
/*     */     //   198: aload 12
/*     */     //   200: aload 7
/*     */     //   202: ldc_w 345
/*     */     //   205: invokeinterface 347 2 0
/*     */     //   210: invokevirtual 351	java/sql/Date:toString	()Ljava/lang/String;
/*     */     //   213: invokevirtual 352	com/groom/bean/TestsTopicList:setTestDate	(Ljava/lang/String;)V
/*     */     //   216: new 306	java/util/Date
/*     */     //   219: dup
/*     */     //   220: aload 7
/*     */     //   222: ldc_w 345
/*     */     //   225: invokeinterface 347 2 0
/*     */     //   230: invokevirtual 308	java/sql/Date:getTime	()J
/*     */     //   233: invokespecial 313	java/util/Date:<init>	(J)V
/*     */     //   236: astore 13
/*     */     //   238: aload 11
/*     */     //   240: aload 11
/*     */     //   242: aload 13
/*     */     //   244: invokevirtual 321	java/text/SimpleDateFormat:format	(Ljava/util/Date;)Ljava/lang/String;
/*     */     //   247: invokevirtual 325	java/text/SimpleDateFormat:parse	(Ljava/lang/String;)Ljava/util/Date;
/*     */     //   250: astore 13
/*     */     //   252: aload 13
/*     */     //   254: aload 10
/*     */     //   256: invokevirtual 355	java/util/Date:compareTo	(Ljava/util/Date;)I
/*     */     //   259: ifgt +13 -> 272
/*     */     //   262: aload 13
/*     */     //   264: aload 10
/*     */     //   266: invokevirtual 355	java/util/Date:compareTo	(Ljava/util/Date;)I
/*     */     //   269: ifne +14 -> 283
/*     */     //   272: aload 12
/*     */     //   274: ldc_w 359
/*     */     //   277: invokevirtual 361	com/groom/bean/TestsTopicList:setIsKeyAndResultAvailable	(Ljava/lang/String;)V
/*     */     //   280: goto +11 -> 291
/*     */     //   283: aload 12
/*     */     //   285: ldc_w 364
/*     */     //   288: invokevirtual 361	com/groom/bean/TestsTopicList:setIsKeyAndResultAvailable	(Ljava/lang/String;)V
/*     */     //   291: new 36	java/lang/StringBuilder
/*     */     //   294: dup
/*     */     //   295: ldc_w 286
/*     */     //   298: invokespecial 40	java/lang/StringBuilder:<init>	(Ljava/lang/String;)V
/*     */     //   301: aload_2
/*     */     //   302: invokevirtual 43	java/lang/StringBuilder:append	(Ljava/lang/String;)Ljava/lang/StringBuilder;
/*     */     //   305: ldc_w 366
/*     */     //   308: invokevirtual 43	java/lang/StringBuilder:append	(Ljava/lang/String;)Ljava/lang/StringBuilder;
/*     */     //   311: invokevirtual 53	java/lang/StringBuilder:toString	()Ljava/lang/String;
/*     */     //   314: astore 14
/*     */     //   316: aload 5
/*     */     //   318: aload 14
/*     */     //   320: invokeinterface 68 2 0
/*     */     //   325: astore 6
/*     */     //   327: aload 6
/*     */     //   329: iconst_1
/*     */     //   330: iload_1
/*     */     //   331: invokeinterface 74 3 0
/*     */     //   336: aload 6
/*     */     //   338: iconst_2
/*     */     //   339: aload 7
/*     */     //   341: ldc -123
/*     */     //   343: invokeinterface 89 2 0
/*     */     //   348: invokeinterface 74 3 0
/*     */     //   353: aload 6
/*     */     //   355: invokeinterface 80 1 0
/*     */     //   360: astore 15
/*     */     //   362: aload 15
/*     */     //   364: invokeinterface 169 1 0
/*     */     //   369: ifeq +29 -> 398
/*     */     //   372: aload 12
/*     */     //   374: ldc_w 364
/*     */     //   377: invokevirtual 368	com/groom/bean/TestsTopicList:setIsStudentAttempted	(Ljava/lang/String;)V
/*     */     //   380: aload 12
/*     */     //   382: aload 15
/*     */     //   384: ldc_w 371
/*     */     //   387: invokeinterface 101 2 0
/*     */     //   392: invokevirtual 373	com/groom/bean/TestsTopicList:setQuestionIdsList	(Ljava/lang/String;)V
/*     */     //   395: goto +11 -> 406
/*     */     //   398: aload 12
/*     */     //   400: ldc_w 359
/*     */     //   403: invokevirtual 368	com/groom/bean/TestsTopicList:setIsStudentAttempted	(Ljava/lang/String;)V
/*     */     //   406: aload 8
/*     */     //   408: aload 12
/*     */     //   410: invokeinterface 163 2 0
/*     */     //   415: pop
/*     */     //   416: aload 7
/*     */     //   418: invokeinterface 169 1 0
/*     */     //   423: ifne -278 -> 145
/*     */     //   426: goto +136 -> 562
/*     */     //   429: astore 9
/*     */     //   431: aload 9
/*     */     //   433: invokevirtual 173	java/sql/SQLException:printStackTrace	()V
/*     */     //   436: aload 7
/*     */     //   438: ifnull +10 -> 448
/*     */     //   441: aload 7
/*     */     //   443: invokeinterface 176 1 0
/*     */     //   448: aload 6
/*     */     //   450: ifnull +10 -> 460
/*     */     //   453: aload 6
/*     */     //   455: invokeinterface 179 1 0
/*     */     //   460: aload 5
/*     */     //   462: ifnull +136 -> 598
/*     */     //   465: aload 5
/*     */     //   467: invokeinterface 180 1 0
/*     */     //   472: goto +126 -> 598
/*     */     //   475: astore 9
/*     */     //   477: aload 9
/*     */     //   479: invokevirtual 376	java/text/ParseException:printStackTrace	()V
/*     */     //   482: aload 7
/*     */     //   484: ifnull +10 -> 494
/*     */     //   487: aload 7
/*     */     //   489: invokeinterface 176 1 0
/*     */     //   494: aload 6
/*     */     //   496: ifnull +10 -> 506
/*     */     //   499: aload 6
/*     */     //   501: invokeinterface 179 1 0
/*     */     //   506: aload 5
/*     */     //   508: ifnull +90 -> 598
/*     */     //   511: aload 5
/*     */     //   513: invokeinterface 180 1 0
/*     */     //   518: goto +80 -> 598
/*     */     //   521: astore 16
/*     */     //   523: aload 7
/*     */     //   525: ifnull +10 -> 535
/*     */     //   528: aload 7
/*     */     //   530: invokeinterface 176 1 0
/*     */     //   535: aload 6
/*     */     //   537: ifnull +10 -> 547
/*     */     //   540: aload 6
/*     */     //   542: invokeinterface 179 1 0
/*     */     //   547: aload 5
/*     */     //   549: ifnull +10 -> 559
/*     */     //   552: aload 5
/*     */     //   554: invokeinterface 180 1 0
/*     */     //   559: aload 16
/*     */     //   561: athrow
/*     */     //   562: aload 7
/*     */     //   564: ifnull +10 -> 574
/*     */     //   567: aload 7
/*     */     //   569: invokeinterface 176 1 0
/*     */     //   574: aload 6
/*     */     //   576: ifnull +10 -> 586
/*     */     //   579: aload 6
/*     */     //   581: invokeinterface 179 1 0
/*     */     //   586: aload 5
/*     */     //   588: ifnull +10 -> 598
/*     */     //   591: aload 5
/*     */     //   593: invokeinterface 180 1 0
/*     */     //   598: aload 8
/*     */     //   600: areturn
/*     */     // Line number table:
/*     */     //   Java source line #182	-> byte code offset #0
/*     */     //   Java source line #183	-> byte code offset #10
/*     */     //   Java source line #184	-> byte code offset #13
/*     */     //   Java source line #185	-> byte code offset #16
/*     */     //   Java source line #188	-> byte code offset #25
/*     */     //   Java source line #189	-> byte code offset #39
/*     */     //   Java source line #190	-> byte code offset #45
/*     */     //   Java source line #188	-> byte code offset #57
/*     */     //   Java source line #192	-> byte code offset #62
/*     */     //   Java source line #193	-> byte code offset #73
/*     */     //   Java source line #194	-> byte code offset #82
/*     */     //   Java source line #195	-> byte code offset #92
/*     */     //   Java source line #197	-> byte code offset #101
/*     */     //   Java source line #198	-> byte code offset #105
/*     */     //   Java source line #197	-> byte code offset #111
/*     */     //   Java source line #199	-> byte code offset #116
/*     */     //   Java source line #200	-> byte code offset #128
/*     */     //   Java source line #201	-> byte code offset #142
/*     */     //   Java source line #203	-> byte code offset #145
/*     */     //   Java source line #204	-> byte code offset #154
/*     */     //   Java source line #205	-> byte code offset #168
/*     */     //   Java source line #206	-> byte code offset #183
/*     */     //   Java source line #207	-> byte code offset #198
/*     */     //   Java source line #209	-> byte code offset #216
/*     */     //   Java source line #210	-> byte code offset #222
/*     */     //   Java source line #209	-> byte code offset #225
/*     */     //   Java source line #210	-> byte code offset #230
/*     */     //   Java source line #209	-> byte code offset #233
/*     */     //   Java source line #211	-> byte code offset #238
/*     */     //   Java source line #217	-> byte code offset #252
/*     */     //   Java source line #218	-> byte code offset #262
/*     */     //   Java source line #219	-> byte code offset #272
/*     */     //   Java source line #220	-> byte code offset #280
/*     */     //   Java source line #221	-> byte code offset #283
/*     */     //   Java source line #222	-> byte code offset #291
/*     */     //   Java source line #223	-> byte code offset #305
/*     */     //   Java source line #222	-> byte code offset #311
/*     */     //   Java source line #224	-> byte code offset #316
/*     */     //   Java source line #225	-> byte code offset #327
/*     */     //   Java source line #226	-> byte code offset #336
/*     */     //   Java source line #227	-> byte code offset #353
/*     */     //   Java source line #228	-> byte code offset #355
/*     */     //   Java source line #227	-> byte code offset #360
/*     */     //   Java source line #229	-> byte code offset #362
/*     */     //   Java source line #230	-> byte code offset #372
/*     */     //   Java source line #231	-> byte code offset #380
/*     */     //   Java source line #232	-> byte code offset #384
/*     */     //   Java source line #231	-> byte code offset #392
/*     */     //   Java source line #233	-> byte code offset #395
/*     */     //   Java source line #234	-> byte code offset #398
/*     */     //   Java source line #236	-> byte code offset #406
/*     */     //   Java source line #201	-> byte code offset #416
/*     */     //   Java source line #239	-> byte code offset #426
/*     */     //   Java source line #240	-> byte code offset #431
/*     */     //   Java source line #246	-> byte code offset #436
/*     */     //   Java source line #247	-> byte code offset #441
/*     */     //   Java source line #248	-> byte code offset #448
/*     */     //   Java source line #249	-> byte code offset #453
/*     */     //   Java source line #250	-> byte code offset #460
/*     */     //   Java source line #251	-> byte code offset #465
/*     */     //   Java source line #241	-> byte code offset #475
/*     */     //   Java source line #242	-> byte code offset #477
/*     */     //   Java source line #246	-> byte code offset #482
/*     */     //   Java source line #247	-> byte code offset #487
/*     */     //   Java source line #248	-> byte code offset #494
/*     */     //   Java source line #249	-> byte code offset #499
/*     */     //   Java source line #250	-> byte code offset #506
/*     */     //   Java source line #251	-> byte code offset #511
/*     */     //   Java source line #245	-> byte code offset #521
/*     */     //   Java source line #246	-> byte code offset #523
/*     */     //   Java source line #247	-> byte code offset #528
/*     */     //   Java source line #248	-> byte code offset #535
/*     */     //   Java source line #249	-> byte code offset #540
/*     */     //   Java source line #250	-> byte code offset #547
/*     */     //   Java source line #251	-> byte code offset #552
/*     */     //   Java source line #252	-> byte code offset #559
/*     */     //   Java source line #246	-> byte code offset #562
/*     */     //   Java source line #247	-> byte code offset #567
/*     */     //   Java source line #248	-> byte code offset #574
/*     */     //   Java source line #249	-> byte code offset #579
/*     */     //   Java source line #250	-> byte code offset #586
/*     */     //   Java source line #251	-> byte code offset #591
/*     */     //   Java source line #254	-> byte code offset #598
/*     */     // Local variable table:
/*     */     //   start	length	slot	name	signature
/*     */     //   0	601	0	this	QuizDAOImpl
/*     */     //   0	601	1	userid	int
/*     */     //   0	601	2	category	String
/*     */     //   0	601	3	standard	int
/*     */     //   0	601	4	test_category_id	int
/*     */     //   8	584	5	connection	Connection
/*     */     //   11	569	6	preparedStatement	PreparedStatement
/*     */     //   14	554	7	resultSet	ResultSet
/*     */     //   23	576	8	topicLists	List<com.groom.bean.TestsTopicList>
/*     */     //   60	5	9	query	String
/*     */     //   429	3	9	exception	SQLException
/*     */     //   475	3	9	exception	java.text.ParseException
/*     */     //   114	151	10	currentDate	java.util.Date
/*     */     //   126	115	11	dateFormat	java.text.SimpleDateFormat
/*     */     //   152	257	12	topic	com.groom.bean.TestsTopicList
/*     */     //   236	27	13	testDate	java.util.Date
/*     */     //   314	5	14	pointsQuery	String
/*     */     //   360	23	15	userPointsResultSet	ResultSet
/*     */     //   521	39	16	localObject	Object
/*     */     // Exception table:
/*     */     //   from	to	target	type
/*     */     //   25	426	429	java/sql/SQLException
/*     */     //   25	426	475	java/text/ParseException
/*     */     //   25	436	521	finally
/*     */     //   475	482	521	finally
/*     */   }
/*     */   
/*     */   public boolean incrementQuestionsAttemptedCount(List<Integer> qids, String category)
/*     */     throws SQLException
/*     */   {
/* 260 */     Connection connection = ds.getConnection();
/* 261 */     PreparedStatement preparedStatement = null;
/*     */     try {
/* 263 */       String ids = StringUtils.join(qids, ",");
/* 264 */       String query = "UPDATE " + category + 
/* 265 */         " SET NO_OF_ATTEMPTS=NO_OF_ATTEMPTS+1 WHERE Q_ID IN(" + 
/* 266 */         ids + ")";
/* 267 */       System.out.println(query);
/* 268 */       preparedStatement = connection.prepareStatement(query);
/* 269 */       int updateStatus = preparedStatement.executeUpdate();
/* 270 */       if (updateStatus != 0)
/* 271 */         return true;
/*     */     } catch (SQLException exception) {
/* 273 */       exception.printStackTrace();
/*     */     }
/*     */     finally {
/* 276 */       if (preparedStatement != null)
/* 277 */         preparedStatement.close();
/* 278 */       if (connection != null) {
/* 279 */         connection.close();
/*     */       }
/*     */     }
/* 276 */     if (preparedStatement != null)
/* 277 */       preparedStatement.close();
/* 278 */     if (connection != null) {
/* 279 */       connection.close();
/*     */     }
/*     */     
/* 282 */     return false;
/*     */   }
/*     */   
/*     */   public boolean incrementCorrectQuestionsAttemptedCount(List<Integer> qids, String category)
/*     */     throws SQLException
/*     */   {
/* 288 */     Connection connection = ds.getConnection();
/* 289 */     PreparedStatement preparedStatement = null;
/*     */     try {
/* 291 */       String ids = StringUtils.join(qids, ",");
/* 292 */       String query = "UPDATE " + 
/* 293 */         category + 
/* 294 */         " SET NO_OF_CORRECT_ANSWERS=NO_OF_CORRECT_ANSWERS+1 WHERE Q_ID IN(" + 
/* 295 */         ids + ")";
/* 296 */       System.out.println(query);
/* 297 */       preparedStatement = connection.prepareStatement(query);
/* 298 */       int updateStatus = preparedStatement.executeUpdate();
/* 299 */       if (updateStatus != 0)
/* 300 */         return true;
/*     */     } catch (SQLException exception) {
/* 302 */       exception.printStackTrace();
/*     */     }
/*     */     finally {
/* 305 */       if (preparedStatement != null)
/* 306 */         preparedStatement.close();
/* 307 */       if (connection != null) {
/* 308 */         connection.close();
/*     */       }
/*     */     }
/* 305 */     if (preparedStatement != null)
/* 306 */       preparedStatement.close();
/* 307 */     if (connection != null) {
/* 308 */       connection.close();
/*     */     }
/*     */     
/* 311 */     return false;
/*     */   }
/*     */   
/*     */   /* Error */
/*     */   public String getUserTestQuestionsIdsString(int topicid, int userid, String category)
/*     */     throws SQLException
/*     */   {
/*     */     // Byte code:
/*     */     //   0: getstatic 23	com/groom/dao/impl/QuizDAOImpl:ds	Ljavax/sql/DataSource;
/*     */     //   3: invokeinterface 27 1 0
/*     */     //   8: astore 4
/*     */     //   10: aconst_null
/*     */     //   11: astore 5
/*     */     //   13: aconst_null
/*     */     //   14: astore 6
/*     */     //   16: aconst_null
/*     */     //   17: astore 7
/*     */     //   19: new 36	java/lang/StringBuilder
/*     */     //   22: dup
/*     */     //   23: ldc_w 417
/*     */     //   26: invokespecial 40	java/lang/StringBuilder:<init>	(Ljava/lang/String;)V
/*     */     //   29: aload_3
/*     */     //   30: invokevirtual 43	java/lang/StringBuilder:append	(Ljava/lang/String;)Ljava/lang/StringBuilder;
/*     */     //   33: ldc_w 366
/*     */     //   36: invokevirtual 43	java/lang/StringBuilder:append	(Ljava/lang/String;)Ljava/lang/StringBuilder;
/*     */     //   39: invokevirtual 53	java/lang/StringBuilder:toString	()Ljava/lang/String;
/*     */     //   42: astore 8
/*     */     //   44: aload 4
/*     */     //   46: aload 8
/*     */     //   48: invokeinterface 68 2 0
/*     */     //   53: astore 5
/*     */     //   55: aload 5
/*     */     //   57: iconst_1
/*     */     //   58: iload_2
/*     */     //   59: invokeinterface 74 3 0
/*     */     //   64: aload 5
/*     */     //   66: iconst_2
/*     */     //   67: iload_1
/*     */     //   68: invokeinterface 74 3 0
/*     */     //   73: aload 5
/*     */     //   75: invokeinterface 80 1 0
/*     */     //   80: astore 6
/*     */     //   82: goto +15 -> 97
/*     */     //   85: aload 6
/*     */     //   87: ldc_w 371
/*     */     //   90: invokeinterface 101 2 0
/*     */     //   95: astore 7
/*     */     //   97: aload 6
/*     */     //   99: invokeinterface 169 1 0
/*     */     //   104: ifne -19 -> 85
/*     */     //   107: goto +90 -> 197
/*     */     //   110: astore 8
/*     */     //   112: aload 8
/*     */     //   114: invokevirtual 173	java/sql/SQLException:printStackTrace	()V
/*     */     //   117: aload 6
/*     */     //   119: ifnull +10 -> 129
/*     */     //   122: aload 6
/*     */     //   124: invokeinterface 176 1 0
/*     */     //   129: aload 5
/*     */     //   131: ifnull +10 -> 141
/*     */     //   134: aload 5
/*     */     //   136: invokeinterface 179 1 0
/*     */     //   141: aload 4
/*     */     //   143: ifnull +90 -> 233
/*     */     //   146: aload 4
/*     */     //   148: invokeinterface 180 1 0
/*     */     //   153: goto +80 -> 233
/*     */     //   156: astore 9
/*     */     //   158: aload 6
/*     */     //   160: ifnull +10 -> 170
/*     */     //   163: aload 6
/*     */     //   165: invokeinterface 176 1 0
/*     */     //   170: aload 5
/*     */     //   172: ifnull +10 -> 182
/*     */     //   175: aload 5
/*     */     //   177: invokeinterface 179 1 0
/*     */     //   182: aload 4
/*     */     //   184: ifnull +10 -> 194
/*     */     //   187: aload 4
/*     */     //   189: invokeinterface 180 1 0
/*     */     //   194: aload 9
/*     */     //   196: athrow
/*     */     //   197: aload 6
/*     */     //   199: ifnull +10 -> 209
/*     */     //   202: aload 6
/*     */     //   204: invokeinterface 176 1 0
/*     */     //   209: aload 5
/*     */     //   211: ifnull +10 -> 221
/*     */     //   214: aload 5
/*     */     //   216: invokeinterface 179 1 0
/*     */     //   221: aload 4
/*     */     //   223: ifnull +10 -> 233
/*     */     //   226: aload 4
/*     */     //   228: invokeinterface 180 1 0
/*     */     //   233: aload 7
/*     */     //   235: areturn
/*     */     // Line number table:
/*     */     //   Java source line #317	-> byte code offset #0
/*     */     //   Java source line #318	-> byte code offset #10
/*     */     //   Java source line #319	-> byte code offset #13
/*     */     //   Java source line #320	-> byte code offset #16
/*     */     //   Java source line #322	-> byte code offset #19
/*     */     //   Java source line #323	-> byte code offset #33
/*     */     //   Java source line #322	-> byte code offset #39
/*     */     //   Java source line #325	-> byte code offset #44
/*     */     //   Java source line #326	-> byte code offset #55
/*     */     //   Java source line #327	-> byte code offset #64
/*     */     //   Java source line #328	-> byte code offset #73
/*     */     //   Java source line #329	-> byte code offset #82
/*     */     //   Java source line #330	-> byte code offset #85
/*     */     //   Java source line #329	-> byte code offset #97
/*     */     //   Java source line #334	-> byte code offset #107
/*     */     //   Java source line #335	-> byte code offset #112
/*     */     //   Java source line #337	-> byte code offset #117
/*     */     //   Java source line #338	-> byte code offset #122
/*     */     //   Java source line #339	-> byte code offset #129
/*     */     //   Java source line #340	-> byte code offset #134
/*     */     //   Java source line #341	-> byte code offset #141
/*     */     //   Java source line #342	-> byte code offset #146
/*     */     //   Java source line #336	-> byte code offset #156
/*     */     //   Java source line #337	-> byte code offset #158
/*     */     //   Java source line #338	-> byte code offset #163
/*     */     //   Java source line #339	-> byte code offset #170
/*     */     //   Java source line #340	-> byte code offset #175
/*     */     //   Java source line #341	-> byte code offset #182
/*     */     //   Java source line #342	-> byte code offset #187
/*     */     //   Java source line #343	-> byte code offset #194
/*     */     //   Java source line #337	-> byte code offset #197
/*     */     //   Java source line #338	-> byte code offset #202
/*     */     //   Java source line #339	-> byte code offset #209
/*     */     //   Java source line #340	-> byte code offset #214
/*     */     //   Java source line #341	-> byte code offset #221
/*     */     //   Java source line #342	-> byte code offset #226
/*     */     //   Java source line #344	-> byte code offset #233
/*     */     // Local variable table:
/*     */     //   start	length	slot	name	signature
/*     */     //   0	236	0	this	QuizDAOImpl
/*     */     //   0	236	1	topicid	int
/*     */     //   0	236	2	userid	int
/*     */     //   0	236	3	category	String
/*     */     //   8	219	4	connection	Connection
/*     */     //   11	204	5	preparedStatement	PreparedStatement
/*     */     //   14	189	6	resultSet	ResultSet
/*     */     //   17	217	7	questionids	String
/*     */     //   42	5	8	query	String
/*     */     //   110	3	8	exception	SQLException
/*     */     //   156	39	9	localObject	Object
/*     */     // Exception table:
/*     */     //   from	to	target	type
/*     */     //   19	107	110	java/sql/SQLException
/*     */     //   19	117	156	finally
/*     */   }
/*     */   
/*     */   /* Error */
/*     */   public List<com.groom.bean.QuizQuestionDetails> getQuizKey(String category, int topicid, int userid)
/*     */     throws SQLException
/*     */   {
/*     */     // Byte code:
/*     */     //   0: getstatic 23	com/groom/dao/impl/QuizDAOImpl:ds	Ljavax/sql/DataSource;
/*     */     //   3: invokeinterface 27 1 0
/*     */     //   8: astore 4
/*     */     //   10: aconst_null
/*     */     //   11: astore 5
/*     */     //   13: aconst_null
/*     */     //   14: astore 6
/*     */     //   16: new 33	java/util/ArrayList
/*     */     //   19: dup
/*     */     //   20: invokespecial 35	java/util/ArrayList:<init>	()V
/*     */     //   23: astore 7
/*     */     //   25: aload_0
/*     */     //   26: iload_2
/*     */     //   27: iload_3
/*     */     //   28: aload_1
/*     */     //   29: invokevirtual 423	com/groom/dao/impl/QuizDAOImpl:getUserTestQuestionsIdsString	(IILjava/lang/String;)Ljava/lang/String;
/*     */     //   32: astore 8
/*     */     //   34: new 36	java/lang/StringBuilder
/*     */     //   37: dup
/*     */     //   38: ldc_w 286
/*     */     //   41: invokespecial 40	java/lang/StringBuilder:<init>	(Ljava/lang/String;)V
/*     */     //   44: aload_1
/*     */     //   45: invokevirtual 43	java/lang/StringBuilder:append	(Ljava/lang/String;)Ljava/lang/StringBuilder;
/*     */     //   48: ldc -45
/*     */     //   50: invokevirtual 43	java/lang/StringBuilder:append	(Ljava/lang/String;)Ljava/lang/StringBuilder;
/*     */     //   53: aload 8
/*     */     //   55: invokevirtual 43	java/lang/StringBuilder:append	(Ljava/lang/String;)Ljava/lang/StringBuilder;
/*     */     //   58: ldc_w 425
/*     */     //   61: invokevirtual 43	java/lang/StringBuilder:append	(Ljava/lang/String;)Ljava/lang/StringBuilder;
/*     */     //   64: aload 8
/*     */     //   66: invokevirtual 43	java/lang/StringBuilder:append	(Ljava/lang/String;)Ljava/lang/StringBuilder;
/*     */     //   69: ldc -43
/*     */     //   71: invokevirtual 43	java/lang/StringBuilder:append	(Ljava/lang/String;)Ljava/lang/StringBuilder;
/*     */     //   74: invokevirtual 53	java/lang/StringBuilder:toString	()Ljava/lang/String;
/*     */     //   77: astore 9
/*     */     //   79: getstatic 57	java/lang/System:out	Ljava/io/PrintStream;
/*     */     //   82: aload 9
/*     */     //   84: invokevirtual 63	java/io/PrintStream:println	(Ljava/lang/String;)V
/*     */     //   87: aload 4
/*     */     //   89: aload 9
/*     */     //   91: invokeinterface 68 2 0
/*     */     //   96: astore 5
/*     */     //   98: aload_0
/*     */     //   99: aload_1
/*     */     //   100: iload_2
/*     */     //   101: iload_3
/*     */     //   102: invokespecial 427	com/groom/dao/impl/QuizDAOImpl:getUserAnswers	(Ljava/lang/String;II)Ljava/lang/String;
/*     */     //   105: astore 10
/*     */     //   107: aload 5
/*     */     //   109: invokeinterface 80 1 0
/*     */     //   114: astore 6
/*     */     //   116: iconst_0
/*     */     //   117: istore 11
/*     */     //   119: goto +240 -> 359
/*     */     //   122: new 84	com/groom/bean/QuizQuestionDetails
/*     */     //   125: dup
/*     */     //   126: invokespecial 86	com/groom/bean/QuizQuestionDetails:<init>	()V
/*     */     //   129: astore 12
/*     */     //   131: aload 12
/*     */     //   133: aload 6
/*     */     //   135: ldc 87
/*     */     //   137: invokeinterface 89 2 0
/*     */     //   142: invokevirtual 95	com/groom/bean/QuizQuestionDetails:setQ_id	(I)V
/*     */     //   145: aload 12
/*     */     //   147: aload 6
/*     */     //   149: ldc 99
/*     */     //   151: invokeinterface 101 2 0
/*     */     //   156: invokevirtual 105	com/groom/bean/QuizQuestionDetails:setQuestion	(Ljava/lang/String;)V
/*     */     //   159: aload 12
/*     */     //   161: aload 6
/*     */     //   163: ldc 108
/*     */     //   165: invokeinterface 101 2 0
/*     */     //   170: invokevirtual 110	com/groom/bean/QuizQuestionDetails:setOption_a	(Ljava/lang/String;)V
/*     */     //   173: aload 12
/*     */     //   175: aload 6
/*     */     //   177: ldc 113
/*     */     //   179: invokeinterface 101 2 0
/*     */     //   184: invokevirtual 115	com/groom/bean/QuizQuestionDetails:setOption_b	(Ljava/lang/String;)V
/*     */     //   187: aload 12
/*     */     //   189: aload 6
/*     */     //   191: ldc 118
/*     */     //   193: invokeinterface 101 2 0
/*     */     //   198: invokevirtual 120	com/groom/bean/QuizQuestionDetails:setOption_c	(Ljava/lang/String;)V
/*     */     //   201: aload 12
/*     */     //   203: aload 6
/*     */     //   205: ldc 123
/*     */     //   207: invokeinterface 101 2 0
/*     */     //   212: invokevirtual 125	com/groom/bean/QuizQuestionDetails:setOption_d	(Ljava/lang/String;)V
/*     */     //   215: aload 12
/*     */     //   217: aload 6
/*     */     //   219: ldc -128
/*     */     //   221: invokeinterface 101 2 0
/*     */     //   226: invokevirtual 130	com/groom/bean/QuizQuestionDetails:setAnswer	(Ljava/lang/String;)V
/*     */     //   229: aload 12
/*     */     //   231: aload 6
/*     */     //   233: ldc -123
/*     */     //   235: invokeinterface 89 2 0
/*     */     //   240: invokevirtual 135	com/groom/bean/QuizQuestionDetails:setTopicid	(I)V
/*     */     //   243: aload 12
/*     */     //   245: aload 6
/*     */     //   247: ldc -118
/*     */     //   249: invokeinterface 101 2 0
/*     */     //   254: invokevirtual 145	com/groom/bean/QuizQuestionDetails:setImage_name	(Ljava/lang/String;)V
/*     */     //   257: aload 12
/*     */     //   259: aload 6
/*     */     //   261: ldc -108
/*     */     //   263: invokeinterface 101 2 0
/*     */     //   268: invokevirtual 150	com/groom/bean/QuizQuestionDetails:setExplanation	(Ljava/lang/String;)V
/*     */     //   271: aload 12
/*     */     //   273: aload 6
/*     */     //   275: ldc_w 431
/*     */     //   278: invokeinterface 89 2 0
/*     */     //   283: invokevirtual 433	com/groom/bean/QuizQuestionDetails:setNo_of_attempts	(I)V
/*     */     //   286: aload 12
/*     */     //   288: aload 6
/*     */     //   290: ldc_w 436
/*     */     //   293: invokeinterface 89 2 0
/*     */     //   298: invokevirtual 438	com/groom/bean/QuizQuestionDetails:setNo_of_correct_answers	(I)V
/*     */     //   301: aload 10
/*     */     //   303: iload 11
/*     */     //   305: invokevirtual 441	java/lang/String:charAt	(I)C
/*     */     //   308: invokestatic 445	java/lang/String:valueOf	(C)Ljava/lang/String;
/*     */     //   311: ldc_w 448
/*     */     //   314: invokevirtual 450	java/lang/String:equals	(Ljava/lang/Object;)Z
/*     */     //   317: ifeq +14 -> 331
/*     */     //   320: aload 12
/*     */     //   322: ldc_w 453
/*     */     //   325: invokevirtual 455	com/groom/bean/QuizQuestionDetails:setUserAnswer	(Ljava/lang/String;)V
/*     */     //   328: goto +18 -> 346
/*     */     //   331: aload 12
/*     */     //   333: aload 10
/*     */     //   335: iload 11
/*     */     //   337: invokevirtual 441	java/lang/String:charAt	(I)C
/*     */     //   340: invokestatic 445	java/lang/String:valueOf	(C)Ljava/lang/String;
/*     */     //   343: invokevirtual 455	com/groom/bean/QuizQuestionDetails:setUserAnswer	(Ljava/lang/String;)V
/*     */     //   346: aload 7
/*     */     //   348: aload 12
/*     */     //   350: invokeinterface 163 2 0
/*     */     //   355: pop
/*     */     //   356: iinc 11 1
/*     */     //   359: aload 6
/*     */     //   361: invokeinterface 169 1 0
/*     */     //   366: ifne -244 -> 122
/*     */     //   369: goto +90 -> 459
/*     */     //   372: astore 9
/*     */     //   374: aload 9
/*     */     //   376: invokevirtual 173	java/sql/SQLException:printStackTrace	()V
/*     */     //   379: aload 6
/*     */     //   381: ifnull +10 -> 391
/*     */     //   384: aload 6
/*     */     //   386: invokeinterface 176 1 0
/*     */     //   391: aload 5
/*     */     //   393: ifnull +10 -> 403
/*     */     //   396: aload 5
/*     */     //   398: invokeinterface 179 1 0
/*     */     //   403: aload 4
/*     */     //   405: ifnull +90 -> 495
/*     */     //   408: aload 4
/*     */     //   410: invokeinterface 180 1 0
/*     */     //   415: goto +80 -> 495
/*     */     //   418: astore 13
/*     */     //   420: aload 6
/*     */     //   422: ifnull +10 -> 432
/*     */     //   425: aload 6
/*     */     //   427: invokeinterface 176 1 0
/*     */     //   432: aload 5
/*     */     //   434: ifnull +10 -> 444
/*     */     //   437: aload 5
/*     */     //   439: invokeinterface 179 1 0
/*     */     //   444: aload 4
/*     */     //   446: ifnull +10 -> 456
/*     */     //   449: aload 4
/*     */     //   451: invokeinterface 180 1 0
/*     */     //   456: aload 13
/*     */     //   458: athrow
/*     */     //   459: aload 6
/*     */     //   461: ifnull +10 -> 471
/*     */     //   464: aload 6
/*     */     //   466: invokeinterface 176 1 0
/*     */     //   471: aload 5
/*     */     //   473: ifnull +10 -> 483
/*     */     //   476: aload 5
/*     */     //   478: invokeinterface 179 1 0
/*     */     //   483: aload 4
/*     */     //   485: ifnull +10 -> 495
/*     */     //   488: aload 4
/*     */     //   490: invokeinterface 180 1 0
/*     */     //   495: aload 7
/*     */     //   497: areturn
/*     */     // Line number table:
/*     */     //   Java source line #350	-> byte code offset #0
/*     */     //   Java source line #351	-> byte code offset #10
/*     */     //   Java source line #352	-> byte code offset #13
/*     */     //   Java source line #353	-> byte code offset #16
/*     */     //   Java source line #354	-> byte code offset #25
/*     */     //   Java source line #356	-> byte code offset #34
/*     */     //   Java source line #357	-> byte code offset #53
/*     */     //   Java source line #356	-> byte code offset #74
/*     */     //   Java source line #358	-> byte code offset #79
/*     */     //   Java source line #359	-> byte code offset #87
/*     */     //   Java source line #360	-> byte code offset #98
/*     */     //   Java source line #361	-> byte code offset #107
/*     */     //   Java source line #362	-> byte code offset #116
/*     */     //   Java source line #363	-> byte code offset #119
/*     */     //   Java source line #364	-> byte code offset #122
/*     */     //   Java source line #365	-> byte code offset #131
/*     */     //   Java source line #366	-> byte code offset #145
/*     */     //   Java source line #367	-> byte code offset #159
/*     */     //   Java source line #368	-> byte code offset #173
/*     */     //   Java source line #369	-> byte code offset #187
/*     */     //   Java source line #370	-> byte code offset #201
/*     */     //   Java source line #371	-> byte code offset #215
/*     */     //   Java source line #372	-> byte code offset #229
/*     */     //   Java source line #373	-> byte code offset #243
/*     */     //   Java source line #374	-> byte code offset #257
/*     */     //   Java source line #375	-> byte code offset #271
/*     */     //   Java source line #376	-> byte code offset #286
/*     */     //   Java source line #377	-> byte code offset #290
/*     */     //   Java source line #376	-> byte code offset #298
/*     */     //   Java source line #378	-> byte code offset #301
/*     */     //   Java source line #379	-> byte code offset #320
/*     */     //   Java source line #381	-> byte code offset #331
/*     */     //   Java source line #382	-> byte code offset #346
/*     */     //   Java source line #383	-> byte code offset #356
/*     */     //   Java source line #363	-> byte code offset #359
/*     */     //   Java source line #387	-> byte code offset #369
/*     */     //   Java source line #388	-> byte code offset #374
/*     */     //   Java source line #390	-> byte code offset #379
/*     */     //   Java source line #391	-> byte code offset #384
/*     */     //   Java source line #392	-> byte code offset #391
/*     */     //   Java source line #393	-> byte code offset #396
/*     */     //   Java source line #394	-> byte code offset #403
/*     */     //   Java source line #395	-> byte code offset #408
/*     */     //   Java source line #389	-> byte code offset #418
/*     */     //   Java source line #390	-> byte code offset #420
/*     */     //   Java source line #391	-> byte code offset #425
/*     */     //   Java source line #392	-> byte code offset #432
/*     */     //   Java source line #393	-> byte code offset #437
/*     */     //   Java source line #394	-> byte code offset #444
/*     */     //   Java source line #395	-> byte code offset #449
/*     */     //   Java source line #396	-> byte code offset #456
/*     */     //   Java source line #390	-> byte code offset #459
/*     */     //   Java source line #391	-> byte code offset #464
/*     */     //   Java source line #392	-> byte code offset #471
/*     */     //   Java source line #393	-> byte code offset #476
/*     */     //   Java source line #394	-> byte code offset #483
/*     */     //   Java source line #395	-> byte code offset #488
/*     */     //   Java source line #397	-> byte code offset #495
/*     */     // Local variable table:
/*     */     //   start	length	slot	name	signature
/*     */     //   0	498	0	this	QuizDAOImpl
/*     */     //   0	498	1	category	String
/*     */     //   0	498	2	topicid	int
/*     */     //   0	498	3	userid	int
/*     */     //   8	481	4	connection	Connection
/*     */     //   11	466	5	preparedStatement	PreparedStatement
/*     */     //   14	451	6	resultSet	ResultSet
/*     */     //   23	473	7	questionDetails	List<com.groom.bean.QuizQuestionDetails>
/*     */     //   32	33	8	qids	String
/*     */     //   77	13	9	query	String
/*     */     //   372	3	9	exception	SQLException
/*     */     //   105	229	10	userString	String
/*     */     //   117	240	11	i	int
/*     */     //   129	220	12	details	com.groom.bean.QuizQuestionDetails
/*     */     //   418	39	13	localObject	Object
/*     */     // Exception table:
/*     */     //   from	to	target	type
/*     */     //   34	369	372	java/sql/SQLException
/*     */     //   34	379	418	finally
/*     */   }
/*     */   
/*     */   /* Error */
/*     */   private String getUserAnswers(String category, int topicid, int userid)
/*     */     throws SQLException
/*     */   {
/*     */     // Byte code:
/*     */     //   0: getstatic 23	com/groom/dao/impl/QuizDAOImpl:ds	Ljavax/sql/DataSource;
/*     */     //   3: invokeinterface 27 1 0
/*     */     //   8: astore 4
/*     */     //   10: aconst_null
/*     */     //   11: astore 5
/*     */     //   13: aconst_null
/*     */     //   14: astore 6
/*     */     //   16: aconst_null
/*     */     //   17: astore 7
/*     */     //   19: new 36	java/lang/StringBuilder
/*     */     //   22: dup
/*     */     //   23: ldc_w 460
/*     */     //   26: invokespecial 40	java/lang/StringBuilder:<init>	(Ljava/lang/String;)V
/*     */     //   29: aload_1
/*     */     //   30: invokevirtual 43	java/lang/StringBuilder:append	(Ljava/lang/String;)Ljava/lang/StringBuilder;
/*     */     //   33: ldc_w 366
/*     */     //   36: invokevirtual 43	java/lang/StringBuilder:append	(Ljava/lang/String;)Ljava/lang/StringBuilder;
/*     */     //   39: invokevirtual 53	java/lang/StringBuilder:toString	()Ljava/lang/String;
/*     */     //   42: astore 8
/*     */     //   44: aload 4
/*     */     //   46: aload 8
/*     */     //   48: invokeinterface 68 2 0
/*     */     //   53: astore 5
/*     */     //   55: aload 5
/*     */     //   57: iconst_1
/*     */     //   58: iload_3
/*     */     //   59: invokeinterface 74 3 0
/*     */     //   64: aload 5
/*     */     //   66: iconst_2
/*     */     //   67: iload_2
/*     */     //   68: invokeinterface 74 3 0
/*     */     //   73: aload 5
/*     */     //   75: invokeinterface 80 1 0
/*     */     //   80: astore 6
/*     */     //   82: goto +15 -> 97
/*     */     //   85: aload 6
/*     */     //   87: ldc_w 462
/*     */     //   90: invokeinterface 101 2 0
/*     */     //   95: astore 7
/*     */     //   97: aload 6
/*     */     //   99: invokeinterface 169 1 0
/*     */     //   104: ifne -19 -> 85
/*     */     //   107: goto +90 -> 197
/*     */     //   110: astore 8
/*     */     //   112: aload 8
/*     */     //   114: invokevirtual 173	java/sql/SQLException:printStackTrace	()V
/*     */     //   117: aload 6
/*     */     //   119: ifnull +10 -> 129
/*     */     //   122: aload 6
/*     */     //   124: invokeinterface 176 1 0
/*     */     //   129: aload 5
/*     */     //   131: ifnull +10 -> 141
/*     */     //   134: aload 5
/*     */     //   136: invokeinterface 179 1 0
/*     */     //   141: aload 4
/*     */     //   143: ifnull +90 -> 233
/*     */     //   146: aload 4
/*     */     //   148: invokeinterface 180 1 0
/*     */     //   153: goto +80 -> 233
/*     */     //   156: astore 9
/*     */     //   158: aload 6
/*     */     //   160: ifnull +10 -> 170
/*     */     //   163: aload 6
/*     */     //   165: invokeinterface 176 1 0
/*     */     //   170: aload 5
/*     */     //   172: ifnull +10 -> 182
/*     */     //   175: aload 5
/*     */     //   177: invokeinterface 179 1 0
/*     */     //   182: aload 4
/*     */     //   184: ifnull +10 -> 194
/*     */     //   187: aload 4
/*     */     //   189: invokeinterface 180 1 0
/*     */     //   194: aload 9
/*     */     //   196: athrow
/*     */     //   197: aload 6
/*     */     //   199: ifnull +10 -> 209
/*     */     //   202: aload 6
/*     */     //   204: invokeinterface 176 1 0
/*     */     //   209: aload 5
/*     */     //   211: ifnull +10 -> 221
/*     */     //   214: aload 5
/*     */     //   216: invokeinterface 179 1 0
/*     */     //   221: aload 4
/*     */     //   223: ifnull +10 -> 233
/*     */     //   226: aload 4
/*     */     //   228: invokeinterface 180 1 0
/*     */     //   233: aload 7
/*     */     //   235: areturn
/*     */     // Line number table:
/*     */     //   Java source line #402	-> byte code offset #0
/*     */     //   Java source line #403	-> byte code offset #10
/*     */     //   Java source line #404	-> byte code offset #13
/*     */     //   Java source line #405	-> byte code offset #16
/*     */     //   Java source line #407	-> byte code offset #19
/*     */     //   Java source line #408	-> byte code offset #33
/*     */     //   Java source line #407	-> byte code offset #39
/*     */     //   Java source line #409	-> byte code offset #44
/*     */     //   Java source line #410	-> byte code offset #55
/*     */     //   Java source line #411	-> byte code offset #64
/*     */     //   Java source line #412	-> byte code offset #73
/*     */     //   Java source line #413	-> byte code offset #82
/*     */     //   Java source line #414	-> byte code offset #85
/*     */     //   Java source line #413	-> byte code offset #97
/*     */     //   Java source line #418	-> byte code offset #107
/*     */     //   Java source line #419	-> byte code offset #112
/*     */     //   Java source line #421	-> byte code offset #117
/*     */     //   Java source line #422	-> byte code offset #122
/*     */     //   Java source line #423	-> byte code offset #129
/*     */     //   Java source line #424	-> byte code offset #134
/*     */     //   Java source line #425	-> byte code offset #141
/*     */     //   Java source line #426	-> byte code offset #146
/*     */     //   Java source line #420	-> byte code offset #156
/*     */     //   Java source line #421	-> byte code offset #158
/*     */     //   Java source line #422	-> byte code offset #163
/*     */     //   Java source line #423	-> byte code offset #170
/*     */     //   Java source line #424	-> byte code offset #175
/*     */     //   Java source line #425	-> byte code offset #182
/*     */     //   Java source line #426	-> byte code offset #187
/*     */     //   Java source line #427	-> byte code offset #194
/*     */     //   Java source line #421	-> byte code offset #197
/*     */     //   Java source line #422	-> byte code offset #202
/*     */     //   Java source line #423	-> byte code offset #209
/*     */     //   Java source line #424	-> byte code offset #214
/*     */     //   Java source line #425	-> byte code offset #221
/*     */     //   Java source line #426	-> byte code offset #226
/*     */     //   Java source line #428	-> byte code offset #233
/*     */     // Local variable table:
/*     */     //   start	length	slot	name	signature
/*     */     //   0	236	0	this	QuizDAOImpl
/*     */     //   0	236	1	category	String
/*     */     //   0	236	2	topicid	int
/*     */     //   0	236	3	userid	int
/*     */     //   8	219	4	connection	Connection
/*     */     //   11	204	5	preparedStatement	PreparedStatement
/*     */     //   14	189	6	resultSet	ResultSet
/*     */     //   17	217	7	userAnswers	String
/*     */     //   42	5	8	query	String
/*     */     //   110	3	8	exception	SQLException
/*     */     //   156	39	9	localObject	Object
/*     */     // Exception table:
/*     */     //   from	to	target	type
/*     */     //   19	107	110	java/sql/SQLException
/*     */     //   19	117	156	finally
/*     */   }
/*     */   
/*     */   /* Error */
/*     */   public QuizPoints getTopicScore(String category, int topicid, int userid, int total_questions)
/*     */     throws SQLException
/*     */   {
/*     */     // Byte code:
/*     */     //   0: getstatic 23	com/groom/dao/impl/QuizDAOImpl:ds	Ljavax/sql/DataSource;
/*     */     //   3: invokeinterface 27 1 0
/*     */     //   8: astore 5
/*     */     //   10: aconst_null
/*     */     //   11: astore 6
/*     */     //   13: aconst_null
/*     */     //   14: astore 7
/*     */     //   16: new 236	com/groom/bean/QuizPoints
/*     */     //   19: dup
/*     */     //   20: invokespecial 467	com/groom/bean/QuizPoints:<init>	()V
/*     */     //   23: astore 8
/*     */     //   25: new 36	java/lang/StringBuilder
/*     */     //   28: dup
/*     */     //   29: ldc_w 286
/*     */     //   32: invokespecial 40	java/lang/StringBuilder:<init>	(Ljava/lang/String;)V
/*     */     //   35: aload_1
/*     */     //   36: invokevirtual 43	java/lang/StringBuilder:append	(Ljava/lang/String;)Ljava/lang/StringBuilder;
/*     */     //   39: ldc_w 366
/*     */     //   42: invokevirtual 43	java/lang/StringBuilder:append	(Ljava/lang/String;)Ljava/lang/StringBuilder;
/*     */     //   45: invokevirtual 53	java/lang/StringBuilder:toString	()Ljava/lang/String;
/*     */     //   48: astore 9
/*     */     //   50: aload 5
/*     */     //   52: aload 9
/*     */     //   54: invokeinterface 68 2 0
/*     */     //   59: astore 6
/*     */     //   61: aload 6
/*     */     //   63: iconst_1
/*     */     //   64: iload_3
/*     */     //   65: invokeinterface 74 3 0
/*     */     //   70: aload 6
/*     */     //   72: iconst_2
/*     */     //   73: iload_2
/*     */     //   74: invokeinterface 74 3 0
/*     */     //   79: aload 6
/*     */     //   81: invokeinterface 80 1 0
/*     */     //   86: astore 7
/*     */     //   88: goto +151 -> 239
/*     */     //   91: aload 8
/*     */     //   93: aload 7
/*     */     //   95: ldc_w 468
/*     */     //   98: invokeinterface 89 2 0
/*     */     //   103: invokevirtual 470	com/groom/bean/QuizPoints:setU_id	(I)V
/*     */     //   106: aload 8
/*     */     //   108: aload 7
/*     */     //   110: ldc -123
/*     */     //   112: invokeinterface 89 2 0
/*     */     //   117: invokevirtual 473	com/groom/bean/QuizPoints:setTopicid	(I)V
/*     */     //   120: aload 8
/*     */     //   122: aload 7
/*     */     //   124: ldc_w 462
/*     */     //   127: invokeinterface 101 2 0
/*     */     //   132: invokevirtual 474	com/groom/bean/QuizPoints:setAnswers	(Ljava/lang/String;)V
/*     */     //   135: aload 8
/*     */     //   137: aload 7
/*     */     //   139: ldc_w 477
/*     */     //   142: invokeinterface 89 2 0
/*     */     //   147: invokevirtual 479	com/groom/bean/QuizPoints:setPoints	(I)V
/*     */     //   150: aload 8
/*     */     //   152: aload 7
/*     */     //   154: ldc_w 371
/*     */     //   157: invokeinterface 101 2 0
/*     */     //   162: invokevirtual 482	com/groom/bean/QuizPoints:setQuestionIds	(Ljava/lang/String;)V
/*     */     //   165: aload 8
/*     */     //   167: aload 7
/*     */     //   169: ldc_w 345
/*     */     //   172: invokeinterface 347 2 0
/*     */     //   177: invokevirtual 485	com/groom/bean/QuizPoints:setTestDate	(Ljava/sql/Date;)V
/*     */     //   180: aload 8
/*     */     //   182: aload 7
/*     */     //   184: ldc_w 488
/*     */     //   187: invokeinterface 490 2 0
/*     */     //   192: invokevirtual 493	com/groom/bean/QuizPoints:setTime	(Ljava/sql/Time;)V
/*     */     //   195: aload 7
/*     */     //   197: ldc_w 462
/*     */     //   200: invokeinterface 101 2 0
/*     */     //   205: astore 10
/*     */     //   207: aload 8
/*     */     //   209: iload 4
/*     */     //   211: aload 10
/*     */     //   213: ldc_w 448
/*     */     //   216: invokestatic 496	org/apache/commons/lang3/StringUtils:countMatches	(Ljava/lang/CharSequence;Ljava/lang/CharSequence;)I
/*     */     //   219: isub
/*     */     //   220: invokevirtual 500	com/groom/bean/QuizPoints:setTotalAttempted	(I)V
/*     */     //   223: aload 8
/*     */     //   225: aload 8
/*     */     //   227: invokevirtual 503	com/groom/bean/QuizPoints:getTotalAttempted	()I
/*     */     //   230: aload 8
/*     */     //   232: invokevirtual 246	com/groom/bean/QuizPoints:getPoints	()I
/*     */     //   235: isub
/*     */     //   236: invokevirtual 506	com/groom/bean/QuizPoints:setWrongAnswers	(I)V
/*     */     //   239: aload 7
/*     */     //   241: invokeinterface 169 1 0
/*     */     //   246: ifne -155 -> 91
/*     */     //   249: goto +90 -> 339
/*     */     //   252: astore 9
/*     */     //   254: aload 9
/*     */     //   256: invokevirtual 173	java/sql/SQLException:printStackTrace	()V
/*     */     //   259: aload 7
/*     */     //   261: ifnull +10 -> 271
/*     */     //   264: aload 7
/*     */     //   266: invokeinterface 176 1 0
/*     */     //   271: aload 6
/*     */     //   273: ifnull +10 -> 283
/*     */     //   276: aload 6
/*     */     //   278: invokeinterface 179 1 0
/*     */     //   283: aload 5
/*     */     //   285: ifnull +90 -> 375
/*     */     //   288: aload 5
/*     */     //   290: invokeinterface 180 1 0
/*     */     //   295: goto +80 -> 375
/*     */     //   298: astore 11
/*     */     //   300: aload 7
/*     */     //   302: ifnull +10 -> 312
/*     */     //   305: aload 7
/*     */     //   307: invokeinterface 176 1 0
/*     */     //   312: aload 6
/*     */     //   314: ifnull +10 -> 324
/*     */     //   317: aload 6
/*     */     //   319: invokeinterface 179 1 0
/*     */     //   324: aload 5
/*     */     //   326: ifnull +10 -> 336
/*     */     //   329: aload 5
/*     */     //   331: invokeinterface 180 1 0
/*     */     //   336: aload 11
/*     */     //   338: athrow
/*     */     //   339: aload 7
/*     */     //   341: ifnull +10 -> 351
/*     */     //   344: aload 7
/*     */     //   346: invokeinterface 176 1 0
/*     */     //   351: aload 6
/*     */     //   353: ifnull +10 -> 363
/*     */     //   356: aload 6
/*     */     //   358: invokeinterface 179 1 0
/*     */     //   363: aload 5
/*     */     //   365: ifnull +10 -> 375
/*     */     //   368: aload 5
/*     */     //   370: invokeinterface 180 1 0
/*     */     //   375: aload 8
/*     */     //   377: areturn
/*     */     // Line number table:
/*     */     //   Java source line #435	-> byte code offset #0
/*     */     //   Java source line #436	-> byte code offset #10
/*     */     //   Java source line #437	-> byte code offset #13
/*     */     //   Java source line #438	-> byte code offset #16
/*     */     //   Java source line #440	-> byte code offset #25
/*     */     //   Java source line #441	-> byte code offset #39
/*     */     //   Java source line #440	-> byte code offset #45
/*     */     //   Java source line #443	-> byte code offset #50
/*     */     //   Java source line #444	-> byte code offset #61
/*     */     //   Java source line #445	-> byte code offset #70
/*     */     //   Java source line #446	-> byte code offset #79
/*     */     //   Java source line #447	-> byte code offset #88
/*     */     //   Java source line #448	-> byte code offset #91
/*     */     //   Java source line #449	-> byte code offset #106
/*     */     //   Java source line #451	-> byte code offset #120
/*     */     //   Java source line #452	-> byte code offset #135
/*     */     //   Java source line #453	-> byte code offset #150
/*     */     //   Java source line #454	-> byte code offset #165
/*     */     //   Java source line #455	-> byte code offset #180
/*     */     //   Java source line #456	-> byte code offset #195
/*     */     //   Java source line #458	-> byte code offset #207
/*     */     //   Java source line #459	-> byte code offset #211
/*     */     //   Java source line #458	-> byte code offset #216
/*     */     //   Java source line #460	-> byte code offset #223
/*     */     //   Java source line #447	-> byte code offset #239
/*     */     //   Java source line #464	-> byte code offset #249
/*     */     //   Java source line #465	-> byte code offset #254
/*     */     //   Java source line #467	-> byte code offset #259
/*     */     //   Java source line #468	-> byte code offset #264
/*     */     //   Java source line #469	-> byte code offset #271
/*     */     //   Java source line #470	-> byte code offset #276
/*     */     //   Java source line #471	-> byte code offset #283
/*     */     //   Java source line #472	-> byte code offset #288
/*     */     //   Java source line #466	-> byte code offset #298
/*     */     //   Java source line #467	-> byte code offset #300
/*     */     //   Java source line #468	-> byte code offset #305
/*     */     //   Java source line #469	-> byte code offset #312
/*     */     //   Java source line #470	-> byte code offset #317
/*     */     //   Java source line #471	-> byte code offset #324
/*     */     //   Java source line #472	-> byte code offset #329
/*     */     //   Java source line #473	-> byte code offset #336
/*     */     //   Java source line #467	-> byte code offset #339
/*     */     //   Java source line #468	-> byte code offset #344
/*     */     //   Java source line #469	-> byte code offset #351
/*     */     //   Java source line #470	-> byte code offset #356
/*     */     //   Java source line #471	-> byte code offset #363
/*     */     //   Java source line #472	-> byte code offset #368
/*     */     //   Java source line #474	-> byte code offset #375
/*     */     // Local variable table:
/*     */     //   start	length	slot	name	signature
/*     */     //   0	378	0	this	QuizDAOImpl
/*     */     //   0	378	1	category	String
/*     */     //   0	378	2	topicid	int
/*     */     //   0	378	3	userid	int
/*     */     //   0	378	4	total_questions	int
/*     */     //   8	361	5	connection	Connection
/*     */     //   11	346	6	preparedStatement	PreparedStatement
/*     */     //   14	331	7	resultSet	ResultSet
/*     */     //   23	353	8	quizPoints	QuizPoints
/*     */     //   48	5	9	query	String
/*     */     //   252	3	9	exception	SQLException
/*     */     //   205	7	10	answerString	String
/*     */     //   298	39	11	localObject	Object
/*     */     // Exception table:
/*     */     //   from	to	target	type
/*     */     //   25	249	252	java/sql/SQLException
/*     */     //   25	259	298	finally
/*     */   }
/*     */   
/*     */   /* Error */
/*     */   public com.groom.bean.UserRankBean getUserRankInSubjectTopic(String subject, int user_id, int topic_id)
/*     */     throws SQLException
/*     */   {
/*     */     // Byte code:
/*     */     //   0: getstatic 23	com/groom/dao/impl/QuizDAOImpl:ds	Ljavax/sql/DataSource;
/*     */     //   3: invokeinterface 27 1 0
/*     */     //   8: astore 4
/*     */     //   10: aconst_null
/*     */     //   11: astore 5
/*     */     //   13: aconst_null
/*     */     //   14: astore 6
/*     */     //   16: new 513	com/groom/bean/UserRankBean
/*     */     //   19: dup
/*     */     //   20: invokespecial 515	com/groom/bean/UserRankBean:<init>	()V
/*     */     //   23: astore 7
/*     */     //   25: aload 4
/*     */     //   27: invokeinterface 516 1 0
/*     */     //   32: astore 8
/*     */     //   34: aload 8
/*     */     //   36: ldc_w 520
/*     */     //   39: invokeinterface 522 2 0
/*     */     //   44: pop
/*     */     //   45: aload 8
/*     */     //   47: ldc_w 528
/*     */     //   50: invokeinterface 522 2 0
/*     */     //   55: pop
/*     */     //   56: new 36	java/lang/StringBuilder
/*     */     //   59: dup
/*     */     //   60: ldc_w 530
/*     */     //   63: invokespecial 40	java/lang/StringBuilder:<init>	(Ljava/lang/String;)V
/*     */     //   66: aload_1
/*     */     //   67: invokevirtual 43	java/lang/StringBuilder:append	(Ljava/lang/String;)Ljava/lang/StringBuilder;
/*     */     //   70: ldc_w 532
/*     */     //   73: invokevirtual 43	java/lang/StringBuilder:append	(Ljava/lang/String;)Ljava/lang/StringBuilder;
/*     */     //   76: ldc_w 534
/*     */     //   79: invokevirtual 43	java/lang/StringBuilder:append	(Ljava/lang/String;)Ljava/lang/StringBuilder;
/*     */     //   82: aload_1
/*     */     //   83: invokevirtual 43	java/lang/StringBuilder:append	(Ljava/lang/String;)Ljava/lang/StringBuilder;
/*     */     //   86: ldc_w 536
/*     */     //   89: invokevirtual 43	java/lang/StringBuilder:append	(Ljava/lang/String;)Ljava/lang/StringBuilder;
/*     */     //   92: ldc_w 538
/*     */     //   95: invokevirtual 43	java/lang/StringBuilder:append	(Ljava/lang/String;)Ljava/lang/StringBuilder;
/*     */     //   98: invokevirtual 53	java/lang/StringBuilder:toString	()Ljava/lang/String;
/*     */     //   101: astore 9
/*     */     //   103: getstatic 57	java/lang/System:out	Ljava/io/PrintStream;
/*     */     //   106: aload 9
/*     */     //   108: invokevirtual 63	java/io/PrintStream:println	(Ljava/lang/String;)V
/*     */     //   111: aload 4
/*     */     //   113: aload 9
/*     */     //   115: invokeinterface 68 2 0
/*     */     //   120: astore 5
/*     */     //   122: aload 5
/*     */     //   124: iconst_1
/*     */     //   125: iload_3
/*     */     //   126: invokeinterface 74 3 0
/*     */     //   131: aload 5
/*     */     //   133: iconst_2
/*     */     //   134: iload_3
/*     */     //   135: invokeinterface 74 3 0
/*     */     //   140: aload 5
/*     */     //   142: iconst_3
/*     */     //   143: iload_2
/*     */     //   144: invokeinterface 74 3 0
/*     */     //   149: aload 5
/*     */     //   151: invokeinterface 80 1 0
/*     */     //   156: astore 6
/*     */     //   158: goto +123 -> 281
/*     */     //   161: aload 7
/*     */     //   163: aload 6
/*     */     //   165: ldc_w 468
/*     */     //   168: invokeinterface 89 2 0
/*     */     //   173: invokevirtual 540	com/groom/bean/UserRankBean:setUser_id	(I)V
/*     */     //   176: aload 7
/*     */     //   178: aload 6
/*     */     //   180: ldc_w 477
/*     */     //   183: invokeinterface 89 2 0
/*     */     //   188: invokevirtual 543	com/groom/bean/UserRankBean:setPoints	(I)V
/*     */     //   191: aload 7
/*     */     //   193: aload 6
/*     */     //   195: ldc_w 544
/*     */     //   198: invokeinterface 89 2 0
/*     */     //   203: invokevirtual 546	com/groom/bean/UserRankBean:setRank	(I)V
/*     */     //   206: aload 7
/*     */     //   208: aload 6
/*     */     //   210: ldc_w 549
/*     */     //   213: invokeinterface 89 2 0
/*     */     //   218: invokevirtual 551	com/groom/bean/UserRankBean:setTotal_ranks	(I)V
/*     */     //   221: aload 6
/*     */     //   223: ldc_w 544
/*     */     //   226: invokeinterface 89 2 0
/*     */     //   231: i2d
/*     */     //   232: aload 6
/*     */     //   234: ldc_w 549
/*     */     //   237: invokeinterface 89 2 0
/*     */     //   242: i2d
/*     */     //   243: ddiv
/*     */     //   244: dstore 10
/*     */     //   246: new 554	java/text/DecimalFormat
/*     */     //   249: dup
/*     */     //   250: ldc_w 556
/*     */     //   253: invokespecial 558	java/text/DecimalFormat:<init>	(Ljava/lang/String;)V
/*     */     //   256: astore 12
/*     */     //   258: aload 7
/*     */     //   260: aload 12
/*     */     //   262: ldc2_w 559
/*     */     //   265: dload 10
/*     */     //   267: ldc2_w 559
/*     */     //   270: dmul
/*     */     //   271: dsub
/*     */     //   272: invokevirtual 561	java/text/DecimalFormat:format	(D)Ljava/lang/String;
/*     */     //   275: invokestatic 564	java/lang/Double:parseDouble	(Ljava/lang/String;)D
/*     */     //   278: invokevirtual 570	com/groom/bean/UserRankBean:setSubject_percentile	(D)V
/*     */     //   281: aload 6
/*     */     //   283: invokeinterface 169 1 0
/*     */     //   288: ifne -127 -> 161
/*     */     //   291: getstatic 57	java/lang/System:out	Ljava/io/PrintStream;
/*     */     //   294: aload 7
/*     */     //   296: invokevirtual 574	com/groom/bean/UserRankBean:getRank	()I
/*     */     //   299: invokevirtual 577	java/io/PrintStream:println	(I)V
/*     */     //   302: getstatic 57	java/lang/System:out	Ljava/io/PrintStream;
/*     */     //   305: aload 7
/*     */     //   307: invokevirtual 579	com/groom/bean/UserRankBean:getTotal_ranks	()I
/*     */     //   310: invokevirtual 577	java/io/PrintStream:println	(I)V
/*     */     //   313: goto +90 -> 403
/*     */     //   316: astore 8
/*     */     //   318: aload 8
/*     */     //   320: invokevirtual 173	java/sql/SQLException:printStackTrace	()V
/*     */     //   323: aload 6
/*     */     //   325: ifnull +10 -> 335
/*     */     //   328: aload 6
/*     */     //   330: invokeinterface 176 1 0
/*     */     //   335: aload 5
/*     */     //   337: ifnull +10 -> 347
/*     */     //   340: aload 5
/*     */     //   342: invokeinterface 179 1 0
/*     */     //   347: aload 4
/*     */     //   349: ifnull +90 -> 439
/*     */     //   352: aload 4
/*     */     //   354: invokeinterface 180 1 0
/*     */     //   359: goto +80 -> 439
/*     */     //   362: astore 13
/*     */     //   364: aload 6
/*     */     //   366: ifnull +10 -> 376
/*     */     //   369: aload 6
/*     */     //   371: invokeinterface 176 1 0
/*     */     //   376: aload 5
/*     */     //   378: ifnull +10 -> 388
/*     */     //   381: aload 5
/*     */     //   383: invokeinterface 179 1 0
/*     */     //   388: aload 4
/*     */     //   390: ifnull +10 -> 400
/*     */     //   393: aload 4
/*     */     //   395: invokeinterface 180 1 0
/*     */     //   400: aload 13
/*     */     //   402: athrow
/*     */     //   403: aload 6
/*     */     //   405: ifnull +10 -> 415
/*     */     //   408: aload 6
/*     */     //   410: invokeinterface 176 1 0
/*     */     //   415: aload 5
/*     */     //   417: ifnull +10 -> 427
/*     */     //   420: aload 5
/*     */     //   422: invokeinterface 179 1 0
/*     */     //   427: aload 4
/*     */     //   429: ifnull +10 -> 439
/*     */     //   432: aload 4
/*     */     //   434: invokeinterface 180 1 0
/*     */     //   439: aload 7
/*     */     //   441: areturn
/*     */     // Line number table:
/*     */     //   Java source line #480	-> byte code offset #0
/*     */     //   Java source line #481	-> byte code offset #10
/*     */     //   Java source line #482	-> byte code offset #13
/*     */     //   Java source line #483	-> byte code offset #16
/*     */     //   Java source line #485	-> byte code offset #25
/*     */     //   Java source line #486	-> byte code offset #34
/*     */     //   Java source line #487	-> byte code offset #45
/*     */     //   Java source line #489	-> byte code offset #56
/*     */     //   Java source line #493	-> byte code offset #66
/*     */     //   Java source line #494	-> byte code offset #70
/*     */     //   Java source line #495	-> byte code offset #76
/*     */     //   Java source line #496	-> byte code offset #82
/*     */     //   Java source line #497	-> byte code offset #86
/*     */     //   Java source line #498	-> byte code offset #92
/*     */     //   Java source line #489	-> byte code offset #98
/*     */     //   Java source line #499	-> byte code offset #103
/*     */     //   Java source line #500	-> byte code offset #111
/*     */     //   Java source line #501	-> byte code offset #122
/*     */     //   Java source line #502	-> byte code offset #131
/*     */     //   Java source line #503	-> byte code offset #140
/*     */     //   Java source line #504	-> byte code offset #149
/*     */     //   Java source line #505	-> byte code offset #158
/*     */     //   Java source line #506	-> byte code offset #161
/*     */     //   Java source line #507	-> byte code offset #176
/*     */     //   Java source line #508	-> byte code offset #191
/*     */     //   Java source line #509	-> byte code offset #206
/*     */     //   Java source line #510	-> byte code offset #221
/*     */     //   Java source line #511	-> byte code offset #246
/*     */     //   Java source line #512	-> byte code offset #258
/*     */     //   Java source line #505	-> byte code offset #281
/*     */     //   Java source line #514	-> byte code offset #291
/*     */     //   Java source line #515	-> byte code offset #302
/*     */     //   Java source line #516	-> byte code offset #313
/*     */     //   Java source line #517	-> byte code offset #318
/*     */     //   Java source line #519	-> byte code offset #323
/*     */     //   Java source line #520	-> byte code offset #328
/*     */     //   Java source line #521	-> byte code offset #335
/*     */     //   Java source line #522	-> byte code offset #340
/*     */     //   Java source line #523	-> byte code offset #347
/*     */     //   Java source line #524	-> byte code offset #352
/*     */     //   Java source line #518	-> byte code offset #362
/*     */     //   Java source line #519	-> byte code offset #364
/*     */     //   Java source line #520	-> byte code offset #369
/*     */     //   Java source line #521	-> byte code offset #376
/*     */     //   Java source line #522	-> byte code offset #381
/*     */     //   Java source line #523	-> byte code offset #388
/*     */     //   Java source line #524	-> byte code offset #393
/*     */     //   Java source line #525	-> byte code offset #400
/*     */     //   Java source line #519	-> byte code offset #403
/*     */     //   Java source line #520	-> byte code offset #408
/*     */     //   Java source line #521	-> byte code offset #415
/*     */     //   Java source line #522	-> byte code offset #420
/*     */     //   Java source line #523	-> byte code offset #427
/*     */     //   Java source line #524	-> byte code offset #432
/*     */     //   Java source line #526	-> byte code offset #439
/*     */     // Local variable table:
/*     */     //   start	length	slot	name	signature
/*     */     //   0	442	0	this	QuizDAOImpl
/*     */     //   0	442	1	subject	String
/*     */     //   0	442	2	user_id	int
/*     */     //   0	442	3	topic_id	int
/*     */     //   8	425	4	connection	Connection
/*     */     //   11	410	5	preparedStatement	PreparedStatement
/*     */     //   14	395	6	resultSet	ResultSet
/*     */     //   23	417	7	userRankBean	com.groom.bean.UserRankBean
/*     */     //   32	14	8	statement	java.sql.Statement
/*     */     //   316	3	8	exception	SQLException
/*     */     //   101	13	9	query	String
/*     */     //   244	22	10	subjectRank	double
/*     */     //   256	5	12	noOfDecimals	java.text.DecimalFormat
/*     */     //   362	39	13	localObject	Object
/*     */     // Exception table:
/*     */     //   from	to	target	type
/*     */     //   25	313	316	java/sql/SQLException
/*     */     //   25	323	362	finally
/*     */   }
/*     */   
/*     */   /* Error */
/*     */   public com.groom.bean.UserRankBean getUserRankInSubjectTopicbyLocation(String subject, int user_id, int topic_id, String locationType, String location)
/*     */     throws SQLException
/*     */   {
/*     */     // Byte code:
/*     */     //   0: getstatic 23	com/groom/dao/impl/QuizDAOImpl:ds	Ljavax/sql/DataSource;
/*     */     //   3: invokeinterface 27 1 0
/*     */     //   8: astore 6
/*     */     //   10: aconst_null
/*     */     //   11: astore 7
/*     */     //   13: aconst_null
/*     */     //   14: astore 8
/*     */     //   16: new 513	com/groom/bean/UserRankBean
/*     */     //   19: dup
/*     */     //   20: invokespecial 515	com/groom/bean/UserRankBean:<init>	()V
/*     */     //   23: astore 9
/*     */     //   25: aload 6
/*     */     //   27: invokeinterface 516 1 0
/*     */     //   32: astore 10
/*     */     //   34: aload 10
/*     */     //   36: ldc_w 520
/*     */     //   39: invokeinterface 522 2 0
/*     */     //   44: pop
/*     */     //   45: aload 10
/*     */     //   47: ldc_w 528
/*     */     //   50: invokeinterface 522 2 0
/*     */     //   55: pop
/*     */     //   56: new 36	java/lang/StringBuilder
/*     */     //   59: dup
/*     */     //   60: ldc_w 595
/*     */     //   63: invokespecial 40	java/lang/StringBuilder:<init>	(Ljava/lang/String;)V
/*     */     //   66: aload_1
/*     */     //   67: invokevirtual 43	java/lang/StringBuilder:append	(Ljava/lang/String;)Ljava/lang/StringBuilder;
/*     */     //   70: ldc_w 597
/*     */     //   73: invokevirtual 43	java/lang/StringBuilder:append	(Ljava/lang/String;)Ljava/lang/StringBuilder;
/*     */     //   76: ldc_w 599
/*     */     //   79: invokevirtual 43	java/lang/StringBuilder:append	(Ljava/lang/String;)Ljava/lang/StringBuilder;
/*     */     //   82: aload 4
/*     */     //   84: invokevirtual 43	java/lang/StringBuilder:append	(Ljava/lang/String;)Ljava/lang/StringBuilder;
/*     */     //   87: ldc_w 601
/*     */     //   90: invokevirtual 43	java/lang/StringBuilder:append	(Ljava/lang/String;)Ljava/lang/StringBuilder;
/*     */     //   93: ldc_w 603
/*     */     //   96: invokevirtual 43	java/lang/StringBuilder:append	(Ljava/lang/String;)Ljava/lang/StringBuilder;
/*     */     //   99: aload_1
/*     */     //   100: invokevirtual 43	java/lang/StringBuilder:append	(Ljava/lang/String;)Ljava/lang/StringBuilder;
/*     */     //   103: ldc_w 605
/*     */     //   106: invokevirtual 43	java/lang/StringBuilder:append	(Ljava/lang/String;)Ljava/lang/StringBuilder;
/*     */     //   109: ldc_w 599
/*     */     //   112: invokevirtual 43	java/lang/StringBuilder:append	(Ljava/lang/String;)Ljava/lang/StringBuilder;
/*     */     //   115: aload 4
/*     */     //   117: invokevirtual 43	java/lang/StringBuilder:append	(Ljava/lang/String;)Ljava/lang/StringBuilder;
/*     */     //   120: ldc_w 607
/*     */     //   123: invokevirtual 43	java/lang/StringBuilder:append	(Ljava/lang/String;)Ljava/lang/StringBuilder;
/*     */     //   126: invokevirtual 53	java/lang/StringBuilder:toString	()Ljava/lang/String;
/*     */     //   129: astore 11
/*     */     //   131: getstatic 57	java/lang/System:out	Ljava/io/PrintStream;
/*     */     //   134: aload 11
/*     */     //   136: invokevirtual 63	java/io/PrintStream:println	(Ljava/lang/String;)V
/*     */     //   139: aload 6
/*     */     //   141: aload 11
/*     */     //   143: invokeinterface 68 2 0
/*     */     //   148: astore 7
/*     */     //   150: aload 7
/*     */     //   152: iconst_1
/*     */     //   153: aload 5
/*     */     //   155: invokeinterface 255 3 0
/*     */     //   160: aload 7
/*     */     //   162: iconst_2
/*     */     //   163: iload_3
/*     */     //   164: invokeinterface 74 3 0
/*     */     //   169: aload 7
/*     */     //   171: iconst_3
/*     */     //   172: iload_3
/*     */     //   173: invokeinterface 74 3 0
/*     */     //   178: aload 7
/*     */     //   180: iconst_4
/*     */     //   181: aload 5
/*     */     //   183: invokeinterface 255 3 0
/*     */     //   188: aload 7
/*     */     //   190: iconst_5
/*     */     //   191: iload_2
/*     */     //   192: invokeinterface 74 3 0
/*     */     //   197: aload 7
/*     */     //   199: invokeinterface 80 1 0
/*     */     //   204: astore 8
/*     */     //   206: goto +93 -> 299
/*     */     //   209: aload 9
/*     */     //   211: aload 8
/*     */     //   213: ldc_w 544
/*     */     //   216: invokeinterface 89 2 0
/*     */     //   221: invokevirtual 546	com/groom/bean/UserRankBean:setRank	(I)V
/*     */     //   224: aload 9
/*     */     //   226: aload 8
/*     */     //   228: ldc_w 549
/*     */     //   231: invokeinterface 89 2 0
/*     */     //   236: invokevirtual 551	com/groom/bean/UserRankBean:setTotal_ranks	(I)V
/*     */     //   239: aload 8
/*     */     //   241: ldc_w 544
/*     */     //   244: invokeinterface 89 2 0
/*     */     //   249: i2d
/*     */     //   250: aload 8
/*     */     //   252: ldc_w 549
/*     */     //   255: invokeinterface 89 2 0
/*     */     //   260: i2d
/*     */     //   261: ddiv
/*     */     //   262: dstore 12
/*     */     //   264: new 554	java/text/DecimalFormat
/*     */     //   267: dup
/*     */     //   268: ldc_w 556
/*     */     //   271: invokespecial 558	java/text/DecimalFormat:<init>	(Ljava/lang/String;)V
/*     */     //   274: astore 14
/*     */     //   276: aload 9
/*     */     //   278: aload 14
/*     */     //   280: ldc2_w 559
/*     */     //   283: dload 12
/*     */     //   285: ldc2_w 559
/*     */     //   288: dmul
/*     */     //   289: dsub
/*     */     //   290: invokevirtual 561	java/text/DecimalFormat:format	(D)Ljava/lang/String;
/*     */     //   293: invokestatic 564	java/lang/Double:parseDouble	(Ljava/lang/String;)D
/*     */     //   296: invokevirtual 570	com/groom/bean/UserRankBean:setSubject_percentile	(D)V
/*     */     //   299: aload 8
/*     */     //   301: invokeinterface 169 1 0
/*     */     //   306: ifne -97 -> 209
/*     */     //   309: getstatic 57	java/lang/System:out	Ljava/io/PrintStream;
/*     */     //   312: new 36	java/lang/StringBuilder
/*     */     //   315: dup
/*     */     //   316: ldc_w 609
/*     */     //   319: invokespecial 40	java/lang/StringBuilder:<init>	(Ljava/lang/String;)V
/*     */     //   322: aload 9
/*     */     //   324: invokevirtual 574	com/groom/bean/UserRankBean:getRank	()I
/*     */     //   327: invokevirtual 611	java/lang/StringBuilder:append	(I)Ljava/lang/StringBuilder;
/*     */     //   330: ldc_w 614
/*     */     //   333: invokevirtual 43	java/lang/StringBuilder:append	(Ljava/lang/String;)Ljava/lang/StringBuilder;
/*     */     //   336: aload 9
/*     */     //   338: invokevirtual 579	com/groom/bean/UserRankBean:getTotal_ranks	()I
/*     */     //   341: invokevirtual 611	java/lang/StringBuilder:append	(I)Ljava/lang/StringBuilder;
/*     */     //   344: ldc_w 616
/*     */     //   347: invokevirtual 43	java/lang/StringBuilder:append	(Ljava/lang/String;)Ljava/lang/StringBuilder;
/*     */     //   350: aload 9
/*     */     //   352: invokevirtual 618	com/groom/bean/UserRankBean:getSubject_percentile	()D
/*     */     //   355: invokevirtual 622	java/lang/StringBuilder:append	(D)Ljava/lang/StringBuilder;
/*     */     //   358: invokevirtual 53	java/lang/StringBuilder:toString	()Ljava/lang/String;
/*     */     //   361: invokevirtual 63	java/io/PrintStream:println	(Ljava/lang/String;)V
/*     */     //   364: goto +90 -> 454
/*     */     //   367: astore 10
/*     */     //   369: aload 10
/*     */     //   371: invokevirtual 173	java/sql/SQLException:printStackTrace	()V
/*     */     //   374: aload 8
/*     */     //   376: ifnull +10 -> 386
/*     */     //   379: aload 8
/*     */     //   381: invokeinterface 176 1 0
/*     */     //   386: aload 7
/*     */     //   388: ifnull +10 -> 398
/*     */     //   391: aload 7
/*     */     //   393: invokeinterface 179 1 0
/*     */     //   398: aload 6
/*     */     //   400: ifnull +90 -> 490
/*     */     //   403: aload 6
/*     */     //   405: invokeinterface 180 1 0
/*     */     //   410: goto +80 -> 490
/*     */     //   413: astore 15
/*     */     //   415: aload 8
/*     */     //   417: ifnull +10 -> 427
/*     */     //   420: aload 8
/*     */     //   422: invokeinterface 176 1 0
/*     */     //   427: aload 7
/*     */     //   429: ifnull +10 -> 439
/*     */     //   432: aload 7
/*     */     //   434: invokeinterface 179 1 0
/*     */     //   439: aload 6
/*     */     //   441: ifnull +10 -> 451
/*     */     //   444: aload 6
/*     */     //   446: invokeinterface 180 1 0
/*     */     //   451: aload 15
/*     */     //   453: athrow
/*     */     //   454: aload 8
/*     */     //   456: ifnull +10 -> 466
/*     */     //   459: aload 8
/*     */     //   461: invokeinterface 176 1 0
/*     */     //   466: aload 7
/*     */     //   468: ifnull +10 -> 478
/*     */     //   471: aload 7
/*     */     //   473: invokeinterface 179 1 0
/*     */     //   478: aload 6
/*     */     //   480: ifnull +10 -> 490
/*     */     //   483: aload 6
/*     */     //   485: invokeinterface 180 1 0
/*     */     //   490: aload 9
/*     */     //   492: areturn
/*     */     // Line number table:
/*     */     //   Java source line #533	-> byte code offset #0
/*     */     //   Java source line #534	-> byte code offset #10
/*     */     //   Java source line #535	-> byte code offset #13
/*     */     //   Java source line #536	-> byte code offset #16
/*     */     //   Java source line #538	-> byte code offset #25
/*     */     //   Java source line #539	-> byte code offset #34
/*     */     //   Java source line #540	-> byte code offset #45
/*     */     //   Java source line #541	-> byte code offset #56
/*     */     //   Java source line #544	-> byte code offset #66
/*     */     //   Java source line #545	-> byte code offset #76
/*     */     //   Java source line #546	-> byte code offset #93
/*     */     //   Java source line #547	-> byte code offset #109
/*     */     //   Java source line #541	-> byte code offset #126
/*     */     //   Java source line #549	-> byte code offset #131
/*     */     //   Java source line #550	-> byte code offset #139
/*     */     //   Java source line #551	-> byte code offset #150
/*     */     //   Java source line #552	-> byte code offset #160
/*     */     //   Java source line #553	-> byte code offset #169
/*     */     //   Java source line #554	-> byte code offset #178
/*     */     //   Java source line #555	-> byte code offset #188
/*     */     //   Java source line #556	-> byte code offset #197
/*     */     //   Java source line #557	-> byte code offset #206
/*     */     //   Java source line #558	-> byte code offset #209
/*     */     //   Java source line #559	-> byte code offset #224
/*     */     //   Java source line #560	-> byte code offset #239
/*     */     //   Java source line #561	-> byte code offset #264
/*     */     //   Java source line #562	-> byte code offset #276
/*     */     //   Java source line #557	-> byte code offset #299
/*     */     //   Java source line #564	-> byte code offset #309
/*     */     //   Java source line #566	-> byte code offset #364
/*     */     //   Java source line #567	-> byte code offset #369
/*     */     //   Java source line #569	-> byte code offset #374
/*     */     //   Java source line #570	-> byte code offset #379
/*     */     //   Java source line #571	-> byte code offset #386
/*     */     //   Java source line #572	-> byte code offset #391
/*     */     //   Java source line #573	-> byte code offset #398
/*     */     //   Java source line #574	-> byte code offset #403
/*     */     //   Java source line #568	-> byte code offset #413
/*     */     //   Java source line #569	-> byte code offset #415
/*     */     //   Java source line #570	-> byte code offset #420
/*     */     //   Java source line #571	-> byte code offset #427
/*     */     //   Java source line #572	-> byte code offset #432
/*     */     //   Java source line #573	-> byte code offset #439
/*     */     //   Java source line #574	-> byte code offset #444
/*     */     //   Java source line #575	-> byte code offset #451
/*     */     //   Java source line #569	-> byte code offset #454
/*     */     //   Java source line #570	-> byte code offset #459
/*     */     //   Java source line #571	-> byte code offset #466
/*     */     //   Java source line #572	-> byte code offset #471
/*     */     //   Java source line #573	-> byte code offset #478
/*     */     //   Java source line #574	-> byte code offset #483
/*     */     //   Java source line #576	-> byte code offset #490
/*     */     // Local variable table:
/*     */     //   start	length	slot	name	signature
/*     */     //   0	493	0	this	QuizDAOImpl
/*     */     //   0	493	1	subject	String
/*     */     //   0	493	2	user_id	int
/*     */     //   0	493	3	topic_id	int
/*     */     //   0	493	4	locationType	String
/*     */     //   0	493	5	location	String
/*     */     //   8	476	6	connection	Connection
/*     */     //   11	461	7	preparedStatement	PreparedStatement
/*     */     //   14	446	8	resultSet	ResultSet
/*     */     //   23	468	9	userRank	com.groom.bean.UserRankBean
/*     */     //   32	14	10	statement	java.sql.Statement
/*     */     //   367	3	10	exception	SQLException
/*     */     //   129	13	11	query	String
/*     */     //   262	22	12	subjectRank	double
/*     */     //   274	5	14	noOfDecimals	java.text.DecimalFormat
/*     */     //   413	39	15	localObject	Object
/*     */     // Exception table:
/*     */     //   from	to	target	type
/*     */     //   25	364	367	java/sql/SQLException
/*     */     //   25	374	413	finally
/*     */   }
/*     */   
/*     */   /* Error */
/*     */   public com.groom.bean.SubjectAnalysisBean getUserSubjectWiseAnalysis(int user_id, int standard)
/*     */     throws SQLException
/*     */   {
/*     */     // Byte code:
/*     */     //   0: getstatic 23	com/groom/dao/impl/QuizDAOImpl:ds	Ljavax/sql/DataSource;
/*     */     //   3: invokeinterface 27 1 0
/*     */     //   8: astore_3
/*     */     //   9: aconst_null
/*     */     //   10: astore 4
/*     */     //   12: aconst_null
/*     */     //   13: astore 5
/*     */     //   15: new 630	com/groom/bean/SubjectAnalysisBean
/*     */     //   18: dup
/*     */     //   19: invokespecial 632	com/groom/bean/SubjectAnalysisBean:<init>	()V
/*     */     //   22: astore 6
/*     */     //   24: ldc_w 633
/*     */     //   27: astore 7
/*     */     //   29: getstatic 57	java/lang/System:out	Ljava/io/PrintStream;
/*     */     //   32: aload 7
/*     */     //   34: invokevirtual 63	java/io/PrintStream:println	(Ljava/lang/String;)V
/*     */     //   37: aload_3
/*     */     //   38: aload 7
/*     */     //   40: invokeinterface 68 2 0
/*     */     //   45: astore 4
/*     */     //   47: aload 4
/*     */     //   49: iconst_1
/*     */     //   50: iload_2
/*     */     //   51: invokeinterface 74 3 0
/*     */     //   56: aload 4
/*     */     //   58: iconst_2
/*     */     //   59: iload_2
/*     */     //   60: invokeinterface 74 3 0
/*     */     //   65: aload 4
/*     */     //   67: iconst_3
/*     */     //   68: iload_2
/*     */     //   69: invokeinterface 74 3 0
/*     */     //   74: aload 4
/*     */     //   76: iconst_4
/*     */     //   77: iload_2
/*     */     //   78: invokeinterface 74 3 0
/*     */     //   83: aload 4
/*     */     //   85: iconst_5
/*     */     //   86: iload_2
/*     */     //   87: invokeinterface 74 3 0
/*     */     //   92: aload 4
/*     */     //   94: bipush 6
/*     */     //   96: iload_1
/*     */     //   97: invokeinterface 74 3 0
/*     */     //   102: aload 4
/*     */     //   104: invokeinterface 80 1 0
/*     */     //   109: astore 5
/*     */     //   111: goto +309 -> 420
/*     */     //   114: aload 6
/*     */     //   116: aload 5
/*     */     //   118: ldc_w 468
/*     */     //   121: invokeinterface 89 2 0
/*     */     //   126: invokevirtual 635	com/groom/bean/SubjectAnalysisBean:setUser_id	(I)V
/*     */     //   129: aload 6
/*     */     //   131: aload 5
/*     */     //   133: ldc_w 636
/*     */     //   136: invokeinterface 101 2 0
/*     */     //   141: invokevirtual 638	com/groom/bean/SubjectAnalysisBean:setFirst_name	(Ljava/lang/String;)V
/*     */     //   144: aload 6
/*     */     //   146: aload 5
/*     */     //   148: ldc_w 641
/*     */     //   151: invokeinterface 101 2 0
/*     */     //   156: invokevirtual 643	com/groom/bean/SubjectAnalysisBean:setLast_name	(Ljava/lang/String;)V
/*     */     //   159: aload 6
/*     */     //   161: aload 5
/*     */     //   163: ldc_w 646
/*     */     //   166: invokeinterface 89 2 0
/*     */     //   171: invokevirtual 648	com/groom/bean/SubjectAnalysisBean:setMaths_points	(I)V
/*     */     //   174: aload 6
/*     */     //   176: aload 5
/*     */     //   178: ldc_w 651
/*     */     //   181: invokeinterface 89 2 0
/*     */     //   186: invokevirtual 653	com/groom/bean/SubjectAnalysisBean:setPhysics_points	(I)V
/*     */     //   189: aload 6
/*     */     //   191: aload 5
/*     */     //   193: ldc_w 656
/*     */     //   196: invokeinterface 89 2 0
/*     */     //   201: invokevirtual 658	com/groom/bean/SubjectAnalysisBean:setChemistry_points	(I)V
/*     */     //   204: aload 6
/*     */     //   206: aload 5
/*     */     //   208: ldc_w 661
/*     */     //   211: invokeinterface 89 2 0
/*     */     //   216: invokevirtual 663	com/groom/bean/SubjectAnalysisBean:setMaths_rank	(I)V
/*     */     //   219: aload 6
/*     */     //   221: aload 5
/*     */     //   223: ldc_w 666
/*     */     //   226: invokeinterface 89 2 0
/*     */     //   231: invokevirtual 668	com/groom/bean/SubjectAnalysisBean:setPhysics_rank	(I)V
/*     */     //   234: aload 6
/*     */     //   236: aload 5
/*     */     //   238: ldc_w 671
/*     */     //   241: invokeinterface 89 2 0
/*     */     //   246: invokevirtual 673	com/groom/bean/SubjectAnalysisBean:setChemistry_rank	(I)V
/*     */     //   249: aload 6
/*     */     //   251: aload 5
/*     */     //   253: ldc_w 549
/*     */     //   256: invokeinterface 89 2 0
/*     */     //   261: invokevirtual 676	com/groom/bean/SubjectAnalysisBean:setTotal_ranks	(I)V
/*     */     //   264: aload 5
/*     */     //   266: ldc_w 661
/*     */     //   269: invokeinterface 89 2 0
/*     */     //   274: i2d
/*     */     //   275: aload 5
/*     */     //   277: ldc_w 549
/*     */     //   280: invokeinterface 89 2 0
/*     */     //   285: i2d
/*     */     //   286: ddiv
/*     */     //   287: dstore 8
/*     */     //   289: aload 5
/*     */     //   291: ldc_w 666
/*     */     //   294: invokeinterface 89 2 0
/*     */     //   299: i2d
/*     */     //   300: aload 5
/*     */     //   302: ldc_w 549
/*     */     //   305: invokeinterface 89 2 0
/*     */     //   310: i2d
/*     */     //   311: ddiv
/*     */     //   312: dstore 10
/*     */     //   314: aload 5
/*     */     //   316: ldc_w 671
/*     */     //   319: invokeinterface 89 2 0
/*     */     //   324: i2d
/*     */     //   325: aload 5
/*     */     //   327: ldc_w 549
/*     */     //   330: invokeinterface 89 2 0
/*     */     //   335: i2d
/*     */     //   336: ddiv
/*     */     //   337: dstore 12
/*     */     //   339: new 554	java/text/DecimalFormat
/*     */     //   342: dup
/*     */     //   343: ldc_w 556
/*     */     //   346: invokespecial 558	java/text/DecimalFormat:<init>	(Ljava/lang/String;)V
/*     */     //   349: astore 14
/*     */     //   351: aload 6
/*     */     //   353: aload 14
/*     */     //   355: ldc2_w 559
/*     */     //   358: dload 8
/*     */     //   360: ldc2_w 559
/*     */     //   363: dmul
/*     */     //   364: dsub
/*     */     //   365: invokevirtual 561	java/text/DecimalFormat:format	(D)Ljava/lang/String;
/*     */     //   368: invokestatic 564	java/lang/Double:parseDouble	(Ljava/lang/String;)D
/*     */     //   371: invokevirtual 677	com/groom/bean/SubjectAnalysisBean:setMaths_percentile	(D)V
/*     */     //   374: aload 6
/*     */     //   376: aload 14
/*     */     //   378: ldc2_w 559
/*     */     //   381: dload 10
/*     */     //   383: ldc2_w 559
/*     */     //   386: dmul
/*     */     //   387: dsub
/*     */     //   388: invokevirtual 561	java/text/DecimalFormat:format	(D)Ljava/lang/String;
/*     */     //   391: invokestatic 564	java/lang/Double:parseDouble	(Ljava/lang/String;)D
/*     */     //   394: invokevirtual 680	com/groom/bean/SubjectAnalysisBean:setPhysics_percentile	(D)V
/*     */     //   397: aload 6
/*     */     //   399: aload 14
/*     */     //   401: ldc2_w 559
/*     */     //   404: dload 12
/*     */     //   406: ldc2_w 559
/*     */     //   409: dmul
/*     */     //   410: dsub
/*     */     //   411: invokevirtual 561	java/text/DecimalFormat:format	(D)Ljava/lang/String;
/*     */     //   414: invokestatic 564	java/lang/Double:parseDouble	(Ljava/lang/String;)D
/*     */     //   417: invokevirtual 683	com/groom/bean/SubjectAnalysisBean:setChemistry_percentile	(D)V
/*     */     //   420: aload 5
/*     */     //   422: invokeinterface 169 1 0
/*     */     //   427: ifne -313 -> 114
/*     */     //   430: goto +86 -> 516
/*     */     //   433: astore 7
/*     */     //   435: aload 7
/*     */     //   437: invokevirtual 173	java/sql/SQLException:printStackTrace	()V
/*     */     //   440: aload 5
/*     */     //   442: ifnull +10 -> 452
/*     */     //   445: aload 5
/*     */     //   447: invokeinterface 176 1 0
/*     */     //   452: aload 4
/*     */     //   454: ifnull +10 -> 464
/*     */     //   457: aload 4
/*     */     //   459: invokeinterface 179 1 0
/*     */     //   464: aload_3
/*     */     //   465: ifnull +85 -> 550
/*     */     //   468: aload_3
/*     */     //   469: invokeinterface 180 1 0
/*     */     //   474: goto +76 -> 550
/*     */     //   477: astore 15
/*     */     //   479: aload 5
/*     */     //   481: ifnull +10 -> 491
/*     */     //   484: aload 5
/*     */     //   486: invokeinterface 176 1 0
/*     */     //   491: aload 4
/*     */     //   493: ifnull +10 -> 503
/*     */     //   496: aload 4
/*     */     //   498: invokeinterface 179 1 0
/*     */     //   503: aload_3
/*     */     //   504: ifnull +9 -> 513
/*     */     //   507: aload_3
/*     */     //   508: invokeinterface 180 1 0
/*     */     //   513: aload 15
/*     */     //   515: athrow
/*     */     //   516: aload 5
/*     */     //   518: ifnull +10 -> 528
/*     */     //   521: aload 5
/*     */     //   523: invokeinterface 176 1 0
/*     */     //   528: aload 4
/*     */     //   530: ifnull +10 -> 540
/*     */     //   533: aload 4
/*     */     //   535: invokeinterface 179 1 0
/*     */     //   540: aload_3
/*     */     //   541: ifnull +9 -> 550
/*     */     //   544: aload_3
/*     */     //   545: invokeinterface 180 1 0
/*     */     //   550: aload 6
/*     */     //   552: areturn
/*     */     // Line number table:
/*     */     //   Java source line #582	-> byte code offset #0
/*     */     //   Java source line #583	-> byte code offset #9
/*     */     //   Java source line #584	-> byte code offset #12
/*     */     //   Java source line #585	-> byte code offset #15
/*     */     //   Java source line #588	-> byte code offset #24
/*     */     //   Java source line #594	-> byte code offset #29
/*     */     //   Java source line #595	-> byte code offset #37
/*     */     //   Java source line #596	-> byte code offset #47
/*     */     //   Java source line #597	-> byte code offset #56
/*     */     //   Java source line #598	-> byte code offset #65
/*     */     //   Java source line #599	-> byte code offset #74
/*     */     //   Java source line #600	-> byte code offset #83
/*     */     //   Java source line #601	-> byte code offset #92
/*     */     //   Java source line #602	-> byte code offset #102
/*     */     //   Java source line #603	-> byte code offset #111
/*     */     //   Java source line #604	-> byte code offset #114
/*     */     //   Java source line #605	-> byte code offset #129
/*     */     //   Java source line #606	-> byte code offset #144
/*     */     //   Java source line #607	-> byte code offset #159
/*     */     //   Java source line #608	-> byte code offset #174
/*     */     //   Java source line #609	-> byte code offset #189
/*     */     //   Java source line #610	-> byte code offset #204
/*     */     //   Java source line #611	-> byte code offset #219
/*     */     //   Java source line #612	-> byte code offset #234
/*     */     //   Java source line #613	-> byte code offset #249
/*     */     //   Java source line #614	-> byte code offset #264
/*     */     //   Java source line #615	-> byte code offset #289
/*     */     //   Java source line #616	-> byte code offset #314
/*     */     //   Java source line #617	-> byte code offset #339
/*     */     //   Java source line #618	-> byte code offset #351
/*     */     //   Java source line #619	-> byte code offset #374
/*     */     //   Java source line #620	-> byte code offset #397
/*     */     //   Java source line #603	-> byte code offset #420
/*     */     //   Java source line #624	-> byte code offset #430
/*     */     //   Java source line #625	-> byte code offset #435
/*     */     //   Java source line #627	-> byte code offset #440
/*     */     //   Java source line #628	-> byte code offset #445
/*     */     //   Java source line #629	-> byte code offset #452
/*     */     //   Java source line #630	-> byte code offset #457
/*     */     //   Java source line #631	-> byte code offset #464
/*     */     //   Java source line #632	-> byte code offset #468
/*     */     //   Java source line #626	-> byte code offset #477
/*     */     //   Java source line #627	-> byte code offset #479
/*     */     //   Java source line #628	-> byte code offset #484
/*     */     //   Java source line #629	-> byte code offset #491
/*     */     //   Java source line #630	-> byte code offset #496
/*     */     //   Java source line #631	-> byte code offset #503
/*     */     //   Java source line #632	-> byte code offset #507
/*     */     //   Java source line #633	-> byte code offset #513
/*     */     //   Java source line #627	-> byte code offset #516
/*     */     //   Java source line #628	-> byte code offset #521
/*     */     //   Java source line #629	-> byte code offset #528
/*     */     //   Java source line #630	-> byte code offset #533
/*     */     //   Java source line #631	-> byte code offset #540
/*     */     //   Java source line #632	-> byte code offset #544
/*     */     //   Java source line #634	-> byte code offset #550
/*     */     // Local variable table:
/*     */     //   start	length	slot	name	signature
/*     */     //   0	553	0	this	QuizDAOImpl
/*     */     //   0	553	1	user_id	int
/*     */     //   0	553	2	standard	int
/*     */     //   8	537	3	connection	Connection
/*     */     //   10	524	4	preparedStatement	PreparedStatement
/*     */     //   13	509	5	resultSet	ResultSet
/*     */     //   22	529	6	analysisBean	com.groom.bean.SubjectAnalysisBean
/*     */     //   27	12	7	query	String
/*     */     //   433	3	7	exception	SQLException
/*     */     //   287	72	8	mathsRank	double
/*     */     //   312	70	10	physicsRank	double
/*     */     //   337	68	12	chemistryRank	double
/*     */     //   349	51	14	noOfDecimals	java.text.DecimalFormat
/*     */     //   477	37	15	localObject	Object
/*     */     // Exception table:
/*     */     //   from	to	target	type
/*     */     //   24	430	433	java/sql/SQLException
/*     */     //   24	440	477	finally
/*     */   }
/*     */   
/*     */   /* Error */
/*     */   public com.groom.bean.SubjectAnalysisBean getUserSubjectWiseAnalysisByLocation(int user_id, int standard, String locationType, String location)
/*     */     throws SQLException
/*     */   {
/*     */     // Byte code:
/*     */     //   0: getstatic 23	com/groom/dao/impl/QuizDAOImpl:ds	Ljavax/sql/DataSource;
/*     */     //   3: invokeinterface 27 1 0
/*     */     //   8: astore 5
/*     */     //   10: aconst_null
/*     */     //   11: astore 6
/*     */     //   13: aconst_null
/*     */     //   14: astore 7
/*     */     //   16: new 630	com/groom/bean/SubjectAnalysisBean
/*     */     //   19: dup
/*     */     //   20: invokespecial 632	com/groom/bean/SubjectAnalysisBean:<init>	()V
/*     */     //   23: astore 8
/*     */     //   25: new 36	java/lang/StringBuilder
/*     */     //   28: dup
/*     */     //   29: ldc_w 693
/*     */     //   32: invokespecial 40	java/lang/StringBuilder:<init>	(Ljava/lang/String;)V
/*     */     //   35: aload_3
/*     */     //   36: invokevirtual 43	java/lang/StringBuilder:append	(Ljava/lang/String;)Ljava/lang/StringBuilder;
/*     */     //   39: ldc_w 695
/*     */     //   42: invokevirtual 43	java/lang/StringBuilder:append	(Ljava/lang/String;)Ljava/lang/StringBuilder;
/*     */     //   45: ldc_w 697
/*     */     //   48: invokevirtual 43	java/lang/StringBuilder:append	(Ljava/lang/String;)Ljava/lang/StringBuilder;
/*     */     //   51: aload_3
/*     */     //   52: invokevirtual 43	java/lang/StringBuilder:append	(Ljava/lang/String;)Ljava/lang/StringBuilder;
/*     */     //   55: ldc_w 699
/*     */     //   58: invokevirtual 43	java/lang/StringBuilder:append	(Ljava/lang/String;)Ljava/lang/StringBuilder;
/*     */     //   61: ldc_w 701
/*     */     //   64: invokevirtual 43	java/lang/StringBuilder:append	(Ljava/lang/String;)Ljava/lang/StringBuilder;
/*     */     //   67: aload_3
/*     */     //   68: invokevirtual 43	java/lang/StringBuilder:append	(Ljava/lang/String;)Ljava/lang/StringBuilder;
/*     */     //   71: ldc_w 703
/*     */     //   74: invokevirtual 43	java/lang/StringBuilder:append	(Ljava/lang/String;)Ljava/lang/StringBuilder;
/*     */     //   77: ldc_w 705
/*     */     //   80: invokevirtual 43	java/lang/StringBuilder:append	(Ljava/lang/String;)Ljava/lang/StringBuilder;
/*     */     //   83: aload_3
/*     */     //   84: invokevirtual 43	java/lang/StringBuilder:append	(Ljava/lang/String;)Ljava/lang/StringBuilder;
/*     */     //   87: ldc_w 707
/*     */     //   90: invokevirtual 43	java/lang/StringBuilder:append	(Ljava/lang/String;)Ljava/lang/StringBuilder;
/*     */     //   93: invokevirtual 53	java/lang/StringBuilder:toString	()Ljava/lang/String;
/*     */     //   96: astore 9
/*     */     //   98: getstatic 57	java/lang/System:out	Ljava/io/PrintStream;
/*     */     //   101: aload 9
/*     */     //   103: invokevirtual 63	java/io/PrintStream:println	(Ljava/lang/String;)V
/*     */     //   106: aload 5
/*     */     //   108: aload 9
/*     */     //   110: invokeinterface 68 2 0
/*     */     //   115: astore 6
/*     */     //   117: aload 6
/*     */     //   119: iconst_1
/*     */     //   120: aload 4
/*     */     //   122: invokeinterface 255 3 0
/*     */     //   127: aload 6
/*     */     //   129: iconst_2
/*     */     //   130: iload_2
/*     */     //   131: invokeinterface 74 3 0
/*     */     //   136: aload 6
/*     */     //   138: iconst_3
/*     */     //   139: aload 4
/*     */     //   141: invokeinterface 255 3 0
/*     */     //   146: aload 6
/*     */     //   148: iconst_4
/*     */     //   149: iload_2
/*     */     //   150: invokeinterface 74 3 0
/*     */     //   155: aload 6
/*     */     //   157: iconst_5
/*     */     //   158: aload 4
/*     */     //   160: invokeinterface 255 3 0
/*     */     //   165: aload 6
/*     */     //   167: bipush 6
/*     */     //   169: iload_2
/*     */     //   170: invokeinterface 74 3 0
/*     */     //   175: aload 6
/*     */     //   177: bipush 7
/*     */     //   179: aload 4
/*     */     //   181: invokeinterface 255 3 0
/*     */     //   186: aload 6
/*     */     //   188: bipush 8
/*     */     //   190: iload_2
/*     */     //   191: invokeinterface 74 3 0
/*     */     //   196: aload 6
/*     */     //   198: bipush 9
/*     */     //   200: iload_2
/*     */     //   201: invokeinterface 74 3 0
/*     */     //   206: aload 6
/*     */     //   208: bipush 10
/*     */     //   210: iload_1
/*     */     //   211: invokeinterface 74 3 0
/*     */     //   216: aload 6
/*     */     //   218: invokeinterface 80 1 0
/*     */     //   223: astore 7
/*     */     //   225: goto +309 -> 534
/*     */     //   228: aload 8
/*     */     //   230: aload 7
/*     */     //   232: ldc_w 468
/*     */     //   235: invokeinterface 89 2 0
/*     */     //   240: invokevirtual 635	com/groom/bean/SubjectAnalysisBean:setUser_id	(I)V
/*     */     //   243: aload 8
/*     */     //   245: aload 7
/*     */     //   247: ldc_w 636
/*     */     //   250: invokeinterface 101 2 0
/*     */     //   255: invokevirtual 638	com/groom/bean/SubjectAnalysisBean:setFirst_name	(Ljava/lang/String;)V
/*     */     //   258: aload 8
/*     */     //   260: aload 7
/*     */     //   262: ldc_w 641
/*     */     //   265: invokeinterface 101 2 0
/*     */     //   270: invokevirtual 643	com/groom/bean/SubjectAnalysisBean:setLast_name	(Ljava/lang/String;)V
/*     */     //   273: aload 8
/*     */     //   275: aload 7
/*     */     //   277: ldc_w 646
/*     */     //   280: invokeinterface 89 2 0
/*     */     //   285: invokevirtual 648	com/groom/bean/SubjectAnalysisBean:setMaths_points	(I)V
/*     */     //   288: aload 8
/*     */     //   290: aload 7
/*     */     //   292: ldc_w 651
/*     */     //   295: invokeinterface 89 2 0
/*     */     //   300: invokevirtual 653	com/groom/bean/SubjectAnalysisBean:setPhysics_points	(I)V
/*     */     //   303: aload 8
/*     */     //   305: aload 7
/*     */     //   307: ldc_w 656
/*     */     //   310: invokeinterface 89 2 0
/*     */     //   315: invokevirtual 658	com/groom/bean/SubjectAnalysisBean:setChemistry_points	(I)V
/*     */     //   318: aload 8
/*     */     //   320: aload 7
/*     */     //   322: ldc_w 661
/*     */     //   325: invokeinterface 89 2 0
/*     */     //   330: invokevirtual 663	com/groom/bean/SubjectAnalysisBean:setMaths_rank	(I)V
/*     */     //   333: aload 8
/*     */     //   335: aload 7
/*     */     //   337: ldc_w 666
/*     */     //   340: invokeinterface 89 2 0
/*     */     //   345: invokevirtual 668	com/groom/bean/SubjectAnalysisBean:setPhysics_rank	(I)V
/*     */     //   348: aload 8
/*     */     //   350: aload 7
/*     */     //   352: ldc_w 671
/*     */     //   355: invokeinterface 89 2 0
/*     */     //   360: invokevirtual 673	com/groom/bean/SubjectAnalysisBean:setChemistry_rank	(I)V
/*     */     //   363: aload 8
/*     */     //   365: aload 7
/*     */     //   367: ldc_w 549
/*     */     //   370: invokeinterface 89 2 0
/*     */     //   375: invokevirtual 676	com/groom/bean/SubjectAnalysisBean:setTotal_ranks	(I)V
/*     */     //   378: aload 7
/*     */     //   380: ldc_w 661
/*     */     //   383: invokeinterface 89 2 0
/*     */     //   388: i2d
/*     */     //   389: aload 7
/*     */     //   391: ldc_w 549
/*     */     //   394: invokeinterface 89 2 0
/*     */     //   399: i2d
/*     */     //   400: ddiv
/*     */     //   401: dstore 10
/*     */     //   403: aload 7
/*     */     //   405: ldc_w 666
/*     */     //   408: invokeinterface 89 2 0
/*     */     //   413: i2d
/*     */     //   414: aload 7
/*     */     //   416: ldc_w 549
/*     */     //   419: invokeinterface 89 2 0
/*     */     //   424: i2d
/*     */     //   425: ddiv
/*     */     //   426: dstore 12
/*     */     //   428: aload 7
/*     */     //   430: ldc_w 671
/*     */     //   433: invokeinterface 89 2 0
/*     */     //   438: i2d
/*     */     //   439: aload 7
/*     */     //   441: ldc_w 549
/*     */     //   444: invokeinterface 89 2 0
/*     */     //   449: i2d
/*     */     //   450: ddiv
/*     */     //   451: dstore 14
/*     */     //   453: new 554	java/text/DecimalFormat
/*     */     //   456: dup
/*     */     //   457: ldc_w 556
/*     */     //   460: invokespecial 558	java/text/DecimalFormat:<init>	(Ljava/lang/String;)V
/*     */     //   463: astore 16
/*     */     //   465: aload 8
/*     */     //   467: aload 16
/*     */     //   469: ldc2_w 559
/*     */     //   472: dload 10
/*     */     //   474: ldc2_w 559
/*     */     //   477: dmul
/*     */     //   478: dsub
/*     */     //   479: invokevirtual 561	java/text/DecimalFormat:format	(D)Ljava/lang/String;
/*     */     //   482: invokestatic 564	java/lang/Double:parseDouble	(Ljava/lang/String;)D
/*     */     //   485: invokevirtual 677	com/groom/bean/SubjectAnalysisBean:setMaths_percentile	(D)V
/*     */     //   488: aload 8
/*     */     //   490: aload 16
/*     */     //   492: ldc2_w 559
/*     */     //   495: dload 12
/*     */     //   497: ldc2_w 559
/*     */     //   500: dmul
/*     */     //   501: dsub
/*     */     //   502: invokevirtual 561	java/text/DecimalFormat:format	(D)Ljava/lang/String;
/*     */     //   505: invokestatic 564	java/lang/Double:parseDouble	(Ljava/lang/String;)D
/*     */     //   508: invokevirtual 680	com/groom/bean/SubjectAnalysisBean:setPhysics_percentile	(D)V
/*     */     //   511: aload 8
/*     */     //   513: aload 16
/*     */     //   515: ldc2_w 559
/*     */     //   518: dload 14
/*     */     //   520: ldc2_w 559
/*     */     //   523: dmul
/*     */     //   524: dsub
/*     */     //   525: invokevirtual 561	java/text/DecimalFormat:format	(D)Ljava/lang/String;
/*     */     //   528: invokestatic 564	java/lang/Double:parseDouble	(Ljava/lang/String;)D
/*     */     //   531: invokevirtual 683	com/groom/bean/SubjectAnalysisBean:setChemistry_percentile	(D)V
/*     */     //   534: aload 7
/*     */     //   536: invokeinterface 169 1 0
/*     */     //   541: ifne -313 -> 228
/*     */     //   544: goto +90 -> 634
/*     */     //   547: astore 9
/*     */     //   549: aload 9
/*     */     //   551: invokevirtual 173	java/sql/SQLException:printStackTrace	()V
/*     */     //   554: aload 7
/*     */     //   556: ifnull +10 -> 566
/*     */     //   559: aload 7
/*     */     //   561: invokeinterface 176 1 0
/*     */     //   566: aload 6
/*     */     //   568: ifnull +10 -> 578
/*     */     //   571: aload 6
/*     */     //   573: invokeinterface 179 1 0
/*     */     //   578: aload 5
/*     */     //   580: ifnull +90 -> 670
/*     */     //   583: aload 5
/*     */     //   585: invokeinterface 180 1 0
/*     */     //   590: goto +80 -> 670
/*     */     //   593: astore 17
/*     */     //   595: aload 7
/*     */     //   597: ifnull +10 -> 607
/*     */     //   600: aload 7
/*     */     //   602: invokeinterface 176 1 0
/*     */     //   607: aload 6
/*     */     //   609: ifnull +10 -> 619
/*     */     //   612: aload 6
/*     */     //   614: invokeinterface 179 1 0
/*     */     //   619: aload 5
/*     */     //   621: ifnull +10 -> 631
/*     */     //   624: aload 5
/*     */     //   626: invokeinterface 180 1 0
/*     */     //   631: aload 17
/*     */     //   633: athrow
/*     */     //   634: aload 7
/*     */     //   636: ifnull +10 -> 646
/*     */     //   639: aload 7
/*     */     //   641: invokeinterface 176 1 0
/*     */     //   646: aload 6
/*     */     //   648: ifnull +10 -> 658
/*     */     //   651: aload 6
/*     */     //   653: invokeinterface 179 1 0
/*     */     //   658: aload 5
/*     */     //   660: ifnull +10 -> 670
/*     */     //   663: aload 5
/*     */     //   665: invokeinterface 180 1 0
/*     */     //   670: aload 8
/*     */     //   672: areturn
/*     */     // Line number table:
/*     */     //   Java source line #641	-> byte code offset #0
/*     */     //   Java source line #642	-> byte code offset #10
/*     */     //   Java source line #643	-> byte code offset #13
/*     */     //   Java source line #644	-> byte code offset #16
/*     */     //   Java source line #647	-> byte code offset #25
/*     */     //   Java source line #648	-> byte code offset #35
/*     */     //   Java source line #649	-> byte code offset #45
/*     */     //   Java source line #650	-> byte code offset #61
/*     */     //   Java source line #651	-> byte code offset #77
/*     */     //   Java source line #647	-> byte code offset #93
/*     */     //   Java source line #653	-> byte code offset #98
/*     */     //   Java source line #654	-> byte code offset #106
/*     */     //   Java source line #655	-> byte code offset #117
/*     */     //   Java source line #656	-> byte code offset #127
/*     */     //   Java source line #657	-> byte code offset #136
/*     */     //   Java source line #658	-> byte code offset #146
/*     */     //   Java source line #659	-> byte code offset #155
/*     */     //   Java source line #660	-> byte code offset #165
/*     */     //   Java source line #661	-> byte code offset #175
/*     */     //   Java source line #662	-> byte code offset #186
/*     */     //   Java source line #663	-> byte code offset #196
/*     */     //   Java source line #664	-> byte code offset #206
/*     */     //   Java source line #665	-> byte code offset #216
/*     */     //   Java source line #666	-> byte code offset #225
/*     */     //   Java source line #667	-> byte code offset #228
/*     */     //   Java source line #668	-> byte code offset #243
/*     */     //   Java source line #669	-> byte code offset #258
/*     */     //   Java source line #670	-> byte code offset #273
/*     */     //   Java source line #671	-> byte code offset #288
/*     */     //   Java source line #672	-> byte code offset #303
/*     */     //   Java source line #673	-> byte code offset #318
/*     */     //   Java source line #674	-> byte code offset #333
/*     */     //   Java source line #675	-> byte code offset #348
/*     */     //   Java source line #676	-> byte code offset #363
/*     */     //   Java source line #677	-> byte code offset #378
/*     */     //   Java source line #678	-> byte code offset #403
/*     */     //   Java source line #679	-> byte code offset #428
/*     */     //   Java source line #680	-> byte code offset #453
/*     */     //   Java source line #681	-> byte code offset #465
/*     */     //   Java source line #682	-> byte code offset #488
/*     */     //   Java source line #683	-> byte code offset #511
/*     */     //   Java source line #666	-> byte code offset #534
/*     */     //   Java source line #689	-> byte code offset #544
/*     */     //   Java source line #690	-> byte code offset #549
/*     */     //   Java source line #692	-> byte code offset #554
/*     */     //   Java source line #693	-> byte code offset #559
/*     */     //   Java source line #694	-> byte code offset #566
/*     */     //   Java source line #695	-> byte code offset #571
/*     */     //   Java source line #696	-> byte code offset #578
/*     */     //   Java source line #697	-> byte code offset #583
/*     */     //   Java source line #691	-> byte code offset #593
/*     */     //   Java source line #692	-> byte code offset #595
/*     */     //   Java source line #693	-> byte code offset #600
/*     */     //   Java source line #694	-> byte code offset #607
/*     */     //   Java source line #695	-> byte code offset #612
/*     */     //   Java source line #696	-> byte code offset #619
/*     */     //   Java source line #697	-> byte code offset #624
/*     */     //   Java source line #698	-> byte code offset #631
/*     */     //   Java source line #692	-> byte code offset #634
/*     */     //   Java source line #693	-> byte code offset #639
/*     */     //   Java source line #694	-> byte code offset #646
/*     */     //   Java source line #695	-> byte code offset #651
/*     */     //   Java source line #696	-> byte code offset #658
/*     */     //   Java source line #697	-> byte code offset #663
/*     */     //   Java source line #699	-> byte code offset #670
/*     */     // Local variable table:
/*     */     //   start	length	slot	name	signature
/*     */     //   0	673	0	this	QuizDAOImpl
/*     */     //   0	673	1	user_id	int
/*     */     //   0	673	2	standard	int
/*     */     //   0	673	3	locationType	String
/*     */     //   0	673	4	location	String
/*     */     //   8	656	5	connection	Connection
/*     */     //   11	641	6	preparedStatement	PreparedStatement
/*     */     //   14	626	7	resultSet	ResultSet
/*     */     //   23	648	8	analysisBean	com.groom.bean.SubjectAnalysisBean
/*     */     //   96	13	9	query	String
/*     */     //   547	3	9	exception	SQLException
/*     */     //   401	72	10	mathsRank	double
/*     */     //   426	70	12	physicsRank	double
/*     */     //   451	68	14	chemistryRank	double
/*     */     //   463	51	16	noOfDecimals	java.text.DecimalFormat
/*     */     //   593	39	17	localObject	Object
/*     */     // Exception table:
/*     */     //   from	to	target	type
/*     */     //   25	544	547	java/sql/SQLException
/*     */     //   25	554	593	finally
/*     */   }
/*     */   
/*     */   /* Error */
/*     */   public List<com.groom.bean.TestsTopicList> getTestTopicsByCategory(int userid, String category, int division, int test_category_id)
/*     */     throws SQLException
/*     */   {
/*     */     // Byte code:
/*     */     //   0: getstatic 23	com/groom/dao/impl/QuizDAOImpl:ds	Ljavax/sql/DataSource;
/*     */     //   3: invokeinterface 27 1 0
/*     */     //   8: astore 5
/*     */     //   10: aconst_null
/*     */     //   11: astore 6
/*     */     //   13: aconst_null
/*     */     //   14: astore 7
/*     */     //   16: new 33	java/util/ArrayList
/*     */     //   19: dup
/*     */     //   20: invokespecial 35	java/util/ArrayList:<init>	()V
/*     */     //   23: astore 8
/*     */     //   25: new 36	java/lang/StringBuilder
/*     */     //   28: dup
/*     */     //   29: ldc_w 710
/*     */     //   32: invokespecial 40	java/lang/StringBuilder:<init>	(Ljava/lang/String;)V
/*     */     //   35: invokestatic 290	com/groom/util/GroomUtil:getCurrentDate	()Ljava/sql/Date;
/*     */     //   38: invokevirtual 301	java/lang/StringBuilder:append	(Ljava/lang/Object;)Ljava/lang/StringBuilder;
/*     */     //   41: ldc_w 712
/*     */     //   44: invokevirtual 43	java/lang/StringBuilder:append	(Ljava/lang/String;)Ljava/lang/StringBuilder;
/*     */     //   47: invokevirtual 53	java/lang/StringBuilder:toString	()Ljava/lang/String;
/*     */     //   50: astore 9
/*     */     //   52: aload 5
/*     */     //   54: aload 9
/*     */     //   56: invokeinterface 68 2 0
/*     */     //   61: astore 6
/*     */     //   63: aload 6
/*     */     //   65: iconst_1
/*     */     //   66: iload_3
/*     */     //   67: invokeinterface 74 3 0
/*     */     //   72: aload 6
/*     */     //   74: iconst_2
/*     */     //   75: iload 4
/*     */     //   77: invokeinterface 74 3 0
/*     */     //   82: aload 6
/*     */     //   84: invokeinterface 80 1 0
/*     */     //   89: astore 7
/*     */     //   91: new 306	java/util/Date
/*     */     //   94: dup
/*     */     //   95: invokestatic 290	com/groom/util/GroomUtil:getCurrentDate	()Ljava/sql/Date;
/*     */     //   98: invokevirtual 308	java/sql/Date:getTime	()J
/*     */     //   101: invokespecial 313	java/util/Date:<init>	(J)V
/*     */     //   104: astore 10
/*     */     //   106: new 316	java/text/SimpleDateFormat
/*     */     //   109: dup
/*     */     //   110: ldc_w 318
/*     */     //   113: invokespecial 320	java/text/SimpleDateFormat:<init>	(Ljava/lang/String;)V
/*     */     //   116: astore 11
/*     */     //   118: aload 11
/*     */     //   120: aload 11
/*     */     //   122: aload 10
/*     */     //   124: invokevirtual 321	java/text/SimpleDateFormat:format	(Ljava/util/Date;)Ljava/lang/String;
/*     */     //   127: invokevirtual 325	java/text/SimpleDateFormat:parse	(Ljava/lang/String;)Ljava/util/Date;
/*     */     //   130: astore 10
/*     */     //   132: goto +274 -> 406
/*     */     //   135: new 329	com/groom/bean/TestsTopicList
/*     */     //   138: dup
/*     */     //   139: invokespecial 331	com/groom/bean/TestsTopicList:<init>	()V
/*     */     //   142: astore 12
/*     */     //   144: aload 12
/*     */     //   146: aload 7
/*     */     //   148: ldc -123
/*     */     //   150: invokeinterface 89 2 0
/*     */     //   155: invokevirtual 332	com/groom/bean/TestsTopicList:setTopicId	(I)V
/*     */     //   158: aload 12
/*     */     //   160: aload 7
/*     */     //   162: ldc_w 335
/*     */     //   165: invokeinterface 101 2 0
/*     */     //   170: invokevirtual 337	com/groom/bean/TestsTopicList:setTopicName	(Ljava/lang/String;)V
/*     */     //   173: aload 12
/*     */     //   175: aload 7
/*     */     //   177: ldc_w 340
/*     */     //   180: invokeinterface 89 2 0
/*     */     //   185: invokevirtual 342	com/groom/bean/TestsTopicList:setTopicClass	(I)V
/*     */     //   188: aload 12
/*     */     //   190: aload 7
/*     */     //   192: ldc_w 345
/*     */     //   195: invokeinterface 347 2 0
/*     */     //   200: invokevirtual 351	java/sql/Date:toString	()Ljava/lang/String;
/*     */     //   203: invokevirtual 352	com/groom/bean/TestsTopicList:setTestDate	(Ljava/lang/String;)V
/*     */     //   206: new 306	java/util/Date
/*     */     //   209: dup
/*     */     //   210: aload 7
/*     */     //   212: ldc_w 345
/*     */     //   215: invokeinterface 347 2 0
/*     */     //   220: invokevirtual 308	java/sql/Date:getTime	()J
/*     */     //   223: invokespecial 313	java/util/Date:<init>	(J)V
/*     */     //   226: astore 13
/*     */     //   228: aload 11
/*     */     //   230: aload 11
/*     */     //   232: aload 13
/*     */     //   234: invokevirtual 321	java/text/SimpleDateFormat:format	(Ljava/util/Date;)Ljava/lang/String;
/*     */     //   237: invokevirtual 325	java/text/SimpleDateFormat:parse	(Ljava/lang/String;)Ljava/util/Date;
/*     */     //   240: astore 13
/*     */     //   242: aload 13
/*     */     //   244: aload 10
/*     */     //   246: invokevirtual 355	java/util/Date:compareTo	(Ljava/util/Date;)I
/*     */     //   249: ifgt +13 -> 262
/*     */     //   252: aload 13
/*     */     //   254: aload 10
/*     */     //   256: invokevirtual 355	java/util/Date:compareTo	(Ljava/util/Date;)I
/*     */     //   259: ifne +14 -> 273
/*     */     //   262: aload 12
/*     */     //   264: ldc_w 359
/*     */     //   267: invokevirtual 361	com/groom/bean/TestsTopicList:setIsKeyAndResultAvailable	(Ljava/lang/String;)V
/*     */     //   270: goto +11 -> 281
/*     */     //   273: aload 12
/*     */     //   275: ldc_w 364
/*     */     //   278: invokevirtual 361	com/groom/bean/TestsTopicList:setIsKeyAndResultAvailable	(Ljava/lang/String;)V
/*     */     //   281: new 36	java/lang/StringBuilder
/*     */     //   284: dup
/*     */     //   285: ldc_w 286
/*     */     //   288: invokespecial 40	java/lang/StringBuilder:<init>	(Ljava/lang/String;)V
/*     */     //   291: aload_2
/*     */     //   292: invokevirtual 43	java/lang/StringBuilder:append	(Ljava/lang/String;)Ljava/lang/StringBuilder;
/*     */     //   295: ldc_w 366
/*     */     //   298: invokevirtual 43	java/lang/StringBuilder:append	(Ljava/lang/String;)Ljava/lang/StringBuilder;
/*     */     //   301: invokevirtual 53	java/lang/StringBuilder:toString	()Ljava/lang/String;
/*     */     //   304: astore 14
/*     */     //   306: aload 5
/*     */     //   308: aload 14
/*     */     //   310: invokeinterface 68 2 0
/*     */     //   315: astore 6
/*     */     //   317: aload 6
/*     */     //   319: iconst_1
/*     */     //   320: iload_1
/*     */     //   321: invokeinterface 74 3 0
/*     */     //   326: aload 6
/*     */     //   328: iconst_2
/*     */     //   329: aload 7
/*     */     //   331: ldc -123
/*     */     //   333: invokeinterface 89 2 0
/*     */     //   338: invokeinterface 74 3 0
/*     */     //   343: aload 6
/*     */     //   345: invokeinterface 80 1 0
/*     */     //   350: astore 15
/*     */     //   352: aload 15
/*     */     //   354: invokeinterface 169 1 0
/*     */     //   359: ifeq +29 -> 388
/*     */     //   362: aload 12
/*     */     //   364: ldc_w 364
/*     */     //   367: invokevirtual 368	com/groom/bean/TestsTopicList:setIsStudentAttempted	(Ljava/lang/String;)V
/*     */     //   370: aload 12
/*     */     //   372: aload 15
/*     */     //   374: ldc_w 371
/*     */     //   377: invokeinterface 101 2 0
/*     */     //   382: invokevirtual 373	com/groom/bean/TestsTopicList:setQuestionIdsList	(Ljava/lang/String;)V
/*     */     //   385: goto +11 -> 396
/*     */     //   388: aload 12
/*     */     //   390: ldc_w 359
/*     */     //   393: invokevirtual 368	com/groom/bean/TestsTopicList:setIsStudentAttempted	(Ljava/lang/String;)V
/*     */     //   396: aload 8
/*     */     //   398: aload 12
/*     */     //   400: invokeinterface 163 2 0
/*     */     //   405: pop
/*     */     //   406: aload 7
/*     */     //   408: invokeinterface 169 1 0
/*     */     //   413: ifne -278 -> 135
/*     */     //   416: goto +136 -> 552
/*     */     //   419: astore 9
/*     */     //   421: aload 9
/*     */     //   423: invokevirtual 173	java/sql/SQLException:printStackTrace	()V
/*     */     //   426: aload 7
/*     */     //   428: ifnull +10 -> 438
/*     */     //   431: aload 7
/*     */     //   433: invokeinterface 176 1 0
/*     */     //   438: aload 6
/*     */     //   440: ifnull +10 -> 450
/*     */     //   443: aload 6
/*     */     //   445: invokeinterface 179 1 0
/*     */     //   450: aload 5
/*     */     //   452: ifnull +136 -> 588
/*     */     //   455: aload 5
/*     */     //   457: invokeinterface 180 1 0
/*     */     //   462: goto +126 -> 588
/*     */     //   465: astore 9
/*     */     //   467: aload 9
/*     */     //   469: invokevirtual 376	java/text/ParseException:printStackTrace	()V
/*     */     //   472: aload 7
/*     */     //   474: ifnull +10 -> 484
/*     */     //   477: aload 7
/*     */     //   479: invokeinterface 176 1 0
/*     */     //   484: aload 6
/*     */     //   486: ifnull +10 -> 496
/*     */     //   489: aload 6
/*     */     //   491: invokeinterface 179 1 0
/*     */     //   496: aload 5
/*     */     //   498: ifnull +90 -> 588
/*     */     //   501: aload 5
/*     */     //   503: invokeinterface 180 1 0
/*     */     //   508: goto +80 -> 588
/*     */     //   511: astore 16
/*     */     //   513: aload 7
/*     */     //   515: ifnull +10 -> 525
/*     */     //   518: aload 7
/*     */     //   520: invokeinterface 176 1 0
/*     */     //   525: aload 6
/*     */     //   527: ifnull +10 -> 537
/*     */     //   530: aload 6
/*     */     //   532: invokeinterface 179 1 0
/*     */     //   537: aload 5
/*     */     //   539: ifnull +10 -> 549
/*     */     //   542: aload 5
/*     */     //   544: invokeinterface 180 1 0
/*     */     //   549: aload 16
/*     */     //   551: athrow
/*     */     //   552: aload 7
/*     */     //   554: ifnull +10 -> 564
/*     */     //   557: aload 7
/*     */     //   559: invokeinterface 176 1 0
/*     */     //   564: aload 6
/*     */     //   566: ifnull +10 -> 576
/*     */     //   569: aload 6
/*     */     //   571: invokeinterface 179 1 0
/*     */     //   576: aload 5
/*     */     //   578: ifnull +10 -> 588
/*     */     //   581: aload 5
/*     */     //   583: invokeinterface 180 1 0
/*     */     //   588: aload 8
/*     */     //   590: areturn
/*     */     // Line number table:
/*     */     //   Java source line #705	-> byte code offset #0
/*     */     //   Java source line #706	-> byte code offset #10
/*     */     //   Java source line #707	-> byte code offset #13
/*     */     //   Java source line #708	-> byte code offset #16
/*     */     //   Java source line #711	-> byte code offset #25
/*     */     //   Java source line #712	-> byte code offset #35
/*     */     //   Java source line #711	-> byte code offset #47
/*     */     //   Java source line #714	-> byte code offset #52
/*     */     //   Java source line #715	-> byte code offset #63
/*     */     //   Java source line #716	-> byte code offset #72
/*     */     //   Java source line #717	-> byte code offset #82
/*     */     //   Java source line #719	-> byte code offset #91
/*     */     //   Java source line #720	-> byte code offset #95
/*     */     //   Java source line #719	-> byte code offset #101
/*     */     //   Java source line #721	-> byte code offset #106
/*     */     //   Java source line #722	-> byte code offset #118
/*     */     //   Java source line #723	-> byte code offset #132
/*     */     //   Java source line #725	-> byte code offset #135
/*     */     //   Java source line #726	-> byte code offset #144
/*     */     //   Java source line #727	-> byte code offset #158
/*     */     //   Java source line #728	-> byte code offset #173
/*     */     //   Java source line #729	-> byte code offset #188
/*     */     //   Java source line #731	-> byte code offset #206
/*     */     //   Java source line #732	-> byte code offset #212
/*     */     //   Java source line #731	-> byte code offset #215
/*     */     //   Java source line #732	-> byte code offset #220
/*     */     //   Java source line #731	-> byte code offset #223
/*     */     //   Java source line #733	-> byte code offset #228
/*     */     //   Java source line #739	-> byte code offset #242
/*     */     //   Java source line #740	-> byte code offset #252
/*     */     //   Java source line #741	-> byte code offset #262
/*     */     //   Java source line #742	-> byte code offset #270
/*     */     //   Java source line #743	-> byte code offset #273
/*     */     //   Java source line #744	-> byte code offset #281
/*     */     //   Java source line #745	-> byte code offset #295
/*     */     //   Java source line #744	-> byte code offset #301
/*     */     //   Java source line #746	-> byte code offset #306
/*     */     //   Java source line #747	-> byte code offset #317
/*     */     //   Java source line #748	-> byte code offset #326
/*     */     //   Java source line #749	-> byte code offset #343
/*     */     //   Java source line #750	-> byte code offset #345
/*     */     //   Java source line #749	-> byte code offset #350
/*     */     //   Java source line #751	-> byte code offset #352
/*     */     //   Java source line #752	-> byte code offset #362
/*     */     //   Java source line #753	-> byte code offset #370
/*     */     //   Java source line #754	-> byte code offset #374
/*     */     //   Java source line #753	-> byte code offset #382
/*     */     //   Java source line #755	-> byte code offset #385
/*     */     //   Java source line #756	-> byte code offset #388
/*     */     //   Java source line #758	-> byte code offset #396
/*     */     //   Java source line #723	-> byte code offset #406
/*     */     //   Java source line #761	-> byte code offset #416
/*     */     //   Java source line #762	-> byte code offset #421
/*     */     //   Java source line #768	-> byte code offset #426
/*     */     //   Java source line #769	-> byte code offset #431
/*     */     //   Java source line #770	-> byte code offset #438
/*     */     //   Java source line #771	-> byte code offset #443
/*     */     //   Java source line #772	-> byte code offset #450
/*     */     //   Java source line #773	-> byte code offset #455
/*     */     //   Java source line #763	-> byte code offset #465
/*     */     //   Java source line #764	-> byte code offset #467
/*     */     //   Java source line #768	-> byte code offset #472
/*     */     //   Java source line #769	-> byte code offset #477
/*     */     //   Java source line #770	-> byte code offset #484
/*     */     //   Java source line #771	-> byte code offset #489
/*     */     //   Java source line #772	-> byte code offset #496
/*     */     //   Java source line #773	-> byte code offset #501
/*     */     //   Java source line #767	-> byte code offset #511
/*     */     //   Java source line #768	-> byte code offset #513
/*     */     //   Java source line #769	-> byte code offset #518
/*     */     //   Java source line #770	-> byte code offset #525
/*     */     //   Java source line #771	-> byte code offset #530
/*     */     //   Java source line #772	-> byte code offset #537
/*     */     //   Java source line #773	-> byte code offset #542
/*     */     //   Java source line #774	-> byte code offset #549
/*     */     //   Java source line #768	-> byte code offset #552
/*     */     //   Java source line #769	-> byte code offset #557
/*     */     //   Java source line #770	-> byte code offset #564
/*     */     //   Java source line #771	-> byte code offset #569
/*     */     //   Java source line #772	-> byte code offset #576
/*     */     //   Java source line #773	-> byte code offset #581
/*     */     //   Java source line #776	-> byte code offset #588
/*     */     // Local variable table:
/*     */     //   start	length	slot	name	signature
/*     */     //   0	591	0	this	QuizDAOImpl
/*     */     //   0	591	1	userid	int
/*     */     //   0	591	2	category	String
/*     */     //   0	591	3	division	int
/*     */     //   0	591	4	test_category_id	int
/*     */     //   8	574	5	connection	Connection
/*     */     //   11	559	6	preparedStatement	PreparedStatement
/*     */     //   14	544	7	resultSet	ResultSet
/*     */     //   23	566	8	topicLists	List<com.groom.bean.TestsTopicList>
/*     */     //   50	5	9	query	String
/*     */     //   419	3	9	exception	SQLException
/*     */     //   465	3	9	exception	java.text.ParseException
/*     */     //   104	151	10	currentDate	java.util.Date
/*     */     //   116	115	11	dateFormat	java.text.SimpleDateFormat
/*     */     //   142	257	12	topic	com.groom.bean.TestsTopicList
/*     */     //   226	27	13	testDate	java.util.Date
/*     */     //   304	5	14	pointsQuery	String
/*     */     //   350	23	15	userPointsResultSet	ResultSet
/*     */     //   511	39	16	localObject	Object
/*     */     // Exception table:
/*     */     //   from	to	target	type
/*     */     //   25	416	419	java/sql/SQLException
/*     */     //   25	416	465	java/text/ParseException
/*     */     //   25	426	511	finally
/*     */     //   465	472	511	finally
/*     */   }
/*     */   
/*     */   /* Error */
/*     */   public List<com.groom.bean.TestsTopicList> getTestTopicsByBoard(int userid, String category, int standard, int division)
/*     */     throws SQLException
/*     */   {
/*     */     // Byte code:
/*     */     //   0: getstatic 23	com/groom/dao/impl/QuizDAOImpl:ds	Ljavax/sql/DataSource;
/*     */     //   3: invokeinterface 27 1 0
/*     */     //   8: astore 5
/*     */     //   10: aconst_null
/*     */     //   11: astore 6
/*     */     //   13: aconst_null
/*     */     //   14: astore 7
/*     */     //   16: aload_2
/*     */     //   17: astore 8
/*     */     //   19: new 33	java/util/ArrayList
/*     */     //   22: dup
/*     */     //   23: invokespecial 35	java/util/ArrayList:<init>	()V
/*     */     //   26: astore 9
/*     */     //   28: new 36	java/lang/StringBuilder
/*     */     //   31: dup
/*     */     //   32: ldc_w 286
/*     */     //   35: invokespecial 40	java/lang/StringBuilder:<init>	(Ljava/lang/String;)V
/*     */     //   38: aload_2
/*     */     //   39: invokevirtual 43	java/lang/StringBuilder:append	(Ljava/lang/String;)Ljava/lang/StringBuilder;
/*     */     //   42: ldc_w 299
/*     */     //   45: invokevirtual 43	java/lang/StringBuilder:append	(Ljava/lang/String;)Ljava/lang/StringBuilder;
/*     */     //   48: invokestatic 290	com/groom/util/GroomUtil:getCurrentDate	()Ljava/sql/Date;
/*     */     //   51: invokevirtual 301	java/lang/StringBuilder:append	(Ljava/lang/Object;)Ljava/lang/StringBuilder;
/*     */     //   54: ldc_w 712
/*     */     //   57: invokevirtual 43	java/lang/StringBuilder:append	(Ljava/lang/String;)Ljava/lang/StringBuilder;
/*     */     //   60: invokevirtual 53	java/lang/StringBuilder:toString	()Ljava/lang/String;
/*     */     //   63: astore 10
/*     */     //   65: aload 5
/*     */     //   67: aload 10
/*     */     //   69: invokeinterface 68 2 0
/*     */     //   74: astore 6
/*     */     //   76: aload 6
/*     */     //   78: iconst_1
/*     */     //   79: iload_3
/*     */     //   80: invokeinterface 74 3 0
/*     */     //   85: aload 6
/*     */     //   87: iconst_2
/*     */     //   88: iload 4
/*     */     //   90: invokeinterface 74 3 0
/*     */     //   95: aload 8
/*     */     //   97: ldc_w 716
/*     */     //   100: invokevirtual 718	java/lang/String:equalsIgnoreCase	(Ljava/lang/String;)Z
/*     */     //   103: ifeq +12 -> 115
/*     */     //   106: aload 6
/*     */     //   108: iconst_3
/*     */     //   109: iconst_4
/*     */     //   110: invokeinterface 74 3 0
/*     */     //   115: aload 8
/*     */     //   117: ldc_w 721
/*     */     //   120: invokevirtual 718	java/lang/String:equalsIgnoreCase	(Ljava/lang/String;)Z
/*     */     //   123: ifeq +13 -> 136
/*     */     //   126: aload 6
/*     */     //   128: iconst_3
/*     */     //   129: bipush 8
/*     */     //   131: invokeinterface 74 3 0
/*     */     //   136: aload 8
/*     */     //   138: ldc_w 723
/*     */     //   141: invokevirtual 718	java/lang/String:equalsIgnoreCase	(Ljava/lang/String;)Z
/*     */     //   144: ifeq +13 -> 157
/*     */     //   147: aload 6
/*     */     //   149: iconst_3
/*     */     //   150: bipush 9
/*     */     //   152: invokeinterface 74 3 0
/*     */     //   157: aload 8
/*     */     //   159: ldc_w 725
/*     */     //   162: invokevirtual 718	java/lang/String:equalsIgnoreCase	(Ljava/lang/String;)Z
/*     */     //   165: ifeq +12 -> 177
/*     */     //   168: aload 6
/*     */     //   170: iconst_3
/*     */     //   171: iconst_5
/*     */     //   172: invokeinterface 74 3 0
/*     */     //   177: aload 8
/*     */     //   179: ldc_w 727
/*     */     //   182: invokevirtual 718	java/lang/String:equalsIgnoreCase	(Ljava/lang/String;)Z
/*     */     //   185: ifeq +13 -> 198
/*     */     //   188: aload 6
/*     */     //   190: iconst_3
/*     */     //   191: bipush 6
/*     */     //   193: invokeinterface 74 3 0
/*     */     //   198: aload 6
/*     */     //   200: invokeinterface 80 1 0
/*     */     //   205: astore 7
/*     */     //   207: new 306	java/util/Date
/*     */     //   210: dup
/*     */     //   211: invokestatic 290	com/groom/util/GroomUtil:getCurrentDate	()Ljava/sql/Date;
/*     */     //   214: invokevirtual 308	java/sql/Date:getTime	()J
/*     */     //   217: invokespecial 313	java/util/Date:<init>	(J)V
/*     */     //   220: astore 11
/*     */     //   222: new 316	java/text/SimpleDateFormat
/*     */     //   225: dup
/*     */     //   226: ldc_w 318
/*     */     //   229: invokespecial 320	java/text/SimpleDateFormat:<init>	(Ljava/lang/String;)V
/*     */     //   232: astore 12
/*     */     //   234: aload 12
/*     */     //   236: aload 12
/*     */     //   238: aload 11
/*     */     //   240: invokevirtual 321	java/text/SimpleDateFormat:format	(Ljava/util/Date;)Ljava/lang/String;
/*     */     //   243: invokevirtual 325	java/text/SimpleDateFormat:parse	(Ljava/lang/String;)Ljava/util/Date;
/*     */     //   246: astore 11
/*     */     //   248: goto +274 -> 522
/*     */     //   251: new 329	com/groom/bean/TestsTopicList
/*     */     //   254: dup
/*     */     //   255: invokespecial 331	com/groom/bean/TestsTopicList:<init>	()V
/*     */     //   258: astore 13
/*     */     //   260: aload 13
/*     */     //   262: aload 7
/*     */     //   264: ldc -123
/*     */     //   266: invokeinterface 89 2 0
/*     */     //   271: invokevirtual 332	com/groom/bean/TestsTopicList:setTopicId	(I)V
/*     */     //   274: aload 13
/*     */     //   276: aload 7
/*     */     //   278: ldc_w 335
/*     */     //   281: invokeinterface 101 2 0
/*     */     //   286: invokevirtual 337	com/groom/bean/TestsTopicList:setTopicName	(Ljava/lang/String;)V
/*     */     //   289: aload 13
/*     */     //   291: aload 7
/*     */     //   293: ldc_w 340
/*     */     //   296: invokeinterface 89 2 0
/*     */     //   301: invokevirtual 342	com/groom/bean/TestsTopicList:setTopicClass	(I)V
/*     */     //   304: aload 13
/*     */     //   306: aload 7
/*     */     //   308: ldc_w 345
/*     */     //   311: invokeinterface 347 2 0
/*     */     //   316: invokevirtual 351	java/sql/Date:toString	()Ljava/lang/String;
/*     */     //   319: invokevirtual 352	com/groom/bean/TestsTopicList:setTestDate	(Ljava/lang/String;)V
/*     */     //   322: new 306	java/util/Date
/*     */     //   325: dup
/*     */     //   326: aload 7
/*     */     //   328: ldc_w 345
/*     */     //   331: invokeinterface 347 2 0
/*     */     //   336: invokevirtual 308	java/sql/Date:getTime	()J
/*     */     //   339: invokespecial 313	java/util/Date:<init>	(J)V
/*     */     //   342: astore 14
/*     */     //   344: aload 12
/*     */     //   346: aload 12
/*     */     //   348: aload 14
/*     */     //   350: invokevirtual 321	java/text/SimpleDateFormat:format	(Ljava/util/Date;)Ljava/lang/String;
/*     */     //   353: invokevirtual 325	java/text/SimpleDateFormat:parse	(Ljava/lang/String;)Ljava/util/Date;
/*     */     //   356: astore 14
/*     */     //   358: aload 14
/*     */     //   360: aload 11
/*     */     //   362: invokevirtual 355	java/util/Date:compareTo	(Ljava/util/Date;)I
/*     */     //   365: ifgt +13 -> 378
/*     */     //   368: aload 14
/*     */     //   370: aload 11
/*     */     //   372: invokevirtual 355	java/util/Date:compareTo	(Ljava/util/Date;)I
/*     */     //   375: ifne +14 -> 389
/*     */     //   378: aload 13
/*     */     //   380: ldc_w 359
/*     */     //   383: invokevirtual 361	com/groom/bean/TestsTopicList:setIsKeyAndResultAvailable	(Ljava/lang/String;)V
/*     */     //   386: goto +11 -> 397
/*     */     //   389: aload 13
/*     */     //   391: ldc_w 364
/*     */     //   394: invokevirtual 361	com/groom/bean/TestsTopicList:setIsKeyAndResultAvailable	(Ljava/lang/String;)V
/*     */     //   397: new 36	java/lang/StringBuilder
/*     */     //   400: dup
/*     */     //   401: ldc_w 286
/*     */     //   404: invokespecial 40	java/lang/StringBuilder:<init>	(Ljava/lang/String;)V
/*     */     //   407: aload_2
/*     */     //   408: invokevirtual 43	java/lang/StringBuilder:append	(Ljava/lang/String;)Ljava/lang/StringBuilder;
/*     */     //   411: ldc_w 366
/*     */     //   414: invokevirtual 43	java/lang/StringBuilder:append	(Ljava/lang/String;)Ljava/lang/StringBuilder;
/*     */     //   417: invokevirtual 53	java/lang/StringBuilder:toString	()Ljava/lang/String;
/*     */     //   420: astore 15
/*     */     //   422: aload 5
/*     */     //   424: aload 15
/*     */     //   426: invokeinterface 68 2 0
/*     */     //   431: astore 6
/*     */     //   433: aload 6
/*     */     //   435: iconst_1
/*     */     //   436: iload_1
/*     */     //   437: invokeinterface 74 3 0
/*     */     //   442: aload 6
/*     */     //   444: iconst_2
/*     */     //   445: aload 7
/*     */     //   447: ldc -123
/*     */     //   449: invokeinterface 89 2 0
/*     */     //   454: invokeinterface 74 3 0
/*     */     //   459: aload 6
/*     */     //   461: invokeinterface 80 1 0
/*     */     //   466: astore 16
/*     */     //   468: aload 16
/*     */     //   470: invokeinterface 169 1 0
/*     */     //   475: ifeq +29 -> 504
/*     */     //   478: aload 13
/*     */     //   480: ldc_w 364
/*     */     //   483: invokevirtual 368	com/groom/bean/TestsTopicList:setIsStudentAttempted	(Ljava/lang/String;)V
/*     */     //   486: aload 13
/*     */     //   488: aload 16
/*     */     //   490: ldc_w 371
/*     */     //   493: invokeinterface 101 2 0
/*     */     //   498: invokevirtual 373	com/groom/bean/TestsTopicList:setQuestionIdsList	(Ljava/lang/String;)V
/*     */     //   501: goto +11 -> 512
/*     */     //   504: aload 13
/*     */     //   506: ldc_w 359
/*     */     //   509: invokevirtual 368	com/groom/bean/TestsTopicList:setIsStudentAttempted	(Ljava/lang/String;)V
/*     */     //   512: aload 9
/*     */     //   514: aload 13
/*     */     //   516: invokeinterface 163 2 0
/*     */     //   521: pop
/*     */     //   522: aload 7
/*     */     //   524: invokeinterface 169 1 0
/*     */     //   529: ifne -278 -> 251
/*     */     //   532: goto +136 -> 668
/*     */     //   535: astore 10
/*     */     //   537: aload 10
/*     */     //   539: invokevirtual 173	java/sql/SQLException:printStackTrace	()V
/*     */     //   542: aload 7
/*     */     //   544: ifnull +10 -> 554
/*     */     //   547: aload 7
/*     */     //   549: invokeinterface 176 1 0
/*     */     //   554: aload 6
/*     */     //   556: ifnull +10 -> 566
/*     */     //   559: aload 6
/*     */     //   561: invokeinterface 179 1 0
/*     */     //   566: aload 5
/*     */     //   568: ifnull +136 -> 704
/*     */     //   571: aload 5
/*     */     //   573: invokeinterface 180 1 0
/*     */     //   578: goto +126 -> 704
/*     */     //   581: astore 10
/*     */     //   583: aload 10
/*     */     //   585: invokevirtual 376	java/text/ParseException:printStackTrace	()V
/*     */     //   588: aload 7
/*     */     //   590: ifnull +10 -> 600
/*     */     //   593: aload 7
/*     */     //   595: invokeinterface 176 1 0
/*     */     //   600: aload 6
/*     */     //   602: ifnull +10 -> 612
/*     */     //   605: aload 6
/*     */     //   607: invokeinterface 179 1 0
/*     */     //   612: aload 5
/*     */     //   614: ifnull +90 -> 704
/*     */     //   617: aload 5
/*     */     //   619: invokeinterface 180 1 0
/*     */     //   624: goto +80 -> 704
/*     */     //   627: astore 17
/*     */     //   629: aload 7
/*     */     //   631: ifnull +10 -> 641
/*     */     //   634: aload 7
/*     */     //   636: invokeinterface 176 1 0
/*     */     //   641: aload 6
/*     */     //   643: ifnull +10 -> 653
/*     */     //   646: aload 6
/*     */     //   648: invokeinterface 179 1 0
/*     */     //   653: aload 5
/*     */     //   655: ifnull +10 -> 665
/*     */     //   658: aload 5
/*     */     //   660: invokeinterface 180 1 0
/*     */     //   665: aload 17
/*     */     //   667: athrow
/*     */     //   668: aload 7
/*     */     //   670: ifnull +10 -> 680
/*     */     //   673: aload 7
/*     */     //   675: invokeinterface 176 1 0
/*     */     //   680: aload 6
/*     */     //   682: ifnull +10 -> 692
/*     */     //   685: aload 6
/*     */     //   687: invokeinterface 179 1 0
/*     */     //   692: aload 5
/*     */     //   694: ifnull +10 -> 704
/*     */     //   697: aload 5
/*     */     //   699: invokeinterface 180 1 0
/*     */     //   704: aload 9
/*     */     //   706: areturn
/*     */     // Line number table:
/*     */     //   Java source line #782	-> byte code offset #0
/*     */     //   Java source line #783	-> byte code offset #10
/*     */     //   Java source line #784	-> byte code offset #13
/*     */     //   Java source line #785	-> byte code offset #16
/*     */     //   Java source line #786	-> byte code offset #19
/*     */     //   Java source line #789	-> byte code offset #28
/*     */     //   Java source line #790	-> byte code offset #42
/*     */     //   Java source line #791	-> byte code offset #48
/*     */     //   Java source line #789	-> byte code offset #60
/*     */     //   Java source line #793	-> byte code offset #65
/*     */     //   Java source line #794	-> byte code offset #76
/*     */     //   Java source line #795	-> byte code offset #85
/*     */     //   Java source line #797	-> byte code offset #95
/*     */     //   Java source line #798	-> byte code offset #106
/*     */     //   Java source line #800	-> byte code offset #115
/*     */     //   Java source line #801	-> byte code offset #126
/*     */     //   Java source line #803	-> byte code offset #136
/*     */     //   Java source line #804	-> byte code offset #147
/*     */     //   Java source line #806	-> byte code offset #157
/*     */     //   Java source line #807	-> byte code offset #168
/*     */     //   Java source line #809	-> byte code offset #177
/*     */     //   Java source line #810	-> byte code offset #188
/*     */     //   Java source line #813	-> byte code offset #198
/*     */     //   Java source line #815	-> byte code offset #207
/*     */     //   Java source line #816	-> byte code offset #211
/*     */     //   Java source line #815	-> byte code offset #217
/*     */     //   Java source line #817	-> byte code offset #222
/*     */     //   Java source line #818	-> byte code offset #234
/*     */     //   Java source line #819	-> byte code offset #248
/*     */     //   Java source line #821	-> byte code offset #251
/*     */     //   Java source line #822	-> byte code offset #260
/*     */     //   Java source line #823	-> byte code offset #274
/*     */     //   Java source line #824	-> byte code offset #289
/*     */     //   Java source line #825	-> byte code offset #304
/*     */     //   Java source line #827	-> byte code offset #322
/*     */     //   Java source line #828	-> byte code offset #328
/*     */     //   Java source line #827	-> byte code offset #331
/*     */     //   Java source line #828	-> byte code offset #336
/*     */     //   Java source line #827	-> byte code offset #339
/*     */     //   Java source line #829	-> byte code offset #344
/*     */     //   Java source line #835	-> byte code offset #358
/*     */     //   Java source line #836	-> byte code offset #368
/*     */     //   Java source line #837	-> byte code offset #378
/*     */     //   Java source line #838	-> byte code offset #386
/*     */     //   Java source line #839	-> byte code offset #389
/*     */     //   Java source line #840	-> byte code offset #397
/*     */     //   Java source line #841	-> byte code offset #411
/*     */     //   Java source line #840	-> byte code offset #417
/*     */     //   Java source line #842	-> byte code offset #422
/*     */     //   Java source line #843	-> byte code offset #433
/*     */     //   Java source line #844	-> byte code offset #442
/*     */     //   Java source line #845	-> byte code offset #459
/*     */     //   Java source line #846	-> byte code offset #461
/*     */     //   Java source line #845	-> byte code offset #466
/*     */     //   Java source line #847	-> byte code offset #468
/*     */     //   Java source line #848	-> byte code offset #478
/*     */     //   Java source line #849	-> byte code offset #486
/*     */     //   Java source line #850	-> byte code offset #490
/*     */     //   Java source line #849	-> byte code offset #498
/*     */     //   Java source line #851	-> byte code offset #501
/*     */     //   Java source line #852	-> byte code offset #504
/*     */     //   Java source line #854	-> byte code offset #512
/*     */     //   Java source line #819	-> byte code offset #522
/*     */     //   Java source line #857	-> byte code offset #532
/*     */     //   Java source line #858	-> byte code offset #537
/*     */     //   Java source line #864	-> byte code offset #542
/*     */     //   Java source line #865	-> byte code offset #547
/*     */     //   Java source line #866	-> byte code offset #554
/*     */     //   Java source line #867	-> byte code offset #559
/*     */     //   Java source line #868	-> byte code offset #566
/*     */     //   Java source line #869	-> byte code offset #571
/*     */     //   Java source line #859	-> byte code offset #581
/*     */     //   Java source line #860	-> byte code offset #583
/*     */     //   Java source line #864	-> byte code offset #588
/*     */     //   Java source line #865	-> byte code offset #593
/*     */     //   Java source line #866	-> byte code offset #600
/*     */     //   Java source line #867	-> byte code offset #605
/*     */     //   Java source line #868	-> byte code offset #612
/*     */     //   Java source line #869	-> byte code offset #617
/*     */     //   Java source line #863	-> byte code offset #627
/*     */     //   Java source line #864	-> byte code offset #629
/*     */     //   Java source line #865	-> byte code offset #634
/*     */     //   Java source line #866	-> byte code offset #641
/*     */     //   Java source line #867	-> byte code offset #646
/*     */     //   Java source line #868	-> byte code offset #653
/*     */     //   Java source line #869	-> byte code offset #658
/*     */     //   Java source line #870	-> byte code offset #665
/*     */     //   Java source line #864	-> byte code offset #668
/*     */     //   Java source line #865	-> byte code offset #673
/*     */     //   Java source line #866	-> byte code offset #680
/*     */     //   Java source line #867	-> byte code offset #685
/*     */     //   Java source line #868	-> byte code offset #692
/*     */     //   Java source line #869	-> byte code offset #697
/*     */     //   Java source line #872	-> byte code offset #704
/*     */     // Local variable table:
/*     */     //   start	length	slot	name	signature
/*     */     //   0	707	0	this	QuizDAOImpl
/*     */     //   0	707	1	userid	int
/*     */     //   0	707	2	category	String
/*     */     //   0	707	3	standard	int
/*     */     //   0	707	4	division	int
/*     */     //   8	690	5	connection	Connection
/*     */     //   11	675	6	preparedStatement	PreparedStatement
/*     */     //   14	660	7	resultSet	ResultSet
/*     */     //   17	161	8	subjectName	String
/*     */     //   26	679	9	topicLists	List<com.groom.bean.TestsTopicList>
/*     */     //   63	5	10	query	String
/*     */     //   535	3	10	exception	SQLException
/*     */     //   581	3	10	exception	java.text.ParseException
/*     */     //   220	151	11	currentDate	java.util.Date
/*     */     //   232	115	12	dateFormat	java.text.SimpleDateFormat
/*     */     //   258	257	13	topic	com.groom.bean.TestsTopicList
/*     */     //   342	27	14	testDate	java.util.Date
/*     */     //   420	5	15	pointsQuery	String
/*     */     //   466	23	16	userPointsResultSet	ResultSet
/*     */     //   627	39	17	localObject	Object
/*     */     // Exception table:
/*     */     //   from	to	target	type
/*     */     //   28	532	535	java/sql/SQLException
/*     */     //   28	532	581	java/text/ParseException
/*     */     //   28	542	627	finally
/*     */     //   581	588	627	finally
/*     */   }
/*     */   
/*     */   /* Error */
/*     */   public List<com.groom.bean.TestsTopicList> getSampleTestTopics(int userid, String category, int test_category_id, int standard)
/*     */     throws SQLException
/*     */   {
/*     */     // Byte code:
/*     */     //   0: getstatic 23	com/groom/dao/impl/QuizDAOImpl:ds	Ljavax/sql/DataSource;
/*     */     //   3: invokeinterface 27 1 0
/*     */     //   8: astore 5
/*     */     //   10: aconst_null
/*     */     //   11: astore 6
/*     */     //   13: aconst_null
/*     */     //   14: astore 7
/*     */     //   16: new 33	java/util/ArrayList
/*     */     //   19: dup
/*     */     //   20: invokespecial 35	java/util/ArrayList:<init>	()V
/*     */     //   23: astore 8
/*     */     //   25: new 36	java/lang/StringBuilder
/*     */     //   28: dup
/*     */     //   29: ldc_w 710
/*     */     //   32: invokespecial 40	java/lang/StringBuilder:<init>	(Ljava/lang/String;)V
/*     */     //   35: invokestatic 290	com/groom/util/GroomUtil:getCurrentDate	()Ljava/sql/Date;
/*     */     //   38: invokevirtual 301	java/lang/StringBuilder:append	(Ljava/lang/Object;)Ljava/lang/StringBuilder;
/*     */     //   41: ldc_w 731
/*     */     //   44: invokevirtual 43	java/lang/StringBuilder:append	(Ljava/lang/String;)Ljava/lang/StringBuilder;
/*     */     //   47: invokevirtual 53	java/lang/StringBuilder:toString	()Ljava/lang/String;
/*     */     //   50: astore 9
/*     */     //   52: aload 5
/*     */     //   54: aload 9
/*     */     //   56: invokeinterface 68 2 0
/*     */     //   61: astore 6
/*     */     //   63: aload 6
/*     */     //   65: iconst_1
/*     */     //   66: iload 4
/*     */     //   68: invokeinterface 74 3 0
/*     */     //   73: aload 6
/*     */     //   75: iconst_2
/*     */     //   76: iload_3
/*     */     //   77: invokeinterface 74 3 0
/*     */     //   82: aload 6
/*     */     //   84: invokeinterface 80 1 0
/*     */     //   89: astore 7
/*     */     //   91: new 306	java/util/Date
/*     */     //   94: dup
/*     */     //   95: invokestatic 290	com/groom/util/GroomUtil:getCurrentDate	()Ljava/sql/Date;
/*     */     //   98: invokevirtual 308	java/sql/Date:getTime	()J
/*     */     //   101: invokespecial 313	java/util/Date:<init>	(J)V
/*     */     //   104: astore 10
/*     */     //   106: new 316	java/text/SimpleDateFormat
/*     */     //   109: dup
/*     */     //   110: ldc_w 318
/*     */     //   113: invokespecial 320	java/text/SimpleDateFormat:<init>	(Ljava/lang/String;)V
/*     */     //   116: astore 11
/*     */     //   118: aload 11
/*     */     //   120: aload 11
/*     */     //   122: aload 10
/*     */     //   124: invokevirtual 321	java/text/SimpleDateFormat:format	(Ljava/util/Date;)Ljava/lang/String;
/*     */     //   127: invokevirtual 325	java/text/SimpleDateFormat:parse	(Ljava/lang/String;)Ljava/util/Date;
/*     */     //   130: astore 10
/*     */     //   132: goto +274 -> 406
/*     */     //   135: new 329	com/groom/bean/TestsTopicList
/*     */     //   138: dup
/*     */     //   139: invokespecial 331	com/groom/bean/TestsTopicList:<init>	()V
/*     */     //   142: astore 12
/*     */     //   144: aload 12
/*     */     //   146: aload 7
/*     */     //   148: ldc -123
/*     */     //   150: invokeinterface 89 2 0
/*     */     //   155: invokevirtual 332	com/groom/bean/TestsTopicList:setTopicId	(I)V
/*     */     //   158: aload 12
/*     */     //   160: aload 7
/*     */     //   162: ldc_w 335
/*     */     //   165: invokeinterface 101 2 0
/*     */     //   170: invokevirtual 337	com/groom/bean/TestsTopicList:setTopicName	(Ljava/lang/String;)V
/*     */     //   173: aload 12
/*     */     //   175: aload 7
/*     */     //   177: ldc_w 340
/*     */     //   180: invokeinterface 89 2 0
/*     */     //   185: invokevirtual 342	com/groom/bean/TestsTopicList:setTopicClass	(I)V
/*     */     //   188: aload 12
/*     */     //   190: aload 7
/*     */     //   192: ldc_w 345
/*     */     //   195: invokeinterface 347 2 0
/*     */     //   200: invokevirtual 351	java/sql/Date:toString	()Ljava/lang/String;
/*     */     //   203: invokevirtual 352	com/groom/bean/TestsTopicList:setTestDate	(Ljava/lang/String;)V
/*     */     //   206: new 306	java/util/Date
/*     */     //   209: dup
/*     */     //   210: aload 7
/*     */     //   212: ldc_w 345
/*     */     //   215: invokeinterface 347 2 0
/*     */     //   220: invokevirtual 308	java/sql/Date:getTime	()J
/*     */     //   223: invokespecial 313	java/util/Date:<init>	(J)V
/*     */     //   226: astore 13
/*     */     //   228: aload 11
/*     */     //   230: aload 11
/*     */     //   232: aload 13
/*     */     //   234: invokevirtual 321	java/text/SimpleDateFormat:format	(Ljava/util/Date;)Ljava/lang/String;
/*     */     //   237: invokevirtual 325	java/text/SimpleDateFormat:parse	(Ljava/lang/String;)Ljava/util/Date;
/*     */     //   240: astore 13
/*     */     //   242: aload 13
/*     */     //   244: aload 10
/*     */     //   246: invokevirtual 355	java/util/Date:compareTo	(Ljava/util/Date;)I
/*     */     //   249: ifgt +13 -> 262
/*     */     //   252: aload 13
/*     */     //   254: aload 10
/*     */     //   256: invokevirtual 355	java/util/Date:compareTo	(Ljava/util/Date;)I
/*     */     //   259: ifne +14 -> 273
/*     */     //   262: aload 12
/*     */     //   264: ldc_w 359
/*     */     //   267: invokevirtual 361	com/groom/bean/TestsTopicList:setIsKeyAndResultAvailable	(Ljava/lang/String;)V
/*     */     //   270: goto +11 -> 281
/*     */     //   273: aload 12
/*     */     //   275: ldc_w 364
/*     */     //   278: invokevirtual 361	com/groom/bean/TestsTopicList:setIsKeyAndResultAvailable	(Ljava/lang/String;)V
/*     */     //   281: new 36	java/lang/StringBuilder
/*     */     //   284: dup
/*     */     //   285: ldc_w 286
/*     */     //   288: invokespecial 40	java/lang/StringBuilder:<init>	(Ljava/lang/String;)V
/*     */     //   291: aload_2
/*     */     //   292: invokevirtual 43	java/lang/StringBuilder:append	(Ljava/lang/String;)Ljava/lang/StringBuilder;
/*     */     //   295: ldc_w 366
/*     */     //   298: invokevirtual 43	java/lang/StringBuilder:append	(Ljava/lang/String;)Ljava/lang/StringBuilder;
/*     */     //   301: invokevirtual 53	java/lang/StringBuilder:toString	()Ljava/lang/String;
/*     */     //   304: astore 14
/*     */     //   306: aload 5
/*     */     //   308: aload 14
/*     */     //   310: invokeinterface 68 2 0
/*     */     //   315: astore 6
/*     */     //   317: aload 6
/*     */     //   319: iconst_1
/*     */     //   320: iload_1
/*     */     //   321: invokeinterface 74 3 0
/*     */     //   326: aload 6
/*     */     //   328: iconst_2
/*     */     //   329: aload 7
/*     */     //   331: ldc -123
/*     */     //   333: invokeinterface 89 2 0
/*     */     //   338: invokeinterface 74 3 0
/*     */     //   343: aload 6
/*     */     //   345: invokeinterface 80 1 0
/*     */     //   350: astore 15
/*     */     //   352: aload 15
/*     */     //   354: invokeinterface 169 1 0
/*     */     //   359: ifeq +29 -> 388
/*     */     //   362: aload 12
/*     */     //   364: ldc_w 364
/*     */     //   367: invokevirtual 368	com/groom/bean/TestsTopicList:setIsStudentAttempted	(Ljava/lang/String;)V
/*     */     //   370: aload 12
/*     */     //   372: aload 15
/*     */     //   374: ldc_w 371
/*     */     //   377: invokeinterface 101 2 0
/*     */     //   382: invokevirtual 373	com/groom/bean/TestsTopicList:setQuestionIdsList	(Ljava/lang/String;)V
/*     */     //   385: goto +11 -> 396
/*     */     //   388: aload 12
/*     */     //   390: ldc_w 359
/*     */     //   393: invokevirtual 368	com/groom/bean/TestsTopicList:setIsStudentAttempted	(Ljava/lang/String;)V
/*     */     //   396: aload 8
/*     */     //   398: aload 12
/*     */     //   400: invokeinterface 163 2 0
/*     */     //   405: pop
/*     */     //   406: aload 7
/*     */     //   408: invokeinterface 169 1 0
/*     */     //   413: ifne -278 -> 135
/*     */     //   416: goto +136 -> 552
/*     */     //   419: astore 9
/*     */     //   421: aload 9
/*     */     //   423: invokevirtual 173	java/sql/SQLException:printStackTrace	()V
/*     */     //   426: aload 7
/*     */     //   428: ifnull +10 -> 438
/*     */     //   431: aload 7
/*     */     //   433: invokeinterface 176 1 0
/*     */     //   438: aload 6
/*     */     //   440: ifnull +10 -> 450
/*     */     //   443: aload 6
/*     */     //   445: invokeinterface 179 1 0
/*     */     //   450: aload 5
/*     */     //   452: ifnull +136 -> 588
/*     */     //   455: aload 5
/*     */     //   457: invokeinterface 180 1 0
/*     */     //   462: goto +126 -> 588
/*     */     //   465: astore 9
/*     */     //   467: aload 9
/*     */     //   469: invokevirtual 376	java/text/ParseException:printStackTrace	()V
/*     */     //   472: aload 7
/*     */     //   474: ifnull +10 -> 484
/*     */     //   477: aload 7
/*     */     //   479: invokeinterface 176 1 0
/*     */     //   484: aload 6
/*     */     //   486: ifnull +10 -> 496
/*     */     //   489: aload 6
/*     */     //   491: invokeinterface 179 1 0
/*     */     //   496: aload 5
/*     */     //   498: ifnull +90 -> 588
/*     */     //   501: aload 5
/*     */     //   503: invokeinterface 180 1 0
/*     */     //   508: goto +80 -> 588
/*     */     //   511: astore 16
/*     */     //   513: aload 7
/*     */     //   515: ifnull +10 -> 525
/*     */     //   518: aload 7
/*     */     //   520: invokeinterface 176 1 0
/*     */     //   525: aload 6
/*     */     //   527: ifnull +10 -> 537
/*     */     //   530: aload 6
/*     */     //   532: invokeinterface 179 1 0
/*     */     //   537: aload 5
/*     */     //   539: ifnull +10 -> 549
/*     */     //   542: aload 5
/*     */     //   544: invokeinterface 180 1 0
/*     */     //   549: aload 16
/*     */     //   551: athrow
/*     */     //   552: aload 7
/*     */     //   554: ifnull +10 -> 564
/*     */     //   557: aload 7
/*     */     //   559: invokeinterface 176 1 0
/*     */     //   564: aload 6
/*     */     //   566: ifnull +10 -> 576
/*     */     //   569: aload 6
/*     */     //   571: invokeinterface 179 1 0
/*     */     //   576: aload 5
/*     */     //   578: ifnull +10 -> 588
/*     */     //   581: aload 5
/*     */     //   583: invokeinterface 180 1 0
/*     */     //   588: aload 8
/*     */     //   590: areturn
/*     */     // Line number table:
/*     */     //   Java source line #879	-> byte code offset #0
/*     */     //   Java source line #880	-> byte code offset #10
/*     */     //   Java source line #881	-> byte code offset #13
/*     */     //   Java source line #882	-> byte code offset #16
/*     */     //   Java source line #885	-> byte code offset #25
/*     */     //   Java source line #886	-> byte code offset #35
/*     */     //   Java source line #885	-> byte code offset #47
/*     */     //   Java source line #888	-> byte code offset #52
/*     */     //   Java source line #889	-> byte code offset #63
/*     */     //   Java source line #890	-> byte code offset #73
/*     */     //   Java source line #891	-> byte code offset #82
/*     */     //   Java source line #893	-> byte code offset #91
/*     */     //   Java source line #894	-> byte code offset #95
/*     */     //   Java source line #893	-> byte code offset #101
/*     */     //   Java source line #895	-> byte code offset #106
/*     */     //   Java source line #896	-> byte code offset #118
/*     */     //   Java source line #897	-> byte code offset #132
/*     */     //   Java source line #899	-> byte code offset #135
/*     */     //   Java source line #900	-> byte code offset #144
/*     */     //   Java source line #901	-> byte code offset #158
/*     */     //   Java source line #902	-> byte code offset #173
/*     */     //   Java source line #903	-> byte code offset #188
/*     */     //   Java source line #905	-> byte code offset #206
/*     */     //   Java source line #906	-> byte code offset #212
/*     */     //   Java source line #905	-> byte code offset #215
/*     */     //   Java source line #906	-> byte code offset #220
/*     */     //   Java source line #905	-> byte code offset #223
/*     */     //   Java source line #907	-> byte code offset #228
/*     */     //   Java source line #913	-> byte code offset #242
/*     */     //   Java source line #914	-> byte code offset #252
/*     */     //   Java source line #915	-> byte code offset #262
/*     */     //   Java source line #916	-> byte code offset #270
/*     */     //   Java source line #917	-> byte code offset #273
/*     */     //   Java source line #918	-> byte code offset #281
/*     */     //   Java source line #919	-> byte code offset #295
/*     */     //   Java source line #918	-> byte code offset #301
/*     */     //   Java source line #920	-> byte code offset #306
/*     */     //   Java source line #921	-> byte code offset #317
/*     */     //   Java source line #922	-> byte code offset #326
/*     */     //   Java source line #923	-> byte code offset #343
/*     */     //   Java source line #924	-> byte code offset #345
/*     */     //   Java source line #923	-> byte code offset #350
/*     */     //   Java source line #925	-> byte code offset #352
/*     */     //   Java source line #926	-> byte code offset #362
/*     */     //   Java source line #927	-> byte code offset #370
/*     */     //   Java source line #928	-> byte code offset #374
/*     */     //   Java source line #927	-> byte code offset #382
/*     */     //   Java source line #929	-> byte code offset #385
/*     */     //   Java source line #930	-> byte code offset #388
/*     */     //   Java source line #932	-> byte code offset #396
/*     */     //   Java source line #897	-> byte code offset #406
/*     */     //   Java source line #935	-> byte code offset #416
/*     */     //   Java source line #936	-> byte code offset #421
/*     */     //   Java source line #942	-> byte code offset #426
/*     */     //   Java source line #943	-> byte code offset #431
/*     */     //   Java source line #944	-> byte code offset #438
/*     */     //   Java source line #945	-> byte code offset #443
/*     */     //   Java source line #946	-> byte code offset #450
/*     */     //   Java source line #947	-> byte code offset #455
/*     */     //   Java source line #937	-> byte code offset #465
/*     */     //   Java source line #938	-> byte code offset #467
/*     */     //   Java source line #942	-> byte code offset #472
/*     */     //   Java source line #943	-> byte code offset #477
/*     */     //   Java source line #944	-> byte code offset #484
/*     */     //   Java source line #945	-> byte code offset #489
/*     */     //   Java source line #946	-> byte code offset #496
/*     */     //   Java source line #947	-> byte code offset #501
/*     */     //   Java source line #941	-> byte code offset #511
/*     */     //   Java source line #942	-> byte code offset #513
/*     */     //   Java source line #943	-> byte code offset #518
/*     */     //   Java source line #944	-> byte code offset #525
/*     */     //   Java source line #945	-> byte code offset #530
/*     */     //   Java source line #946	-> byte code offset #537
/*     */     //   Java source line #947	-> byte code offset #542
/*     */     //   Java source line #948	-> byte code offset #549
/*     */     //   Java source line #942	-> byte code offset #552
/*     */     //   Java source line #943	-> byte code offset #557
/*     */     //   Java source line #944	-> byte code offset #564
/*     */     //   Java source line #945	-> byte code offset #569
/*     */     //   Java source line #946	-> byte code offset #576
/*     */     //   Java source line #947	-> byte code offset #581
/*     */     //   Java source line #950	-> byte code offset #588
/*     */     // Local variable table:
/*     */     //   start	length	slot	name	signature
/*     */     //   0	591	0	this	QuizDAOImpl
/*     */     //   0	591	1	userid	int
/*     */     //   0	591	2	category	String
/*     */     //   0	591	3	test_category_id	int
/*     */     //   0	591	4	standard	int
/*     */     //   8	574	5	connection	Connection
/*     */     //   11	559	6	preparedStatement	PreparedStatement
/*     */     //   14	544	7	resultSet	ResultSet
/*     */     //   23	566	8	topicLists	List<com.groom.bean.TestsTopicList>
/*     */     //   50	5	9	query	String
/*     */     //   419	3	9	exception	SQLException
/*     */     //   465	3	9	exception	java.text.ParseException
/*     */     //   104	151	10	currentDate	java.util.Date
/*     */     //   116	115	11	dateFormat	java.text.SimpleDateFormat
/*     */     //   142	257	12	topic	com.groom.bean.TestsTopicList
/*     */     //   226	27	13	testDate	java.util.Date
/*     */     //   304	5	14	pointsQuery	String
/*     */     //   350	23	15	userPointsResultSet	ResultSet
/*     */     //   511	39	16	localObject	Object
/*     */     // Exception table:
/*     */     //   from	to	target	type
/*     */     //   25	416	419	java/sql/SQLException
/*     */     //   25	416	465	java/text/ParseException
/*     */     //   25	426	511	finally
/*     */     //   465	472	511	finally
/*     */   }
/*     */   
/*     */   /* Error */
/*     */   public int getQuizDivision(String category, int topicid)
/*     */     throws SQLException
/*     */   {
/*     */     // Byte code:
/*     */     //   0: iconst_0
/*     */     //   1: istore_3
/*     */     //   2: aconst_null
/*     */     //   3: astore 4
/*     */     //   5: aconst_null
/*     */     //   6: astore 5
/*     */     //   8: aconst_null
/*     */     //   9: astore 6
/*     */     //   11: getstatic 23	com/groom/dao/impl/QuizDAOImpl:ds	Ljavax/sql/DataSource;
/*     */     //   14: invokeinterface 27 1 0
/*     */     //   19: astore 4
/*     */     //   21: aload 4
/*     */     //   23: new 36	java/lang/StringBuilder
/*     */     //   26: dup
/*     */     //   27: ldc_w 735
/*     */     //   30: invokespecial 40	java/lang/StringBuilder:<init>	(Ljava/lang/String;)V
/*     */     //   33: aload_1
/*     */     //   34: invokevirtual 43	java/lang/StringBuilder:append	(Ljava/lang/String;)Ljava/lang/StringBuilder;
/*     */     //   37: ldc_w 737
/*     */     //   40: invokevirtual 43	java/lang/StringBuilder:append	(Ljava/lang/String;)Ljava/lang/StringBuilder;
/*     */     //   43: invokevirtual 53	java/lang/StringBuilder:toString	()Ljava/lang/String;
/*     */     //   46: invokeinterface 68 2 0
/*     */     //   51: astore 5
/*     */     //   53: aload 5
/*     */     //   55: iconst_1
/*     */     //   56: iload_2
/*     */     //   57: invokeinterface 74 3 0
/*     */     //   62: aload 5
/*     */     //   64: invokeinterface 80 1 0
/*     */     //   69: astore 6
/*     */     //   71: goto +12 -> 83
/*     */     //   74: aload 6
/*     */     //   76: iconst_1
/*     */     //   77: invokeinterface 739 2 0
/*     */     //   82: istore_3
/*     */     //   83: aload 6
/*     */     //   85: invokeinterface 169 1 0
/*     */     //   90: ifne -16 -> 74
/*     */     //   93: goto +44 -> 137
/*     */     //   96: astore 7
/*     */     //   98: aload 5
/*     */     //   100: ifnull +10 -> 110
/*     */     //   103: aload 5
/*     */     //   105: invokeinterface 179 1 0
/*     */     //   110: aload 6
/*     */     //   112: ifnull +10 -> 122
/*     */     //   115: aload 6
/*     */     //   117: invokeinterface 176 1 0
/*     */     //   122: aload 4
/*     */     //   124: ifnull +10 -> 134
/*     */     //   127: aload 4
/*     */     //   129: invokeinterface 180 1 0
/*     */     //   134: aload 7
/*     */     //   136: athrow
/*     */     //   137: aload 5
/*     */     //   139: ifnull +10 -> 149
/*     */     //   142: aload 5
/*     */     //   144: invokeinterface 179 1 0
/*     */     //   149: aload 6
/*     */     //   151: ifnull +10 -> 161
/*     */     //   154: aload 6
/*     */     //   156: invokeinterface 176 1 0
/*     */     //   161: aload 4
/*     */     //   163: ifnull +10 -> 173
/*     */     //   166: aload 4
/*     */     //   168: invokeinterface 180 1 0
/*     */     //   173: iload_3
/*     */     //   174: invokestatic 215	java/lang/Integer:valueOf	(I)Ljava/lang/Integer;
/*     */     //   177: invokevirtual 742	java/lang/Integer:intValue	()I
/*     */     //   180: ireturn
/*     */     // Line number table:
/*     */     //   Java source line #954	-> byte code offset #0
/*     */     //   Java source line #956	-> byte code offset #2
/*     */     //   Java source line #957	-> byte code offset #5
/*     */     //   Java source line #958	-> byte code offset #8
/*     */     //   Java source line #960	-> byte code offset #11
/*     */     //   Java source line #961	-> byte code offset #21
/*     */     //   Java source line #962	-> byte code offset #23
/*     */     //   Java source line #961	-> byte code offset #51
/*     */     //   Java source line #963	-> byte code offset #53
/*     */     //   Java source line #964	-> byte code offset #62
/*     */     //   Java source line #965	-> byte code offset #71
/*     */     //   Java source line #966	-> byte code offset #74
/*     */     //   Java source line #965	-> byte code offset #83
/*     */     //   Java source line #967	-> byte code offset #93
/*     */     //   Java source line #968	-> byte code offset #98
/*     */     //   Java source line #969	-> byte code offset #103
/*     */     //   Java source line #971	-> byte code offset #110
/*     */     //   Java source line #972	-> byte code offset #115
/*     */     //   Java source line #973	-> byte code offset #122
/*     */     //   Java source line #974	-> byte code offset #127
/*     */     //   Java source line #975	-> byte code offset #134
/*     */     //   Java source line #968	-> byte code offset #137
/*     */     //   Java source line #969	-> byte code offset #142
/*     */     //   Java source line #971	-> byte code offset #149
/*     */     //   Java source line #972	-> byte code offset #154
/*     */     //   Java source line #973	-> byte code offset #161
/*     */     //   Java source line #974	-> byte code offset #166
/*     */     //   Java source line #976	-> byte code offset #173
/*     */     // Local variable table:
/*     */     //   start	length	slot	name	signature
/*     */     //   0	181	0	this	QuizDAOImpl
/*     */     //   0	181	1	category	String
/*     */     //   0	181	2	topicid	int
/*     */     //   1	173	3	div	int
/*     */     //   3	164	4	conn	Connection
/*     */     //   6	137	5	ps	PreparedStatement
/*     */     //   9	146	6	rs	ResultSet
/*     */     //   96	39	7	localObject	Object
/*     */     // Exception table:
/*     */     //   from	to	target	type
/*     */     //   11	96	96	finally
/*     */   }
/*     */ }


/* Location:              D:\New folder\WEB-INF\classes\com\groom.zip!\groom\dao\impl\QuizDAOImpl.class
 * Java compiler version: 7 (51.0)
 * JD-Core Version:       0.7.1
 */