/*     */ package com.groom.dao.impl;
/*     */ 
/*     */ import com.groom.bean.User;
/*     */ import com.groom.bean.UserActivation;
/*     */ import com.groom.dao.BaseDAO;
/*     */ import com.groom.dao.UserDAO;
/*     */ import java.sql.Connection;
/*     */ import java.sql.PreparedStatement;
/*     */ import java.sql.ResultSet;
/*     */ import java.sql.SQLException;
/*     */ import javax.sql.DataSource;
/*     */ 
/*     */ public class UserDAOImpl
/*     */   extends BaseDAO
/*     */   implements UserDAO
/*     */ {
/*     */   public boolean validateUser(User user) throws SQLException
/*     */   {
/*  19 */     Connection connection = ds.getConnection();
/*  20 */     PreparedStatement preparedStatement = null;
/*  21 */     ResultSet resultSet = null;
/*     */     try {
/*  23 */       String query = "SELECT ACTIVE FROM USER WHERE USER_NAME=? AND PASSWORD=?";
/*  24 */       preparedStatement = connection.prepareStatement(query);
/*  25 */       preparedStatement.setString(1, user.getUsername());
/*     */       
/*  27 */       preparedStatement.setString(2, user.getPassword());
/*  28 */       resultSet = preparedStatement.executeQuery();
/*  29 */       if ((resultSet.next()) && 
/*  30 */         (resultSet.getInt("ACTIVE") == 1))
/*  31 */         return true;
/*     */     } catch (SQLException exception) {
/*  33 */       exception.printStackTrace();
/*     */     } finally {
/*  35 */       if (resultSet != null)
/*  36 */         resultSet.close();
/*  37 */       if (preparedStatement != null)
/*  38 */         preparedStatement.close();
/*  39 */       if (connection != null) {
/*  40 */         connection.close();
/*     */       }
/*     */     }
/*  35 */     if (resultSet != null)
/*  36 */       resultSet.close();
/*  37 */     if (preparedStatement != null)
/*  38 */       preparedStatement.close();
/*  39 */     if (connection != null) {
/*  40 */       connection.close();
/*     */     }
/*  42 */     return false;
/*     */   }
/*     */   
/*     */   /* Error */
/*     */   public int registerUser(User user)
/*     */     throws SQLException
/*     */   {
/*     */     // Byte code:
/*     */     //   0: getstatic 21	com/groom/dao/impl/UserDAOImpl:ds	Ljavax/sql/DataSource;
/*     */     //   3: invokeinterface 25 1 0
/*     */     //   8: astore_2
/*     */     //   9: aconst_null
/*     */     //   10: astore_3
/*     */     //   11: aconst_null
/*     */     //   12: astore 4
/*     */     //   14: iconst_0
/*     */     //   15: istore 5
/*     */     //   17: ldc 97
/*     */     //   19: astore 6
/*     */     //   21: aload_2
/*     */     //   22: aload 6
/*     */     //   24: invokeinterface 33 2 0
/*     */     //   29: astore_3
/*     */     //   30: aload_3
/*     */     //   31: iconst_1
/*     */     //   32: aload_1
/*     */     //   33: invokevirtual 39	com/groom/bean/User:getUsername	()Ljava/lang/String;
/*     */     //   36: invokeinterface 45 3 0
/*     */     //   41: aload_3
/*     */     //   42: iconst_2
/*     */     //   43: aload_1
/*     */     //   44: invokevirtual 51	com/groom/bean/User:getPassword	()Ljava/lang/String;
/*     */     //   47: invokeinterface 45 3 0
/*     */     //   52: aload_3
/*     */     //   53: iconst_3
/*     */     //   54: aload_1
/*     */     //   55: invokevirtual 99	com/groom/bean/User:getFirstname	()Ljava/lang/String;
/*     */     //   58: invokeinterface 45 3 0
/*     */     //   63: aload_3
/*     */     //   64: iconst_4
/*     */     //   65: aload_1
/*     */     //   66: invokevirtual 102	com/groom/bean/User:getLastname	()Ljava/lang/String;
/*     */     //   69: invokeinterface 45 3 0
/*     */     //   74: aload_3
/*     */     //   75: iconst_5
/*     */     //   76: aload_1
/*     */     //   77: invokevirtual 105	com/groom/bean/User:getMail	()Ljava/lang/String;
/*     */     //   80: invokeinterface 45 3 0
/*     */     //   85: aload_3
/*     */     //   86: bipush 6
/*     */     //   88: aload_1
/*     */     //   89: invokevirtual 108	com/groom/bean/User:getMobile	()Ljava/lang/String;
/*     */     //   92: invokeinterface 45 3 0
/*     */     //   97: aload_3
/*     */     //   98: bipush 7
/*     */     //   100: aload_1
/*     */     //   101: invokevirtual 111	com/groom/bean/User:getCountry	()Ljava/lang/String;
/*     */     //   104: invokeinterface 45 3 0
/*     */     //   109: aload_3
/*     */     //   110: bipush 8
/*     */     //   112: aload_1
/*     */     //   113: invokevirtual 114	com/groom/bean/User:getState	()Ljava/lang/String;
/*     */     //   116: invokeinterface 45 3 0
/*     */     //   121: aload_3
/*     */     //   122: bipush 9
/*     */     //   124: aload_1
/*     */     //   125: invokevirtual 117	com/groom/bean/User:getCity	()Ljava/lang/String;
/*     */     //   128: invokeinterface 45 3 0
/*     */     //   133: aload_3
/*     */     //   134: bipush 10
/*     */     //   136: invokestatic 120	com/groom/util/GroomUtil:getCurrentDate	()Ljava/sql/Date;
/*     */     //   139: invokeinterface 126 3 0
/*     */     //   144: aload_3
/*     */     //   145: bipush 11
/*     */     //   147: aload_1
/*     */     //   148: invokevirtual 130	com/groom/bean/User:getStandard	()Ljava/lang/String;
/*     */     //   151: invokestatic 133	java/lang/Integer:parseInt	(Ljava/lang/String;)I
/*     */     //   154: invokeinterface 138 3 0
/*     */     //   159: aload_3
/*     */     //   160: bipush 12
/*     */     //   162: aload_1
/*     */     //   163: invokevirtual 142	com/groom/bean/User:getSchool	()Ljava/lang/String;
/*     */     //   166: invokeinterface 45 3 0
/*     */     //   171: aload_3
/*     */     //   172: bipush 13
/*     */     //   174: aload_1
/*     */     //   175: invokevirtual 145	com/groom/bean/User:getRefText	()Ljava/lang/String;
/*     */     //   178: invokeinterface 45 3 0
/*     */     //   183: aload_3
/*     */     //   184: invokeinterface 148 1 0
/*     */     //   189: iconst_1
/*     */     //   190: if_icmpne +120 -> 310
/*     */     //   193: aload_2
/*     */     //   194: ldc -104
/*     */     //   196: invokeinterface 33 2 0
/*     */     //   201: astore_3
/*     */     //   202: aload_3
/*     */     //   203: invokeinterface 54 1 0
/*     */     //   208: astore 4
/*     */     //   210: aload 4
/*     */     //   212: invokeinterface 58 1 0
/*     */     //   217: pop
/*     */     //   218: aload 4
/*     */     //   220: iconst_1
/*     */     //   221: invokeinterface 154 2 0
/*     */     //   226: istore 5
/*     */     //   228: goto +82 -> 310
/*     */     //   231: astore 6
/*     */     //   233: aload 6
/*     */     //   235: invokevirtual 75	java/sql/SQLException:printStackTrace	()V
/*     */     //   238: aload 4
/*     */     //   240: ifnull +10 -> 250
/*     */     //   243: aload 4
/*     */     //   245: invokeinterface 70 1 0
/*     */     //   250: aload_3
/*     */     //   251: ifnull +9 -> 260
/*     */     //   254: aload_3
/*     */     //   255: invokeinterface 73 1 0
/*     */     //   260: aload_2
/*     */     //   261: ifnull +81 -> 342
/*     */     //   264: aload_2
/*     */     //   265: invokeinterface 74 1 0
/*     */     //   270: goto +72 -> 342
/*     */     //   273: astore 7
/*     */     //   275: aload 4
/*     */     //   277: ifnull +10 -> 287
/*     */     //   280: aload 4
/*     */     //   282: invokeinterface 70 1 0
/*     */     //   287: aload_3
/*     */     //   288: ifnull +9 -> 297
/*     */     //   291: aload_3
/*     */     //   292: invokeinterface 73 1 0
/*     */     //   297: aload_2
/*     */     //   298: ifnull +9 -> 307
/*     */     //   301: aload_2
/*     */     //   302: invokeinterface 74 1 0
/*     */     //   307: aload 7
/*     */     //   309: athrow
/*     */     //   310: aload 4
/*     */     //   312: ifnull +10 -> 322
/*     */     //   315: aload 4
/*     */     //   317: invokeinterface 70 1 0
/*     */     //   322: aload_3
/*     */     //   323: ifnull +9 -> 332
/*     */     //   326: aload_3
/*     */     //   327: invokeinterface 73 1 0
/*     */     //   332: aload_2
/*     */     //   333: ifnull +9 -> 342
/*     */     //   336: aload_2
/*     */     //   337: invokeinterface 74 1 0
/*     */     //   342: iload 5
/*     */     //   344: ireturn
/*     */     // Line number table:
/*     */     //   Java source line #47	-> byte code offset #0
/*     */     //   Java source line #48	-> byte code offset #9
/*     */     //   Java source line #49	-> byte code offset #11
/*     */     //   Java source line #50	-> byte code offset #14
/*     */     //   Java source line #52	-> byte code offset #17
/*     */     //   Java source line #53	-> byte code offset #21
/*     */     //   Java source line #54	-> byte code offset #30
/*     */     //   Java source line #55	-> byte code offset #41
/*     */     //   Java source line #58	-> byte code offset #52
/*     */     //   Java source line #59	-> byte code offset #63
/*     */     //   Java source line #60	-> byte code offset #74
/*     */     //   Java source line #61	-> byte code offset #85
/*     */     //   Java source line #62	-> byte code offset #97
/*     */     //   Java source line #63	-> byte code offset #109
/*     */     //   Java source line #64	-> byte code offset #121
/*     */     //   Java source line #65	-> byte code offset #133
/*     */     //   Java source line #66	-> byte code offset #144
/*     */     //   Java source line #67	-> byte code offset #159
/*     */     //   Java source line #68	-> byte code offset #171
/*     */     //   Java source line #69	-> byte code offset #183
/*     */     //   Java source line #70	-> byte code offset #193
/*     */     //   Java source line #71	-> byte code offset #194
/*     */     //   Java source line #70	-> byte code offset #201
/*     */     //   Java source line #72	-> byte code offset #202
/*     */     //   Java source line #73	-> byte code offset #210
/*     */     //   Java source line #74	-> byte code offset #218
/*     */     //   Java source line #76	-> byte code offset #228
/*     */     //   Java source line #77	-> byte code offset #233
/*     */     //   Java source line #79	-> byte code offset #238
/*     */     //   Java source line #80	-> byte code offset #243
/*     */     //   Java source line #81	-> byte code offset #250
/*     */     //   Java source line #82	-> byte code offset #254
/*     */     //   Java source line #83	-> byte code offset #260
/*     */     //   Java source line #84	-> byte code offset #264
/*     */     //   Java source line #78	-> byte code offset #273
/*     */     //   Java source line #79	-> byte code offset #275
/*     */     //   Java source line #80	-> byte code offset #280
/*     */     //   Java source line #81	-> byte code offset #287
/*     */     //   Java source line #82	-> byte code offset #291
/*     */     //   Java source line #83	-> byte code offset #297
/*     */     //   Java source line #84	-> byte code offset #301
/*     */     //   Java source line #85	-> byte code offset #307
/*     */     //   Java source line #79	-> byte code offset #310
/*     */     //   Java source line #80	-> byte code offset #315
/*     */     //   Java source line #81	-> byte code offset #322
/*     */     //   Java source line #82	-> byte code offset #326
/*     */     //   Java source line #83	-> byte code offset #332
/*     */     //   Java source line #84	-> byte code offset #336
/*     */     //   Java source line #86	-> byte code offset #342
/*     */     // Local variable table:
/*     */     //   start	length	slot	name	signature
/*     */     //   0	345	0	this	UserDAOImpl
/*     */     //   0	345	1	user	User
/*     */     //   8	329	2	connection	Connection
/*     */     //   10	317	3	preparedStatement	PreparedStatement
/*     */     //   12	304	4	resultSet	ResultSet
/*     */     //   15	328	5	userid	int
/*     */     //   19	4	6	query	String
/*     */     //   231	3	6	exception	SQLException
/*     */     //   273	35	7	localObject	Object
/*     */     // Exception table:
/*     */     //   from	to	target	type
/*     */     //   17	228	231	java/sql/SQLException
/*     */     //   17	238	273	finally
/*     */   }
/*     */   
/*     */   public boolean isUsernameExist(String username)
/*     */     throws SQLException
/*     */   {
/*  91 */     Connection connection = ds.getConnection();
/*  92 */     PreparedStatement preparedStatement = null;
/*  93 */     ResultSet resultSet = null;
/*     */     try {
/*  95 */       String query = "SELECT * FROM USER WHERE USER_NAME=?";
/*  96 */       preparedStatement = connection.prepareStatement(query);
/*  97 */       preparedStatement.setString(1, username);
/*     */       
/*  99 */       resultSet = preparedStatement.executeQuery();
/* 100 */       if (resultSet.next())
/* 101 */         return true;
/*     */     } catch (SQLException exception) {
/* 103 */       exception.printStackTrace();
/*     */     } finally {
/* 105 */       if (resultSet != null)
/* 106 */         resultSet.close();
/* 107 */       if (preparedStatement != null)
/* 108 */         preparedStatement.close();
/* 109 */       if (connection != null) {
/* 110 */         connection.close();
/*     */       }
/*     */     }
/* 105 */     if (resultSet != null)
/* 106 */       resultSet.close();
/* 107 */     if (preparedStatement != null)
/* 108 */       preparedStatement.close();
/* 109 */     if (connection != null) {
/* 110 */       connection.close();
/*     */     }
/* 112 */     return false;
/*     */   }
/*     */   
/*     */   public boolean isMailExist(String mail) throws SQLException
/*     */   {
/* 117 */     Connection connection = ds.getConnection();
/* 118 */     PreparedStatement preparedStatement = null;
/* 119 */     ResultSet resultSet = null;
/*     */     try {
/* 121 */       String query = "SELECT * FROM USER WHERE MAIL=?";
/* 122 */       preparedStatement = connection.prepareStatement(query);
/* 123 */       preparedStatement.setString(1, mail);
/*     */       
/* 125 */       resultSet = preparedStatement.executeQuery();
/* 126 */       if (resultSet.next())
/* 127 */         return true;
/*     */     } catch (SQLException exception) {
/* 129 */       exception.printStackTrace();
/*     */     } finally {
/* 131 */       if (resultSet != null)
/* 132 */         resultSet.close();
/* 133 */       if (preparedStatement != null)
/* 134 */         preparedStatement.close();
/* 135 */       if (connection != null) {
/* 136 */         connection.close();
/*     */       }
/*     */     }
/* 131 */     if (resultSet != null)
/* 132 */       resultSet.close();
/* 133 */     if (preparedStatement != null)
/* 134 */       preparedStatement.close();
/* 135 */     if (connection != null) {
/* 136 */       connection.close();
/*     */     }
/* 138 */     return false;
/*     */   }
/*     */   
/*     */   public boolean isPhoneNumberExist(String phone) throws SQLException
/*     */   {
/* 143 */     Connection connection = ds.getConnection();
/* 144 */     PreparedStatement preparedStatement = null;
/* 145 */     ResultSet resultSet = null;
/*     */     try {
/* 147 */       String query = "SELECT * FROM USER WHERE PHONE=?";
/* 148 */       preparedStatement = connection.prepareStatement(query);
/* 149 */       preparedStatement.setString(1, phone);
/*     */       
/* 151 */       resultSet = preparedStatement.executeQuery();
/* 152 */       if (resultSet.next())
/* 153 */         return true;
/*     */     } catch (SQLException exception) {
/* 155 */       exception.printStackTrace();
/*     */     } finally {
/* 157 */       if (resultSet != null)
/* 158 */         resultSet.close();
/* 159 */       if (preparedStatement != null)
/* 160 */         preparedStatement.close();
/* 161 */       if (connection != null) {
/* 162 */         connection.close();
/*     */       }
/*     */     }
/* 157 */     if (resultSet != null)
/* 158 */       resultSet.close();
/* 159 */     if (preparedStatement != null)
/* 160 */       preparedStatement.close();
/* 161 */     if (connection != null) {
/* 162 */       connection.close();
/*     */     }
/* 164 */     return false;
/*     */   }
/*     */   
/*     */   /* Error */
/*     */   public User getUserDetails(String username)
/*     */     throws SQLException
/*     */   {
/*     */     // Byte code:
/*     */     //   0: getstatic 21	com/groom/dao/impl/UserDAOImpl:ds	Ljavax/sql/DataSource;
/*     */     //   3: invokeinterface 25 1 0
/*     */     //   8: astore_2
/*     */     //   9: aconst_null
/*     */     //   10: astore_3
/*     */     //   11: aconst_null
/*     */     //   12: astore 4
/*     */     //   14: new 40	com/groom/bean/User
/*     */     //   17: dup
/*     */     //   18: invokespecial 174	com/groom/bean/User:<init>	()V
/*     */     //   21: astore 5
/*     */     //   23: ldc -95
/*     */     //   25: astore 6
/*     */     //   27: aload_2
/*     */     //   28: aload 6
/*     */     //   30: invokeinterface 33 2 0
/*     */     //   35: astore_3
/*     */     //   36: aload_3
/*     */     //   37: iconst_1
/*     */     //   38: aload_1
/*     */     //   39: invokeinterface 45 3 0
/*     */     //   44: aload_3
/*     */     //   45: invokeinterface 54 1 0
/*     */     //   50: astore 4
/*     */     //   52: aload 4
/*     */     //   54: invokeinterface 58 1 0
/*     */     //   59: pop
/*     */     //   60: aload 5
/*     */     //   62: aload 4
/*     */     //   64: ldc -81
/*     */     //   66: invokeinterface 177 2 0
/*     */     //   71: invokevirtual 181	com/groom/bean/User:setCity	(Ljava/lang/String;)V
/*     */     //   74: aload 5
/*     */     //   76: aload 4
/*     */     //   78: ldc -71
/*     */     //   80: invokeinterface 177 2 0
/*     */     //   85: invokevirtual 187	com/groom/bean/User:setUsername	(Ljava/lang/String;)V
/*     */     //   88: aload 5
/*     */     //   90: aload 4
/*     */     //   92: ldc -66
/*     */     //   94: invokeinterface 177 2 0
/*     */     //   99: invokevirtual 192	com/groom/bean/User:setPassword	(Ljava/lang/String;)V
/*     */     //   102: aload 5
/*     */     //   104: aload 4
/*     */     //   106: ldc -61
/*     */     //   108: invokeinterface 177 2 0
/*     */     //   113: invokevirtual 197	com/groom/bean/User:setFirstname	(Ljava/lang/String;)V
/*     */     //   116: aload 5
/*     */     //   118: aload 4
/*     */     //   120: ldc -56
/*     */     //   122: invokeinterface 177 2 0
/*     */     //   127: invokevirtual 202	com/groom/bean/User:setLastname	(Ljava/lang/String;)V
/*     */     //   130: aload 5
/*     */     //   132: aload 4
/*     */     //   134: ldc -51
/*     */     //   136: invokeinterface 177 2 0
/*     */     //   141: invokevirtual 207	com/groom/bean/User:setMail	(Ljava/lang/String;)V
/*     */     //   144: aload 5
/*     */     //   146: aload 4
/*     */     //   148: ldc -46
/*     */     //   150: invokeinterface 177 2 0
/*     */     //   155: invokevirtual 212	com/groom/bean/User:setCountry	(Ljava/lang/String;)V
/*     */     //   158: aload 5
/*     */     //   160: aload 4
/*     */     //   162: ldc -41
/*     */     //   164: invokeinterface 177 2 0
/*     */     //   169: invokevirtual 217	com/groom/bean/User:setState	(Ljava/lang/String;)V
/*     */     //   172: aload 5
/*     */     //   174: aload 4
/*     */     //   176: ldc -36
/*     */     //   178: invokeinterface 66 2 0
/*     */     //   183: invokevirtual 222	com/groom/bean/User:setUserId	(I)V
/*     */     //   186: aload 5
/*     */     //   188: aload 4
/*     */     //   190: ldc -30
/*     */     //   192: invokeinterface 228 2 0
/*     */     //   197: invokevirtual 232	com/groom/bean/User:setDate_registered	(Ljava/sql/Date;)V
/*     */     //   200: aload 5
/*     */     //   202: aload 4
/*     */     //   204: ldc -20
/*     */     //   206: invokeinterface 177 2 0
/*     */     //   211: invokevirtual 238	com/groom/bean/User:setMobile	(Ljava/lang/String;)V
/*     */     //   214: aload 5
/*     */     //   216: aload 4
/*     */     //   218: ldc -15
/*     */     //   220: invokeinterface 66 2 0
/*     */     //   225: invokestatic 243	java/lang/String:valueOf	(I)Ljava/lang/String;
/*     */     //   228: invokevirtual 247	com/groom/bean/User:setStandard	(Ljava/lang/String;)V
/*     */     //   231: aload 5
/*     */     //   233: aload 4
/*     */     //   235: ldc -6
/*     */     //   237: invokeinterface 177 2 0
/*     */     //   242: invokevirtual 252	com/groom/bean/User:setSchool	(Ljava/lang/String;)V
/*     */     //   245: goto +82 -> 327
/*     */     //   248: astore 6
/*     */     //   250: aload 6
/*     */     //   252: invokevirtual 75	java/sql/SQLException:printStackTrace	()V
/*     */     //   255: aload 4
/*     */     //   257: ifnull +10 -> 267
/*     */     //   260: aload 4
/*     */     //   262: invokeinterface 70 1 0
/*     */     //   267: aload_3
/*     */     //   268: ifnull +9 -> 277
/*     */     //   271: aload_3
/*     */     //   272: invokeinterface 73 1 0
/*     */     //   277: aload_2
/*     */     //   278: ifnull +81 -> 359
/*     */     //   281: aload_2
/*     */     //   282: invokeinterface 74 1 0
/*     */     //   287: goto +72 -> 359
/*     */     //   290: astore 7
/*     */     //   292: aload 4
/*     */     //   294: ifnull +10 -> 304
/*     */     //   297: aload 4
/*     */     //   299: invokeinterface 70 1 0
/*     */     //   304: aload_3
/*     */     //   305: ifnull +9 -> 314
/*     */     //   308: aload_3
/*     */     //   309: invokeinterface 73 1 0
/*     */     //   314: aload_2
/*     */     //   315: ifnull +9 -> 324
/*     */     //   318: aload_2
/*     */     //   319: invokeinterface 74 1 0
/*     */     //   324: aload 7
/*     */     //   326: athrow
/*     */     //   327: aload 4
/*     */     //   329: ifnull +10 -> 339
/*     */     //   332: aload 4
/*     */     //   334: invokeinterface 70 1 0
/*     */     //   339: aload_3
/*     */     //   340: ifnull +9 -> 349
/*     */     //   343: aload_3
/*     */     //   344: invokeinterface 73 1 0
/*     */     //   349: aload_2
/*     */     //   350: ifnull +9 -> 359
/*     */     //   353: aload_2
/*     */     //   354: invokeinterface 74 1 0
/*     */     //   359: aload 5
/*     */     //   361: areturn
/*     */     // Line number table:
/*     */     //   Java source line #169	-> byte code offset #0
/*     */     //   Java source line #170	-> byte code offset #9
/*     */     //   Java source line #171	-> byte code offset #11
/*     */     //   Java source line #172	-> byte code offset #14
/*     */     //   Java source line #174	-> byte code offset #23
/*     */     //   Java source line #175	-> byte code offset #27
/*     */     //   Java source line #176	-> byte code offset #36
/*     */     //   Java source line #178	-> byte code offset #44
/*     */     //   Java source line #179	-> byte code offset #52
/*     */     //   Java source line #180	-> byte code offset #60
/*     */     //   Java source line #181	-> byte code offset #74
/*     */     //   Java source line #182	-> byte code offset #88
/*     */     //   Java source line #183	-> byte code offset #102
/*     */     //   Java source line #184	-> byte code offset #116
/*     */     //   Java source line #185	-> byte code offset #130
/*     */     //   Java source line #186	-> byte code offset #144
/*     */     //   Java source line #187	-> byte code offset #158
/*     */     //   Java source line #188	-> byte code offset #172
/*     */     //   Java source line #189	-> byte code offset #186
/*     */     //   Java source line #190	-> byte code offset #200
/*     */     //   Java source line #191	-> byte code offset #214
/*     */     //   Java source line #192	-> byte code offset #231
/*     */     //   Java source line #194	-> byte code offset #245
/*     */     //   Java source line #195	-> byte code offset #250
/*     */     //   Java source line #197	-> byte code offset #255
/*     */     //   Java source line #198	-> byte code offset #260
/*     */     //   Java source line #199	-> byte code offset #267
/*     */     //   Java source line #200	-> byte code offset #271
/*     */     //   Java source line #201	-> byte code offset #277
/*     */     //   Java source line #202	-> byte code offset #281
/*     */     //   Java source line #196	-> byte code offset #290
/*     */     //   Java source line #197	-> byte code offset #292
/*     */     //   Java source line #198	-> byte code offset #297
/*     */     //   Java source line #199	-> byte code offset #304
/*     */     //   Java source line #200	-> byte code offset #308
/*     */     //   Java source line #201	-> byte code offset #314
/*     */     //   Java source line #202	-> byte code offset #318
/*     */     //   Java source line #203	-> byte code offset #324
/*     */     //   Java source line #197	-> byte code offset #327
/*     */     //   Java source line #198	-> byte code offset #332
/*     */     //   Java source line #199	-> byte code offset #339
/*     */     //   Java source line #200	-> byte code offset #343
/*     */     //   Java source line #201	-> byte code offset #349
/*     */     //   Java source line #202	-> byte code offset #353
/*     */     //   Java source line #204	-> byte code offset #359
/*     */     // Local variable table:
/*     */     //   start	length	slot	name	signature
/*     */     //   0	362	0	this	UserDAOImpl
/*     */     //   0	362	1	username	String
/*     */     //   8	346	2	connection	Connection
/*     */     //   10	334	3	preparedStatement	PreparedStatement
/*     */     //   12	321	4	resultSet	ResultSet
/*     */     //   21	339	5	user	User
/*     */     //   25	4	6	query	String
/*     */     //   248	3	6	exception	SQLException
/*     */     //   290	35	7	localObject	Object
/*     */     // Exception table:
/*     */     //   from	to	target	type
/*     */     //   23	245	248	java/sql/SQLException
/*     */     //   23	255	290	finally
/*     */   }
/*     */   
/*     */   /* Error */
/*     */   public User getUserForgotPwdDetails(String userNameMail)
/*     */     throws SQLException
/*     */   {
/*     */     // Byte code:
/*     */     //   0: getstatic 21	com/groom/dao/impl/UserDAOImpl:ds	Ljavax/sql/DataSource;
/*     */     //   3: invokeinterface 25 1 0
/*     */     //   8: astore_2
/*     */     //   9: aconst_null
/*     */     //   10: astore_3
/*     */     //   11: aconst_null
/*     */     //   12: astore 4
/*     */     //   14: new 40	com/groom/bean/User
/*     */     //   17: dup
/*     */     //   18: invokespecial 174	com/groom/bean/User:<init>	()V
/*     */     //   21: astore 5
/*     */     //   23: ldc_w 256
/*     */     //   26: astore 6
/*     */     //   28: aload_2
/*     */     //   29: aload 6
/*     */     //   31: invokeinterface 33 2 0
/*     */     //   36: astore_3
/*     */     //   37: aload_3
/*     */     //   38: iconst_1
/*     */     //   39: aload_1
/*     */     //   40: invokeinterface 45 3 0
/*     */     //   45: aload_3
/*     */     //   46: iconst_2
/*     */     //   47: aload_1
/*     */     //   48: invokeinterface 45 3 0
/*     */     //   53: aload_3
/*     */     //   54: invokeinterface 54 1 0
/*     */     //   59: astore 4
/*     */     //   61: goto +31 -> 92
/*     */     //   64: aload 5
/*     */     //   66: aload 4
/*     */     //   68: ldc -51
/*     */     //   70: invokeinterface 177 2 0
/*     */     //   75: invokevirtual 207	com/groom/bean/User:setMail	(Ljava/lang/String;)V
/*     */     //   78: aload 5
/*     */     //   80: aload 4
/*     */     //   82: ldc -66
/*     */     //   84: invokeinterface 177 2 0
/*     */     //   89: invokevirtual 192	com/groom/bean/User:setPassword	(Ljava/lang/String;)V
/*     */     //   92: aload 4
/*     */     //   94: invokeinterface 58 1 0
/*     */     //   99: ifne -35 -> 64
/*     */     //   102: goto +82 -> 184
/*     */     //   105: astore 6
/*     */     //   107: aload 6
/*     */     //   109: invokevirtual 75	java/sql/SQLException:printStackTrace	()V
/*     */     //   112: aload 4
/*     */     //   114: ifnull +10 -> 124
/*     */     //   117: aload 4
/*     */     //   119: invokeinterface 70 1 0
/*     */     //   124: aload_3
/*     */     //   125: ifnull +9 -> 134
/*     */     //   128: aload_3
/*     */     //   129: invokeinterface 73 1 0
/*     */     //   134: aload_2
/*     */     //   135: ifnull +81 -> 216
/*     */     //   138: aload_2
/*     */     //   139: invokeinterface 74 1 0
/*     */     //   144: goto +72 -> 216
/*     */     //   147: astore 7
/*     */     //   149: aload 4
/*     */     //   151: ifnull +10 -> 161
/*     */     //   154: aload 4
/*     */     //   156: invokeinterface 70 1 0
/*     */     //   161: aload_3
/*     */     //   162: ifnull +9 -> 171
/*     */     //   165: aload_3
/*     */     //   166: invokeinterface 73 1 0
/*     */     //   171: aload_2
/*     */     //   172: ifnull +9 -> 181
/*     */     //   175: aload_2
/*     */     //   176: invokeinterface 74 1 0
/*     */     //   181: aload 7
/*     */     //   183: athrow
/*     */     //   184: aload 4
/*     */     //   186: ifnull +10 -> 196
/*     */     //   189: aload 4
/*     */     //   191: invokeinterface 70 1 0
/*     */     //   196: aload_3
/*     */     //   197: ifnull +9 -> 206
/*     */     //   200: aload_3
/*     */     //   201: invokeinterface 73 1 0
/*     */     //   206: aload_2
/*     */     //   207: ifnull +9 -> 216
/*     */     //   210: aload_2
/*     */     //   211: invokeinterface 74 1 0
/*     */     //   216: aload 5
/*     */     //   218: areturn
/*     */     // Line number table:
/*     */     //   Java source line #210	-> byte code offset #0
/*     */     //   Java source line #211	-> byte code offset #9
/*     */     //   Java source line #212	-> byte code offset #11
/*     */     //   Java source line #213	-> byte code offset #14
/*     */     //   Java source line #215	-> byte code offset #23
/*     */     //   Java source line #216	-> byte code offset #28
/*     */     //   Java source line #217	-> byte code offset #37
/*     */     //   Java source line #218	-> byte code offset #45
/*     */     //   Java source line #220	-> byte code offset #53
/*     */     //   Java source line #221	-> byte code offset #61
/*     */     //   Java source line #222	-> byte code offset #64
/*     */     //   Java source line #223	-> byte code offset #78
/*     */     //   Java source line #221	-> byte code offset #92
/*     */     //   Java source line #225	-> byte code offset #102
/*     */     //   Java source line #226	-> byte code offset #107
/*     */     //   Java source line #228	-> byte code offset #112
/*     */     //   Java source line #229	-> byte code offset #117
/*     */     //   Java source line #230	-> byte code offset #124
/*     */     //   Java source line #231	-> byte code offset #128
/*     */     //   Java source line #232	-> byte code offset #134
/*     */     //   Java source line #233	-> byte code offset #138
/*     */     //   Java source line #227	-> byte code offset #147
/*     */     //   Java source line #228	-> byte code offset #149
/*     */     //   Java source line #229	-> byte code offset #154
/*     */     //   Java source line #230	-> byte code offset #161
/*     */     //   Java source line #231	-> byte code offset #165
/*     */     //   Java source line #232	-> byte code offset #171
/*     */     //   Java source line #233	-> byte code offset #175
/*     */     //   Java source line #234	-> byte code offset #181
/*     */     //   Java source line #228	-> byte code offset #184
/*     */     //   Java source line #229	-> byte code offset #189
/*     */     //   Java source line #230	-> byte code offset #196
/*     */     //   Java source line #231	-> byte code offset #200
/*     */     //   Java source line #232	-> byte code offset #206
/*     */     //   Java source line #233	-> byte code offset #210
/*     */     //   Java source line #236	-> byte code offset #216
/*     */     // Local variable table:
/*     */     //   start	length	slot	name	signature
/*     */     //   0	219	0	this	UserDAOImpl
/*     */     //   0	219	1	userNameMail	String
/*     */     //   8	203	2	connection	Connection
/*     */     //   10	191	3	preparedStatement	PreparedStatement
/*     */     //   12	178	4	resultSet	ResultSet
/*     */     //   21	196	5	user	User
/*     */     //   26	4	6	query	String
/*     */     //   105	3	6	exception	SQLException
/*     */     //   147	35	7	localObject	Object
/*     */     // Exception table:
/*     */     //   from	to	target	type
/*     */     //   23	102	105	java/sql/SQLException
/*     */     //   23	112	147	finally
/*     */   }
/*     */   
/*     */   /* Error */
/*     */   public User getUserDetails(int userid)
/*     */     throws SQLException
/*     */   {
/*     */     // Byte code:
/*     */     //   0: getstatic 21	com/groom/dao/impl/UserDAOImpl:ds	Ljavax/sql/DataSource;
/*     */     //   3: invokeinterface 25 1 0
/*     */     //   8: astore_2
/*     */     //   9: aconst_null
/*     */     //   10: astore_3
/*     */     //   11: aconst_null
/*     */     //   12: astore 4
/*     */     //   14: new 40	com/groom/bean/User
/*     */     //   17: dup
/*     */     //   18: invokespecial 174	com/groom/bean/User:<init>	()V
/*     */     //   21: astore 5
/*     */     //   23: ldc_w 260
/*     */     //   26: astore 6
/*     */     //   28: aload_2
/*     */     //   29: aload 6
/*     */     //   31: invokeinterface 33 2 0
/*     */     //   36: astore_3
/*     */     //   37: aload_3
/*     */     //   38: iconst_1
/*     */     //   39: iload_1
/*     */     //   40: invokeinterface 138 3 0
/*     */     //   45: aload_3
/*     */     //   46: invokeinterface 54 1 0
/*     */     //   51: astore 4
/*     */     //   53: aload 4
/*     */     //   55: invokeinterface 58 1 0
/*     */     //   60: pop
/*     */     //   61: aload 5
/*     */     //   63: aload 4
/*     */     //   65: ldc -81
/*     */     //   67: invokeinterface 177 2 0
/*     */     //   72: invokevirtual 181	com/groom/bean/User:setCity	(Ljava/lang/String;)V
/*     */     //   75: aload 5
/*     */     //   77: aload 4
/*     */     //   79: ldc -71
/*     */     //   81: invokeinterface 177 2 0
/*     */     //   86: invokevirtual 187	com/groom/bean/User:setUsername	(Ljava/lang/String;)V
/*     */     //   89: aload 5
/*     */     //   91: aload 4
/*     */     //   93: ldc -61
/*     */     //   95: invokeinterface 177 2 0
/*     */     //   100: invokevirtual 197	com/groom/bean/User:setFirstname	(Ljava/lang/String;)V
/*     */     //   103: aload 5
/*     */     //   105: aload 4
/*     */     //   107: ldc -56
/*     */     //   109: invokeinterface 177 2 0
/*     */     //   114: invokevirtual 202	com/groom/bean/User:setLastname	(Ljava/lang/String;)V
/*     */     //   117: aload 5
/*     */     //   119: aload 4
/*     */     //   121: ldc -51
/*     */     //   123: invokeinterface 177 2 0
/*     */     //   128: invokevirtual 207	com/groom/bean/User:setMail	(Ljava/lang/String;)V
/*     */     //   131: aload 5
/*     */     //   133: aload 4
/*     */     //   135: ldc -46
/*     */     //   137: invokeinterface 177 2 0
/*     */     //   142: invokevirtual 212	com/groom/bean/User:setCountry	(Ljava/lang/String;)V
/*     */     //   145: aload 5
/*     */     //   147: aload 4
/*     */     //   149: ldc -41
/*     */     //   151: invokeinterface 177 2 0
/*     */     //   156: invokevirtual 217	com/groom/bean/User:setState	(Ljava/lang/String;)V
/*     */     //   159: aload 5
/*     */     //   161: aload 4
/*     */     //   163: ldc -36
/*     */     //   165: invokeinterface 66 2 0
/*     */     //   170: invokevirtual 222	com/groom/bean/User:setUserId	(I)V
/*     */     //   173: aload 5
/*     */     //   175: aload 4
/*     */     //   177: ldc -30
/*     */     //   179: invokeinterface 228 2 0
/*     */     //   184: invokevirtual 232	com/groom/bean/User:setDate_registered	(Ljava/sql/Date;)V
/*     */     //   187: aload 5
/*     */     //   189: aload 4
/*     */     //   191: ldc -20
/*     */     //   193: invokeinterface 177 2 0
/*     */     //   198: invokevirtual 238	com/groom/bean/User:setMobile	(Ljava/lang/String;)V
/*     */     //   201: aload 5
/*     */     //   203: aload 4
/*     */     //   205: ldc -15
/*     */     //   207: invokeinterface 66 2 0
/*     */     //   212: invokestatic 243	java/lang/String:valueOf	(I)Ljava/lang/String;
/*     */     //   215: invokevirtual 247	com/groom/bean/User:setStandard	(Ljava/lang/String;)V
/*     */     //   218: aload 5
/*     */     //   220: aload 4
/*     */     //   222: ldc -6
/*     */     //   224: invokeinterface 177 2 0
/*     */     //   229: invokevirtual 252	com/groom/bean/User:setSchool	(Ljava/lang/String;)V
/*     */     //   232: goto +82 -> 314
/*     */     //   235: astore 6
/*     */     //   237: aload 6
/*     */     //   239: invokevirtual 75	java/sql/SQLException:printStackTrace	()V
/*     */     //   242: aload 4
/*     */     //   244: ifnull +10 -> 254
/*     */     //   247: aload 4
/*     */     //   249: invokeinterface 70 1 0
/*     */     //   254: aload_3
/*     */     //   255: ifnull +9 -> 264
/*     */     //   258: aload_3
/*     */     //   259: invokeinterface 73 1 0
/*     */     //   264: aload_2
/*     */     //   265: ifnull +81 -> 346
/*     */     //   268: aload_2
/*     */     //   269: invokeinterface 74 1 0
/*     */     //   274: goto +72 -> 346
/*     */     //   277: astore 7
/*     */     //   279: aload 4
/*     */     //   281: ifnull +10 -> 291
/*     */     //   284: aload 4
/*     */     //   286: invokeinterface 70 1 0
/*     */     //   291: aload_3
/*     */     //   292: ifnull +9 -> 301
/*     */     //   295: aload_3
/*     */     //   296: invokeinterface 73 1 0
/*     */     //   301: aload_2
/*     */     //   302: ifnull +9 -> 311
/*     */     //   305: aload_2
/*     */     //   306: invokeinterface 74 1 0
/*     */     //   311: aload 7
/*     */     //   313: athrow
/*     */     //   314: aload 4
/*     */     //   316: ifnull +10 -> 326
/*     */     //   319: aload 4
/*     */     //   321: invokeinterface 70 1 0
/*     */     //   326: aload_3
/*     */     //   327: ifnull +9 -> 336
/*     */     //   330: aload_3
/*     */     //   331: invokeinterface 73 1 0
/*     */     //   336: aload_2
/*     */     //   337: ifnull +9 -> 346
/*     */     //   340: aload_2
/*     */     //   341: invokeinterface 74 1 0
/*     */     //   346: aload 5
/*     */     //   348: areturn
/*     */     // Line number table:
/*     */     //   Java source line #241	-> byte code offset #0
/*     */     //   Java source line #242	-> byte code offset #9
/*     */     //   Java source line #243	-> byte code offset #11
/*     */     //   Java source line #244	-> byte code offset #14
/*     */     //   Java source line #246	-> byte code offset #23
/*     */     //   Java source line #247	-> byte code offset #28
/*     */     //   Java source line #248	-> byte code offset #37
/*     */     //   Java source line #250	-> byte code offset #45
/*     */     //   Java source line #251	-> byte code offset #53
/*     */     //   Java source line #252	-> byte code offset #61
/*     */     //   Java source line #253	-> byte code offset #75
/*     */     //   Java source line #254	-> byte code offset #89
/*     */     //   Java source line #255	-> byte code offset #103
/*     */     //   Java source line #256	-> byte code offset #117
/*     */     //   Java source line #257	-> byte code offset #131
/*     */     //   Java source line #258	-> byte code offset #145
/*     */     //   Java source line #259	-> byte code offset #159
/*     */     //   Java source line #260	-> byte code offset #173
/*     */     //   Java source line #261	-> byte code offset #187
/*     */     //   Java source line #262	-> byte code offset #201
/*     */     //   Java source line #263	-> byte code offset #218
/*     */     //   Java source line #265	-> byte code offset #232
/*     */     //   Java source line #266	-> byte code offset #237
/*     */     //   Java source line #268	-> byte code offset #242
/*     */     //   Java source line #269	-> byte code offset #247
/*     */     //   Java source line #270	-> byte code offset #254
/*     */     //   Java source line #271	-> byte code offset #258
/*     */     //   Java source line #272	-> byte code offset #264
/*     */     //   Java source line #273	-> byte code offset #268
/*     */     //   Java source line #267	-> byte code offset #277
/*     */     //   Java source line #268	-> byte code offset #279
/*     */     //   Java source line #269	-> byte code offset #284
/*     */     //   Java source line #270	-> byte code offset #291
/*     */     //   Java source line #271	-> byte code offset #295
/*     */     //   Java source line #272	-> byte code offset #301
/*     */     //   Java source line #273	-> byte code offset #305
/*     */     //   Java source line #274	-> byte code offset #311
/*     */     //   Java source line #268	-> byte code offset #314
/*     */     //   Java source line #269	-> byte code offset #319
/*     */     //   Java source line #270	-> byte code offset #326
/*     */     //   Java source line #271	-> byte code offset #330
/*     */     //   Java source line #272	-> byte code offset #336
/*     */     //   Java source line #273	-> byte code offset #340
/*     */     //   Java source line #275	-> byte code offset #346
/*     */     // Local variable table:
/*     */     //   start	length	slot	name	signature
/*     */     //   0	349	0	this	UserDAOImpl
/*     */     //   0	349	1	userid	int
/*     */     //   8	333	2	connection	Connection
/*     */     //   10	321	3	preparedStatement	PreparedStatement
/*     */     //   12	308	4	resultSet	ResultSet
/*     */     //   21	326	5	user	User
/*     */     //   26	4	6	query	String
/*     */     //   235	3	6	exception	SQLException
/*     */     //   277	35	7	localObject	Object
/*     */     // Exception table:
/*     */     //   from	to	target	type
/*     */     //   23	232	235	java/sql/SQLException
/*     */     //   23	242	277	finally
/*     */   }
/*     */   
/*     */   public boolean saveUserActivationRecord(UserActivation userActivation)
/*     */     throws SQLException
/*     */   {
/* 281 */     Connection connection = ds.getConnection();
/* 282 */     PreparedStatement preparedStatement = null;
/* 283 */     ResultSet resultSet = null;
/*     */     try
/*     */     {
/* 286 */       String query = "INSERT INTO USER_ACTIVATION(ACTIVATION_KEY,USER_ID) VALUES(?,?)";
/* 287 */       preparedStatement = connection.prepareStatement(query);
/* 288 */       preparedStatement.setString(1, userActivation.getActivationKey());
/* 289 */       preparedStatement.setInt(2, userActivation.getUserId());
/*     */       
/* 291 */       if (preparedStatement.executeUpdate() == 1) {
/* 292 */         return true;
/*     */       }
/*     */     } catch (SQLException exception) {
/* 295 */       exception.printStackTrace();
/*     */     } finally {
/* 297 */       if (resultSet != null)
/* 298 */         resultSet.close();
/* 299 */       if (preparedStatement != null)
/* 300 */         preparedStatement.close();
/* 301 */       if (connection != null) {
/* 302 */         connection.close();
/*     */       }
/*     */     }
/* 297 */     if (resultSet != null)
/* 298 */       resultSet.close();
/* 299 */     if (preparedStatement != null)
/* 300 */       preparedStatement.close();
/* 301 */     if (connection != null) {
/* 302 */       connection.close();
/*     */     }
/* 304 */     return false;
/*     */   }
/*     */   
/*     */   public boolean activateUser(String aCode) throws SQLException
/*     */   {
/* 309 */     Connection connection = ds.getConnection();
/* 310 */     PreparedStatement preparedStatement = null;
/* 311 */     ResultSet resultSet = null;
/* 312 */     int user_id = 0;
/*     */     try {
/* 314 */       String query = "SELECT USER_ID FROM USER_ACTIVATION WHERE ACTIVATION_KEY=?";
/* 315 */       preparedStatement = connection.prepareStatement(query);
/* 316 */       preparedStatement.setString(1, aCode);
/*     */       
/* 318 */       resultSet = preparedStatement.executeQuery();
/* 319 */       if (resultSet.next())
/*     */       {
/* 321 */         user_id = resultSet.getInt("USER_ID");
/* 322 */         String updateQuery = "UPDATE USER SET ACTIVE=1  WHERE USER_ID=?";
/* 323 */         preparedStatement = connection.prepareStatement(updateQuery);
/* 324 */         preparedStatement.setInt(1, user_id);
/* 325 */         int userUpdateStatus = preparedStatement.executeUpdate();
/* 326 */         if (userUpdateStatus == 1) {
/* 327 */           String deleteQuery = "DELETE FROM USER_ACTIVATION WHERE ACTIVATION_KEY=?";
/* 328 */           preparedStatement = connection
/* 329 */             .prepareStatement(deleteQuery);
/* 330 */           preparedStatement.setString(1, aCode);
/* 331 */           int userActivationRecordDelteStatus = preparedStatement
/* 332 */             .executeUpdate();
/* 333 */           if (userActivationRecordDelteStatus == 1) {
/* 334 */             return true;
/*     */           }
/* 336 */           return false;
/*     */         }
/* 338 */         return false;
/*     */       }
/* 340 */       return false;
/*     */     } catch (SQLException exception) {
/* 342 */       exception.printStackTrace();
/*     */     } finally {
/* 344 */       if (resultSet != null)
/* 345 */         resultSet.close();
/* 346 */       if (preparedStatement != null)
/* 347 */         preparedStatement.close();
/* 348 */       if (connection != null)
/* 349 */         connection.close();
/*     */     }
/* 351 */     return false;
/*     */   }
/*     */   
/*     */   public boolean updateUserSubjectPoints(String subject, int userid, int points)
/*     */     throws SQLException
/*     */   {
/* 357 */     Connection connection = ds.getConnection();
/* 358 */     PreparedStatement preparedStatement = null;
/*     */     try
/*     */     {
/* 361 */       String query = "UPDATE USER SET " + subject + "_POINTS=" + subject + 
/* 362 */         "_POINTS+? WHERE USER_ID=?";
/* 363 */       preparedStatement = connection.prepareStatement(query);
/* 364 */       preparedStatement.setInt(1, points);
/* 365 */       preparedStatement.setInt(2, userid);
/*     */       
/* 367 */       if (preparedStatement.executeUpdate() == 1) {
/* 368 */         return true;
/*     */       }
/*     */     } catch (SQLException exception) {
/* 371 */       exception.printStackTrace();
/*     */     }
/*     */     finally {
/* 374 */       if (preparedStatement != null)
/* 375 */         preparedStatement.close();
/* 376 */       if (connection != null) {
/* 377 */         connection.close();
/*     */       }
/*     */     }
/* 374 */     if (preparedStatement != null)
/* 375 */       preparedStatement.close();
/* 376 */     if (connection != null) {
/* 377 */       connection.close();
/*     */     }
/* 379 */     return false;
/*     */   }
/*     */   
/*     */   public boolean updateUserTotalPoints(int userid, int points)
/*     */     throws SQLException
/*     */   {
/* 385 */     Connection connection = ds.getConnection();
/* 386 */     PreparedStatement preparedStatement = null;
/*     */     try
/*     */     {
/* 389 */       String query = "UPDATE USER SET TOTAL_POINTS=TOTAL_POINTS+? WHERE USER_ID=?";
/* 390 */       preparedStatement = connection.prepareStatement(query);
/* 391 */       preparedStatement.setInt(1, points);
/* 392 */       preparedStatement.setInt(2, userid);
/*     */       
/* 394 */       if (preparedStatement.executeUpdate() == 1) {
/* 395 */         return true;
/*     */       }
/*     */     } catch (SQLException exception) {
/* 398 */       exception.printStackTrace();
/*     */     }
/*     */     finally {
/* 401 */       if (preparedStatement != null)
/* 402 */         preparedStatement.close();
/* 403 */       if (connection != null) {
/* 404 */         connection.close();
/*     */       }
/*     */     }
/* 401 */     if (preparedStatement != null)
/* 402 */       preparedStatement.close();
/* 403 */     if (connection != null) {
/* 404 */       connection.close();
/*     */     }
/* 406 */     return false;
/*     */   }
/*     */   
/*     */   /* Error */
/*     */   public int addprodigy(String username, String teamname, String school, String teamdetails, String city, String email, String phone, String theme, String idea)
/*     */     throws SQLException
/*     */   {
/*     */     // Byte code:
/*     */     //   0: getstatic 21	com/groom/dao/impl/UserDAOImpl:ds	Ljavax/sql/DataSource;
/*     */     //   3: invokeinterface 25 1 0
/*     */     //   8: astore 10
/*     */     //   10: aconst_null
/*     */     //   11: astore 11
/*     */     //   13: aconst_null
/*     */     //   14: astore 12
/*     */     //   16: iconst_0
/*     */     //   17: istore 13
/*     */     //   19: ldc_w 316
/*     */     //   22: astore 14
/*     */     //   24: aload 10
/*     */     //   26: aload 14
/*     */     //   28: invokeinterface 33 2 0
/*     */     //   33: astore 11
/*     */     //   35: aload 11
/*     */     //   37: iconst_1
/*     */     //   38: aload_1
/*     */     //   39: invokeinterface 45 3 0
/*     */     //   44: aload 11
/*     */     //   46: iconst_2
/*     */     //   47: aload_2
/*     */     //   48: invokeinterface 45 3 0
/*     */     //   53: aload 11
/*     */     //   55: iconst_3
/*     */     //   56: aload_3
/*     */     //   57: invokeinterface 45 3 0
/*     */     //   62: aload 11
/*     */     //   64: iconst_4
/*     */     //   65: aload 4
/*     */     //   67: invokeinterface 45 3 0
/*     */     //   72: aload 11
/*     */     //   74: iconst_5
/*     */     //   75: aload 5
/*     */     //   77: invokeinterface 45 3 0
/*     */     //   82: aload 11
/*     */     //   84: bipush 6
/*     */     //   86: aload 6
/*     */     //   88: invokeinterface 45 3 0
/*     */     //   93: aload 11
/*     */     //   95: bipush 7
/*     */     //   97: aload 7
/*     */     //   99: invokeinterface 45 3 0
/*     */     //   104: aload 11
/*     */     //   106: bipush 8
/*     */     //   108: aload 8
/*     */     //   110: invokeinterface 45 3 0
/*     */     //   115: aload 11
/*     */     //   117: bipush 9
/*     */     //   119: aload 9
/*     */     //   121: invokeinterface 45 3 0
/*     */     //   126: aload 11
/*     */     //   128: bipush 10
/*     */     //   130: invokestatic 120	com/groom/util/GroomUtil:getCurrentDate	()Ljava/sql/Date;
/*     */     //   133: invokeinterface 126 3 0
/*     */     //   138: aload 11
/*     */     //   140: invokeinterface 148 1 0
/*     */     //   145: iconst_1
/*     */     //   146: if_icmpne +131 -> 277
/*     */     //   149: aload 10
/*     */     //   151: ldc -104
/*     */     //   153: invokeinterface 33 2 0
/*     */     //   158: astore 11
/*     */     //   160: aload 11
/*     */     //   162: invokeinterface 54 1 0
/*     */     //   167: astore 12
/*     */     //   169: aload 12
/*     */     //   171: invokeinterface 58 1 0
/*     */     //   176: pop
/*     */     //   177: aload 12
/*     */     //   179: iconst_1
/*     */     //   180: invokeinterface 154 2 0
/*     */     //   185: istore 13
/*     */     //   187: goto +90 -> 277
/*     */     //   190: astore 14
/*     */     //   192: aload 14
/*     */     //   194: invokevirtual 75	java/sql/SQLException:printStackTrace	()V
/*     */     //   197: aload 12
/*     */     //   199: ifnull +10 -> 209
/*     */     //   202: aload 12
/*     */     //   204: invokeinterface 70 1 0
/*     */     //   209: aload 11
/*     */     //   211: ifnull +10 -> 221
/*     */     //   214: aload 11
/*     */     //   216: invokeinterface 73 1 0
/*     */     //   221: aload 10
/*     */     //   223: ifnull +90 -> 313
/*     */     //   226: aload 10
/*     */     //   228: invokeinterface 74 1 0
/*     */     //   233: goto +80 -> 313
/*     */     //   236: astore 15
/*     */     //   238: aload 12
/*     */     //   240: ifnull +10 -> 250
/*     */     //   243: aload 12
/*     */     //   245: invokeinterface 70 1 0
/*     */     //   250: aload 11
/*     */     //   252: ifnull +10 -> 262
/*     */     //   255: aload 11
/*     */     //   257: invokeinterface 73 1 0
/*     */     //   262: aload 10
/*     */     //   264: ifnull +10 -> 274
/*     */     //   267: aload 10
/*     */     //   269: invokeinterface 74 1 0
/*     */     //   274: aload 15
/*     */     //   276: athrow
/*     */     //   277: aload 12
/*     */     //   279: ifnull +10 -> 289
/*     */     //   282: aload 12
/*     */     //   284: invokeinterface 70 1 0
/*     */     //   289: aload 11
/*     */     //   291: ifnull +10 -> 301
/*     */     //   294: aload 11
/*     */     //   296: invokeinterface 73 1 0
/*     */     //   301: aload 10
/*     */     //   303: ifnull +10 -> 313
/*     */     //   306: aload 10
/*     */     //   308: invokeinterface 74 1 0
/*     */     //   313: iload 13
/*     */     //   315: ireturn
/*     */     // Line number table:
/*     */     //   Java source line #412	-> byte code offset #0
/*     */     //   Java source line #413	-> byte code offset #10
/*     */     //   Java source line #414	-> byte code offset #13
/*     */     //   Java source line #415	-> byte code offset #16
/*     */     //   Java source line #417	-> byte code offset #19
/*     */     //   Java source line #418	-> byte code offset #24
/*     */     //   Java source line #419	-> byte code offset #35
/*     */     //   Java source line #420	-> byte code offset #44
/*     */     //   Java source line #421	-> byte code offset #53
/*     */     //   Java source line #422	-> byte code offset #62
/*     */     //   Java source line #423	-> byte code offset #72
/*     */     //   Java source line #424	-> byte code offset #82
/*     */     //   Java source line #425	-> byte code offset #93
/*     */     //   Java source line #426	-> byte code offset #104
/*     */     //   Java source line #427	-> byte code offset #115
/*     */     //   Java source line #428	-> byte code offset #126
/*     */     //   Java source line #431	-> byte code offset #138
/*     */     //   Java source line #432	-> byte code offset #149
/*     */     //   Java source line #433	-> byte code offset #151
/*     */     //   Java source line #432	-> byte code offset #158
/*     */     //   Java source line #434	-> byte code offset #160
/*     */     //   Java source line #435	-> byte code offset #169
/*     */     //   Java source line #436	-> byte code offset #177
/*     */     //   Java source line #438	-> byte code offset #187
/*     */     //   Java source line #439	-> byte code offset #192
/*     */     //   Java source line #441	-> byte code offset #197
/*     */     //   Java source line #442	-> byte code offset #202
/*     */     //   Java source line #443	-> byte code offset #209
/*     */     //   Java source line #444	-> byte code offset #214
/*     */     //   Java source line #445	-> byte code offset #221
/*     */     //   Java source line #446	-> byte code offset #226
/*     */     //   Java source line #440	-> byte code offset #236
/*     */     //   Java source line #441	-> byte code offset #238
/*     */     //   Java source line #442	-> byte code offset #243
/*     */     //   Java source line #443	-> byte code offset #250
/*     */     //   Java source line #444	-> byte code offset #255
/*     */     //   Java source line #445	-> byte code offset #262
/*     */     //   Java source line #446	-> byte code offset #267
/*     */     //   Java source line #447	-> byte code offset #274
/*     */     //   Java source line #441	-> byte code offset #277
/*     */     //   Java source line #442	-> byte code offset #282
/*     */     //   Java source line #443	-> byte code offset #289
/*     */     //   Java source line #444	-> byte code offset #294
/*     */     //   Java source line #445	-> byte code offset #301
/*     */     //   Java source line #446	-> byte code offset #306
/*     */     //   Java source line #448	-> byte code offset #313
/*     */     // Local variable table:
/*     */     //   start	length	slot	name	signature
/*     */     //   0	316	0	this	UserDAOImpl
/*     */     //   0	316	1	username	String
/*     */     //   0	316	2	teamname	String
/*     */     //   0	316	3	school	String
/*     */     //   0	316	4	teamdetails	String
/*     */     //   0	316	5	city	String
/*     */     //   0	316	6	email	String
/*     */     //   0	316	7	phone	String
/*     */     //   0	316	8	theme	String
/*     */     //   0	316	9	idea	String
/*     */     //   8	299	10	connection	Connection
/*     */     //   11	284	11	preparedStatement	PreparedStatement
/*     */     //   14	269	12	resultSet	ResultSet
/*     */     //   17	297	13	id	int
/*     */     //   22	5	14	query	String
/*     */     //   190	3	14	exception	SQLException
/*     */     //   236	39	15	localObject	Object
/*     */     // Exception table:
/*     */     //   from	to	target	type
/*     */     //   19	187	190	java/sql/SQLException
/*     */     //   19	197	236	finally
/*     */   }
/*     */   
/*     */   /* Error */
/*     */   public void incLoginCount(String username)
/*     */     throws SQLException
/*     */   {
/*     */     // Byte code:
/*     */     //   0: aconst_null
/*     */     //   1: astore_2
/*     */     //   2: aconst_null
/*     */     //   3: astore_3
/*     */     //   4: getstatic 327	java/lang/System:out	Ljava/io/PrintStream;
/*     */     //   7: new 291	java/lang/StringBuilder
/*     */     //   10: dup
/*     */     //   11: ldc_w 333
/*     */     //   14: invokespecial 295	java/lang/StringBuilder:<init>	(Ljava/lang/String;)V
/*     */     //   17: aload_1
/*     */     //   18: invokevirtual 297	java/lang/StringBuilder:append	(Ljava/lang/String;)Ljava/lang/StringBuilder;
/*     */     //   21: invokevirtual 305	java/lang/StringBuilder:toString	()Ljava/lang/String;
/*     */     //   24: invokevirtual 335	java/io/PrintStream:println	(Ljava/lang/String;)V
/*     */     //   27: getstatic 21	com/groom/dao/impl/UserDAOImpl:ds	Ljavax/sql/DataSource;
/*     */     //   30: invokeinterface 25 1 0
/*     */     //   35: astore_2
/*     */     //   36: aload_2
/*     */     //   37: ldc_w 340
/*     */     //   40: invokeinterface 33 2 0
/*     */     //   45: astore_3
/*     */     //   46: aload_3
/*     */     //   47: iconst_1
/*     */     //   48: aload_1
/*     */     //   49: invokeinterface 45 3 0
/*     */     //   54: aload_3
/*     */     //   55: invokeinterface 148 1 0
/*     */     //   60: pop
/*     */     //   61: goto +28 -> 89
/*     */     //   64: astore 4
/*     */     //   66: aload_3
/*     */     //   67: ifnull +9 -> 76
/*     */     //   70: aload_3
/*     */     //   71: invokeinterface 73 1 0
/*     */     //   76: aload_2
/*     */     //   77: ifnull +9 -> 86
/*     */     //   80: aload_2
/*     */     //   81: invokeinterface 74 1 0
/*     */     //   86: aload 4
/*     */     //   88: athrow
/*     */     //   89: aload_3
/*     */     //   90: ifnull +9 -> 99
/*     */     //   93: aload_3
/*     */     //   94: invokeinterface 73 1 0
/*     */     //   99: aload_2
/*     */     //   100: ifnull +9 -> 109
/*     */     //   103: aload_2
/*     */     //   104: invokeinterface 74 1 0
/*     */     //   109: return
/*     */     // Line number table:
/*     */     //   Java source line #452	-> byte code offset #0
/*     */     //   Java source line #453	-> byte code offset #2
/*     */     //   Java source line #454	-> byte code offset #4
/*     */     //   Java source line #456	-> byte code offset #27
/*     */     //   Java source line #458	-> byte code offset #36
/*     */     //   Java source line #459	-> byte code offset #37
/*     */     //   Java source line #458	-> byte code offset #45
/*     */     //   Java source line #460	-> byte code offset #46
/*     */     //   Java source line #461	-> byte code offset #54
/*     */     //   Java source line #462	-> byte code offset #61
/*     */     //   Java source line #463	-> byte code offset #66
/*     */     //   Java source line #464	-> byte code offset #70
/*     */     //   Java source line #466	-> byte code offset #76
/*     */     //   Java source line #467	-> byte code offset #80
/*     */     //   Java source line #468	-> byte code offset #86
/*     */     //   Java source line #463	-> byte code offset #89
/*     */     //   Java source line #464	-> byte code offset #93
/*     */     //   Java source line #466	-> byte code offset #99
/*     */     //   Java source line #467	-> byte code offset #103
/*     */     //   Java source line #469	-> byte code offset #109
/*     */     // Local variable table:
/*     */     //   start	length	slot	name	signature
/*     */     //   0	110	0	this	UserDAOImpl
/*     */     //   0	110	1	username	String
/*     */     //   1	103	2	conn	Connection
/*     */     //   3	91	3	ps	PreparedStatement
/*     */     //   64	23	4	localObject	Object
/*     */     // Exception table:
/*     */     //   from	to	target	type
/*     */     //   27	64	64	finally
/*     */   }
/*     */   
/*     */   public boolean updateDetails(String mail, String phone, String username)
/*     */     throws SQLException
/*     */   {
/* 473 */     Connection connection = ds.getConnection();
/* 474 */     PreparedStatement preparedStatement = null;
/*     */     try
/*     */     {
/* 477 */       String query = "UPDATE USER SET MAIL=?, PHONE=? WHERE USER_NAME=?";
/* 478 */       preparedStatement = connection.prepareStatement(query);
/* 479 */       preparedStatement.setString(1, mail);
/* 480 */       preparedStatement.setString(2, phone);
/* 481 */       preparedStatement.setString(3, username);
/*     */       
/* 483 */       if (preparedStatement.executeUpdate() == 1) {
/* 484 */         return true;
/*     */       }
/*     */     } catch (SQLException exception) {
/* 487 */       exception.printStackTrace();
/*     */     }
/*     */     finally {
/* 490 */       if (preparedStatement != null)
/* 491 */         preparedStatement.close();
/* 492 */       if (connection != null) {
/* 493 */         connection.close();
/*     */       }
/*     */     }
/* 490 */     if (preparedStatement != null)
/* 491 */       preparedStatement.close();
/* 492 */     if (connection != null) {
/* 493 */       connection.close();
/*     */     }
/* 495 */     return false;
/*     */   }
/*     */ }


/* Location:              D:\New folder\WEB-INF\classes\com\groom.zip!\groom\dao\impl\UserDAOImpl.class
 * Java compiler version: 7 (51.0)
 * JD-Core Version:       0.7.1
 */